Workbook
Name coeff_d_e3570590_c0c7_48ab_99fe_9199863db98b: #REF!
Name coeff_d_f6c87698_8b8a_4580_8187_533f99afdba0: #REF!
Name coeff_d_742bd4bf_4fb9_4c16_be4b_074d0687253b: 'Basco Injection -- COBB'!$A$2:$M$89
Name coeff_d_e3cac388_7988_4f67_95ad_68fda5a4d14e: 'Basco Injection -- SOBB'!$A$2:$D$58
Name coeff_d_310c7906_ecbd_41fd_815e_ce444f066fc6: 'COBB (with offload info)'!$A$2:$I$38
Name coeff_d_7575b06d_36ad_4354_9105_86221b23853b: #REF!
Name coeff_d_dce31f25_6a50_4ef2_8731_48e4fc48dfc3: 'Basco Injection -- Main'!$A$2:$G$6
Name coeff_d_396fa8a6_9922_43fe_9fc6_0833ac761b3e: #REF!

Sheet PickupInjection Timeline

Sheet Naming Conventions
A1: PO Naming Convention
A3: Any load from AECN will have the following PO convention
A5: 001T1R0 | B5: - (001) | C5: This refers to the total number of POs, and will increase with each new PO generated
A6: truck to rail | B6: - T1 | C6: This refers to the truck that is being loaded at AECN, and for long haul truck loads, this will always be T1, for loads going rail, this will increase with the number of trucks it takes to fill a railcar
B7: - R1 | C7: This refers to the number railcar that we are filling with trucks, and will increase with each railload starting at 1
A9: Any load from Maize, KS to any site will have the following PO convention
A11: 001R1T1 | B11: - (001) | C11: This refers to the total number of POs, and will increase with each new PO generated
A12: rail to truck | B12: - R1 | C12: This refers to the number railcar that we are unloading with trucks, and will increase with each railload starting at 1
B13: - T1 | C13: This refers to the truck that is being loaded at Maize, KS location, and for loads coming from rail, this will increase with the number of trucks it takes to empty a railcar
A15: Any load from any location directly to Vaulted will have the following PO convention
A17: 001V | B17: - (001) | C17: This refers to the total number of POs, and will increase with each new PO generated
B18: - V | C18: This refers to the load going to Vauled
A21: Month | B21: January | C21: February | D21: March | E21: April | F21: May | G21: June | H21: July | I21: August | J21: September | K21: October | L21: November | M21: December | N21: 2024
A22: Total Metric Tons by Rail | B22: 80 | C22: 240 | D22: 320 | E22: 240 | F22: 560 | G22: 720 | H22: 640 | I22: 560 | J22: 720 | K22: 960 | L22: 240 | M22: 960 | N22: 6240
A23: Total Liters by Rail | B23: =B22*$A$25 -> 80000 | C23: =C22*$A$25 -> 240000 | D23: =D22*$A$25 -> 320000 | E23: =E22*$A$25 -> 240000 | F23: =F22*$A$25 -> 560000 | G23: =G22*$A$25 -> 720000 | H23: =H22*$A$25 -> 640000 | I23: =I22*$A$25 -> 560000 | ... N23: =N22*$A$25 -> 6240000
A25: 1000

Sheet Loads
A1: load_id | B1: PO # | C1: BOL | D1: COA | E1: PCB Invoices (Receipt Received | F1: Invoice (Payment to AECN) | G1: Customs Document Sent (Rail) | H1: Supplier | I1: Mode | J1: Delivery Location | K1: Carrier | L1: ID | M1: Forecasted Asset ID | N1: Pickup Date | O1: Delivery Date | P1: MFO PO # | Q1: Actual Loaded (metric tons) | R1: Gallons Loaded | S1: Single-Blend %C | T1: Carbon Content (%) | U1: Gross (t CO₂e) | V1: Pyrolysis (t CO₂e ) | W1: KAG Transport Distance (mi) | X1: KAG Transport (t CO₂e) | Y1: TBC Transport Distance | Z1: TBC Transport (t CO₂e) | AA1: Train Transport Distance | AB1: Train Transport (t CO₂e) | AC1: Maize Transport Distance | AD1: Maize Transport (t CO₂e) | AE1: Bio-oil Treatment (t CO₂e) | AF1: Hutch Transport Distance | AG1: Hutch Transport (t CO₂e) | AH1: Injection (t CO₂e) | AI1: Emitted (t CO₂e) | AJ1: Net (t CO₂e) | AK1: 2024 t CO₂e | AL1: t CO₂e / t bio-oil | AN1: Blend Count | AO1: PO # | AP1: Chip | AQ1: Link | AR1: BOL Text
A2: 1 | B2: 033T1R0 | D2: RS2-240221 | F2: paid | G2: NA | H2: AECN | I2: truck | K2: KAG | L2: Guy | N2: 45352 | O2: 45355 | Q2: 20.07 | S2: =iferror(if(AN2=1,VLOOKUP(B2, Blends!H$4:AK$1004,32,0), ""), "") | T2: 0.4483 | U2: =Q2*T2*(44.01/12.011) -> 32.967674 | V2: =$Q2*('MRV Calcs'!$E$3+'MRV Calcs'!$E$4) -> 2.9691947 | W2: =IF(H2="AECN",2030,"ERROR") -> 2030 | X2: =IF($I2="truck",($Q2*$W2*'MRV Calcs'!$E$7)+($W2*'MRV Calcs'!$E$8),0) -> 5.4012318 | Y2: =IF($I2="train",'MRV Calcs'!$E$24,0) -> 0 | Z2: =IF($I2="train",($Q2*$Y2*'MRV Calcs'!$E$7)+($Y2*'MRV Calcs'!$E$8),0) -> 0 | AA2: =IF($I2="train",'MRV Calcs'!$E$25,0) -> 0 | AB2: =IF($I2="train",($Q2*$AA2*'MRV Calcs'!$E$11)+($AA2*'MRV Calcs'!$E$12),0) -> 0 | AC2: =IF($I2="train",'MRV Calcs'!$E$26,0) -> 0 | AD2: =IF($I2="train",($Q2*$AC2*'MRV Calcs'!$E$7)+($AC2*'MRV Calcs'!$E$8),0) -> 0 | AE2: =($Q2/30)*SUM('MRV Calcs'!$E$15:$E$16) -> 3.038107 | AF2: ='MRV Calcs'!$E$27 -> 71.2 | AG2: =(($Q2*1.1)*$AF2*'MRV Calcs'!$E$7)+($AF2*'MRV Calcs'!$E$8) -> 0.20783999 | AH2: =(($Q2*1.1)/20)*SUM('MRV Calcs'!$E$19:$E$20) -> 0.02825856 | AI2: =SUM(AH2,AG2,AE2,AD2,AB2,Z2,X2,V2) -> 11.644632 | AJ2: =U2-AI2 -> 21.323042 | AK2: =AJ2 -> 21.323042 | AL2: =AJ2/Q2 -> 1.0624336 | AN2: =COUNTIF(Blends!H$4:H$1007,B2)+COUNTIF(Blends!J$4:J$1007,B2)+COUNTIF(#REF!,B2) -> 0 | AO2: =B2 -> 033T1R0 | AP2: Billing Camion 1117.pdf | AQ2: =IFERROR(__xludf.DUMMYFUNCTION("AP2.url"),"https://drive.google.com/file/d/19_rylkSc1iflh2fzW0GYdWbK3nkiW5OP/view?usp=drive_link") -> https://drive.google.com/file/d/19_rylkSc1iflh2fzW0GYdWbK3nkiW5OP/view?usp=drive_link
A3: 2 | B3: 034T1R0 | D3: RS2-240221 | F3: paid | G3: NA | H3: AECN | I3: truck | K3: KAG | L3: Darryl | N3: 45373 | O3: 45376 | Q3: 19.63 | S3: =iferror(if(AN3=1,VLOOKUP(B3, Blends!H$4:AK$1004,32,0), ""), "") | T3: 0.4257 | U3: =Q3*T3*(44.01/12.011) -> 30.619363 | V3: =$Q3*('MRV Calcs'!$E$3+'MRV Calcs'!$E$4) -> 2.9041002 | W3: =IF(H3="AECN",2030,"ERROR") -> 2030 | X3: =IF($I3="truck",($Q3*$W3*'MRV Calcs'!$E$7)+($W3*'MRV Calcs'!$E$8),0) -> 5.2862348 | Y3: =IF($I3="train",'MRV Calcs'!$E$24,0) -> 0 | Z3: =IF($I3="train",($Q3*$Y3*'MRV Calcs'!$E$7)+($Y3*'MRV Calcs'!$E$8),0) -> 0 | AA3: =IF($I3="train",'MRV Calcs'!$E$25,0) -> 0 | AB3: =IF($I3="train",($Q3*$AA3*'MRV Calcs'!$E$11)+($AA3*'MRV Calcs'!$E$12),0) -> 0 | AC3: =IF($I3="train",'MRV Calcs'!$E$26,0) -> 0 | AD3: =IF($I3="train",($Q3*$AC3*'MRV Calcs'!$E$7)+($AC3*'MRV Calcs'!$E$8),0) -> 0 | AE3: =($Q3/30)*SUM('MRV Calcs'!$E$15:$E$16) -> 2.9715017 | AF3: ='MRV Calcs'!$E$27 -> 71.2 | AG3: =(($Q3*1.1)*$AF3*'MRV Calcs'!$E$7)+($AF3*'MRV Calcs'!$E$8) -> 0.20340326 | AH3: =(($Q3*1.1)/20)*SUM('MRV Calcs'!$E$19:$E$20) -> 0.02763904 | AI3: =SUM(AH3,AG3,AE3,AD3,AB3,Z3,X3,V3) -> 11.392879 | AJ3: =U3-AI3 -> 19.226484 | AK3: =AJ3+AK2 -> 40.549526 | AL3: =AJ3/Q3 -> 0.97944391 | AN3: =COUNTIF(Blends!H$4:H$1007,B3)+COUNTIF(Blends!J$4:J$1007,B3)+COUNTIF(#REF!,B3) -> 1 | AO3: =B3 -> 034T1R0 | AP3: Envoi des documents camion 1178.pdf | AQ3: =IFERROR(__xludf.DUMMYFUNCTION("AP3.url"),"https://drive.google.com/file/d/1Fg9KFgPqKmiJN0v3nSsbov1HhxBi6Wr_/view?usp=drive_link") -> https://drive.google.com/file/d/1Fg9KFgPqKmiJN0v3nSsbov1HhxBi6Wr_/view?usp=drive_link
A4: 3 | B4: 035T1R0 | D4: RS3-240322 | F4: paid | G4: NA | H4: AECN | I4: truck | K4: KAG | L4: Gus/Darryl | N4: 45380 | O4: 45383 | Q4: 21.03 | S4: =iferror(if(AN4=1,VLOOKUP(B4, Blends!H$4:AK$1004,32,0), ""), "") | T4: 0.42 | U4: =Q4*T4*(44.01/12.011) -> 32.363894 | V4: =$Q4*('MRV Calcs'!$E$3+'MRV Calcs'!$E$4) -> 3.1112189 | W4: =IF(H4="AECN",2030,"ERROR") -> 2030 | X4: =IF($I4="truck",($Q4*$W4*'MRV Calcs'!$E$7)+($W4*'MRV Calcs'!$E$8),0) -> 5.6521343 | Y4: =IF($I4="train",'MRV Calcs'!$E$24,0) -> 0 | Z4: =IF($I4="train",($Q4*$Y4*'MRV Calcs'!$E$7)+($Y4*'MRV Calcs'!$E$8),0) -> 0 | AA4: =IF($I4="train",'MRV Calcs'!$E$25,0) -> 0 | AB4: =IF($I4="train",($Q4*$AA4*'MRV Calcs'!$E$11)+($AA4*'MRV Calcs'!$E$12),0) -> 0 | AC4: =IF($I4="train",'MRV Calcs'!$E$26,0) -> 0 | AD4: =IF($I4="train",($Q4*$AC4*'MRV Calcs'!$E$7)+($AC4*'MRV Calcs'!$E$8),0) -> 0 | AE4: =($Q4/30)*SUM('MRV Calcs'!$E$15:$E$16) -> 3.1834275 | AF4: ='MRV Calcs'!$E$27 -> 71.2 | AG4: =(($Q4*1.1)*$AF4*'MRV Calcs'!$E$7)+($AF4*'MRV Calcs'!$E$8) -> 0.21752013 | AH4: =(($Q4*1.1)/20)*SUM('MRV Calcs'!$E$19:$E$20) -> 0.02961024 | AI4: =SUM(AH4,AG4,AE4,AD4,AB4,Z4,X4,V4) -> 12.193911 | AJ4: =U4-AI4 -> 20.169982 | AK4: =AJ4+AK3 -> 60.719509 | AL4: =AJ4/Q4 -> 0.95910521 | AN4: =COUNTIF(Blends!H$4:H$1007,B4)+COUNTIF(Blends!J$4:J$1007,B4)+COUNTIF(#REF!,B4) -> 1 | AO4: =B4 -> 035T1R0 | AP4: Envoi des documents Camion 1192.pdf | AQ4: =IFERROR(__xludf.DUMMYFUNCTION("AP4.url"),"https://drive.google.com/file/d/1OLnsDJWSPWqo9cQ28dNO0ypTjupeCahJ/view?usp=drive_link") -> https://drive.google.com/file/d/1OLnsDJWSPWqo9cQ28dNO0ypTjupeCahJ/view?usp=drive_link
A5: 4 | B5: 036T1R0 | D5: RS3-240322 | F5: paid | G5: NA | H5: AECN | I5: truck | K5: KAG | L5: Guy | N5: 45380 | O5: 45383 | Q5: 20.04 | S5: =iferror(if(AN5=1,VLOOKUP(B5, Blends!H$4:AK$1004,32,0), ""), "") | T5: 0.431 | U5: =Q5*T5*(44.01/12.011) -> 31.648067 | V5: =$Q5*('MRV Calcs'!$E$3+'MRV Calcs'!$E$4) -> 2.9647564 | W5: =IF(H5="AECN",2030,"ERROR") -> 2030 | X5: =IF($I5="truck",($Q5*$W5*'MRV Calcs'!$E$7)+($W5*'MRV Calcs'!$E$8),0) -> 5.3933911 | Y5: =IF($I5="train",'MRV Calcs'!$E$24,0) -> 0 | Z5: =IF($I5="train",($Q5*$Y5*'MRV Calcs'!$E$7)+($Y5*'MRV Calcs'!$E$8),0) -> 0 | AA5: =IF($I5="train",'MRV Calcs'!$E$25,0) -> 0 | AB5: =IF($I5="train",($Q5*$AA5*'MRV Calcs'!$E$11)+($AA5*'MRV Calcs'!$E$12),0) -> 0 | AC5: =IF($I5="train",'MRV Calcs'!$E$26,0) -> 0 | AD5: =IF($I5="train",($Q5*$AC5*'MRV Calcs'!$E$7)+($AC5*'MRV Calcs'!$E$8),0) -> 0 | AE5: =($Q5/30)*SUM('MRV Calcs'!$E$15:$E$16) -> 3.0335657 | AF5: ='MRV Calcs'!$E$27 -> 71.2 | AG5: =(($Q5*1.1)*$AF5*'MRV Calcs'!$E$7)+($AF5*'MRV Calcs'!$E$8) -> 0.20753748 | AH5: =(($Q5*1.1)/20)*SUM('MRV Calcs'!$E$19:$E$20) -> 0.02821632 | AI5: =SUM(AH5,AG5,AE5,AD5,AB5,Z5,X5,V5) -> 11.627467 | AJ5: =U5-AI5 -> 20.0206 | AK5: =AJ5+AK4 -> 80.740109 | AL5: =AJ5/Q5 -> 0.99903193 | AN5: =COUNTIF(Blends!H$4:H$1007,B5)+COUNTIF(Blends!J$4:J$1007,B5)+COUNTIF(#REF!,B5) -> 2 | AO5: =B5 -> 036T1R0 | AP5: Envoi des documents Camion 1193.pdf | AQ5: =IFERROR(__xludf.DUMMYFUNCTION("AP5.url"),"https://drive.google.com/file/d/14-2vZnVgWzlhAjdYzHmLknoAv_PIlC0y/view?usp=drive_link") -> https://drive.google.com/file/d/14-2vZnVgWzlhAjdYzHmLknoAv_PIlC0y/view?usp=drive_link
A6: 5 | B6: 037T1R0 | D6: RS2-240401 | F6: paid | G6: NA | H6: AECN | I6: truck | K6: KAG | L6: Gaston | N6: 45387 | O6: 45390 | Q6: 21 | S6: =iferror(if(AN6=1,VLOOKUP(B6, Blends!H$4:AK$1004,32,0), ""), "") | T6: 0.424 | U6: =Q6*T6*(44.01/12.011) -> 32.625513 | V6: =$Q6*('MRV Calcs'!$E$3+'MRV Calcs'!$E$4) -> 3.1067807 | W6: =IF(H6="AECN",2030,"ERROR") -> 2030 | X6: =IF($I6="truck",($Q6*$W6*'MRV Calcs'!$E$7)+($W6*'MRV Calcs'!$E$8),0) -> 5.6442936 | Y6: =IF($I6="train",'MRV Calcs'!$E$24,0) -> 0 | Z6: =IF($I6="train",($Q6*$Y6*'MRV Calcs'!$E$7)+($Y6*'MRV Calcs'!$E$8),0) -> 0 | AA6: =IF($I6="train",'MRV Calcs'!$E$25,0) -> 0 | AB6: =IF($I6="train",($Q6*$AA6*'MRV Calcs'!$E$11)+($AA6*'MRV Calcs'!$E$12),0) -> 0 | AC6: =IF($I6="train",'MRV Calcs'!$E$26,0) -> 0 | AD6: =IF($I6="train",($Q6*$AC6*'MRV Calcs'!$E$7)+($AC6*'MRV Calcs'!$E$8),0) -> 0 | AE6: =($Q6/30)*SUM('MRV Calcs'!$E$15:$E$16) -> 3.1788862 | AF6: ='MRV Calcs'!$E$27 -> 71.2 | AG6: =(($Q6*1.1)*$AF6*'MRV Calcs'!$E$7)+($AF6*'MRV Calcs'!$E$8) -> 0.21721762 | AH6: =(($Q6*1.1)/20)*SUM('MRV Calcs'!$E$19:$E$20) -> 0.029568 | AI6: =SUM(AH6,AG6,AE6,AD6,AB6,Z6,X6,V6) -> 12.176746 | AJ6: =U6-AI6 -> 20.448767 | AK6: =AJ6+AK5 -> 101.18888 | AL6: =AJ6/Q6 -> 0.97375082 | AN6: =COUNTIF(Blends!H$4:H$1007,B6)+COUNTIF(Blends!J$4:J$1007,B6)+COUNTIF(#REF!,B6) -> 1 | AO6: =B6 -> 037T1R0 | AP6: Billing doc 1211.pdf | AQ6: =IFERROR(__xludf.DUMMYFUNCTION("AP6.url"),"https://drive.google.com/file/d/1xJYGaRC0-HFs2Q7LNvDIHKvQNJx2rQ6l/view?usp=drive_link") -> https://drive.google.com/file/d/1xJYGaRC0-HFs2Q7LNvDIHKvQNJx2rQ6l/view?usp=drive_link
A7: 6 | B7: 041T1R0 | D7: RS1-240407 | F7: paid | G7: NA | H7: AECN | I7: truck | K7: KAG | L7: Guy | N7: 45394 | O7: 45397 | Q7: 20.2 | S7: =iferror(if(AN7=1,VLOOKUP(B7, Blends!H$4:AK$1004,32,0), ""), "") | T7: 0.42 | U7: =Q7*T7*(44.01/12.011) -> 31.086574 | V7: =$Q7*('MRV Calcs'!$E$3+'MRV Calcs'!$E$4) -> 2.9884271 | W7: =IF(H7="AECN",2030,"ERROR") -> 2030 | X7: =IF($I7="truck",($Q7*$W7*'MRV Calcs'!$E$7)+($W7*'MRV Calcs'!$E$8),0) -> 5.4352082 | Y7: =IF($I7="train",'MRV Calcs'!$E$24,0) -> 0 | Z7: =IF($I7="train",($Q7*$Y7*'MRV Calcs'!$E$7)+($Y7*'MRV Calcs'!$E$8),0) -> 0 | AA7: =IF($I7="train",'MRV Calcs'!$E$25,0) -> 0 | AB7: =IF($I7="train",($Q7*$AA7*'MRV Calcs'!$E$11)+($AA7*'MRV Calcs'!$E$12),0) -> 0 | AC7: =IF($I7="train",'MRV Calcs'!$E$26,0) -> 0 | AD7: =IF($I7="train",($Q7*$AC7*'MRV Calcs'!$E$7)+($AC7*'MRV Calcs'!$E$8),0) -> 0 | AE7: =($Q7/30)*SUM('MRV Calcs'!$E$15:$E$16) -> 3.0577858 | AF7: ='MRV Calcs'!$E$27 -> 71.2 | AG7: =(($Q7*1.1)*$AF7*'MRV Calcs'!$E$7)+($AF7*'MRV Calcs'!$E$8) -> 0.20915084 | AH7: =(($Q7*1.1)/20)*SUM('MRV Calcs'!$E$19:$E$20) -> 0.0284416 | AI7: =SUM(AH7,AG7,AE7,AD7,AB7,Z7,X7,V7) -> 11.719014 | AJ7: =U7-AI7 -> 19.36756 | AK7: =AJ7+AK6 -> 120.55644 | AL7: =AJ7/Q7 -> 0.95879012 | AN7: =COUNTIF(Blends!H$4:H$1007,B7)+COUNTIF(Blends!J$4:J$1007,B7)+COUNTIF(#REF!,B7) -> 2 | AO7: =B7 -> 041T1R0 | AP7: documents camion 1233.pdf | AQ7: =IFERROR(__xludf.DUMMYFUNCTION("AP7.url"),"https://drive.google.com/file/d/1MwHEXkZETjEuIxHNwgrns8tM2lLY7C59/view?usp=drive_link") -> https://drive.google.com/file/d/1MwHEXkZETjEuIxHNwgrns8tM2lLY7C59/view?usp=drive_link
A8: 7 | B8: 042T1R0 | D8: RS1-240407 | F8: paid | G8: NA | H8: AECN | I8: truck | K8: KAG | L8: Darryl | N8: 45394 | O8: 45397 | Q8: 20.63 | S8: =iferror(if(AN8=1,VLOOKUP(B8, Blends!H$4:AK$1004,32,0), ""), "") | T8: 0.4163 | U8: =Q8*T8*(44.01/12.011) -> 31.46863 | V8: =$Q8*('MRV Calcs'!$E$3+'MRV Calcs'!$E$4) -> 3.0520422 | W8: =IF(H8="AECN",2030,"ERROR") -> 2030 | X8: =IF($I8="truck",($Q8*$W8*'MRV Calcs'!$E$7)+($W8*'MRV Calcs'!$E$8),0) -> 5.5475916 | Y8: =IF($I8="train",'MRV Calcs'!$E$24,0) -> 0 | Z8: =IF($I8="train",($Q8*$Y8*'MRV Calcs'!$E$7)+($Y8*'MRV Calcs'!$E$8),0) -> 0 | AA8: =IF($I8="train",'MRV Calcs'!$E$25,0) -> 0 | AB8: =IF($I8="train",($Q8*$AA8*'MRV Calcs'!$E$11)+($AA8*'MRV Calcs'!$E$12),0) -> 0 | AC8: =IF($I8="train",'MRV Calcs'!$E$26,0) -> 0 | AD8: =IF($I8="train",($Q8*$AC8*'MRV Calcs'!$E$7)+($AC8*'MRV Calcs'!$E$8),0) -> 0 | AE8: =($Q8/30)*SUM('MRV Calcs'!$E$15:$E$16) -> 3.1228773 | AF8: ='MRV Calcs'!$E$27 -> 71.2 | AG8: =(($Q8*1.1)*$AF8*'MRV Calcs'!$E$7)+($AF8*'MRV Calcs'!$E$8) -> 0.21348674 | AH8: =(($Q8*1.1)/20)*SUM('MRV Calcs'!$E$19:$E$20) -> 0.02904704 | AI8: =SUM(AH8,AG8,AE8,AD8,AB8,Z8,X8,V8) -> 11.965045 | AJ8: =U8-AI8 -> 19.503586 | AK8: =AJ8+AK7 -> 140.06002 | AL8: =AJ8/Q8 -> 0.9453992 | AN8: =COUNTIF(Blends!H$4:H$1007,B8)+COUNTIF(Blends!J$4:J$1007,B8)+COUNTIF(#REF!,B8) -> 1 | AO8: =B8 -> 042T1R0 | AP8: Billing Docs 1234 Corrected PO number.pdf | AQ8: =IFERROR(__xludf.DUMMYFUNCTION("AP8.url"),"https://drive.google.com/file/d/1lGvPefgsd3yKrbNNNClUpWnFQLNXBxPm/view?usp=drive_link") -> https://drive.google.com/file/d/1lGvPefgsd3yKrbNNNClUpWnFQLNXBxPm/view?usp=drive_link
A9: 8 | B9: 038-040T2R1 | D9: RS3-240404 | F9: paid | G9: NA | H9: AECN | I9: train | K9: Transport Baie-Comeau | L9: STPX 094926 | N9: 45394 | O9: 45415 | Q9: =25.95+26.08+25.82 -> 77.85 | S9: =iferror(if(AN9=1,VLOOKUP(B9, Blends!H$4:AK$1004,32,0), ""), "") | T9: 0.42 | U9: =Q9*T9*(44.01/12.011) -> 119.80642 | V9: =$Q9*('MRV Calcs'!$E$3+'MRV Calcs'!$E$4) -> 11.51728 | W9: =IF(H9="AECN",2030,"ERROR") -> 2030 | X9: =IF($I9="truck",($Q9*$W9*'MRV Calcs'!$E$7)+($W9*'MRV Calcs'!$E$8),0) -> 0 | Y9: =IF($I9="train",'MRV Calcs'!$E$24,0) -> 107.497 | Z9: =IF($I9="train",($Q9*$Y9*'MRV Calcs'!$E$7)+($Y9*'MRV Calcs'!$E$8),0) -> 1.0856894 | AA9: =IF($I9="train",'MRV Calcs'!$E$25,0) -> 2087 | AB9: =IF($I9="train",($Q9*$AA9*'MRV Calcs'!$E$11)+($AA9*'MRV Calcs'!$E$12),0) -> 4.351363 | AC9: =IF($I9="train",'MRV Calcs'!$E$26,0) -> 32.6 | AD9: =IF($I9="train",($Q9*$AC9*'MRV Calcs'!$E$7)+($AC9*'MRV Calcs'!$E$8),0) -> 0.32925082 | AE9: =($Q9/30)*SUM('MRV Calcs'!$E$15:$E$16) -> 11.784585 | AF9: ='MRV Calcs'!$E$27 -> 71.2 | AG9: =(($Q9*1.1)*$AF9*'MRV Calcs'!$E$7)+($AF9*'MRV Calcs'!$E$8) -> 0.7904635 | AH9: =(($Q9*1.1)/20)*SUM('MRV Calcs'!$E$19:$E$20) -> 0.1096128 | AI9: =SUM(AH9,AG9,AE9,AD9,AB9,Z9,X9,V9) -> 29.968245 | AJ9: =U9-AI9 -> 89.83818 | AK9: =AJ9+AK8 -> 229.8982 | AL9: =AJ9/Q9 -> 1.1539908 | AN9: =COUNTIF(Blends!H$4:H$1007,B9)+COUNTIF(Blends!J$4:J$1007,B9)+COUNTIF(#REF!,B9) -> 7 | AO9: =B9 -> 038-040T2R1 | AP9: 038T2R1 + 039T2R1 + 040T2R1 Apr 8 & 9 Pickups STPX094926 | AQ9: =IFERROR(__xludf.DUMMYFUNCTION("AP9.url"),"https://drive.google.com/drive/folders/1K2G-UQhB-Pi95Ro7G7E5VoZyDn0EL1AH?usp=drive_link") -> https://drive.google.com/drive/folders/1K2G-UQhB-Pi95Ro7G7E5VoZyDn0EL1AH?usp=drive_link
A10: 9 | B10: 043T1R0 | D10: RS3-240429 | F10: paid | G10: NA | H10: AECN | I10: truck | K10: KAG | L10: Gaston | N10: 45414 | O10: =IF(I10="truck",N10+4,IF(I10="train",N10+16,"")) -> 45418 | Q10: 20.83 | S10: =iferror(if(AN10=1,VLOOKUP(B10, Blends!H$4:AK$1004,32,0), ""), "") | U10: =Q10*T10*(44.01/12.011) -> 0 | V10: =$Q10*('MRV Calcs'!$E$3+'MRV Calcs'!$E$4) -> 3.0816306 | W10: =IF(H10="AECN",2030,"ERROR") -> 2030 | X10: =IF($I10="truck",($Q10*$W10*'MRV Calcs'!$E$7)+($W10*'MRV Calcs'!$E$8),0) -> 5.599863 | Y10: =IF($I10="train",'MRV Calcs'!$E$24,0) -> 0 | Z10: =IF($I10="train",($Q10*$Y10*'MRV Calcs'!$E$7)+($Y10*'MRV Calcs'!$E$8),0) -> 0 | AA10: =IF($I10="train",'MRV Calcs'!$E$25,0) -> 0 | AB10: =IF($I10="train",($Q10*$AA10*'MRV Calcs'!$E$11)+($AA10*'MRV Calcs'!$E$12),0) -> 0 | AC10: =IF($I10="train",'MRV Calcs'!$E$26,0) -> 0 | AD10: =IF($I10="train",($Q10*$AC10*'MRV Calcs'!$E$7)+($AC10*'MRV Calcs'!$E$8),0) -> 0 | AE10: =($Q10/30)*SUM('MRV Calcs'!$E$15:$E$16) -> 3.1531524 | AF10: ='MRV Calcs'!$E$27 -> 71.2 | AG10: =(($Q10*1.1)*$AF10*'MRV Calcs'!$E$7)+($AF10*'MRV Calcs'!$E$8) -> 0.21550343 | AH10: =(($Q10*1.1)/20)*SUM('MRV Calcs'!$E$19:$E$20) -> 0.02932864 | AI10: =SUM(AH10,AG10,AE10,AD10,AB10,Z10,X10,V10) -> 12.079478 | AJ10: =U10-AI10 -> -12.079478 | AK10: =AJ10+AK9 -> 217.81872 | AL10: =AJ10/Q10 -> -0.57990773 | AN10: =COUNTIF(Blends!H$4:H$1007,B10)+COUNTIF(Blends!J$4:J$1007,B10)+COUNTIF(#REF!,B10) -> 2 | AO10: =B10 -> 043T1R0 | AP10: Envoi des documents 1301.pdf | AQ10: =IFERROR(__xludf.DUMMYFUNCTION("AP10.url"),"https://drive.google.com/file/d/10v6SP-oQueAyjXGma8rXybbakBKllOga/view?usp=drive_link") -> https://drive.google.com/file/d/10v6SP-oQueAyjXGma8rXybbakBKllOga/view?usp=drive_link
A11: 10 | B11: 044T1R0 | D11: RS3-240429 | F11: paid | G11: NA | H11: AECN | I11: truck | K11: KAG | L11: Darryl | N11: 45414 | O11: =IF(I11="truck",N11+4,IF(I11="train",N11+16,"")) -> 45418 | Q11: 20.14 | S11: =iferror(if(AN11=1,VLOOKUP(B11, Blends!H$4:AK$1004,32,0), ""), "") | U11: =Q11*T11*(44.01/12.011) -> 0 | V11: =$Q11*('MRV Calcs'!$E$3+'MRV Calcs'!$E$4) -> 2.9795506 | W11: =IF(H11="AECN",2030,"ERROR") -> 2030 | X11: =IF($I11="truck",($Q11*$W11*'MRV Calcs'!$E$7)+($W11*'MRV Calcs'!$E$8),0) -> 5.4195268 | Y11: =IF($I11="train",'MRV Calcs'!$E$24,0) -> 0 | Z11: =IF($I11="train",($Q11*$Y11*'MRV Calcs'!$E$7)+($Y11*'MRV Calcs'!$E$8),0) -> 0 | AA11: =IF($I11="train",'MRV Calcs'!$E$25,0) -> 0 | AB11: =IF($I11="train",($Q11*$AA11*'MRV Calcs'!$E$11)+($AA11*'MRV Calcs'!$E$12),0) -> 0 | AC11: =IF($I11="train",'MRV Calcs'!$E$26,0) -> 0 | AD11: =IF($I11="train",($Q11*$AC11*'MRV Calcs'!$E$7)+($AC11*'MRV Calcs'!$E$8),0) -> 0 | AE11: =($Q11/30)*SUM('MRV Calcs'!$E$15:$E$16) -> 3.0487032 | AF11: ='MRV Calcs'!$E$27 -> 71.2 | AG11: =(($Q11*1.1)*$AF11*'MRV Calcs'!$E$7)+($AF11*'MRV Calcs'!$E$8) -> 0.20854583 | AH11: =(($Q11*1.1)/20)*SUM('MRV Calcs'!$E$19:$E$20) -> 0.02835712 | AI11: =SUM(AH11,AG11,AE11,AD11,AB11,Z11,X11,V11) -> 11.684684 | AJ11: =U11-AI11 -> -11.684684 | AK11: =AJ11+AK10 -> 206.13404 | AL11: =AJ11/Q11 -> -0.58017297 | AN11: =COUNTIF(Blends!H$4:H$1007,B11)+COUNTIF(Blends!J$4:J$1007,B11)+COUNTIF(#REF!,B11) -> 1 | AO11: =B11 -> 044T1R0 | AP11: Envoi des documents 1302.pdf | AQ11: =IFERROR(__xludf.DUMMYFUNCTION("AP11.url"),"https://drive.google.com/file/d/1vMftkmGRJGBWUkariuCQUCy8BvqpKsF3/view?usp=drive_link") -> https://drive.google.com/file/d/1vMftkmGRJGBWUkariuCQUCy8BvqpKsF3/view?usp=drive_link
A12: 11 | B12: 045-047T2R2 | D12: RS2-240428 | F12: paid | G12: TRUE | H12: AECN | I12: train | K12: Transport Baie-Comeau | L12: STPX 094627 | N12: 45415 | O12: 45433 | Q12: 78.8 | S12: =iferror(if(AN12=1,VLOOKUP(B12, Blends!H$4:AK$1004,32,0), ""), "") | U12: =Q12*T12*(44.01/12.011) -> 0 | V12: =$Q12*('MRV Calcs'!$E$3+'MRV Calcs'!$E$4) -> 11.657825 | W12: =IF(H12="AECN",2030,"ERROR") -> 2030 | X12: =IF($I12="truck",($Q12*$W12*'MRV Calcs'!$E$7)+($W12*'MRV Calcs'!$E$8),0) -> 0 | Y12: =IF($I12="train",'MRV Calcs'!$E$24,0) -> 107.497 | Z12: =IF($I12="train",($Q12*$Y12*'MRV Calcs'!$E$7)+($Y12*'MRV Calcs'!$E$8),0) -> 1.0988374 | AA12: =IF($I12="train",'MRV Calcs'!$E$25,0) -> 2087 | AB12: =IF($I12="train",($Q12*$AA12*'MRV Calcs'!$E$11)+($AA12*'MRV Calcs'!$E$12),0) -> 4.4030533 | AC12: =IF($I12="train",'MRV Calcs'!$E$26,0) -> 32.6 | AD12: =IF($I12="train",($Q12*$AC12*'MRV Calcs'!$E$7)+($AC12*'MRV Calcs'!$E$8),0) -> 0.33323812 | AE12: =($Q12/30)*SUM('MRV Calcs'!$E$15:$E$16) -> 11.928392 | AF12: ='MRV Calcs'!$E$27 -> 71.2 | AG12: =(($Q12*1.1)*$AF12*'MRV Calcs'!$E$7)+($AF12*'MRV Calcs'!$E$8) -> 0.80004281 | AH12: =(($Q12*1.1)/20)*SUM('MRV Calcs'!$E$19:$E$20) -> 0.1109504 | AI12: =SUM(AH12,AG12,AE12,AD12,AB12,Z12,X12,V12) -> 30.332339 | AJ12: =U12-AI12 -> -30.332339 | AK12: =AJ12+AK11 -> 175.8017 | AL12: =AJ12/Q12 -> -0.38492816 | AN12: =COUNTIF(Blends!H$4:H$1007,B12)+COUNTIF(Blends!J$4:J$1007,B12)+COUNTIF(#REF!,B12) -> 5 | AO12: =B12 -> 045-047T2R2 | AP12: 045T2R2 - 047T2R2 4/30-5/1 Pickups STPX094627 | AQ12: =IFERROR(__xludf.DUMMYFUNCTION("AP12.url"),"https://drive.google.com/drive/folders/10huZjk9PmQavkXzqdPxfaL7r9y57q9KA?usp=drive_link") -> https://drive.google.com/drive/folders/10huZjk9PmQavkXzqdPxfaL7r9y57q9KA?usp=drive_link
A13: 12 | B13: 048-050T2R3 | D13: RS3-240429 | F13: paid | G13: TRUE | H13: AECN | I13: train | K13: Transport Baie-Comeau | L13: STPX 094625 | N13: 45419 | O13: 45434 | Q13: 79.09 | S13: =iferror(if(AN13=1,VLOOKUP(B13, Blends!H$4:AK$1004,32,0), ""), "") | U13: =Q13*T13*(44.01/12.011) -> 0 | V13: =$Q13*('MRV Calcs'!$E$3+'MRV Calcs'!$E$4) -> 11.700728 | W13: =IF(H13="AECN",2030,"ERROR") -> 2030 | X13: =IF($I13="truck",($Q13*$W13*'MRV Calcs'!$E$7)+($W13*'MRV Calcs'!$E$8),0) -> 0 | Y13: =IF($I13="train",'MRV Calcs'!$E$24,0) -> 107.497 | Z13: =IF($I13="train",($Q13*$Y13*'MRV Calcs'!$E$7)+($Y13*'MRV Calcs'!$E$8),0) -> 1.102851 | AA13: =IF($I13="train",'MRV Calcs'!$E$25,0) -> 2087 | AB13: =IF($I13="train",($Q13*$AA13*'MRV Calcs'!$E$11)+($AA13*'MRV Calcs'!$E$12),0) -> 4.4188324 | AC13: =IF($I13="train",'MRV Calcs'!$E$26,0) -> 32.6 | AD13: =IF($I13="train",($Q13*$AC13*'MRV Calcs'!$E$7)+($AC13*'MRV Calcs'!$E$8),0) -> 0.3344553 | AE13: =($Q13/30)*SUM('MRV Calcs'!$E$15:$E$16) -> 11.972291 | AF13: ='MRV Calcs'!$E$27 -> 71.2 | AG13: =(($Q13*1.1)*$AF13*'MRV Calcs'!$E$7)+($AF13*'MRV Calcs'!$E$8) -> 0.80296702 | AH13: =(($Q13*1.1)/20)*SUM('MRV Calcs'!$E$19:$E$20) -> 0.11135872 | AI13: =SUM(AH13,AG13,AE13,AD13,AB13,Z13,X13,V13) -> 30.443483 | AJ13: =U13-AI13 -> -30.443483 | AK13: =AJ13+AK12 -> 145.35822 | AL13: =AJ13/Q13 -> -0.38492203 | AN13: =COUNTIF(Blends!H$4:H$1007,B13)+COUNTIF(Blends!J$4:J$1007,B13)+COUNTIF(#REF!,B13) -> 5 | AO13: =B13 -> 048-050T2R3 | AP13: 048-050T2R3 5/1-5/2 Pickups STPX094625 | AQ13: =IFERROR(__xludf.DUMMYFUNCTION("AP13.url"),"https://drive.google.com/drive/folders/1R4l6-xHvtaH9yTtFG5n7b7zrpn1Layex?usp=drive_link") -> https://drive.google.com/drive/folders/1R4l6-xHvtaH9yTtFG5n7b7zrpn1Layex?usp=drive_link
A14: 13 | B14: 051-053T2R4 | D14: RS3-240429 and RS1-240501 | F14: paid | G14: TRUE | H14: AECN | I14: train | K14: Transport Baie-Comeau | L14: STPX 094624 | N14: 45419 | O14: 45434 | Q14: 78.98 | S14: =iferror(if(AN14=1,VLOOKUP(B14, Blends!H$4:AK$1004,32,0), ""), "") | U14: =Q14*T14*(44.01/12.011) -> 0 | V14: =$Q14*('MRV Calcs'!$E$3+'MRV Calcs'!$E$4) -> 11.684454 | W14: =IF(H14="AECN",2030,"ERROR") -> 2030 | X14: =IF($I14="truck",($Q14*$W14*'MRV Calcs'!$E$7)+($W14*'MRV Calcs'!$E$8),0) -> 0 | Y14: =IF($I14="train",'MRV Calcs'!$E$24,0) -> 107.497 | Z14: =IF($I14="train",($Q14*$Y14*'MRV Calcs'!$E$7)+($Y14*'MRV Calcs'!$E$8),0) -> 1.1013286 | AA14: =IF($I14="train",'MRV Calcs'!$E$25,0) -> 2087 | AB14: =IF($I14="train",($Q14*$AA14*'MRV Calcs'!$E$11)+($AA14*'MRV Calcs'!$E$12),0) -> 4.4128472 | AC14: =IF($I14="train",'MRV Calcs'!$E$26,0) -> 32.6 | AD14: =IF($I14="train",($Q14*$AC14*'MRV Calcs'!$E$7)+($AC14*'MRV Calcs'!$E$8),0) -> 0.33399361 | AE14: =($Q14/30)*SUM('MRV Calcs'!$E$15:$E$16) -> 11.95564 | AF14: ='MRV Calcs'!$E$27 -> 71.2 | AG14: =(($Q14*1.1)*$AF14*'MRV Calcs'!$E$7)+($AF14*'MRV Calcs'!$E$8) -> 0.80185784 | AH14: =(($Q14*1.1)/20)*SUM('MRV Calcs'!$E$19:$E$20) -> 0.11120384 | AI14: =SUM(AH14,AG14,AE14,AD14,AB14,Z14,X14,V14) -> 30.401325 | AJ14: =U14-AI14 -> -30.401325 | AK14: =AJ14+AK13 -> 114.95689 | AL14: =AJ14/Q14 -> -0.38492435 | AN14: =COUNTIF(Blends!H$4:H$1007,B14)+COUNTIF(Blends!J$4:J$1007,B14)+COUNTIF(#REF!,B14) -> 5 | AO14: =B14 -> 051-053T2R4 | AP14: 051-053T2R4 5/3-5/6 Pickups SPTX94624 | AQ14: =IFERROR(__xludf.DUMMYFUNCTION("AP14.url"),"https://drive.google.com/drive/folders/1bnmztyCdUq_Q2U5fZsp4bCg9iSuPS1rG?usp=drive_link") -> https://drive.google.com/drive/folders/1bnmztyCdUq_Q2U5fZsp4bCg9iSuPS1rG?usp=drive_link
A15: 14 | B15: 054T1R0 | D15: RS1-240501 | F15: paid | G15: NA | H15: AECN | I15: truck | K15: KAG | L15: Guy | N15: 45422 | O15: =IF(I15="truck",N15+4,IF(I15="train",N15+21,"")) -> 45426 | Q15: 20.11 | S15: =iferror(if(AN15=1,VLOOKUP(B15, Blends!H$4:AK$1004,32,0), ""), "") | T15: 0.408 | U15: =Q15*T15*(44.01/12.011) -> 30.063839 | V15: =$Q15*('MRV Calcs'!$E$3+'MRV Calcs'!$E$4) -> 2.9751124 | W15: =IF(H15="AECN",2030,"ERROR") -> 2030 | X15: =IF($I15="truck",($Q15*$W15*'MRV Calcs'!$E$7)+($W15*'MRV Calcs'!$E$8),0) -> 5.4116861 | Y15: =IF($I15="train",'MRV Calcs'!$E$24,0) -> 0 | Z15: =IF($I15="train",($Q15*$Y15*'MRV Calcs'!$E$7)+($Y15*'MRV Calcs'!$E$8),0) -> 0 | AA15: =IF($I15="train",'MRV Calcs'!$E$25,0) -> 0 | AB15: =IF($I15="train",($Q15*$AA15*'MRV Calcs'!$E$11)+($AA15*'MRV Calcs'!$E$12),0) -> 0 | AC15: =IF($I15="train",'MRV Calcs'!$E$26,0) -> 0 | AD15: =IF($I15="train",($Q15*$AC15*'MRV Calcs'!$E$7)+($AC15*'MRV Calcs'!$E$8),0) -> 0 | AE15: =($Q15/30)*SUM('MRV Calcs'!$E$15:$E$16) -> 3.044162 | AF15: ='MRV Calcs'!$E$27 -> 71.2 | AG15: =(($Q15*1.1)*$AF15*'MRV Calcs'!$E$7)+($AF15*'MRV Calcs'!$E$8) -> 0.20824333 | AH15: =(($Q15*1.1)/20)*SUM('MRV Calcs'!$E$19:$E$20) -> 0.02831488 | AI15: =SUM(AH15,AG15,AE15,AD15,AB15,Z15,X15,V15) -> 11.667519 | AJ15: =U15-AI15 -> 18.39632 | AK15: =AJ15+AK14 -> 133.35321 | AL15: =AJ15/Q15 -> 0.9147847 | AN15: =COUNTIF(Blends!H$4:H$1007,B15)+COUNTIF(Blends!J$4:J$1007,B15)+COUNTIF(#REF!,B15) -> 1 | AO15: =B15 -> 054T1R0 | AP15: Documents camion 1305.pdf | AQ15: =IFERROR(__xludf.DUMMYFUNCTION("AP15.url"),"https://drive.google.com/file/d/1nH0plpMTNbfetKZCbvTSiG46-7yYj3CY/view?usp=drive_link") -> https://drive.google.com/file/d/1nH0plpMTNbfetKZCbvTSiG46-7yYj3CY/view?usp=drive_link
A16: 15 | B16: 055T1R0 | D16: RS1-240501 | F16: paid | G16: NA | H16: AECN | I16: truck | K16: KAG | L16: Darryl | N16: 45423 | O16: =IF(I16="truck",N16+4,IF(I16="train",N16+21,"")) -> 45427 | Q16: 20.56 | S16: =iferror(if(AN16=1,VLOOKUP(B16, Blends!H$4:AK$1004,32,0), ""), "") | T16: 0.398 | U16: =Q16*T16*(44.01/12.011) -> 29.983228 | V16: =$Q16*('MRV Calcs'!$E$3+'MRV Calcs'!$E$4) -> 3.0416862 | W16: =IF(H16="AECN",2030,"ERROR") -> 2030 | X16: =IF($I16="truck",($Q16*$W16*'MRV Calcs'!$E$7)+($W16*'MRV Calcs'!$E$8),0) -> 5.5292966 | Y16: =IF($I16="train",'MRV Calcs'!$E$24,0) -> 0 | Z16: =IF($I16="train",($Q16*$Y16*'MRV Calcs'!$E$7)+($Y16*'MRV Calcs'!$E$8),0) -> 0 | AA16: =IF($I16="train",'MRV Calcs'!$E$25,0) -> 0 | AB16: =IF($I16="train",($Q16*$AA16*'MRV Calcs'!$E$11)+($AA16*'MRV Calcs'!$E$12),0) -> 0 | AC16: =IF($I16="train",'MRV Calcs'!$E$26,0) -> 0 | AD16: =IF($I16="train",($Q16*$AC16*'MRV Calcs'!$E$7)+($AC16*'MRV Calcs'!$E$8),0) -> 0 | AE16: =($Q16/30)*SUM('MRV Calcs'!$E$15:$E$16) -> 3.112281 | AF16: ='MRV Calcs'!$E$27 -> 71.2 | AG16: =(($Q16*1.1)*$AF16*'MRV Calcs'!$E$7)+($AF16*'MRV Calcs'!$E$8) -> 0.21278089 | AH16: =(($Q16*1.1)/20)*SUM('MRV Calcs'!$E$19:$E$20) -> 0.02894848 | AI16: =SUM(AH16,AG16,AE16,AD16,AB16,Z16,X16,V16) -> 11.924993 | AJ16: =U16-AI16 -> 18.058235 | AK16: =AJ16+AK15 -> 151.41145 | AL16: =AJ16/Q16 -> 0.8783188 | AN16: =COUNTIF(Blends!H$4:H$1007,B16)+COUNTIF(Blends!J$4:J$1007,B16)+COUNTIF(#REF!,B16) -> 1 | AO16: =B16 -> 055T1R0 | AP16: Documents camion 1306.pdf | AQ16: =IFERROR(__xludf.DUMMYFUNCTION("AP16.url"),"https://drive.google.com/file/d/1zQMVk78NOnW672_OvCACXe114oXe7eFO/view?usp=drive_link") -> https://drive.google.com/file/d/1zQMVk78NOnW672_OvCACXe114oXe7eFO/view?usp=drive_link
A17: 16 | B17: 056T1R0 | D17: RS1-240501 | F17: paid | G17: NA | H17: AECN | I17: truck | K17: KAG | L17: Gaston | N17: 45423 | O17: =IF(I17="truck",N17+4,IF(I17="train",N17+21,"")) -> 45427 | Q17: 21.29 | S17: =iferror(if(AN17=1,VLOOKUP(B17, Blends!H$4:AK$1004,32,0), ""), "") | T17: 0.3993 | U17: =Q17*T17*(44.01/12.011) -> 31.14922 | V17: =$Q17*('MRV Calcs'!$E$3+'MRV Calcs'!$E$4) -> 3.1496839 | W17: =IF(H17="AECN",2030,"ERROR") -> 2030 | X17: =IF($I17="truck",($Q17*$W17*'MRV Calcs'!$E$7)+($W17*'MRV Calcs'!$E$8),0) -> 5.7200871 | Y17: =IF($I17="train",'MRV Calcs'!$E$24,0) -> 0 | Z17: =IF($I17="train",($Q17*$Y17*'MRV Calcs'!$E$7)+($Y17*'MRV Calcs'!$E$8),0) -> 0 | AA17: =IF($I17="train",'MRV Calcs'!$E$25,0) -> 0 | AB17: =IF($I17="train",($Q17*$AA17*'MRV Calcs'!$E$11)+($AA17*'MRV Calcs'!$E$12),0) -> 0 | AC17: =IF($I17="train",'MRV Calcs'!$E$26,0) -> 0 | AD17: =IF($I17="train",($Q17*$AC17*'MRV Calcs'!$E$7)+($AC17*'MRV Calcs'!$E$8),0) -> 0 | AE17: =($Q17/30)*SUM('MRV Calcs'!$E$15:$E$16) -> 3.2227851 | AF17: ='MRV Calcs'!$E$27 -> 71.2 | AG17: =(($Q17*1.1)*$AF17*'MRV Calcs'!$E$7)+($AF17*'MRV Calcs'!$E$8) -> 0.22014183 | AH17: =(($Q17*1.1)/20)*SUM('MRV Calcs'!$E$19:$E$20) -> 0.02997632 | AI17: =SUM(AH17,AG17,AE17,AD17,AB17,Z17,X17,V17) -> 12.342674 | AJ17: =U17-AI17 -> 18.806546 | AK17: =AJ17+AK16 -> 170.21799 | AL17: =AJ17/Q17 -> 0.88335113 | AN17: =COUNTIF(Blends!H$4:H$1007,B17)+COUNTIF(Blends!J$4:J$1007,B17)+COUNTIF(#REF!,B17) -> 2 | AO17: =B17 -> 056T1R0 | AP17: Billing Documents 1307.pdf | AQ17: =IFERROR(__xludf.DUMMYFUNCTION("AP17.url"),"https://drive.google.com/file/d/1q-y_-Zz7QXAH6pd6LoSRhWO0xFXZ1WQM/view?usp=drive_link") -> https://drive.google.com/file/d/1q-y_-Zz7QXAH6pd6LoSRhWO0xFXZ1WQM/view?usp=drive_link
A18: 17 | B18: 057T1R0 | D18: RS1-240501 | F18: paid | G18: NA | H18: AECN | I18: truck | K18: KAG | L18: Guy | N18: 45431 | O18: 45434 | Q18: 20.53 | S18: =iferror(if(AN18=1,VLOOKUP(B18, Blends!H$4:AK$1004,32,0), ""), "") | T18: 0.388 | U18: =Q18*T18*(44.01/12.011) -> 29.18723 | V18: =$Q18*('MRV Calcs'!$E$3+'MRV Calcs'!$E$4) -> 3.037248 | W18: =IF(H18="AECN",2030,"ERROR") -> 2030 | X18: =IF($I18="truck",($Q18*$W18*'MRV Calcs'!$E$7)+($W18*'MRV Calcs'!$E$8),0) -> 5.5214559 | Y18: =IF($I18="train",'MRV Calcs'!$E$24,0) -> 0 | Z18: =IF($I18="train",($Q18*$Y18*'MRV Calcs'!$E$7)+($Y18*'MRV Calcs'!$E$8),0) -> 0 | AA18: =IF($I18="train",'MRV Calcs'!$E$25,0) -> 0 | AB18: =IF($I18="train",($Q18*$AA18*'MRV Calcs'!$E$11)+($AA18*'MRV Calcs'!$E$12),0) -> 0 | AC18: =IF($I18="train",'MRV Calcs'!$E$26,0) -> 0 | AD18: =IF($I18="train",($Q18*$AC18*'MRV Calcs'!$E$7)+($AC18*'MRV Calcs'!$E$8),0) -> 0 | AE18: =($Q18/30)*SUM('MRV Calcs'!$E$15:$E$16) -> 3.1077397 | AF18: ='MRV Calcs'!$E$27 -> 71.2 | AG18: =(($Q18*1.1)*$AF18*'MRV Calcs'!$E$7)+($AF18*'MRV Calcs'!$E$8) -> 0.21247839 | AH18: =(($Q18*1.1)/20)*SUM('MRV Calcs'!$E$19:$E$20) -> 0.02890624 | AI18: =SUM(AH18,AG18,AE18,AD18,AB18,Z18,X18,V18) -> 11.907828 | AJ18: =U18-AI18 -> 17.279402 | AK18: =AJ18+AK17 -> 187.4974 | AL18: =AJ18/Q18 -> 0.84166593 | AN18: =COUNTIF(Blends!H$4:H$1007,B18)+COUNTIF(Blends!J$4:J$1007,B18)+COUNTIF(#REF!,B18) -> 1 | AO18: =B18 -> 057T1R0 | AP18: Billing Docs 1308 PO 057T1R0.pdf | AQ18: =IFERROR(__xludf.DUMMYFUNCTION("AP18.url"),"https://drive.google.com/file/d/1UEOFYoPTkf0IlkSlvbOQqGIlJOvKWIWQ/view?usp=drive_link") -> https://drive.google.com/file/d/1UEOFYoPTkf0IlkSlvbOQqGIlJOvKWIWQ/view?usp=drive_link
A19: 18 | B19: 058T1R0 | D19: RS1-240501 | F19: paid | G19: NA | H19: AECN | I19: truck | K19: Queensway Transport | L19: Furgusson | N19: 45431 | O19: 45435 | Q19: 19.91 | S19: =iferror(if(AN19=1,VLOOKUP(B19, Blends!H$4:AK$1004,32,0), ""), "") | T19: 0.407 | U19: =Q19*T19*(44.01/12.011) -> 29.691892 | V19: =$Q19*('MRV Calcs'!$E$3+'MRV Calcs'!$E$4) -> 2.945524 | W19: =IF(H19="AECN",2030,"ERROR") -> 2030 | X19: =IF($I19="truck",($Q19*$W19*'MRV Calcs'!$E$7)+($W19*'MRV Calcs'!$E$8),0) -> 5.3594147 | Y19: =IF($I19="train",'MRV Calcs'!$E$24,0) -> 0 | Z19: =IF($I19="train",($Q19*$Y19*'MRV Calcs'!$E$7)+($Y19*'MRV Calcs'!$E$8),0) -> 0 | AA19: =IF($I19="train",'MRV Calcs'!$E$25,0) -> 0 | AB19: =IF($I19="train",($Q19*$AA19*'MRV Calcs'!$E$11)+($AA19*'MRV Calcs'!$E$12),0) -> 0 | AC19: =IF($I19="train",'MRV Calcs'!$E$26,0) -> 0 | AD19: =IF($I19="train",($Q19*$AC19*'MRV Calcs'!$E$7)+($AC19*'MRV Calcs'!$E$8),0) -> 0 | AE19: =($Q19/30)*SUM('MRV Calcs'!$E$15:$E$16) -> 3.0138869 | AF19: ='MRV Calcs'!$E$27 -> 71.2 | AG19: =(($Q19*1.1)*$AF19*'MRV Calcs'!$E$7)+($AF19*'MRV Calcs'!$E$8) -> 0.20622663 | AH19: =(($Q19*1.1)/20)*SUM('MRV Calcs'!$E$19:$E$20) -> 0.02803328 | AI19: =SUM(AH19,AG19,AE19,AD19,AB19,Z19,X19,V19) -> 11.553085 | AJ19: =U19-AI19 -> 18.138806 | AK19: =AJ19+AK18 -> 205.6362 | AL19: =AJ19/Q19 -> 0.91104 | AN19: =COUNTIF(Blends!H$4:H$1007,B19)+COUNTIF(Blends!J$4:J$1007,B19)+COUNTIF(#REF!,B19) -> 1 | AO19: =B19 -> 058T1R0 | AP19: Billing Docs Load 1309 PO 058T1R0.pdf | AQ19: =IFERROR(__xludf.DUMMYFUNCTION("AP19.url"),"https://drive.google.com/file/d/1riHpjmeVLgezFQv02eG1NhmUi8A_C8fG/view?usp=drive_link") -> https://drive.google.com/file/d/1riHpjmeVLgezFQv02eG1NhmUi8A_C8fG/view?usp=drive_link
A20: 19 | B20: 059T1R0 | D20: RS1-240501 | F20: paid | G20: NA | H20: AECN | I20: truck | K20: KAG | L20: Gus | N20: 45432 | O20: 45435 | Q20: 21.05 | S20: =iferror(if(AN20=1,VLOOKUP(B20, Blends!H$4:AK$1004,32,0), ""), "") | T20: 0.39 | U20: =Q20*T20*(44.01/12.011) -> 30.080767 | V20: =$Q20*('MRV Calcs'!$E$3+'MRV Calcs'!$E$4) -> 3.1141778 | W20: =IF(H20="AECN",2030,"ERROR") -> 2030 | X20: =IF($I20="truck",($Q20*$W20*'MRV Calcs'!$E$7)+($W20*'MRV Calcs'!$E$8),0) -> 5.6573615 | Y20: =IF($I20="train",'MRV Calcs'!$E$24,0) -> 0 | Z20: =IF($I20="train",($Q20*$Y20*'MRV Calcs'!$E$7)+($Y20*'MRV Calcs'!$E$8),0) -> 0 | AA20: =IF($I20="train",'MRV Calcs'!$E$25,0) -> 0 | AB20: =IF($I20="train",($Q20*$AA20*'MRV Calcs'!$E$11)+($AA20*'MRV Calcs'!$E$12),0) -> 0 | AC20: =IF($I20="train",'MRV Calcs'!$E$26,0) -> 0 | AD20: =IF($I20="train",($Q20*$AC20*'MRV Calcs'!$E$7)+($AC20*'MRV Calcs'!$E$8),0) -> 0 | AE20: =($Q20/30)*SUM('MRV Calcs'!$E$15:$E$16) -> 3.186455 | AF20: ='MRV Calcs'!$E$27 -> 71.2 | AG20: =(($Q20*1.1)*$AF20*'MRV Calcs'!$E$7)+($AF20*'MRV Calcs'!$E$8) -> 0.2177218 | AH20: =(($Q20*1.1)/20)*SUM('MRV Calcs'!$E$19:$E$20) -> 0.0296384 | AI20: =SUM(AH20,AG20,AE20,AD20,AB20,Z20,X20,V20) -> 12.205354 | AJ20: =U20-AI20 -> 17.875413 | AK20: =AJ20+AK19 -> 223.51162 | AL20: =AJ20/Q20 -> 0.84918826 | AN20: =COUNTIF(Blends!H$4:H$1007,B20)+COUNTIF(Blends!J$4:J$1007,B20)+COUNTIF(#REF!,B20) -> 1 | AO20: =B20 -> 059T1R0 | AP20: Billing documents 1310.pdf | AQ20: =IFERROR(__xludf.DUMMYFUNCTION("AP20.url"),"https://drive.google.com/file/d/1ShFxfOkxJobQHF9eu77bH2FUYq_iPV-s/view?usp=drive_link") -> https://drive.google.com/file/d/1ShFxfOkxJobQHF9eu77bH2FUYq_iPV-s/view?usp=drive_link
A21: 20 | B21: 070T1R0 | D21: RS1-240501 | F21: paid | G21: NA | H21: AECN | I21: truck | K21: Queensway Transport | L21: Paul/Stephen | N21: 45434 | O21: 45441 | Q21: 19.47 | S21: =iferror(if(AN21=1,VLOOKUP(B21, Blends!H$4:AK$1004,32,0), ""), "") | T21: 0.4017 | U21: =Q21*T21*(44.01/12.011) -> 28.657611 | V21: =$Q21*('MRV Calcs'!$E$3+'MRV Calcs'!$E$4) -> 2.8804295 | W21: =IF(H21="AECN",2030,"ERROR") -> 2030 | X21: =IF($I21="truck",($Q21*$W21*'MRV Calcs'!$E$7)+($W21*'MRV Calcs'!$E$8),0) -> 5.2444177 | Y21: =IF($I21="train",'MRV Calcs'!$E$24,0) -> 0 | Z21: =IF($I21="train",($Q21*$Y21*'MRV Calcs'!$E$7)+($Y21*'MRV Calcs'!$E$8),0) -> 0 | AA21: =IF($I21="train",'MRV Calcs'!$E$25,0) -> 0 | AB21: =IF($I21="train",($Q21*$AA21*'MRV Calcs'!$E$11)+($AA21*'MRV Calcs'!$E$12),0) -> 0 | AC21: =IF($I21="train",'MRV Calcs'!$E$26,0) -> 0 | AD21: =IF($I21="train",($Q21*$AC21*'MRV Calcs'!$E$7)+($AC21*'MRV Calcs'!$E$8),0) -> 0 | AE21: =($Q21/30)*SUM('MRV Calcs'!$E$15:$E$16) -> 2.9472816 | AF21: ='MRV Calcs'!$E$27 -> 71.2 | AG21: =(($Q21*1.1)*$AF21*'MRV Calcs'!$E$7)+($AF21*'MRV Calcs'!$E$8) -> 0.2017899 | AH21: =(($Q21*1.1)/20)*SUM('MRV Calcs'!$E$19:$E$20) -> 0.02741376 | AI21: =SUM(AH21,AG21,AE21,AD21,AB21,Z21,X21,V21) -> 11.301333 | AJ21: =U21-AI21 -> 17.356279 | AK21: =AJ21+AK20 -> 240.86789 | AL21: =AJ21/Q21 -> 0.89143701 | AN21: =COUNTIF(Blends!H$4:H$1007,B21)+COUNTIF(Blends!J$4:J$1007,B21)+COUNTIF(#REF!,B21) -> 1 | AO21: =B21 -> 070T1R0 | AP21: Billing Docs 1311 PO 070T1R0.pdf | AQ21: =IFERROR(__xludf.DUMMYFUNCTION("AP21.url"),"https://drive.google.com/file/d/12n_BN4HJhUWJHv4D6MPDmQFR5PZf9N0x/view?usp=drive_link") -> https://drive.google.com/file/d/12n_BN4HJhUWJHv4D6MPDmQFR5PZf9N0x/view?usp=drive_link
A22: 21 | B22: 069T1R0 | D22: RS1-240501 | F22: paid | G22: NA | H22: AECN | I22: truck | K22: KAG | L22: Darryl | N22: 45437 | O22: =IF(I22="truck",N22+4,IF(I22="train",N22+21,"")) -> 45441 | Q22: 20.25 | S22: =iferror(if(AN22=1,VLOOKUP(B22, Blends!H$4:AK$1004,32,0), ""), "") | T22: 0.4017 | U22: =Q22*T22*(44.01/12.011) -> 29.805682 | V22: =$Q22*('MRV Calcs'!$E$3+'MRV Calcs'!$E$4) -> 2.9958242 | W22: =IF(H22="AECN",2030,"ERROR") -> 2030 | X22: =IF($I22="truck",($Q22*$W22*'MRV Calcs'!$E$7)+($W22*'MRV Calcs'!$E$8),0) -> 5.448276 | Y22: =IF($I22="train",'MRV Calcs'!$E$24,0) -> 0 | Z22: =IF($I22="train",($Q22*$Y22*'MRV Calcs'!$E$7)+($Y22*'MRV Calcs'!$E$8),0) -> 0 | AA22: =IF($I22="train",'MRV Calcs'!$E$25,0) -> 0 | AB22: =IF($I22="train",($Q22*$AA22*'MRV Calcs'!$E$11)+($AA22*'MRV Calcs'!$E$12),0) -> 0 | AC22: =IF($I22="train",'MRV Calcs'!$E$26,0) -> 0 | AD22: =IF($I22="train",($Q22*$AC22*'MRV Calcs'!$E$7)+($AC22*'MRV Calcs'!$E$8),0) -> 0 | AE22: =($Q22/30)*SUM('MRV Calcs'!$E$15:$E$16) -> 3.0653545 | AF22: ='MRV Calcs'!$E$27 -> 71.2 | AG22: =(($Q22*1.1)*$AF22*'MRV Calcs'!$E$7)+($AF22*'MRV Calcs'!$E$8) -> 0.20965501 | AH22: =(($Q22*1.1)/20)*SUM('MRV Calcs'!$E$19:$E$20) -> 0.028512 | AI22: =SUM(AH22,AG22,AE22,AD22,AB22,Z22,X22,V22) -> 11.747622 | AJ22: =U22-AI22 -> 18.05806 | AK22: =AJ22+AK21 -> 258.92595 | AL22: =AJ22/Q22 -> 0.89175605 | AN22: =COUNTIF(Blends!H$4:H$1007,B22)+COUNTIF(Blends!J$4:J$1007,B22)+COUNTIF(#REF!,B22) -> 2 | AO22: =B22 -> 069T1R0 | AP22: Billing docs 1313.pdf | AQ22: =IFERROR(__xludf.DUMMYFUNCTION("AP22.url"),"https://drive.google.com/file/d/1IhkCrEpY71mN-XeHobUQ0SRvN5W_pdEX/view?usp=drive_link") -> https://drive.google.com/file/d/1IhkCrEpY71mN-XeHobUQ0SRvN5W_pdEX/view?usp=drive_link
A23: 22 | B23: 071T1R0 | D23: RS1-240501 | F23: paid | G23: NA | H23: AECN | I23: truck | K23: KAG | L23: Guy | N23: 45439 | O23: =IF(I23="truck",N23+4,IF(I23="train",N23+21,"")) -> 45443 | Q23: 19.98 | S23: =iferror(if(AN23=1,VLOOKUP(B23, Blends!H$4:AK$1004,32,0), ""), "") | U23: =Q23*T23*(44.01/12.011) -> 0 | V23: =$Q23*('MRV Calcs'!$E$3+'MRV Calcs'!$E$4) -> 2.9558799 | W23: =IF(H23="AECN",2030,"ERROR") -> 2030 | X23: =IF($I23="truck",($Q23*$W23*'MRV Calcs'!$E$7)+($W23*'MRV Calcs'!$E$8),0) -> 5.3777097 | Y23: =IF($I23="train",'MRV Calcs'!$E$24,0) -> 0 | Z23: =IF($I23="train",($Q23*$Y23*'MRV Calcs'!$E$7)+($Y23*'MRV Calcs'!$E$8),0) -> 0 | AA23: =IF($I23="train",'MRV Calcs'!$E$25,0) -> 0 | AB23: =IF($I23="train",($Q23*$AA23*'MRV Calcs'!$E$11)+($AA23*'MRV Calcs'!$E$12),0) -> 0 | AC23: =IF($I23="train",'MRV Calcs'!$E$26,0) -> 0 | AD23: =IF($I23="train",($Q23*$AC23*'MRV Calcs'!$E$7)+($AC23*'MRV Calcs'!$E$8),0) -> 0 | AE23: =($Q23/30)*SUM('MRV Calcs'!$E$15:$E$16) -> 3.0244832 | AF23: ='MRV Calcs'!$E$27 -> 71.2 | AG23: =(($Q23*1.1)*$AF23*'MRV Calcs'!$E$7)+($AF23*'MRV Calcs'!$E$8) -> 0.20693247 | AH23: =(($Q23*1.1)/20)*SUM('MRV Calcs'!$E$19:$E$20) -> 0.02813184 | AI23: =SUM(AH23,AG23,AE23,AD23,AB23,Z23,X23,V23) -> 11.593137 | AJ23: =U23-AI23 -> -11.593137 | AK23: =AJ23+AK22 -> 247.33282 | AL23: =AJ23/Q23 -> -0.58023709 | AN23: =COUNTIF(Blends!H$4:H$1007,B23)+COUNTIF(Blends!J$4:J$1007,B23)+COUNTIF(#REF!,B23) -> 0 | AO23: =B23 -> 071T1R0 | AP23: Billing docs 1313.pdf | AQ23: =IFERROR(__xludf.DUMMYFUNCTION("AP23.url"),"https://drive.google.com/file/d/1IhkCrEpY71mN-XeHobUQ0SRvN5W_pdEX/view?usp=drive_link") -> https://drive.google.com/file/d/1IhkCrEpY71mN-XeHobUQ0SRvN5W_pdEX/view?usp=drive_link
A24: 23 | B24: 072T1R0 | D24: RS1-240501 | F24: paid | G24: NA | H24: AECN | I24: truck | K24: Cherylann | L24: Renee/Mac | N24: 45440 | O24: 45447 | Q24: 20.21 | S24: =iferror(if(AN24=1,VLOOKUP(B24, Blends!H$4:AK$1004,32,0), ""), "") | U24: =Q24*T24*(44.01/12.011) -> 0 | V24: =$Q24*('MRV Calcs'!$E$3+'MRV Calcs'!$E$4) -> 2.9899066 | W24: =IF(H24="AECN",2030,"ERROR") -> 2030 | X24: =IF($I24="truck",($Q24*$W24*'MRV Calcs'!$E$7)+($W24*'MRV Calcs'!$E$8),0) -> 5.4378217 | Y24: =IF($I24="train",'MRV Calcs'!$E$24,0) -> 0 | Z24: =IF($I24="train",($Q24*$Y24*'MRV Calcs'!$E$7)+($Y24*'MRV Calcs'!$E$8),0) -> 0 | AA24: =IF($I24="train",'MRV Calcs'!$E$25,0) -> 0 | AB24: =IF($I24="train",($Q24*$AA24*'MRV Calcs'!$E$11)+($AA24*'MRV Calcs'!$E$12),0) -> 0 | AC24: =IF($I24="train",'MRV Calcs'!$E$26,0) -> 0 | AD24: =IF($I24="train",($Q24*$AC24*'MRV Calcs'!$E$7)+($AC24*'MRV Calcs'!$E$8),0) -> 0 | AE24: =($Q24/30)*SUM('MRV Calcs'!$E$15:$E$16) -> 3.0592995 | AF24: ='MRV Calcs'!$E$27 -> 71.2 | AG24: =(($Q24*1.1)*$AF24*'MRV Calcs'!$E$7)+($AF24*'MRV Calcs'!$E$8) -> 0.20925167 | AH24: =(($Q24*1.1)/20)*SUM('MRV Calcs'!$E$19:$E$20) -> 0.02845568 | AI24: =SUM(AH24,AG24,AE24,AD24,AB24,Z24,X24,V24) -> 11.724735 | AJ24: =U24-AI24 -> -11.724735 | AK24: =AJ24+AK23 -> 235.60808 | AL24: =AJ24/Q24 -> -0.58014523 | AN24: =COUNTIF(Blends!H$4:H$1007,B24)+COUNTIF(Blends!J$4:J$1007,B24)+COUNTIF(#REF!,B24) -> 1 | AO24: =B24 -> 072T1R0 | AP24: documents camion 1314.pdf | AQ24: =IFERROR(__xludf.DUMMYFUNCTION("AP24.url"),"https://drive.google.com/file/d/13NxUMAxcctmTThByx394I91302dhsO2P/view?usp=drive_link") -> https://drive.google.com/file/d/13NxUMAxcctmTThByx394I91302dhsO2P/view?usp=drive_link
A25: 24 | B25: 073T1R0 | D25: RS2-240504 | F25: paid | G25: NA | H25: AECN | I25: truck | K25: Cherylann | L25: Paul/Patrick | N25: 45442 | O25: 45448 | Q25: 20.18 | S25: =iferror(if(AN25=1,VLOOKUP(B25, Blends!H$4:AK$1004,32,0), ""), "") | U25: =Q25*T25*(44.01/12.011) -> 0 | V25: =$Q25*('MRV Calcs'!$E$3+'MRV Calcs'!$E$4) -> 2.9854683 | W25: =IF(H25="AECN",2030,"ERROR") -> 2030 | X25: =IF($I25="truck",($Q25*$W25*'MRV Calcs'!$E$7)+($W25*'MRV Calcs'!$E$8),0) -> 5.429981 | Y25: =IF($I25="train",'MRV Calcs'!$E$24,0) -> 0 | Z25: =IF($I25="train",($Q25*$Y25*'MRV Calcs'!$E$7)+($Y25*'MRV Calcs'!$E$8),0) -> 0 | AA25: =IF($I25="train",'MRV Calcs'!$E$25,0) -> 0 | AB25: =IF($I25="train",($Q25*$AA25*'MRV Calcs'!$E$11)+($AA25*'MRV Calcs'!$E$12),0) -> 0 | AC25: =IF($I25="train",'MRV Calcs'!$E$26,0) -> 0 | AD25: =IF($I25="train",($Q25*$AC25*'MRV Calcs'!$E$7)+($AC25*'MRV Calcs'!$E$8),0) -> 0 | AE25: =($Q25/30)*SUM('MRV Calcs'!$E$15:$E$16) -> 3.0547583 | AF25: ='MRV Calcs'!$E$27 -> 71.2 | AG25: =(($Q25*1.1)*$AF25*'MRV Calcs'!$E$7)+($AF25*'MRV Calcs'!$E$8) -> 0.20894917 | AH25: =(($Q25*1.1)/20)*SUM('MRV Calcs'!$E$19:$E$20) -> 0.02841344 | AI25: =SUM(AH25,AG25,AE25,AD25,AB25,Z25,X25,V25) -> 11.70757 | AJ25: =U25-AI25 -> -11.70757 | AK25: =AJ25+AK24 -> 223.90051 | AL25: =AJ25/Q25 -> -0.5801571 | AN25: =COUNTIF(Blends!H$4:H$1007,B25)+COUNTIF(Blends!J$4:J$1007,B25)+COUNTIF(#REF!,B25) -> 0 | AO25: =B25 -> 073T1R0 | AP25: Billing Documents 1315 Corrected P3.pdf | AQ25: =IFERROR(__xludf.DUMMYFUNCTION("AP25.url"),"https://drive.google.com/file/d/1-C_dWMhablbSrqyYqX8F-DUjV6eqze82/view?usp=drive_link") -> https://drive.google.com/file/d/1-C_dWMhablbSrqyYqX8F-DUjV6eqze82/view?usp=drive_link
A26: 25 | B26: 074T1R0 | D26: RS2-240504 | F26: paid | G26: NA | H26: AECN | I26: truck | K26: KAG | L26: Gus | N26: 45445 | O26: 45448 | Q26: 21.8 | S26: =iferror(if(AN26=1,VLOOKUP(B26, Blends!H$4:AK$1004,32,0), ""), "") | T26: 0.3907 | U26: =Q26*T26*(44.01/12.011) -> 31.208443 | V26: =$Q26*('MRV Calcs'!$E$3+'MRV Calcs'!$E$4) -> 3.2251342 | W26: =IF(H26="AECN",2030,"ERROR") -> 2030 | X26: =IF($I26="truck",($Q26*$W26*'MRV Calcs'!$E$7)+($W26*'MRV Calcs'!$E$8),0) -> 5.8533791 | Y26: =IF($I26="train",'MRV Calcs'!$E$24,0) -> 0 | Z26: =IF($I26="train",($Q26*$Y26*'MRV Calcs'!$E$7)+($Y26*'MRV Calcs'!$E$8),0) -> 0 | AA26: =IF($I26="train",'MRV Calcs'!$E$25,0) -> 0 | AB26: =IF($I26="train",($Q26*$AA26*'MRV Calcs'!$E$11)+($AA26*'MRV Calcs'!$E$12),0) -> 0 | AC26: =IF($I26="train",'MRV Calcs'!$E$26,0) -> 0 | AD26: =IF($I26="train",($Q26*$AC26*'MRV Calcs'!$E$7)+($AC26*'MRV Calcs'!$E$8),0) -> 0 | AE26: =($Q26/30)*SUM('MRV Calcs'!$E$15:$E$16) -> 3.2999866 | AF26: ='MRV Calcs'!$E$27 -> 71.2 | AG26: =(($Q26*1.1)*$AF26*'MRV Calcs'!$E$7)+($AF26*'MRV Calcs'!$E$8) -> 0.22528441 | AH26: =(($Q26*1.1)/20)*SUM('MRV Calcs'!$E$19:$E$20) -> 0.0306944 | AI26: =SUM(AH26,AG26,AE26,AD26,AB26,Z26,X26,V26) -> 12.634479 | AJ26: =U26-AI26 -> 18.573965 | AK26: =AJ26+AK25 -> 242.47448 | AL26: =AJ26/Q26 -> 0.85201672 | AN26: =COUNTIF(Blends!H$4:H$1007,B26)+COUNTIF(Blends!J$4:J$1007,B26)+COUNTIF(#REF!,B26) -> 2 | AO26: =B26 -> 074T1R0 | AP26: Billing documents Truck 1316.pdf | AQ26: =IFERROR(__xludf.DUMMYFUNCTION("AP26.url"),"https://drive.google.com/file/d/17uNOF88hLvhphw_1Diqh39l3RiRs7Sgw/view?usp=drive_link") -> https://drive.google.com/file/d/17uNOF88hLvhphw_1Diqh39l3RiRs7Sgw/view?usp=drive_link
A27: 26 | B27: 075T1R0 | D27: RS2-240504 | F27: paid | G27: NA | H27: AECN | I27: truck | K27: KAG | L27: Darryl | N27: 45446 | O27: 45449 | Q27: 20.42 | S27: =iferror(if(AN27=1,VLOOKUP(B27, Blends!H$4:AK$1004,32,0), ""), "") | T27: 0.3907 | U27: =Q27*T27*(44.01/12.011) -> 29.232863 | V27: =$Q27*('MRV Calcs'!$E$3+'MRV Calcs'!$E$4) -> 3.0209744 | W27: =IF(H27="AECN",2030,"ERROR") -> 2030 | X27: =IF($I27="truck",($Q27*$W27*'MRV Calcs'!$E$7)+($W27*'MRV Calcs'!$E$8),0) -> 5.4927067 | Y27: =IF($I27="train",'MRV Calcs'!$E$24,0) -> 0 | Z27: =IF($I27="train",($Q27*$Y27*'MRV Calcs'!$E$7)+($Y27*'MRV Calcs'!$E$8),0) -> 0 | AA27: =IF($I27="train",'MRV Calcs'!$E$25,0) -> 0 | AB27: =IF($I27="train",($Q27*$AA27*'MRV Calcs'!$E$11)+($AA27*'MRV Calcs'!$E$12),0) -> 0 | AC27: =IF($I27="train",'MRV Calcs'!$E$26,0) -> 0 | AD27: =IF($I27="train",($Q27*$AC27*'MRV Calcs'!$E$7)+($AC27*'MRV Calcs'!$E$8),0) -> 0 | AE27: =($Q27/30)*SUM('MRV Calcs'!$E$15:$E$16) -> 3.0910884 | AF27: ='MRV Calcs'!$E$27 -> 71.2 | AG27: =(($Q27*1.1)*$AF27*'MRV Calcs'!$E$7)+($AF27*'MRV Calcs'!$E$8) -> 0.21136921 | AH27: =(($Q27*1.1)/20)*SUM('MRV Calcs'!$E$19:$E$20) -> 0.02875136 | AI27: =SUM(AH27,AG27,AE27,AD27,AB27,Z27,X27,V27) -> 11.84489 | AJ27: =U27-AI27 -> 17.387973 | AK27: =AJ27+AK26 -> 259.86245 | AL27: =AJ27/Q27 -> 0.8515168 | AN27: =COUNTIF(Blends!H$4:H$1007,B27)+COUNTIF(Blends!J$4:J$1007,B27)+COUNTIF(#REF!,B27) -> 1 | AO27: =B27 -> 075T1R0 | AP27: Envoi des documents Camion 1317 Correction.pdf | AQ27: =IFERROR(__xludf.DUMMYFUNCTION("AP27.url"),"https://drive.google.com/file/d/1ixRHHTl7zI-DRoGQ6CfWJxFksCBt2eCm/view?usp=drive_link") -> https://drive.google.com/file/d/1ixRHHTl7zI-DRoGQ6CfWJxFksCBt2eCm/view?usp=drive_link
A28: 27 | B28: 076T1R0 | D28: RS2-240504 | F28: paid | G28: NA | H28: AECN | I28: truck | K28: KAG | L28: Raymond | N28: 45446 | O28: 45449 | Q28: 20.9 | S28: =iferror(if(AN28=1,VLOOKUP(B28, Blends!H$4:AK$1004,32,0), ""), "") | T28: 0.3907 | U28: =Q28*T28*(44.01/12.011) -> 29.920021 | V28: =$Q28*('MRV Calcs'!$E$3+'MRV Calcs'!$E$4) -> 3.0919865 | W28: =IF(H28="AECN",2030,"ERROR") -> 2030 | X28: =IF($I28="truck",($Q28*$W28*'MRV Calcs'!$E$7)+($W28*'MRV Calcs'!$E$8),0) -> 5.6181579 | Y28: =IF($I28="train",'MRV Calcs'!$E$24,0) -> 0 | Z28: =IF($I28="train",($Q28*$Y28*'MRV Calcs'!$E$7)+($Y28*'MRV Calcs'!$E$8),0) -> 0 | AA28: =IF($I28="train",'MRV Calcs'!$E$25,0) -> 0 | AB28: =IF($I28="train",($Q28*$AA28*'MRV Calcs'!$E$11)+($AA28*'MRV Calcs'!$E$12),0) -> 0 | AC28: =IF($I28="train",'MRV Calcs'!$E$26,0) -> 0 | AD28: =IF($I28="train",($Q28*$AC28*'MRV Calcs'!$E$7)+($AC28*'MRV Calcs'!$E$8),0) -> 0 | AE28: =($Q28/30)*SUM('MRV Calcs'!$E$15:$E$16) -> 3.1637486 | AF28: ='MRV Calcs'!$E$27 -> 71.2 | AG28: =(($Q28*1.1)*$AF28*'MRV Calcs'!$E$7)+($AF28*'MRV Calcs'!$E$8) -> 0.21620928 | AH28: =(($Q28*1.1)/20)*SUM('MRV Calcs'!$E$19:$E$20) -> 0.0294272 | AI28: =SUM(AH28,AG28,AE28,AD28,AB28,Z28,X28,V28) -> 12.11953 | AJ28: =U28-AI28 -> 17.800492 | AK28: =AJ28+AK27 -> 277.66294 | AL28: =AJ28/Q28 -> 0.85169817 | AN28: =COUNTIF(Blends!H$4:H$1007,B28)+COUNTIF(Blends!J$4:J$1007,B28)+COUNTIF(#REF!,B28) -> 1 | AO28: =B28 -> 076T1R0 | AP28: Envoi des documents Camion 1318 Correction.pdf | AQ28: =IFERROR(__xludf.DUMMYFUNCTION("AP28.url"),"https://drive.google.com/file/d/1MnFOnCrAD8vGM8g1RB_9LKq-SHYJp4NA/view?usp=drive_link") -> https://drive.google.com/file/d/1MnFOnCrAD8vGM8g1RB_9LKq-SHYJp4NA/view?usp=drive_link
A29: 28 | B29: 077T1R0 | D29: RS3-240607 | F29: paid | G29: NA | H29: AECN | I29: truck | K29: KAG | L29: Guy | N29: 45453 | O29: 45456 | Q29: 20.33 | S29: =iferror(if(AN29=1,VLOOKUP(B29, Blends!H$4:AK$1004,32,0), ""), "") | T29: 0.409 | U29: =Q29*T29*(44.01/12.011) -> 30.467224 | V29: =$Q29*('MRV Calcs'!$E$3+'MRV Calcs'!$E$4) -> 3.0076596 | W29: =IF(H29="AECN",2030,"ERROR") -> 2030 | X29: =IF($I29="truck",($Q29*$W29*'MRV Calcs'!$E$7)+($W29*'MRV Calcs'!$E$8),0) -> 5.4691846 | Y29: =IF($I29="train",'MRV Calcs'!$E$24,0) -> 0 | Z29: =IF($I29="train",($Q29*$Y29*'MRV Calcs'!$E$7)+($Y29*'MRV Calcs'!$E$8),0) -> 0 | AA29: =IF($I29="train",'MRV Calcs'!$E$25,0) -> 0 | AB29: =IF($I29="train",($Q29*$AA29*'MRV Calcs'!$E$11)+($AA29*'MRV Calcs'!$E$12),0) -> 0 | AC29: =IF($I29="train",'MRV Calcs'!$E$26,0) -> 0 | AD29: =IF($I29="train",($Q29*$AC29*'MRV Calcs'!$E$7)+($AC29*'MRV Calcs'!$E$8),0) -> 0 | AE29: =($Q29/30)*SUM('MRV Calcs'!$E$15:$E$16) -> 3.0774646 | AF29: ='MRV Calcs'!$E$27 -> 71.2 | AG29: =(($Q29*1.1)*$AF29*'MRV Calcs'!$E$7)+($AF29*'MRV Calcs'!$E$8) -> 0.21046169 | AH29: =(($Q29*1.1)/20)*SUM('MRV Calcs'!$E$19:$E$20) -> 0.02862464 | AI29: =SUM(AH29,AG29,AE29,AD29,AB29,Z29,X29,V29) -> 11.793395 | AJ29: =U29-AI29 -> 18.673829 | AK29: =AJ29+AK28 -> 296.33677 | AL29: =AJ29/Q29 -> 0.91853562 | AN29: =COUNTIF(Blends!H$4:H$1007,B29)+COUNTIF(Blends!J$4:J$1007,B29)+COUNTIF(#REF!,B29) -> 1 | AO29: =B29 -> 077T1R0 | AP29: Envoi des documents camion 1332.pdf | AQ29: =IFERROR(__xludf.DUMMYFUNCTION("AP29.url"),"https://drive.google.com/file/d/1X2Gy2qtnYVwewlcLSlqXQQ4tsNpo4ngZ/view?usp=drive_link") -> https://drive.google.com/file/d/1X2Gy2qtnYVwewlcLSlqXQQ4tsNpo4ngZ/view?usp=drive_link
A30: 29 | B30: 078T1R0 | D30: RS3-240607 | F30: paid | G30: NA | H30: AECN | I30: truck | K30: KAG | L30: Gus | N30: 45453 | O30: 45457 | Q30: 21.35 | S30: =iferror(if(AN30=1,VLOOKUP(B30, Blends!H$4:AK$1004,32,0), ""), "") | U30: =Q30*T30*(44.01/12.011) -> 0 | V30: =$Q30*('MRV Calcs'!$E$3+'MRV Calcs'!$E$4) -> 3.1585604 | W30: =IF(H30="AECN",2030,"ERROR") -> 2030 | X30: =IF($I30="truck",($Q30*$W30*'MRV Calcs'!$E$7)+($W30*'MRV Calcs'!$E$8),0) -> 5.7357685 | Y30: =IF($I30="train",'MRV Calcs'!$E$24,0) -> 0 | Z30: =IF($I30="train",($Q30*$Y30*'MRV Calcs'!$E$7)+($Y30*'MRV Calcs'!$E$8),0) -> 0 | AA30: =IF($I30="train",'MRV Calcs'!$E$25,0) -> 0 | AB30: =IF($I30="train",($Q30*$AA30*'MRV Calcs'!$E$11)+($AA30*'MRV Calcs'!$E$12),0) -> 0 | AC30: =IF($I30="train",'MRV Calcs'!$E$26,0) -> 0 | AD30: =IF($I30="train",($Q30*$AC30*'MRV Calcs'!$E$7)+($AC30*'MRV Calcs'!$E$8),0) -> 0 | AE30: =($Q30/30)*SUM('MRV Calcs'!$E$15:$E$16) -> 3.2318676 | AF30: ='MRV Calcs'!$E$27 -> 71.2 | AG30: =(($Q30*1.1)*$AF30*'MRV Calcs'!$E$7)+($AF30*'MRV Calcs'!$E$8) -> 0.22074684 | AH30: =(($Q30*1.1)/20)*SUM('MRV Calcs'!$E$19:$E$20) -> 0.0300608 | AI30: =SUM(AH30,AG30,AE30,AD30,AB30,Z30,X30,V30) -> 12.377004 | AJ30: =U30-AI30 -> -12.377004 | AK30: =AJ30+AK29 -> 283.95977 | AL30: =AJ30/Q30 -> -0.57971916 | AN30: =COUNTIF(Blends!H$4:H$1007,B30)+COUNTIF(Blends!J$4:J$1007,B30)+COUNTIF(#REF!,B30) -> 2 | AO30: =B30 -> 078T1R0 | AP30: Envoi des documents camion 1333.pdf | AQ30: =IFERROR(__xludf.DUMMYFUNCTION("AP30.url"),"https://drive.google.com/file/d/1O4pLKPKPg7vfYcejoZyapVlunJfHYmhq/view?usp=drive_link") -> https://drive.google.com/file/d/1O4pLKPKPg7vfYcejoZyapVlunJfHYmhq/view?usp=drive_link
A31: 30 | B31: 079T1R0 | D31: RS1-240609 | F31: paid | G31: NA | H31: AECN | I31: truck | K31: KAG | L31: Darryl | N31: 45454 | O31: 45457 | Q31: 20.64 | S31: =iferror(if(AN31=1,VLOOKUP(B31, Blends!H$4:AK$1004,32,0), ""), "") | U31: =Q31*T31*(44.01/12.011) -> 0 | V31: =$Q31*('MRV Calcs'!$E$3+'MRV Calcs'!$E$4) -> 3.0535216 | W31: =IF(H31="AECN",2030,"ERROR") -> 2030 | X31: =IF($I31="truck",($Q31*$W31*'MRV Calcs'!$E$7)+($W31*'MRV Calcs'!$E$8),0) -> 5.5502052 | Y31: =IF($I31="train",'MRV Calcs'!$E$24,0) -> 0 | Z31: =IF($I31="train",($Q31*$Y31*'MRV Calcs'!$E$7)+($Y31*'MRV Calcs'!$E$8),0) -> 0 | AA31: =IF($I31="train",'MRV Calcs'!$E$25,0) -> 0 | AB31: =IF($I31="train",($Q31*$AA31*'MRV Calcs'!$E$11)+($AA31*'MRV Calcs'!$E$12),0) -> 0 | AC31: =IF($I31="train",'MRV Calcs'!$E$26,0) -> 0 | AD31: =IF($I31="train",($Q31*$AC31*'MRV Calcs'!$E$7)+($AC31*'MRV Calcs'!$E$8),0) -> 0 | AE31: =($Q31/30)*SUM('MRV Calcs'!$E$15:$E$16) -> 3.124391 | AF31: ='MRV Calcs'!$E$27 -> 71.2 | AG31: =(($Q31*1.1)*$AF31*'MRV Calcs'!$E$7)+($AF31*'MRV Calcs'!$E$8) -> 0.21358757 | AH31: =(($Q31*1.1)/20)*SUM('MRV Calcs'!$E$19:$E$20) -> 0.02906112 | AI31: =SUM(AH31,AG31,AE31,AD31,AB31,Z31,X31,V31) -> 11.970766 | AJ31: =U31-AI31 -> -11.970766 | AK31: =AJ31+AK30 -> 271.989 | AL31: =AJ31/Q31 -> -0.579979 | AN31: =COUNTIF(Blends!H$4:H$1007,B31)+COUNTIF(Blends!J$4:J$1007,B31)+COUNTIF(#REF!,B31) -> 2 | AO31: =B31 -> 079T1R0 | AP31: Billing documents 1336.pdf | AQ31: =IFERROR(__xludf.DUMMYFUNCTION("AP31.url"),"https://drive.google.com/file/d/1PMm4mPO6wTzuSfG50ZJYwKVCSfMj7Ld9/view?usp=drive_link") -> https://drive.google.com/file/d/1PMm4mPO6wTzuSfG50ZJYwKVCSfMj7Ld9/view?usp=drive_link
A32: 31 | B32: 080T1R0 | D32: RS1-240609 | F32: paid | G32: NA | H32: AECN | I32: truck | K32: KAG | L32: Raymond | N32: 45454 | O32: 45457 | Q32: 20.55 | S32: =iferror(if(AN32=1,VLOOKUP(B32, Blends!H$4:AK$1004,32,0), ""), "") | U32: =Q32*T32*(44.01/12.011) -> 0 | V32: =$Q32*('MRV Calcs'!$E$3+'MRV Calcs'!$E$4) -> 3.0402068 | W32: =IF(H32="AECN",2030,"ERROR") -> 2030 | X32: =IF($I32="truck",($Q32*$W32*'MRV Calcs'!$E$7)+($W32*'MRV Calcs'!$E$8),0) -> 5.5266831 | Y32: =IF($I32="train",'MRV Calcs'!$E$24,0) -> 0 | Z32: =IF($I32="train",($Q32*$Y32*'MRV Calcs'!$E$7)+($Y32*'MRV Calcs'!$E$8),0) -> 0 | AA32: =IF($I32="train",'MRV Calcs'!$E$25,0) -> 0 | AB32: =IF($I32="train",($Q32*$AA32*'MRV Calcs'!$E$11)+($AA32*'MRV Calcs'!$E$12),0) -> 0 | AC32: =IF($I32="train",'MRV Calcs'!$E$26,0) -> 0 | AD32: =IF($I32="train",($Q32*$AC32*'MRV Calcs'!$E$7)+($AC32*'MRV Calcs'!$E$8),0) -> 0 | AE32: =($Q32/30)*SUM('MRV Calcs'!$E$15:$E$16) -> 3.1107672 | AF32: ='MRV Calcs'!$E$27 -> 71.2 | AG32: =(($Q32*1.1)*$AF32*'MRV Calcs'!$E$7)+($AF32*'MRV Calcs'!$E$8) -> 0.21268006 | AH32: =(($Q32*1.1)/20)*SUM('MRV Calcs'!$E$19:$E$20) -> 0.0289344 | AI32: =SUM(AH32,AG32,AE32,AD32,AB32,Z32,X32,V32) -> 11.919272 | AJ32: =U32-AI32 -> -11.919272 | AK32: =AJ32+AK31 -> 260.06973 | AL32: =AJ32/Q32 -> -0.58001321 | AN32: =COUNTIF(Blends!H$4:H$1007,B32)+COUNTIF(Blends!J$4:J$1007,B32)+COUNTIF(#REF!,B32) -> 2 | AO32: =B32 -> 080T1R0 | AP32: Envoi des documents truck 1338.pdf | AQ32: =IFERROR(__xludf.DUMMYFUNCTION("AP32.url"),"https://drive.google.com/file/d/1hfTxljZLrN-NZoaiI1t659WvYefkqYun/view?usp=drive_link") -> https://drive.google.com/file/d/1hfTxljZLrN-NZoaiI1t659WvYefkqYun/view?usp=drive_link
A33: 32 | B33: 081T1R0 | D33: RS1-240617 | F33: paid | G33: NA | H33: AECN | I33: truck | K33: KAG | L33: Gus | N33: 45464 | O33: 45468 | Q33: 21.26 | S33: =iferror(if(AN33=1,VLOOKUP(B33, Blends!H$4:AK$1004,32,0), ""), "") | U33: =Q33*T33*(44.01/12.011) -> 0 | V33: =$Q33*('MRV Calcs'!$E$3+'MRV Calcs'!$E$4) -> 3.1452456 | W33: =IF(H33="AECN",2030,"ERROR") -> 2030 | X33: =IF($I33="truck",($Q33*$W33*'MRV Calcs'!$E$7)+($W33*'MRV Calcs'!$E$8),0) -> 5.7122464 | Y33: =IF($I33="train",'MRV Calcs'!$E$24,0) -> 0 | Z33: =IF($I33="train",($Q33*$Y33*'MRV Calcs'!$E$7)+($Y33*'MRV Calcs'!$E$8),0) -> 0 | AA33: =IF($I33="train",'MRV Calcs'!$E$25,0) -> 0 | AB33: =IF($I33="train",($Q33*$AA33*'MRV Calcs'!$E$11)+($AA33*'MRV Calcs'!$E$12),0) -> 0 | AC33: =IF($I33="train",'MRV Calcs'!$E$26,0) -> 0 | AD33: =IF($I33="train",($Q33*$AC33*'MRV Calcs'!$E$7)+($AC33*'MRV Calcs'!$E$8),0) -> 0 | AE33: =($Q33/30)*SUM('MRV Calcs'!$E$15:$E$16) -> 3.2182438 | AF33: ='MRV Calcs'!$E$27 -> 71.2 | AG33: =(($Q33*1.1)*$AF33*'MRV Calcs'!$E$7)+($AF33*'MRV Calcs'!$E$8) -> 0.21983933 | AH33: =(($Q33*1.1)/20)*SUM('MRV Calcs'!$E$19:$E$20) -> 0.02993408 | AI33: =SUM(AH33,AG33,AE33,AD33,AB33,Z33,X33,V33) -> 12.325509 | AJ33: =U33-AI33 -> -12.325509 | AK33: =AJ33+AK32 -> 247.74422 | AL33: =AJ33/Q33 -> -0.57975114 | AN33: =COUNTIF(Blends!H$4:H$1007,B33)+COUNTIF(Blends!J$4:J$1007,B33)+COUNTIF(#REF!,B33) -> 0 | AO33: =B33 -> 081T1R0 | AP33: Envoi des documents Camion 1370.pdf | AQ33: =IFERROR(__xludf.DUMMYFUNCTION("AP33.url"),"https://drive.google.com/file/d/1qc0SfU6CrYEqCOUyi2dSwZrlTyg0eq_m/view?usp=drive_link") -> https://drive.google.com/file/d/1qc0SfU6CrYEqCOUyi2dSwZrlTyg0eq_m/view?usp=drive_link
A34: 33 | B34: 060-62T2R6 | D34: RS1-240617; RS3-240613 | F34: paid | G34: TRUE | H34: AECN | I34: train | K34: Watco | L34: GATX 032974 | N34: 45471 | O34: 45530 | Q34: =26.34+27.51+27.44 -> 81.29 | S34: =iferror(if(AN34=1,VLOOKUP(B34, Blends!H$4:AK$1004,32,0), ""), "") | T34: 0.3933 | U34: =Q34*T34*(44.01/12.011) -> 117.14757 | V34: =$Q34*('MRV Calcs'!$E$3+'MRV Calcs'!$E$4) -> 12.0262 | W34: =IF(H34="AECN",2030,"ERROR") -> 2030 | X34: =IF($I34="truck",($Q34*$W34*'MRV Calcs'!$E$7)+($W34*'MRV Calcs'!$E$8),0) -> 0 | Y34: =IF($I34="train",'MRV Calcs'!$E$24,0) -> 107.497 | Z34: =IF($I34="train",($Q34*$Y34*'MRV Calcs'!$E$7)+($Y34*'MRV Calcs'!$E$8),0) -> 1.1332988 | AA34: =IF($I34="train",'MRV Calcs'!$E$25,0) -> 2087 | AB34: =IF($I34="train",($Q34*$AA34*'MRV Calcs'!$E$11)+($AA34*'MRV Calcs'!$E$12),0) -> 4.5385362 | AC34: =IF($I34="train",'MRV Calcs'!$E$26,0) -> 32.6 | AD34: =IF($I34="train",($Q34*$AC34*'MRV Calcs'!$E$7)+($AC34*'MRV Calcs'!$E$8),0) -> 0.34368905 | AE34: =($Q34/30)*SUM('MRV Calcs'!$E$15:$E$16) -> 12.305317 | AF34: ='MRV Calcs'!$E$27 -> 71.2 | AG34: =(($Q34*1.1)*$AF34*'MRV Calcs'!$E$7)+($AF34*'MRV Calcs'!$E$8) -> 0.82515068 | AH34: =(($Q34*1.1)/20)*SUM('MRV Calcs'!$E$19:$E$20) -> 0.11445632 | AI34: =SUM(AH34,AG34,AE34,AD34,AB34,Z34,X34,V34) -> 31.286648 | AJ34: =U34-AI34 -> 85.860918 | AK34: =AJ34+AK33 -> 333.60514 | AL34: =AJ34/Q34 -> 1.0562298 | AN34: =COUNTIF(Blends!H$4:H$1007,B34)+COUNTIF(Blends!J$4:J$1007,B34)+COUNTIF(#REF!,B34) -> 6 | AO34: =B34 -> 060-62T2R6 | AP34: 060T2R1-062T2R1 6/20-6/21 Pickups GATX032974 | AQ34: =IFERROR(__xludf.DUMMYFUNCTION("AP34.url"),"https://drive.google.com/drive/folders/1PH2j_8KGpG5VSyDZlozK_yuQSUTJUWtL?usp=drive_link") -> https://drive.google.com/drive/folders/1PH2j_8KGpG5VSyDZlozK_yuQSUTJUWtL?usp=drive_link
A35: 34 | B35: 063-65T2R6 | D35: RS2- 240623 | F35: paid | G35: TRUE | H35: AECN | I35: train | K35: Watco | L35: GATX 032959 | N35: 45484 | O35: 45502 | Q35: =27.2+27.08+27.17 -> 81.45 | S35: =iferror(if(AN35=1,VLOOKUP(B35, Blends!H$4:AK$1004,32,0), ""), "") | T35: 0.389 | U35: =Q35*T35*(44.01/12.011) -> 116.09483 | V35: =$Q35*('MRV Calcs'!$E$3+'MRV Calcs'!$E$4) -> 12.049871 | W35: =IF(H35="AECN",2030,"ERROR") -> 2030 | X35: =IF($I35="truck",($Q35*$W35*'MRV Calcs'!$E$7)+($W35*'MRV Calcs'!$E$8),0) -> 0 | Y35: =IF($I35="train",'MRV Calcs'!$E$24,0) -> 107.497 | Z35: =IF($I35="train",($Q35*$Y35*'MRV Calcs'!$E$7)+($Y35*'MRV Calcs'!$E$8),0) -> 1.1355132 | AA35: =IF($I35="train",'MRV Calcs'!$E$25,0) -> 2087 | AB35: =IF($I35="train",($Q35*$AA35*'MRV Calcs'!$E$11)+($AA35*'MRV Calcs'!$E$12),0) -> 4.5472419 | AC35: =IF($I35="train",'MRV Calcs'!$E$26,0) -> 32.6 | AD35: =IF($I35="train",($Q35*$AC35*'MRV Calcs'!$E$7)+($AC35*'MRV Calcs'!$E$8),0) -> 0.3443606 | AE35: =($Q35/30)*SUM('MRV Calcs'!$E$15:$E$16) -> 12.329537 | AF35: ='MRV Calcs'!$E$27 -> 71.2 | AG35: =(($Q35*1.1)*$AF35*'MRV Calcs'!$E$7)+($AF35*'MRV Calcs'!$E$8) -> 0.82676403 | AH35: =(($Q35*1.1)/20)*SUM('MRV Calcs'!$E$19:$E$20) -> 0.1146816 | AI35: =SUM(AH35,AG35,AE35,AD35,AB35,Z35,X35,V35) -> 31.347969 | AJ35: =U35-AI35 -> 84.746864 | AK35: =AJ35+AK34 -> 418.352 | AL35: =AJ35/Q35 -> 1.0404771 | AN35: =COUNTIF(Blends!H$4:H$1007,B35)+COUNTIF(Blends!J$4:J$1007,B35)+COUNTIF(#REF!,B35) -> 6 | AO35: =B35 -> 063-65T2R6 | AP35: 063T2R5-065T2R5 6/26-6/27 Pickups GATX032959 | AQ35: =IFERROR(__xludf.DUMMYFUNCTION("AP35.url"),"https://drive.google.com/drive/folders/17w-3YR6ZBPNIIBji7MOKDdpGShbkVgQ_?usp=drive_link") -> https://drive.google.com/drive/folders/17w-3YR6ZBPNIIBji7MOKDdpGShbkVgQ_?usp=drive_link
A36: 35 | B36: 066-68T2R6 | D36: RS3-240626 | F36: paid | G36: TRUE | H36: AECN | I36: train | K36: Watco | L36: GATX 032958 | N36: 45491 | O36: 45551 | Q36: =27.16+27.2+27.3 -> 81.66 | S36: =iferror(if(AN36=1,VLOOKUP(B36, Blends!H$4:AK$1004,32,0), ""), "") | T36: 0.3907 | U36: =Q36*T36*(44.01/12.011) -> 116.90282 | V36: =$Q36*('MRV Calcs'!$E$3+'MRV Calcs'!$E$4) -> 12.080939 | W36: =IF(H36="AECN",2030,"ERROR") -> 2030 | X36: =IF($I36="truck",($Q36*$W36*'MRV Calcs'!$E$7)+($W36*'MRV Calcs'!$E$8),0) -> 0 | Y36: =IF($I36="train",'MRV Calcs'!$E$24,0) -> 107.497 | Z36: =IF($I36="train",($Q36*$Y36*'MRV Calcs'!$E$7)+($Y36*'MRV Calcs'!$E$8),0) -> 1.1384196 | AA36: =IF($I36="train",'MRV Calcs'!$E$25,0) -> 2087 | AB36: =IF($I36="train",($Q36*$AA36*'MRV Calcs'!$E$11)+($AA36*'MRV Calcs'!$E$12),0) -> 4.5586682 | AC36: =IF($I36="train",'MRV Calcs'!$E$26,0) -> 32.6 | AD36: =IF($I36="train",($Q36*$AC36*'MRV Calcs'!$E$7)+($AC36*'MRV Calcs'!$E$8),0) -> 0.345242 | AE36: =($Q36/30)*SUM('MRV Calcs'!$E$15:$E$16) -> 12.361326 | AF36: ='MRV Calcs'!$E$27 -> 71.2 | AG36: =(($Q36*1.1)*$AF36*'MRV Calcs'!$E$7)+($AF36*'MRV Calcs'!$E$8) -> 0.82888156 | AH36: =(($Q36*1.1)/20)*SUM('MRV Calcs'!$E$19:$E$20) -> 0.11497728 | AI36: =SUM(AH36,AG36,AE36,AD36,AB36,Z36,X36,V36) -> 31.428453 | AJ36: =U36-AI36 -> 85.474367 | AK36: =AJ36+AK35 -> 503.82637 | AL36: =AJ36/Q36 -> 1.0467103 | AN36: =COUNTIF(Blends!H$4:H$1007,B36)+COUNTIF(Blends!J$4:J$1007,B36)+COUNTIF(#REF!,B36) -> 3 | AO36: =B36 -> 066-68T2R6 | AP36: 066T2R6-068T2R6 Jun 27 & Jun 28 Pickups GATX032958 | AQ36: =IFERROR(__xludf.DUMMYFUNCTION("AP36.url"),"https://drive.google.com/drive/folders/18DvSrD2-auzpulJQ-JdiCIwl846b_5nh?usp=drive_link") -> https://drive.google.com/drive/folders/18DvSrD2-auzpulJQ-JdiCIwl846b_5nh?usp=drive_link
A37: 36 | B37: JulyRAIL1-3 | C37: 1400, 1402, 1404 | D37: RS1-240629; RS1-240702 | F37: paid | G37: TRUE | H37: AECN | I37: train | K37: Watco | L37: GATX 032975 | N37: 45499 | O37: 45561 | Q37: =27.27+26.31+27.15 -> 80.73 | S37: =iferror(if(AN37=1,VLOOKUP(B37, Blends!H$4:AK$1004,32,0), ""), "") | U37: =Q37*T37*(44.01/12.011) -> 0 | V37: =$Q37*('MRV Calcs'!$E$3+'MRV Calcs'!$E$4) -> 11.943353 | W37: =IF(H37="AECN",2030,"ERROR") -> 2030 | X37: =IF($I37="truck",($Q37*$W37*'MRV Calcs'!$E$7)+($W37*'MRV Calcs'!$E$8),0) -> 0 | Y37: =IF($I37="train",'MRV Calcs'!$E$24,0) -> 107.497 | Z37: =IF($I37="train",($Q37*$Y37*'MRV Calcs'!$E$7)+($Y37*'MRV Calcs'!$E$8),0) -> 1.1255485 | AA37: =IF($I37="train",'MRV Calcs'!$E$25,0) -> 2087 | AB37: =IF($I37="train",($Q37*$AA37*'MRV Calcs'!$E$11)+($AA37*'MRV Calcs'!$E$12),0) -> 4.5080661 | AC37: =IF($I37="train",'MRV Calcs'!$E$26,0) -> 32.6 | AD37: =IF($I37="train",($Q37*$AC37*'MRV Calcs'!$E$7)+($AC37*'MRV Calcs'!$E$8),0) -> 0.34133864 | AE37: =($Q37/30)*SUM('MRV Calcs'!$E$15:$E$16) -> 12.220547 | AF37: ='MRV Calcs'!$E$27 -> 71.2 | AG37: =(($Q37*1.1)*$AF37*'MRV Calcs'!$E$7)+($AF37*'MRV Calcs'!$E$8) -> 0.81950393 | AH37: =(($Q37*1.1)/20)*SUM('MRV Calcs'!$E$19:$E$20) -> 0.11366784 | AI37: =SUM(AH37,AG37,AE37,AD37,AB37,Z37,X37,V37) -> 31.072024 | AJ37: =U37-AI37 -> -31.072024 | AK37: =AJ37+AK36 -> 472.75434 | AL37: =AJ37/Q37 -> -0.3848882 | AN37: =COUNTIF(Blends!H$4:H$1007,B37)+COUNTIF(Blends!J$4:J$1007,B37)+COUNTIF(#REF!,B37) -> 0 | AO37: =B37 -> JulyRAIL1-3
A38: 37 | B38: JulyRAIL4-6 | C38: 1409, 1406, 1412 | D38: RS2-240702 | F38: paid | G38: TRUE | H38: AECN | I38: train | K38: Watco | L38: STPX 094626 | N38: 45514 | O38: 45572 | Q38: =26.46+27.13+26.42 -> 80.01 | S38: =iferror(if(AN38=1,VLOOKUP(B38, Blends!H$4:AK$1004,32,0), ""), "") | U38: =Q38*T38*(44.01/12.011) -> 0 | V38: =$Q38*('MRV Calcs'!$E$3+'MRV Calcs'!$E$4) -> 11.836834 | W38: =IF(H38="AECN",2030,"ERROR") -> 2030 | X38: =IF($I38="truck",($Q38*$W38*'MRV Calcs'!$E$7)+($W38*'MRV Calcs'!$E$8),0) -> 0 | Y38: =IF($I38="train",'MRV Calcs'!$E$24,0) -> 107.497 | Z38: =IF($I38="train",($Q38*$Y38*'MRV Calcs'!$E$7)+($Y38*'MRV Calcs'!$E$8),0) -> 1.1155837 | AA38: =IF($I38="train",'MRV Calcs'!$E$25,0) -> 2087 | AB38: =IF($I38="train",($Q38*$AA38*'MRV Calcs'!$E$11)+($AA38*'MRV Calcs'!$E$12),0) -> 4.4688904 | AC38: =IF($I38="train",'MRV Calcs'!$E$26,0) -> 32.6 | AD38: =IF($I38="train",($Q38*$AC38*'MRV Calcs'!$E$7)+($AC38*'MRV Calcs'!$E$8),0) -> 0.33831669 | AE38: =($Q38/30)*SUM('MRV Calcs'!$E$15:$E$16) -> 12.111556 | AF38: ='MRV Calcs'!$E$27 -> 71.2 | AG38: =(($Q38*1.1)*$AF38*'MRV Calcs'!$E$7)+($AF38*'MRV Calcs'!$E$8) -> 0.81224382 | AH38: =(($Q38*1.1)/20)*SUM('MRV Calcs'!$E$19:$E$20) -> 0.11265408 | AI38: =SUM(AH38,AG38,AE38,AD38,AB38,Z38,X38,V38) -> 30.79608 | AJ38: =U38-AI38 -> -30.79608 | AK38: =AJ38+AK37 -> 441.95826 | AL38: =AJ38/Q38 -> -0.38490288 | AN38: =COUNTIF(Blends!H$4:H$1007,B38)+COUNTIF(Blends!J$4:J$1007,B38)+COUNTIF(#REF!,B38) -> 0 | AO38: =B38 -> JulyRAIL4-6
A39: 38 | B39: JulyRAIL7-9 | C39: 1425, 1426, 1428 | D39: RS2-240707 | F39: paid | G39: TRUE | H39: AECN | I39: train | K39: Watco | L39: GATX 032955 | N39: 45498 | O39: 45565 | Q39: =26.12+26.45+26.17 -> 78.74 | S39: =iferror(if(AN39=1,VLOOKUP(B39, Blends!H$4:AK$1004,32,0), ""), "") | U39: =Q39*T39*(44.01/12.011) -> 0 | V39: =$Q39*('MRV Calcs'!$E$3+'MRV Calcs'!$E$4) -> 11.648948 | W39: =IF(H39="AECN",2030,"ERROR") -> 2030 | X39: =IF($I39="truck",($Q39*$W39*'MRV Calcs'!$E$7)+($W39*'MRV Calcs'!$E$8),0) -> 0 | Y39: =IF($I39="train",'MRV Calcs'!$E$24,0) -> 107.497 | Z39: =IF($I39="train",($Q39*$Y39*'MRV Calcs'!$E$7)+($Y39*'MRV Calcs'!$E$8),0) -> 1.098007 | AA39: =IF($I39="train",'MRV Calcs'!$E$25,0) -> 2087 | AB39: =IF($I39="train",($Q39*$AA39*'MRV Calcs'!$E$11)+($AA39*'MRV Calcs'!$E$12),0) -> 4.3997886 | AC39: =IF($I39="train",'MRV Calcs'!$E$26,0) -> 32.6 | AD39: =IF($I39="train",($Q39*$AC39*'MRV Calcs'!$E$7)+($AC39*'MRV Calcs'!$E$8),0) -> 0.3329863 | AE39: =($Q39/30)*SUM('MRV Calcs'!$E$15:$E$16) -> 11.919309 | AF39: ='MRV Calcs'!$E$27 -> 71.2 | AG39: =(($Q39*1.1)*$AF39*'MRV Calcs'!$E$7)+($AF39*'MRV Calcs'!$E$8) -> 0.7994378 | AH39: =(($Q39*1.1)/20)*SUM('MRV Calcs'!$E$19:$E$20) -> 0.11086592 | AI39: =SUM(AH39,AG39,AE39,AD39,AB39,Z39,X39,V39) -> 30.309343 | AJ39: =U39-AI39 -> -30.309343 | AK39: =AJ39+AK38 -> 411.64892 | AL39: =AJ39/Q39 -> -0.38492943 | AN39: =COUNTIF(Blends!H$4:H$1007,B39)+COUNTIF(Blends!J$4:J$1007,B39)+COUNTIF(#REF!,B39) -> 0 | AO39: =B39 -> JulyRAIL7-9
A40: 39 | B40: JulyRAIL 2 1-3 | C40: 1466, 1532, 1533 | D40: RS1-240815-1 | F40: paid | G40: TRUE | H40: AECN | I40: train | K40: Watco | L40: GATX 070118 | N40: 45551 | O40: 45583 | Q40: =26.66+26.36+26.71 -> 79.73 | S40: =iferror(if(AN40=1,VLOOKUP(B40, Blends!H$4:AK$1004,32,0), ""), "") | U40: =Q40*T40*(44.01/12.011) -> 0 | V40: =$Q40*('MRV Calcs'!$E$3+'MRV Calcs'!$E$4) -> 11.795411 | W40: =IF(H40="AECN",2030,"ERROR") -> 2030 | X40: =IF($I40="truck",($Q40*$W40*'MRV Calcs'!$E$7)+($W40*'MRV Calcs'!$E$8),0) -> 0 | Y40: =IF($I40="train",'MRV Calcs'!$E$24,0) -> 107.497 | Z40: =IF($I40="train",($Q40*$Y40*'MRV Calcs'!$E$7)+($Y40*'MRV Calcs'!$E$8),0) -> 1.1117085 | AA40: =IF($I40="train",'MRV Calcs'!$E$25,0) -> 2087 | AB40: =IF($I40="train",($Q40*$AA40*'MRV Calcs'!$E$11)+($AA40*'MRV Calcs'!$E$12),0) -> 4.4536553 | AC40: =IF($I40="train",'MRV Calcs'!$E$26,0) -> 32.6 | AD40: =IF($I40="train",($Q40*$AC40*'MRV Calcs'!$E$7)+($AC40*'MRV Calcs'!$E$8),0) -> 0.33714148 | AE40: =($Q40/30)*SUM('MRV Calcs'!$E$15:$E$16) -> 12.069171 | AF40: ='MRV Calcs'!$E$27 -> 71.2 | AG40: =(($Q40*1.1)*$AF40*'MRV Calcs'!$E$7)+($AF40*'MRV Calcs'!$E$8) -> 0.80942045 | AH40: =(($Q40*1.1)/20)*SUM('MRV Calcs'!$E$19:$E$20) -> 0.11225984 | AI40: =SUM(AH40,AG40,AE40,AD40,AB40,Z40,X40,V40) -> 30.688768 | AJ40: =U40-AI40 -> -30.688768 | AK40: =AJ40+AK39 -> 380.96015 | AL40: =AJ40/Q40 -> -0.38490866 | AN40: =COUNTIF(Blends!H$4:H$1007,B40)+COUNTIF(Blends!J$4:J$1007,B40)+COUNTIF(#REF!,B40) -> 0 | AO40: =B40 -> JulyRAIL 2 1-3
A41: 40 | B41: August2024Rail1-3 | C41: 1536, 1548, 1550 | D41: RS1-240815-1; RS2-240822-1 | F41: paid | G41: TRUE | H41: AECN | I41: train | K41: Watco | L41: GATX 003395 | N41: 45551 | O41: 45587 | Q41: =26.38+26.76+26.77 -> 79.91 | S41: =iferror(if(AN41=1,VLOOKUP(B41, Blends!H$4:AK$1004,32,0), ""), "") | U41: =Q41*T41*(44.01/12.011) -> 0 | V41: =$Q41*('MRV Calcs'!$E$3+'MRV Calcs'!$E$4) -> 11.82204 | W41: =IF(H41="AECN",2030,"ERROR") -> 2030 | X41: =IF($I41="truck",($Q41*$W41*'MRV Calcs'!$E$7)+($W41*'MRV Calcs'!$E$8),0) -> 0 | Y41: =IF($I41="train",'MRV Calcs'!$E$24,0) -> 107.497 | Z41: =IF($I41="train",($Q41*$Y41*'MRV Calcs'!$E$7)+($Y41*'MRV Calcs'!$E$8),0) -> 1.1141997 | AA41: =IF($I41="train",'MRV Calcs'!$E$25,0) -> 2087 | AB41: =IF($I41="train",($Q41*$AA41*'MRV Calcs'!$E$11)+($AA41*'MRV Calcs'!$E$12),0) -> 4.4634493 | AC41: =IF($I41="train",'MRV Calcs'!$E$26,0) -> 32.6 | AD41: =IF($I41="train",($Q41*$AC41*'MRV Calcs'!$E$7)+($AC41*'MRV Calcs'!$E$8),0) -> 0.33789697 | AE41: =($Q41/30)*SUM('MRV Calcs'!$E$15:$E$16) -> 12.096419 | AF41: ='MRV Calcs'!$E$27 -> 71.2 | AG41: =(($Q41*1.1)*$AF41*'MRV Calcs'!$E$7)+($AF41*'MRV Calcs'!$E$8) -> 0.81123547 | AH41: =(($Q41*1.1)/20)*SUM('MRV Calcs'!$E$19:$E$20) -> 0.11251328 | AI41: =SUM(AH41,AG41,AE41,AD41,AB41,Z41,X41,V41) -> 30.757754 | AJ41: =U41-AI41 -> -30.757754 | AK41: =AJ41+AK40 -> 350.2024 | AL41: =AJ41/Q41 -> -0.38490494 | AN41: =COUNTIF(Blends!H$4:H$1007,B41)+COUNTIF(Blends!J$4:J$1007,B41)+COUNTIF(#REF!,B41) -> 0 | AO41: =B41 -> August2024Rail1-3
A42: 41 | B42: August2024Rail4-6 | C42: 1605, 1607, 1610 | D42: RS3-240913-1; RS2-240916-1 | F42: paid | G42: TRUE | H42: AECN | I42: train | K42: Watco | L42: GATX 070110 | N42: 45562 | O42: =N42+24 -> 45586 | Q42: =26.63+26.67+26.66 -> 79.96 | S42: =iferror(if(AN42=1,VLOOKUP(B42, Blends!H$4:AK$1004,32,0), ""), "") | U42: =Q42*T42*(44.01/12.011) -> 0 | V42: =$Q42*('MRV Calcs'!$E$3+'MRV Calcs'!$E$4) -> 11.829437 | W42: =IF(H42="AECN",2030,"ERROR") -> 2030 | X42: =IF($I42="truck",($Q42*$W42*'MRV Calcs'!$E$7)+($W42*'MRV Calcs'!$E$8),0) -> 0 | Y42: =IF($I42="train",'MRV Calcs'!$E$24,0) -> 107.497 | Z42: =IF($I42="train",($Q42*$Y42*'MRV Calcs'!$E$7)+($Y42*'MRV Calcs'!$E$8),0) -> 1.1148917 | AA42: =IF($I42="train",'MRV Calcs'!$E$25,0) -> 2087 | AB42: =IF($I42="train",($Q42*$AA42*'MRV Calcs'!$E$11)+($AA42*'MRV Calcs'!$E$12),0) -> 4.4661698 | AC42: =IF($I42="train",'MRV Calcs'!$E$26,0) -> 32.6 | AD42: =IF($I42="train",($Q42*$AC42*'MRV Calcs'!$E$7)+($AC42*'MRV Calcs'!$E$8),0) -> 0.33810683 | AE42: =($Q42/30)*SUM('MRV Calcs'!$E$15:$E$16) -> 12.103988 | AF42: ='MRV Calcs'!$E$27 -> 71.2 | AG42: =(($Q42*1.1)*$AF42*'MRV Calcs'!$E$7)+($AF42*'MRV Calcs'!$E$8) -> 0.81173965 | AH42: =(($Q42*1.1)/20)*SUM('MRV Calcs'!$E$19:$E$20) -> 0.11258368 | AI42: =SUM(AH42,AG42,AE42,AD42,AB42,Z42,X42,V42) -> 30.776917 | AJ42: =U42-AI42 -> -30.776917 | AK42: =AJ42+AK41 -> 319.42548 | AL42: =AJ42/Q42 -> -0.38490391 | AN42: =COUNTIF(Blends!H$4:H$1007,B42)+COUNTIF(Blends!J$4:J$1007,B42)+COUNTIF(#REF!,B42) -> 0 | AO42: =B42 -> August2024Rail4-6
A43: 42 | B43: Oct2024Rail1-3 | C43: 1648, 1651, 1653 | D43: RS2-241001-1; RS3-241002-1 | F43: paid | G43: TRUE | H43: AECN | I43: train | K43: Watco | L43: STPX 094624 | N43: 45569 | O43: =N43+24 -> 45593 | Q43: =26.76+26.45+25.14 -> 78.35 | S43: =iferror(if(AN43=1,VLOOKUP(B43, Blends!H$4:AK$1004,32,0), ""), "") | U43: =Q43*T43*(44.01/12.011) -> 0 | V43: =$Q43*('MRV Calcs'!$E$3+'MRV Calcs'!$E$4) -> 11.591251 | W43: =IF(H43="AECN",2030,"ERROR") -> 2030 | X43: =IF($I43="truck",($Q43*$W43*'MRV Calcs'!$E$7)+($W43*'MRV Calcs'!$E$8),0) -> 0 | Y43: =IF($I43="train",'MRV Calcs'!$E$24,0) -> 107.497 | Z43: =IF($I43="train",($Q43*$Y43*'MRV Calcs'!$E$7)+($Y43*'MRV Calcs'!$E$8),0) -> 1.0926094 | AA43: =IF($I43="train",'MRV Calcs'!$E$25,0) -> 2087 | AB43: =IF($I43="train",($Q43*$AA43*'MRV Calcs'!$E$11)+($AA43*'MRV Calcs'!$E$12),0) -> 4.3785684 | AC43: =IF($I43="train",'MRV Calcs'!$E$26,0) -> 32.6 | AD43: =IF($I43="train",($Q43*$AC43*'MRV Calcs'!$E$7)+($AC43*'MRV Calcs'!$E$8),0) -> 0.3313494 | AE43: =($Q43/30)*SUM('MRV Calcs'!$E$15:$E$16) -> 11.860273 | AF43: ='MRV Calcs'!$E$27 -> 71.2 | AG43: =(($Q43*1.1)*$AF43*'MRV Calcs'!$E$7)+($AF43*'MRV Calcs'!$E$8) -> 0.79550524 | AH43: =(($Q43*1.1)/20)*SUM('MRV Calcs'!$E$19:$E$20) -> 0.1103168 | AI43: =SUM(AH43,AG43,AE43,AD43,AB43,Z43,X43,V43) -> 30.159873 | AJ43: =U43-AI43 -> -30.159873 | AK43: =AJ43+AK42 -> 289.26561 | AL43: =AJ43/Q43 -> -0.38493775 | AN43: =COUNTIF(Blends!H$4:H$1007,B43)+COUNTIF(Blends!J$4:J$1007,B43)+COUNTIF(#REF!,B43) -> 0 | AO43: =B43 -> Oct2024Rail1-3
A44: 43 | B44: Oct2024Rail4-6 | C44: 1655, 1657, 1659 | D44: RS3-241002-1 | F44: paid | G44: TRUE | H44: AECN | I44: train | K44: Watco | L44: STPX 094627 | N44: 45575 | O44: =N44+24 -> 45599 | Q44: =26.74+26.16+26.67 -> 79.57 | S44: =iferror(if(AN44=1,VLOOKUP(B44, Blends!H$4:AK$1004,32,0), ""), "") | U44: =Q44*T44*(44.01/12.011) -> 0 | V44: =$Q44*('MRV Calcs'!$E$3+'MRV Calcs'!$E$4) -> 11.77174 | W44: =IF(H44="AECN",2030,"ERROR") -> 2030 | X44: =IF($I44="truck",($Q44*$W44*'MRV Calcs'!$E$7)+($W44*'MRV Calcs'!$E$8),0) -> 0 | Y44: =IF($I44="train",'MRV Calcs'!$E$24,0) -> 107.497 | Z44: =IF($I44="train",($Q44*$Y44*'MRV Calcs'!$E$7)+($Y44*'MRV Calcs'!$E$8),0) -> 1.1094941 | AA44: =IF($I44="train",'MRV Calcs'!$E$25,0) -> 2087 | AB44: =IF($I44="train",($Q44*$AA44*'MRV Calcs'!$E$11)+($AA44*'MRV Calcs'!$E$12),0) -> 4.4449496 | AC44: =IF($I44="train",'MRV Calcs'!$E$26,0) -> 32.6 | AD44: =IF($I44="train",($Q44*$AC44*'MRV Calcs'!$E$7)+($AC44*'MRV Calcs'!$E$8),0) -> 0.33646994 | AE44: =($Q44/30)*SUM('MRV Calcs'!$E$15:$E$16) -> 12.044951 | AF44: ='MRV Calcs'!$E$27 -> 71.2 | AG44: =(($Q44*1.1)*$AF44*'MRV Calcs'!$E$7)+($AF44*'MRV Calcs'!$E$8) -> 0.80780709 | AH44: =(($Q44*1.1)/20)*SUM('MRV Calcs'!$E$19:$E$20) -> 0.11203456 | AI44: =SUM(AH44,AG44,AE44,AD44,AB44,Z44,X44,V44) -> 30.627446 | AJ44: =U44-AI44 -> -30.627446 | AK44: =AJ44+AK43 -> 258.63816 | AL44: =AJ44/Q44 -> -0.38491198 | AN44: =COUNTIF(Blends!H$4:H$1007,B44)+COUNTIF(Blends!J$4:J$1007,B44)+COUNTIF(#REF!,B44) -> 1 | AO44: =B44 -> Oct2024Rail4-6
A45: 44 | B45: Oct2024Truck 1 | C45: 1711 | D45: RS3-241022-1 | F45: payment processing | G45: NA | H45: AECN | I45: truck | K45: KAG | L45: Gus | N45: 45590 | O45: 45594 | Q45: 21.34 | S45: =iferror(if(AN45=1,VLOOKUP(B45, Blends!H$4:AK$1004,32,0), ""), "") | U45: =Q45*T45*(44.01/12.011) -> 0 | V45: =$Q45*('MRV Calcs'!$E$3+'MRV Calcs'!$E$4) -> 3.1570809 | W45: =IF(H45="AECN",2030,"ERROR") -> 2030 | X45: =IF($I45="truck",($Q45*$W45*'MRV Calcs'!$E$7)+($W45*'MRV Calcs'!$E$8),0) -> 5.7331549 | Y45: =IF($I45="train",'MRV Calcs'!$E$24,0) -> 0 | Z45: =IF($I45="train",($Q45*$Y45*'MRV Calcs'!$E$7)+($Y45*'MRV Calcs'!$E$8),0) -> 0 | AA45: =IF($I45="train",'MRV Calcs'!$E$25,0) -> 0 | AB45: =IF($I45="train",($Q45*$AA45*'MRV Calcs'!$E$11)+($AA45*'MRV Calcs'!$E$12),0) -> 0 | AC45: =IF($I45="train",'MRV Calcs'!$E$26,0) -> 0 | AD45: =IF($I45="train",($Q45*$AC45*'MRV Calcs'!$E$7)+($AC45*'MRV Calcs'!$E$8),0) -> 0 | AE45: =($Q45/30)*SUM('MRV Calcs'!$E$15:$E$16) -> 3.2303539 | AF45: ='MRV Calcs'!$E$27 -> 71.2 | AG45: =(($Q45*1.1)*$AF45*'MRV Calcs'!$E$7)+($AF45*'MRV Calcs'!$E$8) -> 0.22064601 | AH45: =(($Q45*1.1)/20)*SUM('MRV Calcs'!$E$19:$E$20) -> 0.03004672 | AI45: =SUM(AH45,AG45,AE45,AD45,AB45,Z45,X45,V45) -> 12.371282 | AJ45: =U45-AI45 -> -12.371282 | AK45: =AJ45+AK44 -> 246.26688 | AL45: =AJ45/Q45 -> -0.5797227 | AN45: =COUNTIF(Blends!H$4:H$1007,B45)+COUNTIF(Blends!J$4:J$1007,B45)+COUNTIF(#REF!,B45) -> 1 | AO45: =B45 -> Oct2024Truck 1
A46: 45 | B46: Oct2024Rail 7-9 | C46: 1702, 1703, 1704 | D46: RS2-241018-1 | F46: payment processing | G46: TRUE | H46: AECN | I46: train | K46: Watco | L46: STPX 094625 | N46: 45590 | O46: =N46+24 -> 45614 | Q46: =26.83+26.71+26.76 -> 80.3 | S46: =iferror(if(AN46=1,VLOOKUP(B46, Blends!H$4:AK$1004,32,0), ""), "") | U46: =Q46*T46*(44.01/12.011) -> 0 | V46: =$Q46*('MRV Calcs'!$E$3+'MRV Calcs'!$E$4) -> 11.879738 | W46: =IF(H46="AECN",2030,"ERROR") -> 2030 | X46: =IF($I46="truck",($Q46*$W46*'MRV Calcs'!$E$7)+($W46*'MRV Calcs'!$E$8),0) -> 0 | Y46: =IF($I46="train",'MRV Calcs'!$E$24,0) -> 107.497 | Z46: =IF($I46="train",($Q46*$Y46*'MRV Calcs'!$E$7)+($Y46*'MRV Calcs'!$E$8),0) -> 1.1195973 | AA46: =IF($I46="train",'MRV Calcs'!$E$25,0) -> 2087 | AB46: =IF($I46="train",($Q46*$AA46*'MRV Calcs'!$E$11)+($AA46*'MRV Calcs'!$E$12),0) -> 4.4846695 | AC46: =IF($I46="train",'MRV Calcs'!$E$26,0) -> 32.6 | AD46: =IF($I46="train",($Q46*$AC46*'MRV Calcs'!$E$7)+($AC46*'MRV Calcs'!$E$8),0) -> 0.33953386 | AE46: =($Q46/30)*SUM('MRV Calcs'!$E$15:$E$16) -> 12.155455 | AF46: ='MRV Calcs'!$E$27 -> 71.2 | AG46: =(($Q46*1.1)*$AF46*'MRV Calcs'!$E$7)+($AF46*'MRV Calcs'!$E$8) -> 0.81516803 | AH46: =(($Q46*1.1)/20)*SUM('MRV Calcs'!$E$19:$E$20) -> 0.1130624 | AI46: =SUM(AH46,AG46,AE46,AD46,AB46,Z46,X46,V46) -> 30.907224 | AJ46: =U46-AI46 -> -30.907224 | AK46: =AJ46+AK44 -> 227.73094 | AL46: =AJ46/Q46 -> -0.38489694 | AN46: =COUNTIF(Blends!H$4:H$1007,B46)+COUNTIF(Blends!J$4:J$1007,B46)+COUNTIF(#REF!,B46) -> 0 | AO46: =B46 -> Oct2024Rail 7-9
A47: 46 | B47: Oct2024Rail10-12 | C47: 1705, 1706, 1707 | D47: RS2-241018-1 | F47: payment processing | G47: TRUE | H47: AECN | I47: train | K47: Watco | L47: GATX 032959 | N47: 45597 | O47: =N47+24 -> 45621 | Q47: =26.67+26.75+26.83 -> 80.25 | S47: =iferror(if(AN47=1,VLOOKUP(B47, Blends!H$4:AK$1004,32,0), ""), "") | U47: =Q47*T47*(44.01/12.011) -> 0 | V47: =$Q47*('MRV Calcs'!$E$3+'MRV Calcs'!$E$4) -> 11.87234 | W47: =IF(H47="AECN",2030,"ERROR") -> 2030 | X47: =IF($I47="truck",($Q47*$W47*'MRV Calcs'!$E$7)+($W47*'MRV Calcs'!$E$8),0) -> 0 | Y47: =IF($I47="train",'MRV Calcs'!$E$24,0) -> 107.497 | Z47: =IF($I47="train",($Q47*$Y47*'MRV Calcs'!$E$7)+($Y47*'MRV Calcs'!$E$8),0) -> 1.1189053 | AA47: =IF($I47="train",'MRV Calcs'!$E$25,0) -> 2087 | AB47: =IF($I47="train",($Q47*$AA47*'MRV Calcs'!$E$11)+($AA47*'MRV Calcs'!$E$12),0) -> 4.481949 | AC47: =IF($I47="train",'MRV Calcs'!$E$26,0) -> 32.6 | AD47: =IF($I47="train",($Q47*$AC47*'MRV Calcs'!$E$7)+($AC47*'MRV Calcs'!$E$8),0) -> 0.339324 | AE47: =($Q47/30)*SUM('MRV Calcs'!$E$15:$E$16) -> 12.147887 | AF47: ='MRV Calcs'!$E$27 -> 71.2 | AG47: =(($Q47*1.1)*$AF47*'MRV Calcs'!$E$7)+($AF47*'MRV Calcs'!$E$8) -> 0.81466386 | AH47: =(($Q47*1.1)/20)*SUM('MRV Calcs'!$E$19:$E$20) -> 0.112992 | AI47: =SUM(AH47,AG47,AE47,AD47,AB47,Z47,X47,V47) -> 30.888061 | AJ47: =U47-AI47 -> -30.888061 | AK47: =AJ47+AK46 -> 196.84288 | AL47: =AJ47/Q47 -> -0.38489796 | AN47: =COUNTIF(Blends!H$4:H$1007,B47)+COUNTIF(Blends!J$4:J$1007,B47)+COUNTIF(#REF!,B47) -> 0 | AO47: =B47 -> Oct2024Rail10-12
A48: 47 | B48: Oct2024Rail2 1-3 | C48: 1708, 1720, 1721 | D48: RS2-241018-1; RS1-241026-1 | F48: paid | G48: FALSE | H48: AECN | I48: train | K48: Watco | L48: GATX 032974 | N48: 45597 | O48: =N48+24 -> 45621 | Q48: =26.67+26.62+26.67 -> 79.96 | S48: =iferror(if(AN48=1,VLOOKUP(B48, Blends!H$4:AK$1004,32,0), ""), "") | U48: =Q48*T48*(44.01/12.011) -> 0 | V48: =$Q48*('MRV Calcs'!$E$3+'MRV Calcs'!$E$4) -> 11.829437 | W48: =IF(H48="AECN",2030,"ERROR") -> 2030 | X48: =IF($I48="truck",($Q48*$W48*'MRV Calcs'!$E$7)+($W48*'MRV Calcs'!$E$8),0) -> 0 | Y48: =IF($I48="train",'MRV Calcs'!$E$24,0) -> 107.497 | Z48: =IF($I48="train",($Q48*$Y48*'MRV Calcs'!$E$7)+($Y48*'MRV Calcs'!$E$8),0) -> 1.1148917 | AA48: =IF($I48="train",'MRV Calcs'!$E$25,0) -> 2087 | AB48: =IF($I48="train",($Q48*$AA48*'MRV Calcs'!$E$11)+($AA48*'MRV Calcs'!$E$12),0) -> 4.4661698 | AC48: =IF($I48="train",'MRV Calcs'!$E$26,0) -> 32.6 | AD48: =IF($I48="train",($Q48*$AC48*'MRV Calcs'!$E$7)+($AC48*'MRV Calcs'!$E$8),0) -> 0.33810683 | AE48: =($Q48/30)*SUM('MRV Calcs'!$E$15:$E$16) -> 12.103988 | AF48: ='MRV Calcs'!$E$27 -> 71.2 | AG48: =(($Q48*1.1)*$AF48*'MRV Calcs'!$E$7)+($AF48*'MRV Calcs'!$E$8) -> 0.81173965 | AH48: =(($Q48*1.1)/20)*SUM('MRV Calcs'!$E$19:$E$20) -> 0.11258368 | AI48: =SUM(AH48,AG48,AE48,AD48,AB48,Z48,X48,V48) -> 30.776917 | AJ48: =U48-AI48 -> -30.776917 | AK48: =AJ48+AK47 -> 166.06596 | AL48: =AJ48/Q48 -> -0.38490391 | AN48: =COUNTIF(Blends!H$4:H$1007,B48)+COUNTIF(Blends!J$4:J$1007,B48)+COUNTIF(#REF!,B48) -> 0 | AO48: =B48 -> Oct2024Rail2 1-3
A49: 48 | B49: Nov2024Truck 1 | C49: 1745 | D49: RS3-241104-1 | F49: payment processing | G49: NA | H49: AECN | I49: truck | K49: KAG | L49: Gus | N49: 45603 | O49: 45607 | Q49: 21.31 | S49: =iferror(if(AN49=1,VLOOKUP(B49, Blends!H$4:AK$1004,32,0), ""), "") | U49: =Q49*T49*(44.01/12.011) -> 0 | V49: =$Q49*('MRV Calcs'!$E$3+'MRV Calcs'!$E$4) -> 3.1526427 | W49: =IF(H49="AECN",2030,"ERROR") -> 2030 | X49: =IF($I49="truck",($Q49*$W49*'MRV Calcs'!$E$7)+($W49*'MRV Calcs'!$E$8),0) -> 5.7253142 | Y49: =IF($I49="train",'MRV Calcs'!$E$24,0) -> 0 | Z49: =IF($I49="train",($Q49*$Y49*'MRV Calcs'!$E$7)+($Y49*'MRV Calcs'!$E$8),0) -> 0 | AA49: =IF($I49="train",'MRV Calcs'!$E$25,0) -> 0 | AB49: =IF($I49="train",($Q49*$AA49*'MRV Calcs'!$E$11)+($AA49*'MRV Calcs'!$E$12),0) -> 0 | AC49: =IF($I49="train",'MRV Calcs'!$E$26,0) -> 0 | AD49: =IF($I49="train",($Q49*$AC49*'MRV Calcs'!$E$7)+($AC49*'MRV Calcs'!$E$8),0) -> 0 | AE49: =($Q49/30)*SUM('MRV Calcs'!$E$15:$E$16) -> 3.2258126 | AF49: ='MRV Calcs'!$E$27 -> 71.2 | AG49: =(($Q49*1.1)*$AF49*'MRV Calcs'!$E$7)+($AF49*'MRV Calcs'!$E$8) -> 0.2203435 | AH49: =(($Q49*1.1)/20)*SUM('MRV Calcs'!$E$19:$E$20) -> 0.03000448 | AI49: =SUM(AH49,AG49,AE49,AD49,AB49,Z49,X49,V49) -> 12.354118 | AJ49: =U49-AI49 -> -12.354118 | AK49: =AJ49+AK48 -> 153.71184 | AL49: =AJ49/Q49 -> -0.57973334
A50: 49 | B50: Nov2024Truck 2 | C50: 1752 | D50: RS1-241107-1 | F50: paid | G50: TRUE | H50: AECN | I50: truck | K50: Contrans | L50: Jacob | N50: 45607 | O50: 45610 | Q50: 20.35 | S50: =iferror(if(AN50=1,VLOOKUP(B50, Blends!H$4:AK$1004,32,0), ""), "") | U50: =Q50*T50*(44.01/12.011) -> 0 | V50: =$Q50*('MRV Calcs'!$E$3+'MRV Calcs'!$E$4) -> 3.0106184 | W50: =IF(H50="AECN",2030,"ERROR") -> 2030 | X50: =IF($I50="truck",($Q50*$W50*'MRV Calcs'!$E$7)+($W50*'MRV Calcs'!$E$8),0) -> 5.4744117 | Y50: =IF($I50="train",'MRV Calcs'!$E$24,0) -> 0 | Z50: =IF($I50="train",($Q50*$Y50*'MRV Calcs'!$E$7)+($Y50*'MRV Calcs'!$E$8),0) -> 0 | AA50: =IF($I50="train",'MRV Calcs'!$E$25,0) -> 0 | AB50: =IF($I50="train",($Q50*$AA50*'MRV Calcs'!$E$11)+($AA50*'MRV Calcs'!$E$12),0) -> 0 | AC50: =IF($I50="train",'MRV Calcs'!$E$26,0) -> 0 | AD50: =IF($I50="train",($Q50*$AC50*'MRV Calcs'!$E$7)+($AC50*'MRV Calcs'!$E$8),0) -> 0 | AE50: =($Q50/30)*SUM('MRV Calcs'!$E$15:$E$16) -> 3.0804921 | AF50: ='MRV Calcs'!$E$27 -> 71.2 | AG50: =(($Q50*1.1)*$AF50*'MRV Calcs'!$E$7)+($AF50*'MRV Calcs'!$E$8) -> 0.21066336 | AH50: =(($Q50*1.1)/20)*SUM('MRV Calcs'!$E$19:$E$20) -> 0.0286528 | AI50: =SUM(AH50,AG50,AE50,AD50,AB50,Z50,X50,V50) -> 11.804838 | AJ50: =U50-AI50 -> -11.804838 | AK50: =AJ50+AK49 -> 141.907 | AL50: =AJ50/Q50 -> -0.58009034
A51: 50 | B51: Nov2024Truck 3 | C51: 1753 | D51: RS1-241107-1 | F51: paid | G51: TRUE | H51: AECN | I51: truck | K51: Contrans | L51: Mike | N51: 45607 | O51: 45610 | Q51: 20.07 | S51: =iferror(if(AN51=1,VLOOKUP(B51, Blends!H$4:AK$1004,32,0), ""), "") | U51: =Q51*T51*(44.01/12.011) -> 0 | V51: =$Q51*('MRV Calcs'!$E$3+'MRV Calcs'!$E$4) -> 2.9691947 | W51: =IF(H51="AECN",2030,"ERROR") -> 2030 | X51: =IF($I51="truck",($Q51*$W51*'MRV Calcs'!$E$7)+($W51*'MRV Calcs'!$E$8),0) -> 5.4012318 | Y51: =IF($I51="train",'MRV Calcs'!$E$24,0) -> 0 | Z51: =IF($I51="train",($Q51*$Y51*'MRV Calcs'!$E$7)+($Y51*'MRV Calcs'!$E$8),0) -> 0 | AA51: =IF($I51="train",'MRV Calcs'!$E$25,0) -> 0 | AB51: =IF($I51="train",($Q51*$AA51*'MRV Calcs'!$E$11)+($AA51*'MRV Calcs'!$E$12),0) -> 0 | AC51: =IF($I51="train",'MRV Calcs'!$E$26,0) -> 0 | AD51: =IF($I51="train",($Q51*$AC51*'MRV Calcs'!$E$7)+($AC51*'MRV Calcs'!$E$8),0) -> 0 | AE51: =($Q51/30)*SUM('MRV Calcs'!$E$15:$E$16) -> 3.038107 | AF51: ='MRV Calcs'!$E$27 -> 71.2 | AG51: =(($Q51*1.1)*$AF51*'MRV Calcs'!$E$7)+($AF51*'MRV Calcs'!$E$8) -> 0.20783999 | AH51: =(($Q51*1.1)/20)*SUM('MRV Calcs'!$E$19:$E$20) -> 0.02825856 | AI51: =SUM(AH51,AG51,AE51,AD51,AB51,Z51,X51,V51) -> 11.644632 | AJ51: =U51-AI51 -> -11.644632 | AK51: =AJ51+AK50 -> 130.26237 | AL51: =AJ51/Q51 -> -0.5802009
A52: 51 | B52: Nov2024Truck 4 | C52: 1754 | D52: RS1-241107-1 | F52: paid | G52: TRUE | H52: AECN | I52: truck | K52: Contrans | L52: Luc | N52: 45608 | O52: 45611 | Q52: 20.71 | S52: =iferror(if(AN52=1,VLOOKUP(B52, Blends!H$4:AK$1004,32,0), ""), "") | U52: =Q52*T52*(44.01/12.011) -> 0 | V52: =$Q52*('MRV Calcs'!$E$3+'MRV Calcs'!$E$4) -> 3.0638775 | W52: =IF(H52="AECN",2030,"ERROR") -> 2030 | X52: =IF($I52="truck",($Q52*$W52*'MRV Calcs'!$E$7)+($W52*'MRV Calcs'!$E$8),0) -> 5.5685002 | Y52: =IF($I52="train",'MRV Calcs'!$E$24,0) -> 0 | Z52: =IF($I52="train",($Q52*$Y52*'MRV Calcs'!$E$7)+($Y52*'MRV Calcs'!$E$8),0) -> 0 | AA52: =IF($I52="train",'MRV Calcs'!$E$25,0) -> 0 | AB52: =IF($I52="train",($Q52*$AA52*'MRV Calcs'!$E$11)+($AA52*'MRV Calcs'!$E$12),0) -> 0 | AC52: =IF($I52="train",'MRV Calcs'!$E$26,0) -> 0 | AD52: =IF($I52="train",($Q52*$AC52*'MRV Calcs'!$E$7)+($AC52*'MRV Calcs'!$E$8),0) -> 0 | AE52: =($Q52/30)*SUM('MRV Calcs'!$E$15:$E$16) -> 3.1349873 | AF52: ='MRV Calcs'!$E$27 -> 71.2 | AG52: =(($Q52*1.1)*$AF52*'MRV Calcs'!$E$7)+($AF52*'MRV Calcs'!$E$8) -> 0.21429341 | AH52: =(($Q52*1.1)/20)*SUM('MRV Calcs'!$E$19:$E$20) -> 0.02915968 | AI52: =SUM(AH52,AG52,AE52,AD52,AB52,Z52,X52,V52) -> 12.010818 | AJ52: =U52-AI52 -> -12.010818 | AK52: =AJ52+AK51 -> 118.25155 | AL52: =AJ52/Q52 -> -0.57995259
A53: 52 | B53: Nov2024Truck 5 | C53: 1755 | D53: RS1-241107-1 | F53: paid | G53: TRUE | H53: AECN | I53: truck | K53: Contrans | L53: Gord | N53: 45608 | O53: 45611 | Q53: 19.88 | S53: =iferror(if(AN53=1,VLOOKUP(B53, Blends!H$4:AK$1004,32,0), ""), "") | U53: =Q53*T53*(44.01/12.011) -> 0 | V53: =$Q53*('MRV Calcs'!$E$3+'MRV Calcs'!$E$4) -> 2.9410857 | W53: =IF(H53="AECN",2030,"ERROR") -> 2030 | X53: =IF($I53="truck",($Q53*$W53*'MRV Calcs'!$E$7)+($W53*'MRV Calcs'!$E$8),0) -> 5.351574 | Y53: =IF($I53="train",'MRV Calcs'!$E$24,0) -> 0 | Z53: =IF($I53="train",($Q53*$Y53*'MRV Calcs'!$E$7)+($Y53*'MRV Calcs'!$E$8),0) -> 0 | AA53: =IF($I53="train",'MRV Calcs'!$E$25,0) -> 0 | AB53: =IF($I53="train",($Q53*$AA53*'MRV Calcs'!$E$11)+($AA53*'MRV Calcs'!$E$12),0) -> 0 | AC53: =IF($I53="train",'MRV Calcs'!$E$26,0) -> 0 | AD53: =IF($I53="train",($Q53*$AC53*'MRV Calcs'!$E$7)+($AC53*'MRV Calcs'!$E$8),0) -> 0 | AE53: =($Q53/30)*SUM('MRV Calcs'!$E$15:$E$16) -> 3.0093456 | AF53: ='MRV Calcs'!$E$27 -> 71.2 | AG53: =(($Q53*1.1)*$AF53*'MRV Calcs'!$E$7)+($AF53*'MRV Calcs'!$E$8) -> 0.20592413 | AH53: =(($Q53*1.1)/20)*SUM('MRV Calcs'!$E$19:$E$20) -> 0.02799104 | AI53: =SUM(AH53,AG53,AE53,AD53,AB53,Z53,X53,V53) -> 11.53592 | AJ53: =U53-AI53 -> -11.53592 | AK53: =AJ53+AK52 -> 106.71563 | AL53: =AJ53/Q53 -> -0.58027769
A54: 53 | B54: Nov2024Truck 6 | C54: 1758 | D54: RS1-241107-1 | F54: paid | G54: NA | H54: AECN | I54: truck | K54: KAG | L54: Andrew | N54: 45608 | O54: 45615 | Q54: 20.62 | U54: =Q54*T54*(44.01/12.011) -> 0 | V54: =$Q54*('MRV Calcs'!$E$3+'MRV Calcs'!$E$4) -> 3.0505628 | W54: =IF(H54="AECN",2030,"ERROR") -> 2030 | X54: =IF($I54="truck",($Q54*$W54*'MRV Calcs'!$E$7)+($W54*'MRV Calcs'!$E$8),0) -> 5.544978 | Y54: =IF($I54="train",'MRV Calcs'!$E$24,0) -> 0 | Z54: =IF($I54="train",($Q54*$Y54*'MRV Calcs'!$E$7)+($Y54*'MRV Calcs'!$E$8),0) -> 0 | AA54: =IF($I54="train",'MRV Calcs'!$E$25,0) -> 0 | AB54: =IF($I54="train",($Q54*$AA54*'MRV Calcs'!$E$11)+($AA54*'MRV Calcs'!$E$12),0) -> 0 | AC54: =IF($I54="train",'MRV Calcs'!$E$26,0) -> 0 | AD54: =IF($I54="train",($Q54*$AC54*'MRV Calcs'!$E$7)+($AC54*'MRV Calcs'!$E$8),0) -> 0 | AE54: =($Q54/30)*SUM('MRV Calcs'!$E$15:$E$16) -> 3.1213635 | AF54: ='MRV Calcs'!$E$27 -> 71.2 | AG54: =(($Q54*1.1)*$AF54*'MRV Calcs'!$E$7)+($AF54*'MRV Calcs'!$E$8) -> 0.2133859 | AH54: =(($Q54*1.1)/20)*SUM('MRV Calcs'!$E$19:$E$20) -> 0.02903296 | AI54: =SUM(AH54,AG54,AE54,AD54,AB54,Z54,X54,V54) -> 11.959323 | AJ54: =U54-AI54 -> -11.959323 | AK54: =AJ54+AK53 -> 94.756311 | AL54: =AJ54/Q54 -> -0.57998657
A55: 54 | B55: Nov2024Truck 7 | C55: 1768 | D55: RS3-241114-1 | F55: paid | G55: NA | H55: AECN | I55: truck | K55: KAG | L55: Gus | N55: 45615 | O55: 45620 | Q55: 21.29 | U55: =Q55*T55*(44.01/12.011) -> 0 | V55: =$Q55*('MRV Calcs'!$E$3+'MRV Calcs'!$E$4) -> 3.1496839 | W55: =IF(H55="AECN",2030,"ERROR") -> 2030 | X55: =IF($I55="truck",($Q55*$W55*'MRV Calcs'!$E$7)+($W55*'MRV Calcs'!$E$8),0) -> 5.7200871 | Y55: =IF($I55="train",'MRV Calcs'!$E$24,0) -> 0 | Z55: =IF($I55="train",($Q55*$Y55*'MRV Calcs'!$E$7)+($Y55*'MRV Calcs'!$E$8),0) -> 0 | AA55: =IF($I55="train",'MRV Calcs'!$E$25,0) -> 0 | AB55: =IF($I55="train",($Q55*$AA55*'MRV Calcs'!$E$11)+($AA55*'MRV Calcs'!$E$12),0) -> 0 | AC55: =IF($I55="train",'MRV Calcs'!$E$26,0) -> 0 | AD55: =IF($I55="train",($Q55*$AC55*'MRV Calcs'!$E$7)+($AC55*'MRV Calcs'!$E$8),0) -> 0 | AE55: =($Q55/30)*SUM('MRV Calcs'!$E$15:$E$16) -> 3.2227851 | AF55: ='MRV Calcs'!$E$27 -> 71.2 | AG55: =(($Q55*1.1)*$AF55*'MRV Calcs'!$E$7)+($AF55*'MRV Calcs'!$E$8) -> 0.22014183 | AH55: =(($Q55*1.1)/20)*SUM('MRV Calcs'!$E$19:$E$20) -> 0.02997632 | AI55: =SUM(AH55,AG55,AE55,AD55,AB55,Z55,X55,V55) -> 12.342674 | AJ55: =U55-AI55 -> -12.342674 | AK55: =AJ55+AK54 -> 82.413637 | AL55: =AJ55/Q55 -> -0.57974045
A56: 55 | B56: Nov2024Truck 8 | C56: 1769 | D56: RS3-241114-1 | F56: paid | G56: NA | H56: AECN | I56: truck | K56: KAG | L56: Darryl | N56: 45615 | O56: 45620 | Q56: 20.55 | U56: =Q56*T56*(44.01/12.011) -> 0 | V56: =$Q56*('MRV Calcs'!$E$3+'MRV Calcs'!$E$4) -> 3.0402068 | W56: =IF(H56="AECN",2030,"ERROR") -> 2030 | X56: =IF($I56="truck",($Q56*$W56*'MRV Calcs'!$E$7)+($W56*'MRV Calcs'!$E$8),0) -> 5.5266831 | Y56: =IF($I56="train",'MRV Calcs'!$E$24,0) -> 0 | Z56: =IF($I56="train",($Q56*$Y56*'MRV Calcs'!$E$7)+($Y56*'MRV Calcs'!$E$8),0) -> 0 | AA56: =IF($I56="train",'MRV Calcs'!$E$25,0) -> 0 | AB56: =IF($I56="train",($Q56*$AA56*'MRV Calcs'!$E$11)+($AA56*'MRV Calcs'!$E$12),0) -> 0 | AC56: =IF($I56="train",'MRV Calcs'!$E$26,0) -> 0 | AD56: =IF($I56="train",($Q56*$AC56*'MRV Calcs'!$E$7)+($AC56*'MRV Calcs'!$E$8),0) -> 0 | AE56: =($Q56/30)*SUM('MRV Calcs'!$E$15:$E$16) -> 3.1107672 | AF56: ='MRV Calcs'!$E$27 -> 71.2 | AG56: =(($Q56*1.1)*$AF56*'MRV Calcs'!$E$7)+($AF56*'MRV Calcs'!$E$8) -> 0.21268006 | AH56: =(($Q56*1.1)/20)*SUM('MRV Calcs'!$E$19:$E$20) -> 0.0289344 | AI56: =SUM(AH56,AG56,AE56,AD56,AB56,Z56,X56,V56) -> 11.919272 | AJ56: =U56-AI56 -> -11.919272 | AK56: =AJ56+AK55 -> 70.494365 | AL56: =AJ56/Q56 -> -0.58001321
A57: 56 | B57: Nov2024Truck 9 | C57: 1770 | D57: RS3-241114-1 | F57: paid | G57: NA | H57: AECN | I57: truck | K57: KAG | L57: Dave R | N57: 45615 | O57: 45620 | Q57: 21.3 | U57: =Q57*T57*(44.01/12.011) -> 0 | V57: =$Q57*('MRV Calcs'!$E$3+'MRV Calcs'!$E$4) -> 3.1511633 | W57: =IF(H57="AECN",2030,"ERROR") -> 2030 | X57: =IF($I57="truck",($Q57*$W57*'MRV Calcs'!$E$7)+($W57*'MRV Calcs'!$E$8),0) -> 5.7227007 | Y57: =IF($I57="train",'MRV Calcs'!$E$24,0) -> 0 | Z57: =IF($I57="train",($Q57*$Y57*'MRV Calcs'!$E$7)+($Y57*'MRV Calcs'!$E$8),0) -> 0 | AA57: =IF($I57="train",'MRV Calcs'!$E$25,0) -> 0 | AB57: =IF($I57="train",($Q57*$AA57*'MRV Calcs'!$E$11)+($AA57*'MRV Calcs'!$E$12),0) -> 0 | AC57: =IF($I57="train",'MRV Calcs'!$E$26,0) -> 0 | AD57: =IF($I57="train",($Q57*$AC57*'MRV Calcs'!$E$7)+($AC57*'MRV Calcs'!$E$8),0) -> 0 | AE57: =($Q57/30)*SUM('MRV Calcs'!$E$15:$E$16) -> 3.2242989 | AF57: ='MRV Calcs'!$E$27 -> 71.2 | AG57: =(($Q57*1.1)*$AF57*'MRV Calcs'!$E$7)+($AF57*'MRV Calcs'!$E$8) -> 0.22024267 | AH57: =(($Q57*1.1)/20)*SUM('MRV Calcs'!$E$19:$E$20) -> 0.0299904 | AI57: =SUM(AH57,AG57,AE57,AD57,AB57,Z57,X57,V57) -> 12.348396 | AJ57: =U57-AI57 -> -12.348396 | AK57: =AJ57+AK56 -> 58.145969 | AL57: =AJ57/Q57 -> -0.5797369
A58: 57 | B58: Nov2024Truck 10 | C58: 1772 | D58: RS2-241119-1 | F58: paid | G58: NA | H58: AECN | I58: truck | K58: KAG | L58: Andrew | N58: 45619 | O58: 45622 | Q58: 20.52 | U58: =Q58*T58*(44.01/12.011) -> 0 | V58: =$Q58*('MRV Calcs'!$E$3+'MRV Calcs'!$E$4) -> 3.0357686 | W58: =IF(H58="AECN",2030,"ERROR") -> 2030 | X58: =IF($I58="truck",($Q58*$W58*'MRV Calcs'!$E$7)+($W58*'MRV Calcs'!$E$8),0) -> 5.5188424 | Y58: =IF($I58="train",'MRV Calcs'!$E$24,0) -> 0 | Z58: =IF($I58="train",($Q58*$Y58*'MRV Calcs'!$E$7)+($Y58*'MRV Calcs'!$E$8),0) -> 0 | AA58: =IF($I58="train",'MRV Calcs'!$E$25,0) -> 0 | AB58: =IF($I58="train",($Q58*$AA58*'MRV Calcs'!$E$11)+($AA58*'MRV Calcs'!$E$12),0) -> 0 | AC58: =IF($I58="train",'MRV Calcs'!$E$26,0) -> 0 | AD58: =IF($I58="train",($Q58*$AC58*'MRV Calcs'!$E$7)+($AC58*'MRV Calcs'!$E$8),0) -> 0 | AE58: =($Q58/30)*SUM('MRV Calcs'!$E$15:$E$16) -> 3.1062259 | AF58: ='MRV Calcs'!$E$27 -> 71.2 | AG58: =(($Q58*1.1)*$AF58*'MRV Calcs'!$E$7)+($AF58*'MRV Calcs'!$E$8) -> 0.21237755 | AH58: =(($Q58*1.1)/20)*SUM('MRV Calcs'!$E$19:$E$20) -> 0.02889216 | AI58: =SUM(AH58,AG58,AE58,AD58,AB58,Z58,X58,V58) -> 11.902107 | AJ58: =U58-AI58 -> -11.902107 | AK58: =AJ58+AK57 -> 46.243863 | AL58: =AJ58/Q58 -> -0.58002469
A59: 58 | B59: Nov2024Truck 11 | C59: 1773 | D59: RS2-241119-1 | F59: paid | G59: NA | H59: AECN | I59: truck | K59: Contrans | L59: Jacob | N59: 45620 | O59: =N59+4 -> 45624 | Q59: 19.58 | U59: =Q59*T59*(44.01/12.011) -> 0 | V59: =$Q59*('MRV Calcs'!$E$3+'MRV Calcs'!$E$4) -> 2.8967031 | W59: =IF(H59="AECN",2030,"ERROR") -> 2030 | X59: =IF($I59="truck",($Q59*$W59*'MRV Calcs'!$E$7)+($W59*'MRV Calcs'!$E$8),0) -> 5.273167 | Y59: =IF($I59="train",'MRV Calcs'!$E$24,0) -> 0 | Z59: =IF($I59="train",($Q59*$Y59*'MRV Calcs'!$E$7)+($Y59*'MRV Calcs'!$E$8),0) -> 0 | AA59: =IF($I59="train",'MRV Calcs'!$E$25,0) -> 0 | AB59: =IF($I59="train",($Q59*$AA59*'MRV Calcs'!$E$11)+($AA59*'MRV Calcs'!$E$12),0) -> 0 | AC59: =IF($I59="train",'MRV Calcs'!$E$26,0) -> 0 | AD59: =IF($I59="train",($Q59*$AC59*'MRV Calcs'!$E$7)+($AC59*'MRV Calcs'!$E$8),0) -> 0 | AE59: =($Q59/30)*SUM('MRV Calcs'!$E$15:$E$16) -> 2.9639329 | AF59: ='MRV Calcs'!$E$27 -> 71.2 | AG59: =(($Q59*1.1)*$AF59*'MRV Calcs'!$E$7)+($AF59*'MRV Calcs'!$E$8) -> 0.20289908 | AH59: =(($Q59*1.1)/20)*SUM('MRV Calcs'!$E$19:$E$20) -> 0.02756864 | AI59: =SUM(AH59,AG59,AE59,AD59,AB59,Z59,X59,V59) -> 11.364271 | AJ59: =U59-AI59 -> -11.364271 | AK59: =AJ59+AK58 -> 34.879592 | AL59: =AJ59/Q59 -> -0.58040198
A60: 59 | B60: Nov2024Truck 12 | C60: 1776 | D60: RS2-241119-1 | F60: paid | G60: NA | H60: AECN | I60: truck | K60: Contrans | L60: Corey | N60: 45621 | O60: =N60+4 -> 45625 | Q60: 19.5 | U60: =Q60*T60*(44.01/12.011) -> 0 | V60: =$Q60*('MRV Calcs'!$E$3+'MRV Calcs'!$E$4) -> 2.8848678 | W60: =IF(H60="AECN",2030,"ERROR") -> 2030 | X60: =IF($I60="truck",($Q60*$W60*'MRV Calcs'!$E$7)+($W60*'MRV Calcs'!$E$8),0) -> 5.2522584 | Y60: =IF($I60="train",'MRV Calcs'!$E$24,0) -> 0 | Z60: =IF($I60="train",($Q60*$Y60*'MRV Calcs'!$E$7)+($Y60*'MRV Calcs'!$E$8),0) -> 0 | AA60: =IF($I60="train",'MRV Calcs'!$E$25,0) -> 0 | AB60: =IF($I60="train",($Q60*$AA60*'MRV Calcs'!$E$11)+($AA60*'MRV Calcs'!$E$12),0) -> 0 | AC60: =IF($I60="train",'MRV Calcs'!$E$26,0) -> 0 | AD60: =IF($I60="train",($Q60*$AC60*'MRV Calcs'!$E$7)+($AC60*'MRV Calcs'!$E$8),0) -> 0 | AE60: =($Q60/30)*SUM('MRV Calcs'!$E$15:$E$16) -> 2.9518229 | AF60: ='MRV Calcs'!$E$27 -> 71.2 | AG60: =(($Q60*1.1)*$AF60*'MRV Calcs'!$E$7)+($AF60*'MRV Calcs'!$E$8) -> 0.2020924 | AH60: =(($Q60*1.1)/20)*SUM('MRV Calcs'!$E$19:$E$20) -> 0.027456 | AI60: =SUM(AH60,AG60,AE60,AD60,AB60,Z60,X60,V60) -> 11.318497 | AJ60: =U60-AI60 -> -11.318497 | AK60: =AJ60+AK59 -> 23.561094 | AL60: =AJ60/Q60 -> -0.58043577
A61: 60 | B61: Nov2024Truck 13 | C61: 1778 | D61: RS2-241119-1 | F61: paid | G61: NA | H61: AECN | I61: truck | K61: KAG | L61: Darryl | N61: 45623 | O61: =N61+4 -> 45627 | Q61: 20.54 | U61: =Q61*T61*(44.01/12.011) -> 0 | V61: =$Q61*('MRV Calcs'!$E$3+'MRV Calcs'!$E$4) -> 3.0387274 | W61: =IF(H61="AECN",2030,"ERROR") -> 2030 | X61: =IF($I61="truck",($Q61*$W61*'MRV Calcs'!$E$7)+($W61*'MRV Calcs'!$E$8),0) -> 5.5240695 | Y61: =IF($I61="train",'MRV Calcs'!$E$24,0) -> 0 | Z61: =IF($I61="train",($Q61*$Y61*'MRV Calcs'!$E$7)+($Y61*'MRV Calcs'!$E$8),0) -> 0 | AA61: =IF($I61="train",'MRV Calcs'!$E$25,0) -> 0 | AB61: =IF($I61="train",($Q61*$AA61*'MRV Calcs'!$E$11)+($AA61*'MRV Calcs'!$E$12),0) -> 0 | AC61: =IF($I61="train",'MRV Calcs'!$E$26,0) -> 0 | AD61: =IF($I61="train",($Q61*$AC61*'MRV Calcs'!$E$7)+($AC61*'MRV Calcs'!$E$8),0) -> 0 | AE61: =($Q61/30)*SUM('MRV Calcs'!$E$15:$E$16) -> 3.1092535 | AF61: ='MRV Calcs'!$E$27 -> 71.2 | AG61: =(($Q61*1.1)*$AF61*'MRV Calcs'!$E$7)+($AF61*'MRV Calcs'!$E$8) -> 0.21257922 | AH61: =(($Q61*1.1)/20)*SUM('MRV Calcs'!$E$19:$E$20) -> 0.02892032 | AI61: =SUM(AH61,AG61,AE61,AD61,AB61,Z61,X61,V61) -> 11.91355 | AJ61: =U61-AI61 -> -11.91355 | AK61: =AJ61+AK60 -> 11.647545 | AL61: =AJ61/Q61 -> -0.58001703
A62: 61 | B62: Nov2024Truck 14 | C62: 1779 | D62: RS2-241119-1 | F62: paid | G62: NA | H62: AECN | I62: truck | K62: KAG | L62: Dave R | N62: 45623 | O62: =N62+4 -> 45627 | Q62: 21.29 | U62: =Q62*T62*(44.01/12.011) -> 0 | V62: =$Q62*('MRV Calcs'!$E$3+'MRV Calcs'!$E$4) -> 3.1496839 | W62: =IF(H62="AECN",2030,"ERROR") -> 2030 | X62: =IF($I62="truck",($Q62*$W62*'MRV Calcs'!$E$7)+($W62*'MRV Calcs'!$E$8),0) -> 5.7200871 | Y62: =IF($I62="train",'MRV Calcs'!$E$24,0) -> 0 | Z62: =IF($I62="train",($Q62*$Y62*'MRV Calcs'!$E$7)+($Y62*'MRV Calcs'!$E$8),0) -> 0 | AA62: =IF($I62="train",'MRV Calcs'!$E$25,0) -> 0 | AB62: =IF($I62="train",($Q62*$AA62*'MRV Calcs'!$E$11)+($AA62*'MRV Calcs'!$E$12),0) -> 0 | AC62: =IF($I62="train",'MRV Calcs'!$E$26,0) -> 0 | AD62: =IF($I62="train",($Q62*$AC62*'MRV Calcs'!$E$7)+($AC62*'MRV Calcs'!$E$8),0) -> 0 | AE62: =($Q62/30)*SUM('MRV Calcs'!$E$15:$E$16) -> 3.2227851 | AF62: ='MRV Calcs'!$E$27 -> 71.2 | AG62: =(($Q62*1.1)*$AF62*'MRV Calcs'!$E$7)+($AF62*'MRV Calcs'!$E$8) -> 0.22014183 | AH62: =(($Q62*1.1)/20)*SUM('MRV Calcs'!$E$19:$E$20) -> 0.02997632 | AI62: =SUM(AH62,AG62,AE62,AD62,AB62,Z62,X62,V62) -> 12.342674 | AJ62: =U62-AI62 -> -12.342674 | AK62: =AJ62+AK61 -> -0.69512971 | AL62: =AJ62/Q62 -> -0.57974045
A63: 62 | B63: Nov2024Truck 15 | C63: 1780 | D63: RS2-241119-1 | F63: paid | G63: NA | H63: AECN | I63: truck | K63: Contrans | L63: Gord/Gavin | N63: 45623 | O63: =N63+4 -> 45627 | Q63: 20.2 | U63: =Q63*T63*(44.01/12.011) -> 0 | V63: =$Q63*('MRV Calcs'!$E$3+'MRV Calcs'!$E$4) -> 2.9884271 | W63: =IF(H63="AECN",2030,"ERROR") -> 2030 | X63: =IF($I63="truck",($Q63*$W63*'MRV Calcs'!$E$7)+($W63*'MRV Calcs'!$E$8),0) -> 5.4352082 | Y63: =IF($I63="train",'MRV Calcs'!$E$24,0) -> 0 | Z63: =IF($I63="train",($Q63*$Y63*'MRV Calcs'!$E$7)+($Y63*'MRV Calcs'!$E$8),0) -> 0 | AA63: =IF($I63="train",'MRV Calcs'!$E$25,0) -> 0 | AB63: =IF($I63="train",($Q63*$AA63*'MRV Calcs'!$E$11)+($AA63*'MRV Calcs'!$E$12),0) -> 0 | AC63: =IF($I63="train",'MRV Calcs'!$E$26,0) -> 0 | AD63: =IF($I63="train",($Q63*$AC63*'MRV Calcs'!$E$7)+($AC63*'MRV Calcs'!$E$8),0) -> 0 | AE63: =($Q63/30)*SUM('MRV Calcs'!$E$15:$E$16) -> 3.0577858 | AF63: ='MRV Calcs'!$E$27 -> 71.2 | AG63: =(($Q63*1.1)*$AF63*'MRV Calcs'!$E$7)+($AF63*'MRV Calcs'!$E$8) -> 0.20915084 | AH63: =(($Q63*1.1)/20)*SUM('MRV Calcs'!$E$19:$E$20) -> 0.0284416 | AI63: =SUM(AH63,AG63,AE63,AD63,AB63,Z63,X63,V63) -> 11.719014 | AJ63: =U63-AI63 -> -11.719014 | AK63: =AJ63+AK62 -> -12.414143 | AL63: =AJ63/Q63 -> -0.58014918
A64: 63 | B64: Nov2024Truck 16 | C64: 1781 | D64: RS2-241119-1 | F64: paid | G64: NA | H64: AECN | I64: truck | K64: Contrans | L64: Keith | N64: 45624 | O64: =N64+4 -> 45628 | Q64: 19.83 | U64: =Q64*T64*(44.01/12.011) -> 0 | V64: =$Q64*('MRV Calcs'!$E$3+'MRV Calcs'!$E$4) -> 2.9336886 | W64: =IF(H64="AECN",2030,"ERROR") -> 2030 | X64: =IF($I64="truck",($Q64*$W64*'MRV Calcs'!$E$7)+($W64*'MRV Calcs'!$E$8),0) -> 5.3385062 | Y64: =IF($I64="train",'MRV Calcs'!$E$24,0) -> 0 | Z64: =IF($I64="train",($Q64*$Y64*'MRV Calcs'!$E$7)+($Y64*'MRV Calcs'!$E$8),0) -> 0 | AA64: =IF($I64="train",'MRV Calcs'!$E$25,0) -> 0 | AB64: =IF($I64="train",($Q64*$AA64*'MRV Calcs'!$E$11)+($AA64*'MRV Calcs'!$E$12),0) -> 0 | AC64: =IF($I64="train",'MRV Calcs'!$E$26,0) -> 0 | AD64: =IF($I64="train",($Q64*$AC64*'MRV Calcs'!$E$7)+($AC64*'MRV Calcs'!$E$8),0) -> 0 | AE64: =($Q64/30)*SUM('MRV Calcs'!$E$15:$E$16) -> 3.0017768 | AF64: ='MRV Calcs'!$E$27 -> 71.2 | AG64: =(($Q64*1.1)*$AF64*'MRV Calcs'!$E$7)+($AF64*'MRV Calcs'!$E$8) -> 0.20541995 | AH64: =(($Q64*1.1)/20)*SUM('MRV Calcs'!$E$19:$E$20) -> 0.02792064 | AI64: =SUM(AH64,AG64,AE64,AD64,AB64,Z64,X64,V64) -> 11.507312 | AJ64: =U64-AI64 -> -11.507312 | AK64: =AJ64+AK63 -> -23.921455 | AL64: =AJ64/Q64 -> -0.58029814
A65: 64 | B65: Nov2024Truck 17 | C65: 1785 | D65: RS3-241121-1 | F65: paid | G65: NA | H65: AECN | I65: truck | K65: Contrans | L65: Backensie/Mclnnis | N65: 45625 | O65: 45630 | Q65: 19.86 | U65: =Q65*T65*(44.01/12.011) -> 0 | V65: =$Q65*('MRV Calcs'!$E$3+'MRV Calcs'!$E$4) -> 2.9381269 | W65: =IF(H65="AECN",2030,"ERROR") -> 2030 | X65: =IF($I65="truck",($Q65*$W65*'MRV Calcs'!$E$7)+($W65*'MRV Calcs'!$E$8),0) -> 5.3463469 | Y65: =IF($I65="train",'MRV Calcs'!$E$24,0) -> 0 | Z65: =IF($I65="train",($Q65*$Y65*'MRV Calcs'!$E$7)+($Y65*'MRV Calcs'!$E$8),0) -> 0 | AA65: =IF($I65="train",'MRV Calcs'!$E$25,0) -> 0 | AB65: =IF($I65="train",($Q65*$AA65*'MRV Calcs'!$E$11)+($AA65*'MRV Calcs'!$E$12),0) -> 0 | AC65: =IF($I65="train",'MRV Calcs'!$E$26,0) -> 0 | AD65: =IF($I65="train",($Q65*$AC65*'MRV Calcs'!$E$7)+($AC65*'MRV Calcs'!$E$8),0) -> 0 | AE65: =($Q65/30)*SUM('MRV Calcs'!$E$15:$E$16) -> 3.0063181 | AF65: ='MRV Calcs'!$E$27 -> 71.2 | AG65: =(($Q65*1.1)*$AF65*'MRV Calcs'!$E$7)+($AF65*'MRV Calcs'!$E$8) -> 0.20572246 | AH65: =(($Q65*1.1)/20)*SUM('MRV Calcs'!$E$19:$E$20) -> 0.02796288 | AI65: =SUM(AH65,AG65,AE65,AD65,AB65,Z65,X65,V65) -> 11.524477 | AJ65: =U65-AI65 -> -11.524477 | AK65: =AJ65+AK64 -> -35.445933 | AL65: =AJ65/Q65 -> -0.58028586
A66: 65 | B66: Dec2024 Truck 1 | C66: 1786 | D66: RS3-241121-1 | F66: paid | G66: NA | H66: AECN | I66: truck | K66: KAG | L66: Andrew | N66: 45627 | O66: =N66+4 -> 45631 | Q66: 20.18 | U66: =Q66*T66*(44.01/12.011) -> 0 | V66: =$Q66*('MRV Calcs'!$E$3+'MRV Calcs'!$E$4) -> 2.9854683 | W66: =IF(H66="AECN",2030,"ERROR") -> 2030 | X66: =IF($I66="truck",($Q66*$W66*'MRV Calcs'!$E$7)+($W66*'MRV Calcs'!$E$8),0) -> 5.429981 | Y66: =IF($I66="train",'MRV Calcs'!$E$24,0) -> 0 | Z66: =IF($I66="train",($Q66*$Y66*'MRV Calcs'!$E$7)+($Y66*'MRV Calcs'!$E$8),0) -> 0 | AA66: =IF($I66="train",'MRV Calcs'!$E$25,0) -> 0 | AB66: =IF($I66="train",($Q66*$AA66*'MRV Calcs'!$E$11)+($AA66*'MRV Calcs'!$E$12),0) -> 0 | AC66: =IF($I66="train",'MRV Calcs'!$E$26,0) -> 0 | AD66: =IF($I66="train",($Q66*$AC66*'MRV Calcs'!$E$7)+($AC66*'MRV Calcs'!$E$8),0) -> 0 | AE66: =($Q66/30)*SUM('MRV Calcs'!$E$15:$E$16) -> 3.0547583 | AF66: ='MRV Calcs'!$E$27 -> 71.2 | AG66: =(($Q66*1.1)*$AF66*'MRV Calcs'!$E$7)+($AF66*'MRV Calcs'!$E$8) -> 0.20894917 | AH66: =(($Q66*1.1)/20)*SUM('MRV Calcs'!$E$19:$E$20) -> 0.02841344 | AI66: =SUM(AH66,AG66,AE66,AD66,AB66,Z66,X66,V66) -> 11.70757 | AJ66: =U66-AI66 -> -11.70757 | AK66: =AJ66+AK65 -> -47.153503 | AL66: =AJ66/Q66 -> -0.5801571
A67: 66 | B67: Dec2024 Truck 2 | C67: 1788 | D67: RS3-241121-1 | F67: paid | G67: NA | H67: AECN | I67: truck | K67: Contrans | L67: Tim | N67: 45628 | O67: =N67+4 -> 45632 | Q67: 20.66 | U67: =Q67*T67*(44.01/12.011) -> 0 | V67: =$Q67*('MRV Calcs'!$E$3+'MRV Calcs'!$E$4) -> 3.0564804 | W67: =IF(H67="AECN",2030,"ERROR") -> 2030 | X67: =IF($I67="truck",($Q67*$W67*'MRV Calcs'!$E$7)+($W67*'MRV Calcs'!$E$8),0) -> 5.5554323 | Y67: =IF($I67="train",'MRV Calcs'!$E$24,0) -> 0 | Z67: =IF($I67="train",($Q67*$Y67*'MRV Calcs'!$E$7)+($Y67*'MRV Calcs'!$E$8),0) -> 0 | AA67: =IF($I67="train",'MRV Calcs'!$E$25,0) -> 0 | AB67: =IF($I67="train",($Q67*$AA67*'MRV Calcs'!$E$11)+($AA67*'MRV Calcs'!$E$12),0) -> 0 | AC67: =IF($I67="train",'MRV Calcs'!$E$26,0) -> 0 | AD67: =IF($I67="train",($Q67*$AC67*'MRV Calcs'!$E$7)+($AC67*'MRV Calcs'!$E$8),0) -> 0 | AE67: =($Q67/30)*SUM('MRV Calcs'!$E$15:$E$16) -> 3.1274185 | AF67: ='MRV Calcs'!$E$27 -> 71.2 | AG67: =(($Q67*1.1)*$AF67*'MRV Calcs'!$E$7)+($AF67*'MRV Calcs'!$E$8) -> 0.21378924 | AH67: =(($Q67*1.1)/20)*SUM('MRV Calcs'!$E$19:$E$20) -> 0.02908928 | AI67: =SUM(AH67,AG67,AE67,AD67,AB67,Z67,X67,V67) -> 11.98221 | AJ67: =U67-AI67 -> -11.98221 | AK67: =AJ67+AK63 -> -24.396353 | AL67: =AJ67/Q67 -> -0.57997143
A68: 67 | B68: Dec2024 Truck 3 | C68: 1790 | D68: RS1-241203-1 | F68: paid | G68: NA | H68: AECN | I68: truck | K68: Contrans | L68: Mike | N68: 45629 | O68: =N68+4 -> 45633 | Q68: 20.57 | U68: =Q68*T68*(44.01/12.011) -> 0 | V68: =$Q68*('MRV Calcs'!$E$3+'MRV Calcs'!$E$4) -> 3.0431657 | W68: =IF(H68="AECN",2030,"ERROR") -> 2030 | X68: =IF($I68="truck",($Q68*$W68*'MRV Calcs'!$E$7)+($W68*'MRV Calcs'!$E$8),0) -> 5.5319102 | Y68: =IF($I68="train",'MRV Calcs'!$E$24,0) -> 0 | Z68: =IF($I68="train",($Q68*$Y68*'MRV Calcs'!$E$7)+($Y68*'MRV Calcs'!$E$8),0) -> 0 | AA68: =IF($I68="train",'MRV Calcs'!$E$25,0) -> 0 | AB68: =IF($I68="train",($Q68*$AA68*'MRV Calcs'!$E$11)+($AA68*'MRV Calcs'!$E$12),0) -> 0 | AC68: =IF($I68="train",'MRV Calcs'!$E$26,0) -> 0 | AD68: =IF($I68="train",($Q68*$AC68*'MRV Calcs'!$E$7)+($AC68*'MRV Calcs'!$E$8),0) -> 0 | AE68: =($Q68/30)*SUM('MRV Calcs'!$E$15:$E$16) -> 3.1137947 | AF68: ='MRV Calcs'!$E$27 -> 71.2 | AG68: =(($Q68*1.1)*$AF68*'MRV Calcs'!$E$7)+($AF68*'MRV Calcs'!$E$8) -> 0.21288173 | AH68: =(($Q68*1.1)/20)*SUM('MRV Calcs'!$E$19:$E$20) -> 0.02896256 | AI68: =SUM(AH68,AG68,AE68,AD68,AB68,Z68,X68,V68) -> 11.930715 | AJ68: =U68-AI68 -> -11.930715 | AK68: =AJ68+AK64 -> -35.85217 | AL68: =AJ68/Q68 -> -0.58000558
A69: 68 | B69: Dec2024 Truck 4 | C69: 1792 | D69: RS1-241203-1 | F69: paid | G69: NA | H69: AECN | I69: truck | K69: Contrans | L69: Jason | N69: 45630 | O69: =N69+4 -> 45634 | Q69: 20 | U69: =Q69*T69*(44.01/12.011) -> 0 | V69: =$Q69*('MRV Calcs'!$E$3+'MRV Calcs'!$E$4) -> 2.9588388 | W69: =IF(H69="AECN",2030,"ERROR") -> 2030 | X69: =IF($I69="truck",($Q69*$W69*'MRV Calcs'!$E$7)+($W69*'MRV Calcs'!$E$8),0) -> 5.3829368 | Y69: =IF($I69="train",'MRV Calcs'!$E$24,0) -> 0 | Z69: =IF($I69="train",($Q69*$Y69*'MRV Calcs'!$E$7)+($Y69*'MRV Calcs'!$E$8),0) -> 0 | AA69: =IF($I69="train",'MRV Calcs'!$E$25,0) -> 0 | AB69: =IF($I69="train",($Q69*$AA69*'MRV Calcs'!$E$11)+($AA69*'MRV Calcs'!$E$12),0) -> 0 | AC69: =IF($I69="train",'MRV Calcs'!$E$26,0) -> 0 | AD69: =IF($I69="train",($Q69*$AC69*'MRV Calcs'!$E$7)+($AC69*'MRV Calcs'!$E$8),0) -> 0 | AE69: =($Q69/30)*SUM('MRV Calcs'!$E$15:$E$16) -> 3.0275107 | AF69: ='MRV Calcs'!$E$27 -> 71.2 | AG69: =(($Q69*1.1)*$AF69*'MRV Calcs'!$E$7)+($AF69*'MRV Calcs'!$E$8) -> 0.20713414 | AH69: =(($Q69*1.1)/20)*SUM('MRV Calcs'!$E$19:$E$20) -> 0.02816 | AI69: =SUM(AH69,AG69,AE69,AD69,AB69,Z69,X69,V69) -> 11.60458 | AJ69: =U69-AI69 -> -11.60458 | AK69: =AJ69+AK65 -> -47.050513 | AL69: =AJ69/Q69 -> -0.58022902
A70: 69 | B70: Dec2024 Truck 5 | C70: 1794 | D70: RS1-241203-1 | F70: paid | G70: NA | H70: AECN | I70: truck | K70: KAG | L70: Don/Nathan | N70: 45630 | O70: 45638 | Q70: 20.08 | U70: =Q70*T70*(44.01/12.011) -> 0 | V70: =$Q70*('MRV Calcs'!$E$3+'MRV Calcs'!$E$4) -> 2.9706741 | W70: =IF(H70="AECN",2030,"ERROR") -> 2030 | X70: =IF($I70="truck",($Q70*$W70*'MRV Calcs'!$E$7)+($W70*'MRV Calcs'!$E$8),0) -> 5.4038454 | Y70: =IF($I70="train",'MRV Calcs'!$E$24,0) -> 0 | Z70: =IF($I70="train",($Q70*$Y70*'MRV Calcs'!$E$7)+($Y70*'MRV Calcs'!$E$8),0) -> 0 | AA70: =IF($I70="train",'MRV Calcs'!$E$25,0) -> 0 | AB70: =IF($I70="train",($Q70*$AA70*'MRV Calcs'!$E$11)+($AA70*'MRV Calcs'!$E$12),0) -> 0 | AC70: =IF($I70="train",'MRV Calcs'!$E$26,0) -> 0 | AD70: =IF($I70="train",($Q70*$AC70*'MRV Calcs'!$E$7)+($AC70*'MRV Calcs'!$E$8),0) -> 0 | AE70: =($Q70/30)*SUM('MRV Calcs'!$E$15:$E$16) -> 3.0396207 | AF70: ='MRV Calcs'!$E$27 -> 71.2 | AG70: =(($Q70*1.1)*$AF70*'MRV Calcs'!$E$7)+($AF70*'MRV Calcs'!$E$8) -> 0.20794082 | AH70: =(($Q70*1.1)/20)*SUM('MRV Calcs'!$E$19:$E$20) -> 0.02827264 | AI70: =SUM(AH70,AG70,AE70,AD70,AB70,Z70,X70,V70) -> 11.650354 | AJ70: =U70-AI70 -> -11.650354 | AK70: =AJ70+AK67 -> -36.046707 | AL70: =AJ70/Q70 -> -0.58019689
A71: 70 | B71: Dec2024 Truck 6 | C71: 1796 | D71: RS1-241203-1 | F71: paid | G71: NA | H71: AECN | I71: truck | K71: KAG | L71: Gus | N71: 45630 | O71: 45637 | Q71: 21.04 | U71: =Q71*T71*(44.01/12.011) -> 0 | V71: =$Q71*('MRV Calcs'!$E$3+'MRV Calcs'!$E$4) -> 3.1126984 | W71: =IF(H71="AECN",2030,"ERROR") -> 2030 | X71: =IF($I71="truck",($Q71*$W71*'MRV Calcs'!$E$7)+($W71*'MRV Calcs'!$E$8),0) -> 5.6547479 | Y71: =IF($I71="train",'MRV Calcs'!$E$24,0) -> 0 | Z71: =IF($I71="train",($Q71*$Y71*'MRV Calcs'!$E$7)+($Y71*'MRV Calcs'!$E$8),0) -> 0 | AA71: =IF($I71="train",'MRV Calcs'!$E$25,0) -> 0 | AB71: =IF($I71="train",($Q71*$AA71*'MRV Calcs'!$E$11)+($AA71*'MRV Calcs'!$E$12),0) -> 0 | AC71: =IF($I71="train",'MRV Calcs'!$E$26,0) -> 0 | AD71: =IF($I71="train",($Q71*$AC71*'MRV Calcs'!$E$7)+($AC71*'MRV Calcs'!$E$8),0) -> 0 | AE71: =($Q71/30)*SUM('MRV Calcs'!$E$15:$E$16) -> 3.1849412 | AF71: ='MRV Calcs'!$E$27 -> 71.2 | AG71: =(($Q71*1.1)*$AF71*'MRV Calcs'!$E$7)+($AF71*'MRV Calcs'!$E$8) -> 0.21762096 | AH71: =(($Q71*1.1)/20)*SUM('MRV Calcs'!$E$19:$E$20) -> 0.02962432 | AI71: =SUM(AH71,AG71,AE71,AD71,AB71,Z71,X71,V71) -> 12.199633 | AJ71: =U71-AI71 -> -12.199633 | AK71: =AJ71+AK70 -> -48.246339 | AL71: =AJ71/Q71 -> -0.57983045
A72: 71 | B72: Dec2024 Truck 7 | C72: 1798 | D72: RS1-241203-1 | F72: paid | G72: NA | H72: AECN | I72: truck | K72: KAG | L72: Darryl | N72: 45632 | O72: 45639 | Q72: 20.22 | U72: =Q72*T72*(44.01/12.011) -> 0 | V72: =$Q72*('MRV Calcs'!$E$3+'MRV Calcs'!$E$4) -> 2.991386 | W72: =IF(H72="AECN",2030,"ERROR") -> 2030 | X72: =IF($I72="truck",($Q72*$W72*'MRV Calcs'!$E$7)+($W72*'MRV Calcs'!$E$8),0) -> 5.4404353 | Y72: =IF($I72="train",'MRV Calcs'!$E$24,0) -> 0 | Z72: =IF($I72="train",($Q72*$Y72*'MRV Calcs'!$E$7)+($Y72*'MRV Calcs'!$E$8),0) -> 0 | AA72: =IF($I72="train",'MRV Calcs'!$E$25,0) -> 0 | AB72: =IF($I72="train",($Q72*$AA72*'MRV Calcs'!$E$11)+($AA72*'MRV Calcs'!$E$12),0) -> 0 | AC72: =IF($I72="train",'MRV Calcs'!$E$26,0) -> 0 | AD72: =IF($I72="train",($Q72*$AC72*'MRV Calcs'!$E$7)+($AC72*'MRV Calcs'!$E$8),0) -> 0 | AE72: =($Q72/30)*SUM('MRV Calcs'!$E$15:$E$16) -> 3.0608133 | AF72: ='MRV Calcs'!$E$27 -> 71.2 | AG72: =(($Q72*1.1)*$AF72*'MRV Calcs'!$E$7)+($AF72*'MRV Calcs'!$E$8) -> 0.20935251 | AH72: =(($Q72*1.1)/20)*SUM('MRV Calcs'!$E$19:$E$20) -> 0.02846976 | AI72: =SUM(AH72,AG72,AE72,AD72,AB72,Z72,X72,V72) -> 11.730457 | AJ72: =U72-AI72 -> -11.730457 | AK72: =AJ72+AK71 -> -59.976796 | AL72: =AJ72/Q72 -> -0.58014129
A73: 72 | B73: Dec2024 Truck 8 | C73: 1799 | D73: RS2- 241206-1 | F73: paid | G73: NA | H73: AECN | I73: truck | K73: KAG | L73: Dave R | N73: 45632 | O73: 45639 | Q73: 20.98 | U73: =Q73*T73*(44.01/12.011) -> 0 | V73: =$Q73*('MRV Calcs'!$E$3+'MRV Calcs'!$E$4) -> 3.1038218 | W73: =IF(H73="AECN",2030,"ERROR") -> 2030 | X73: =IF($I73="truck",($Q73*$W73*'MRV Calcs'!$E$7)+($W73*'MRV Calcs'!$E$8),0) -> 5.6390665 | Y73: =IF($I73="train",'MRV Calcs'!$E$24,0) -> 0 | Z73: =IF($I73="train",($Q73*$Y73*'MRV Calcs'!$E$7)+($Y73*'MRV Calcs'!$E$8),0) -> 0 | AA73: =IF($I73="train",'MRV Calcs'!$E$25,0) -> 0 | AB73: =IF($I73="train",($Q73*$AA73*'MRV Calcs'!$E$11)+($AA73*'MRV Calcs'!$E$12),0) -> 0 | AC73: =IF($I73="train",'MRV Calcs'!$E$26,0) -> 0 | AD73: =IF($I73="train",($Q73*$AC73*'MRV Calcs'!$E$7)+($AC73*'MRV Calcs'!$E$8),0) -> 0 | AE73: =($Q73/30)*SUM('MRV Calcs'!$E$15:$E$16) -> 3.1758587 | AF73: ='MRV Calcs'!$E$27 -> 71.2 | AG73: =(($Q73*1.1)*$AF73*'MRV Calcs'!$E$7)+($AF73*'MRV Calcs'!$E$8) -> 0.21701595 | AH73: =(($Q73*1.1)/20)*SUM('MRV Calcs'!$E$19:$E$20) -> 0.02953984 | AI73: =SUM(AH73,AG73,AE73,AD73,AB73,Z73,X73,V73) -> 12.165303 | AJ73: =U73-AI73 -> -12.165303 | AK73: =AJ73+AK72 -> -72.142099 | AL73: =AJ73/Q73 -> -0.57985237
A74: 73 | B74: Dec2024 Truck 9 | C74: 1824 | D74: RS3-241218-1 | E74: TRUE | F74: paid | G74: NA | H74: AECN | I74: truck | K74: KAG | L74: Gus | N74: 45649 | O74: 45654 | Q74: 20.84 | U74: =Q74*T74*(44.01/12.011) -> 0 | V74: =$Q74*('MRV Calcs'!$E$3+'MRV Calcs'!$E$4) -> 3.08311 | W74: =IF(H74="AECN",2030,"ERROR") -> 2030 | X74: =IF($I74="truck",($Q74*$W74*'MRV Calcs'!$E$7)+($W74*'MRV Calcs'!$E$8),0) -> 5.6024765 | Y74: =IF($I74="train",'MRV Calcs'!$E$24,0) -> 0 | Z74: =IF($I74="train",($Q74*$Y74*'MRV Calcs'!$E$7)+($Y74*'MRV Calcs'!$E$8),0) -> 0 | AA74: =IF($I74="train",'MRV Calcs'!$E$25,0) -> 0 | AB74: =IF($I74="train",($Q74*$AA74*'MRV Calcs'!$E$11)+($AA74*'MRV Calcs'!$E$12),0) -> 0 | AC74: =IF($I74="train",'MRV Calcs'!$E$26,0) -> 0 | AD74: =IF($I74="train",($Q74*$AC74*'MRV Calcs'!$E$7)+($AC74*'MRV Calcs'!$E$8),0) -> 0 | AE74: =($Q74/30)*SUM('MRV Calcs'!$E$15:$E$16) -> 3.1546661 | AF74: ='MRV Calcs'!$E$27 -> 71.2 | AG74: =(($Q74*1.1)*$AF74*'MRV Calcs'!$E$7)+($AF74*'MRV Calcs'!$E$8) -> 0.21560427 | AH74: =(($Q74*1.1)/20)*SUM('MRV Calcs'!$E$19:$E$20) -> 0.02934272 | AI74: =SUM(AH74,AG74,AE74,AD74,AB74,Z74,X74,V74) -> 12.0852 | AJ74: =U74-AI74 -> -12.0852 | AK74: =AJ74+AK71 -> -60.331539 | AL74: =AJ74/Q74 -> -0.57990401
A75: 74 | B75: INTERNAL CHARM | C75: CH01 | F75: CHARM OIL | G75: CHARM | H75: CHARM | I75: truck | K75: CHARM | O75: 45653 | Q75: X | V75: =$Q75*('MRV Calcs'!$E$3+'MRV Calcs'!$E$4) -> #VALUE! | W75: =IF(H75="AECN",2030,"ERROR") -> ERROR | X75: =IF($I75="truck",($Q75*$W75*'MRV Calcs'!$E$7)+($W75*'MRV Calcs'!$E$8),0) -> #VALUE! | Y75: =IF($I75="train",'MRV Calcs'!$E$24,0) -> 0 | Z75: =IF($I75="train",($Q75*$Y75*'MRV Calcs'!$E$7)+($Y75*'MRV Calcs'!$E$8),0) -> 0 | AA75: =IF($I75="train",'MRV Calcs'!$E$25,0) -> 0 | AB75: =IF($I75="train",($Q75*$AA75*'MRV Calcs'!$E$11)+($AA75*'MRV Calcs'!$E$12),0) -> 0 | AC75: =IF($I75="train",'MRV Calcs'!$E$26,0) -> 0 | AD75: =IF($I75="train",($Q75*$AC75*'MRV Calcs'!$E$7)+($AC75*'MRV Calcs'!$E$8),0) -> 0 | AE75: =($Q75/30)*SUM('MRV Calcs'!$E$15:$E$16) -> #VALUE! | AF75: ='MRV Calcs'!$E$27 -> 71.2 | AG75: =(($Q75*1.1)*$AF75*'MRV Calcs'!$E$7)+($AF75*'MRV Calcs'!$E$8) -> #VALUE! | AH75: =(($Q75*1.1)/20)*SUM('MRV Calcs'!$E$19:$E$20) -> #VALUE! | AI75: =SUM(AH75,AG75,AE75,AD75,AB75,Z75,X75,V75) -> #VALUE! | AK75: =AJ75+AK72 -> -59.976796
A76: 75 | B76: Dec2024 Truck 10 | C76: 1826 | D76: RS3-241218-1 | E76: TRUE | F76: paid | G76: NA | H76: AECN | I76: truck | K76: KAG | L76: Darryl | N76: 45649 | O76: 45652 | Q76: 20.55 | U76: =Q76*T76*(44.01/12.011) -> 0 | V76: =$Q76*('MRV Calcs'!$E$3+'MRV Calcs'!$E$4) -> 3.0402068 | W76: =IF(H76="AECN",2030,"ERROR") -> 2030 | X76: =IF($I76="truck",($Q76*$W76*'MRV Calcs'!$E$7)+($W76*'MRV Calcs'!$E$8),0) -> 5.5266831 | Y76: =IF($I76="train",'MRV Calcs'!$E$24,0) -> 0 | Z76: =IF($I76="train",($Q76*$Y76*'MRV Calcs'!$E$7)+($Y76*'MRV Calcs'!$E$8),0) -> 0 | AA76: =IF($I76="train",'MRV Calcs'!$E$25,0) -> 0 | AB76: =IF($I76="train",($Q76*$AA76*'MRV Calcs'!$E$11)+($AA76*'MRV Calcs'!$E$12),0) -> 0 | AC76: =IF($I76="train",'MRV Calcs'!$E$26,0) -> 0 | AD76: =IF($I76="train",($Q76*$AC76*'MRV Calcs'!$E$7)+($AC76*'MRV Calcs'!$E$8),0) -> 0 | AE76: =($Q76/30)*SUM('MRV Calcs'!$E$15:$E$16) -> 3.1107672 | AF76: ='MRV Calcs'!$E$27 -> 71.2 | AG76: =(($Q76*1.1)*$AF76*'MRV Calcs'!$E$7)+($AF76*'MRV Calcs'!$E$8) -> 0.21268006 | AH76: =(($Q76*1.1)/20)*SUM('MRV Calcs'!$E$19:$E$20) -> 0.0289344 | AI76: =SUM(AH76,AG76,AE76,AD76,AB76,Z76,X76,V76) -> 11.919272 | AJ76: =U76-AI76 -> -11.919272 | AK76: =AJ76+AK74 -> -72.250811 | AL76: =AJ76/Q76 -> -0.58001321
A77: 76 | B77: Dec2024 Truck 11 | C77: 1831 | D77: RS3-241218-1 | E77: TRUE | F77: paid | G77: NA | H77: AECN | I77: truck | K77: Contrans | L77: Kulbir | N77: 45651 | O77: 45653 | Q77: 18.56 | U77: =Q77*T77*(44.01/12.011) -> 0 | V77: =$Q77*('MRV Calcs'!$E$3+'MRV Calcs'!$E$4) -> 2.7458024 | W77: =IF(H77="AECN",2030,"ERROR") -> 2030 | X77: =IF($I77="truck",($Q77*$W77*'MRV Calcs'!$E$7)+($W77*'MRV Calcs'!$E$8),0) -> 5.006583 | Y77: =IF($I77="train",'MRV Calcs'!$E$24,0) -> 0 | Z77: =IF($I77="train",($Q77*$Y77*'MRV Calcs'!$E$7)+($Y77*'MRV Calcs'!$E$8),0) -> 0 | AA77: =IF($I77="train",'MRV Calcs'!$E$25,0) -> 0 | AB77: =IF($I77="train",($Q77*$AA77*'MRV Calcs'!$E$11)+($AA77*'MRV Calcs'!$E$12),0) -> 0 | AC77: =IF($I77="train",'MRV Calcs'!$E$26,0) -> 0 | AD77: =IF($I77="train",($Q77*$AC77*'MRV Calcs'!$E$7)+($AC77*'MRV Calcs'!$E$8),0) -> 0 | AE77: =($Q77/30)*SUM('MRV Calcs'!$E$15:$E$16) -> 2.8095299 | AF77: ='MRV Calcs'!$E$27 -> 71.2 | AG77: =(($Q77*1.1)*$AF77*'MRV Calcs'!$E$7)+($AF77*'MRV Calcs'!$E$8) -> 0.19261393 | AH77: =(($Q77*1.1)/20)*SUM('MRV Calcs'!$E$19:$E$20) -> 0.02613248 | AI77: =SUM(AH77,AG77,AE77,AD77,AB77,Z77,X77,V77) -> 10.780662 | AJ77: =U77-AI77 -> -10.780662 | AK77: =AJ77+AK75 -> -70.757458 | AL77: =AJ77/Q77 -> -0.58085462
A78: 77 | B78: Dec2024 Truck 12 | C78: 1838 | D78: RS1-241221-1 | E78: TRUE | F78: paid | G78: NA | H78: AECN | I78: truck | K78: Contrans | L78: Byron | N78: 45653 | O78: =N78+4 -> 45657 | Q78: 20.11 | U78: =Q78*T78*(44.01/12.011) -> 0 | V78: =$Q78*('MRV Calcs'!$E$3+'MRV Calcs'!$E$4) -> 2.9751124 | W78: =IF(H78="AECN",2030,"ERROR") -> 2030 | X78: =IF($I78="truck",($Q78*$W78*'MRV Calcs'!$E$7)+($W78*'MRV Calcs'!$E$8),0) -> 5.4116861 | Y78: =IF($I78="train",'MRV Calcs'!$E$24,0) -> 0 | Z78: =IF($I78="train",($Q78*$Y78*'MRV Calcs'!$E$7)+($Y78*'MRV Calcs'!$E$8),0) -> 0 | AA78: =IF($I78="train",'MRV Calcs'!$E$25,0) -> 0 | AB78: =IF($I78="train",($Q78*$AA78*'MRV Calcs'!$E$11)+($AA78*'MRV Calcs'!$E$12),0) -> 0 | AC78: =IF($I78="train",'MRV Calcs'!$E$26,0) -> 0 | AD78: =IF($I78="train",($Q78*$AC78*'MRV Calcs'!$E$7)+($AC78*'MRV Calcs'!$E$8),0) -> 0 | AE78: =($Q78/30)*SUM('MRV Calcs'!$E$15:$E$16) -> 3.044162 | AF78: ='MRV Calcs'!$E$27 -> 71.2 | AG78: =(($Q78*1.1)*$AF78*'MRV Calcs'!$E$7)+($AF78*'MRV Calcs'!$E$8) -> 0.20824333 | AH78: =(($Q78*1.1)/20)*SUM('MRV Calcs'!$E$19:$E$20) -> 0.02831488 | AI78: =SUM(AH78,AG78,AE78,AD78,AB78,Z78,X78,V78) -> 11.667519 | AJ78: =U78-AI78 -> -11.667519 | AK78: =AJ78+AK76 -> -83.918329 | AL78: =AJ78/Q78 -> -0.58018491
A79: 78 | B79: Dec2024 Truck 13 | C79: 1840 | D79: RS1-241221-1 | E79: TRUE | F79: paid | G79: NA | H79: AECN | I79: truck | K79: KAG | L79: Dave R | N79: 45653 | O79: =N79+4 -> 45657 | Q79: 20.43 | U79: =Q79*T79*(44.01/12.011) -> 0 | V79: =$Q79*('MRV Calcs'!$E$3+'MRV Calcs'!$E$4) -> 3.0224538 | W79: =IF(H79="AECN",2030,"ERROR") -> 2030 | X79: =IF($I79="truck",($Q79*$W79*'MRV Calcs'!$E$7)+($W79*'MRV Calcs'!$E$8),0) -> 5.4953202 | Y79: =IF($I79="train",'MRV Calcs'!$E$24,0) -> 0 | Z79: =IF($I79="train",($Q79*$Y79*'MRV Calcs'!$E$7)+($Y79*'MRV Calcs'!$E$8),0) -> 0 | AA79: =IF($I79="train",'MRV Calcs'!$E$25,0) -> 0 | AB79: =IF($I79="train",($Q79*$AA79*'MRV Calcs'!$E$11)+($AA79*'MRV Calcs'!$E$12),0) -> 0 | AC79: =IF($I79="train",'MRV Calcs'!$E$26,0) -> 0 | AD79: =IF($I79="train",($Q79*$AC79*'MRV Calcs'!$E$7)+($AC79*'MRV Calcs'!$E$8),0) -> 0 | AE79: =($Q79/30)*SUM('MRV Calcs'!$E$15:$E$16) -> 3.0926021 | AF79: ='MRV Calcs'!$E$27 -> 71.2 | AG79: =(($Q79*1.1)*$AF79*'MRV Calcs'!$E$7)+($AF79*'MRV Calcs'!$E$8) -> 0.21147004 | AH79: =(($Q79*1.1)/20)*SUM('MRV Calcs'!$E$19:$E$20) -> 0.02876544 | AI79: =SUM(AH79,AG79,AE79,AD79,AB79,Z79,X79,V79) -> 11.850612 | AJ79: =U79-AI79 -> -11.850612 | AK79: =AJ79+AK76 -> -84.101422 | AL79: =AJ79/Q79 -> -0.58005931
A80: 79 | B80: Dec2024 Truck 14 | C80: 1842 | D80: RS1-241221-1 | E80: TRUE | F80: paid | G80: NA | H80: AECN | I80: truck | K80: Contrans | L80: Radu | N80: 45654 | O80: 45657 | Q80: 19.87 | U80: =Q80*T80*(44.01/12.011) -> 0 | V80: =$Q80*('MRV Calcs'!$E$3+'MRV Calcs'!$E$4) -> 2.9396063 | W80: =IF(H80="AECN",2030,"ERROR") -> 2030 | X80: =IF($I80="truck",($Q80*$W80*'MRV Calcs'!$E$7)+($W80*'MRV Calcs'!$E$8),0) -> 5.3489604 | Y80: =IF($I80="train",'MRV Calcs'!$E$24,0) -> 0 | Z80: =IF($I80="train",($Q80*$Y80*'MRV Calcs'!$E$7)+($Y80*'MRV Calcs'!$E$8),0) -> 0 | AA80: =IF($I80="train",'MRV Calcs'!$E$25,0) -> 0 | AB80: =IF($I80="train",($Q80*$AA80*'MRV Calcs'!$E$11)+($AA80*'MRV Calcs'!$E$12),0) -> 0 | AC80: =IF($I80="train",'MRV Calcs'!$E$26,0) -> 0 | AD80: =IF($I80="train",($Q80*$AC80*'MRV Calcs'!$E$7)+($AC80*'MRV Calcs'!$E$8),0) -> 0 | AE80: =($Q80/30)*SUM('MRV Calcs'!$E$15:$E$16) -> 3.0078318 | AF80: ='MRV Calcs'!$E$27 -> 71.2 | AG80: =(($Q80*1.1)*$AF80*'MRV Calcs'!$E$7)+($AF80*'MRV Calcs'!$E$8) -> 0.20582329 | AH80: =(($Q80*1.1)/20)*SUM('MRV Calcs'!$E$19:$E$20) -> 0.02797696 | AI80: =SUM(AH80,AG80,AE80,AD80,AB80,Z80,X80,V80) -> 11.530199 | AJ80: =U80-AI80 -> -11.530199 | AK80: =AJ80+AK79 -> -95.631621 | AL80: =AJ80/Q80 -> -0.58028177
A81: 80 | B81: Dec2024 Truck 15 | C81: 1844 | D81: RS1-241221-1 | E81: TRUE | F81: paid | G81: NA | H81: AECN | I81: truck | K81: Contrans | L81: Brian | N81: 45654 | O81: 45657 | Q81: 18.81 | U81: =Q81*T81*(44.01/12.011) -> 0 | V81: =$Q81*('MRV Calcs'!$E$3+'MRV Calcs'!$E$4) -> 2.7827878 | W81: =IF(H81="AECN",2030,"ERROR") -> 2030 | X81: =IF($I81="truck",($Q81*$W81*'MRV Calcs'!$E$7)+($W81*'MRV Calcs'!$E$8),0) -> 5.0719222 | Y81: =IF($I81="train",'MRV Calcs'!$E$24,0) -> 0 | Z81: =IF($I81="train",($Q81*$Y81*'MRV Calcs'!$E$7)+($Y81*'MRV Calcs'!$E$8),0) -> 0 | AA81: =IF($I81="train",'MRV Calcs'!$E$25,0) -> 0 | AB81: =IF($I81="train",($Q81*$AA81*'MRV Calcs'!$E$11)+($AA81*'MRV Calcs'!$E$12),0) -> 0 | AC81: =IF($I81="train",'MRV Calcs'!$E$26,0) -> 0 | AD81: =IF($I81="train",($Q81*$AC81*'MRV Calcs'!$E$7)+($AC81*'MRV Calcs'!$E$8),0) -> 0 | AE81: =($Q81/30)*SUM('MRV Calcs'!$E$15:$E$16) -> 2.8473738 | AF81: ='MRV Calcs'!$E$27 -> 71.2 | AG81: =(($Q81*1.1)*$AF81*'MRV Calcs'!$E$7)+($AF81*'MRV Calcs'!$E$8) -> 0.1951348 | AH81: =(($Q81*1.1)/20)*SUM('MRV Calcs'!$E$19:$E$20) -> 0.02648448 | AI81: =SUM(AH81,AG81,AE81,AD81,AB81,Z81,X81,V81) -> 10.923703 | AJ81: =U81-AI81 -> -10.923703 | AK81: =AJ81+AK80 -> -106.55532 | AL81: =AJ81/Q81 -> -0.58073913
A82: 81 | B82: Dec2024 Truck 16 | C82: 1850 | D82: RS2-241225-1 | E82: TRUE | F82: paid | G82: NA | H82: AECN | I82: truck | K82: Contrans | L82: Jeffrey | N82: 45655 | O82: 45658 | Q82: 19.35 | U82: =Q82*T82*(44.01/12.011) -> 0 | V82: =$Q82*('MRV Calcs'!$E$3+'MRV Calcs'!$E$4) -> 2.8626765 | W82: =IF(H82="AECN",2030,"ERROR") -> 2030 | X82: =IF($I82="truck",($Q82*$W82*'MRV Calcs'!$E$7)+($W82*'MRV Calcs'!$E$8),0) -> 5.2130549 | Y82: =IF($I82="train",'MRV Calcs'!$E$24,0) -> 0 | Z82: =IF($I82="train",($Q82*$Y82*'MRV Calcs'!$E$7)+($Y82*'MRV Calcs'!$E$8),0) -> 0 | AA82: =IF($I82="train",'MRV Calcs'!$E$25,0) -> 0 | AB82: =IF($I82="train",($Q82*$AA82*'MRV Calcs'!$E$11)+($AA82*'MRV Calcs'!$E$12),0) -> 0 | AC82: =IF($I82="train",'MRV Calcs'!$E$26,0) -> 0 | AD82: =IF($I82="train",($Q82*$AC82*'MRV Calcs'!$E$7)+($AC82*'MRV Calcs'!$E$8),0) -> 0 | AE82: =($Q82/30)*SUM('MRV Calcs'!$E$15:$E$16) -> 2.9291166 | AF82: ='MRV Calcs'!$E$27 -> 71.2 | AG82: =(($Q82*1.1)*$AF82*'MRV Calcs'!$E$7)+($AF82*'MRV Calcs'!$E$8) -> 0.20057988 | AH82: =(($Q82*1.1)/20)*SUM('MRV Calcs'!$E$19:$E$20) -> 0.0272448 | AI82: =SUM(AH82,AG82,AE82,AD82,AB82,Z82,X82,V82) -> 11.232673 | AJ82: =U82-AI82 -> -11.232673 | AK82: =AJ82+AK81 -> -117.788 | AL82: =AJ82/Q82 -> -0.58049988
A83: 82 | B83: Dec2024 Truck 17 | C83: 1853 | D83: RS2-241225-1 | E83: TRUE | F83: paid | G83: NA | H83: AECN | I83: truck | K83: Contrans | L83: GIlles | N83: 45656 | O83: 45659 | Q83: 19.34 | U83: =Q83*T83*(44.01/12.011) -> 0 | V83: =$Q83*('MRV Calcs'!$E$3+'MRV Calcs'!$E$4) -> 2.8611971 | W83: =IF(H83="AECN",2030,"ERROR") -> 2030 | X83: =IF($I83="truck",($Q83*$W83*'MRV Calcs'!$E$7)+($W83*'MRV Calcs'!$E$8),0) -> 5.2104413 | Y83: =IF($I83="train",'MRV Calcs'!$E$24,0) -> 0 | Z83: =IF($I83="train",($Q83*$Y83*'MRV Calcs'!$E$7)+($Y83*'MRV Calcs'!$E$8),0) -> 0 | AA83: =IF($I83="train",'MRV Calcs'!$E$25,0) -> 0 | AB83: =IF($I83="train",($Q83*$AA83*'MRV Calcs'!$E$11)+($AA83*'MRV Calcs'!$E$12),0) -> 0 | AC83: =IF($I83="train",'MRV Calcs'!$E$26,0) -> 0 | AD83: =IF($I83="train",($Q83*$AC83*'MRV Calcs'!$E$7)+($AC83*'MRV Calcs'!$E$8),0) -> 0 | AE83: =($Q83/30)*SUM('MRV Calcs'!$E$15:$E$16) -> 2.9276028 | AF83: ='MRV Calcs'!$E$27 -> 71.2 | AG83: =(($Q83*1.1)*$AF83*'MRV Calcs'!$E$7)+($AF83*'MRV Calcs'!$E$8) -> 0.20047905 | AH83: =(($Q83*1.1)/20)*SUM('MRV Calcs'!$E$19:$E$20) -> 0.02723072 | AI83: =SUM(AH83,AG83,AE83,AD83,AB83,Z83,X83,V83) -> 11.226951 | AJ83: =U83-AI83 -> -11.226951 | AK83: =AJ83+AK82 -> -129.01495 | AL83: =AJ83/Q83 -> -0.58050419
A84: 83 | B84: Jan2025 Truck 1 | C84: 1863 | D84: RS3-241230-1 | E84: TRUE | F84: paid | G84: NA | H84: AECN | I84: truck | K84: Contrans | L84: Carl | N84: 45659 | O84: 45665 | Q84: 19.02 | U84: =Q84*T84*(44.01/12.011) -> 0 | V84: =$Q84*('MRV Calcs'!$E$3+'MRV Calcs'!$E$4) -> 2.8138557 | W84: =IF(H84="AECN",2030,"ERROR") -> 2030 | X84: =IF($I84="truck",($Q84*$W84*'MRV Calcs'!$E$7)+($W84*'MRV Calcs'!$E$8),0) -> 5.1268071 | Y84: =IF($I84="train",'MRV Calcs'!$E$24,0) -> 0 | Z84: =IF($I84="train",($Q84*$Y84*'MRV Calcs'!$E$7)+($Y84*'MRV Calcs'!$E$8),0) -> 0 | AA84: =IF($I84="train",'MRV Calcs'!$E$25,0) -> 0 | AB84: =IF($I84="train",($Q84*$AA84*'MRV Calcs'!$E$11)+($AA84*'MRV Calcs'!$E$12),0) -> 0 | AC84: =IF($I84="train",'MRV Calcs'!$E$26,0) -> 0 | AD84: =IF($I84="train",($Q84*$AC84*'MRV Calcs'!$E$7)+($AC84*'MRV Calcs'!$E$8),0) -> 0 | AE84: =($Q84/30)*SUM('MRV Calcs'!$E$15:$E$16) -> 2.8791626 | AF84: ='MRV Calcs'!$E$27 -> 71.2 | AG84: =(($Q84*1.1)*$AF84*'MRV Calcs'!$E$7)+($AF84*'MRV Calcs'!$E$8) -> 0.19725233 | AH84: =(($Q84*1.1)/20)*SUM('MRV Calcs'!$E$19:$E$20) -> 0.02678016 | AI84: =SUM(AH84,AG84,AE84,AD84,AB84,Z84,X84,V84) -> 11.043858 | AJ84: =U84-AI84 -> -11.043858 | AK84: =AJ84+AK83 -> -140.05881 | AL84: =AJ84/Q84 -> -0.58064448
A85: 84 | B85: INTERNAL CHARM | C85: CH02 | E85: NA | F85: CHARM OIL | G85: CHARM | H85: CHARM | I85: truck | K85: CHARM | O85: 45663 | Q85: X | U85: =Q85*T85*(44.01/12.011) -> #VALUE! | V85: =$Q85*('MRV Calcs'!$E$3+'MRV Calcs'!$E$4) -> #VALUE! | W85: =IF(H85="AECN",2030,"ERROR") -> ERROR | X85: =IF($I85="truck",($Q85*$W85*'MRV Calcs'!$E$7)+($W85*'MRV Calcs'!$E$8),0) -> #VALUE! | Y85: =IF($I85="train",'MRV Calcs'!$E$24,0) -> 0 | Z85: =IF($I85="train",($Q85*$Y85*'MRV Calcs'!$E$7)+($Y85*'MRV Calcs'!$E$8),0) -> 0 | AA85: =IF($I85="train",'MRV Calcs'!$E$25,0) -> 0 | AB85: =IF($I85="train",($Q85*$AA85*'MRV Calcs'!$E$11)+($AA85*'MRV Calcs'!$E$12),0) -> 0 | AC85: =IF($I85="train",'MRV Calcs'!$E$26,0) -> 0 | AD85: =IF($I85="train",($Q85*$AC85*'MRV Calcs'!$E$7)+($AC85*'MRV Calcs'!$E$8),0) -> 0 | AE85: =($Q85/30)*SUM('MRV Calcs'!$E$15:$E$16) -> #VALUE! | AF85: ='MRV Calcs'!$E$27 -> 71.2 | AG85: =(($Q85*1.1)*$AF85*'MRV Calcs'!$E$7)+($AF85*'MRV Calcs'!$E$8) -> #VALUE! | AH85: =(($Q85*1.1)/20)*SUM('MRV Calcs'!$E$19:$E$20) -> #VALUE! | AI85: =SUM(AH85,AG85,AE85,AD85,AB85,Z85,X85,V85) -> #VALUE! | AJ85: =U85-AI85 -> #VALUE! | AK85: =AJ85+AK84 -> #VALUE! | AL85: =AJ85/Q85 -> #VALUE!
A86: 85 | B86: Jan 2025 Truck 2 | C86: 1870 | D86: RS1-250103-1 | E86: TRUE | F86: paid | G86: NA | H86: AECN | I86: truck | K86: KAG | L86: Dave R | N86: 45661 | O86: 45666 | Q86: 19.79 | U86: =Q86*T86*(44.01/12.011) -> 0 | V86: =$Q86*('MRV Calcs'!$E$3+'MRV Calcs'!$E$4) -> 2.9277709 | W86: =IF(H86="AECN",2030,"ERROR") -> 2030 | X86: =IF($I86="truck",($Q86*$W86*'MRV Calcs'!$E$7)+($W86*'MRV Calcs'!$E$8),0) -> 5.3280519 | Y86: =IF($I86="train",'MRV Calcs'!$E$24,0) -> 0 | Z86: =IF($I86="train",($Q86*$Y86*'MRV Calcs'!$E$7)+($Y86*'MRV Calcs'!$E$8),0) -> 0 | AA86: =IF($I86="train",'MRV Calcs'!$E$25,0) -> 0 | AB86: =IF($I86="train",($Q86*$AA86*'MRV Calcs'!$E$11)+($AA86*'MRV Calcs'!$E$12),0) -> 0 | AC86: =IF($I86="train",'MRV Calcs'!$E$26,0) -> 0 | AD86: =IF($I86="train",($Q86*$AC86*'MRV Calcs'!$E$7)+($AC86*'MRV Calcs'!$E$8),0) -> 0 | AE86: =($Q86/30)*SUM('MRV Calcs'!$E$15:$E$16) -> 2.9957218 | AF86: ='MRV Calcs'!$E$27 -> 71.2 | AG86: =(($Q86*1.1)*$AF86*'MRV Calcs'!$E$7)+($AF86*'MRV Calcs'!$E$8) -> 0.20501661 | AH86: =(($Q86*1.1)/20)*SUM('MRV Calcs'!$E$19:$E$20) -> 0.02786432 | AI86: =SUM(AH86,AG86,AE86,AD86,AB86,Z86,X86,V86) -> 11.484426 | AJ86: =U86-AI86 -> -11.484426 | AK86: =AJ86+AK85 -> #VALUE! | AL86: =AJ86/Q86 -> -0.58031458
A87: 86 | B87: Jan 2025 Truck 3 | C87: 1874 | D87: RS1-250103-1 | E87: TRUE | F87: paid | G87: NA | H87: AECN | I87: truck | K87: KAG | L87: Darryl | N87: 45662 | O87: 45665 | Q87: 20.07 | S87: =iferror(if(AN87=1,VLOOKUP(#REF!, Blends!H$4:AK$1004,32,0), ""), "") | U87: =Q87*T87*(44.01/12.011) -> 0 | V87: =$Q87*('MRV Calcs'!$E$3+'MRV Calcs'!$E$4) -> 2.9691947 | W87: =IF(H87="AECN",2030,"ERROR") -> 2030 | X87: =IF($I87="truck",($Q87*$W87*'MRV Calcs'!$E$7)+($W87*'MRV Calcs'!$E$8),0) -> 5.4012318 | Y87: =IF($I87="train",'MRV Calcs'!$E$24,0) -> 0 | Z87: =IF($I87="train",($Q87*$Y87*'MRV Calcs'!$E$7)+($Y87*'MRV Calcs'!$E$8),0) -> 0 | AA87: =IF($I87="train",'MRV Calcs'!$E$25,0) -> 0 | AB87: =IF($I87="train",($Q87*$AA87*'MRV Calcs'!$E$11)+($AA87*'MRV Calcs'!$E$12),0) -> 0 | AC87: =IF($I87="train",'MRV Calcs'!$E$26,0) -> 0 | AD87: =IF($I87="train",($Q87*$AC87*'MRV Calcs'!$E$7)+($AC87*'MRV Calcs'!$E$8),0) -> 0 | AE87: =($Q87/30)*SUM('MRV Calcs'!$E$15:$E$16) -> 3.038107 | AF87: ='MRV Calcs'!$E$27 -> 71.2 | AG87: =(($Q87*1.1)*$AF87*'MRV Calcs'!$E$7)+($AF87*'MRV Calcs'!$E$8) -> 0.20783999 | AH87: =(($Q87*1.1)/20)*SUM('MRV Calcs'!$E$19:$E$20) -> 0.02825856 | AI87: =SUM(AH87,AG87,AE87,AD87,AB87,Z87,X87,V87) -> 11.644632 | AJ87: =U87-AI87 -> -11.644632 | AK87: =AJ87+AK86 -> #VALUE! | AL87: =AJ87/Q87 -> -0.5802009 | AN87: =COUNTIF(Blends!H$4:H$1007,#REF!)+COUNTIF(Blends!J$4:J$1007,#REF!)+COUNTIF(#REF!,#REF!) -> 1
A88: 87 | B88: Jan 2025 Truck 4 | C88: 1877 | D88: RS1-250103-1 | E88: TRUE | F88: paid | G88: NA | H88: AECN | I88: truck | K88: KAG | L88: Gus | N88: 45663 | O88: 45666 | Q88: 20.53 | S88: =iferror(if(AN88=1,VLOOKUP(B89, Blends!H$4:AK$1004,32,0), ""), "") | U88: =Q88*T88*(44.01/12.011) -> 0 | V88: =$Q88*('MRV Calcs'!$E$3+'MRV Calcs'!$E$4) -> 3.037248 | W88: =IF(H88="AECN",2030,"ERROR") -> 2030 | X88: =IF($I88="truck",($Q88*$W88*'MRV Calcs'!$E$7)+($W88*'MRV Calcs'!$E$8),0) -> 5.5214559 | Y88: =IF($I88="train",'MRV Calcs'!$E$24,0) -> 0 | Z88: =IF($I88="train",($Q88*$Y88*'MRV Calcs'!$E$7)+($Y88*'MRV Calcs'!$E$8),0) -> 0 | AA88: =IF($I88="train",'MRV Calcs'!$E$25,0) -> 0 | AB88: =IF($I88="train",($Q88*$AA88*'MRV Calcs'!$E$11)+($AA88*'MRV Calcs'!$E$12),0) -> 0 | AC88: =IF($I88="train",'MRV Calcs'!$E$26,0) -> 0 | AD88: =IF($I88="train",($Q88*$AC88*'MRV Calcs'!$E$7)+($AC88*'MRV Calcs'!$E$8),0) -> 0 | AE88: =($Q88/30)*SUM('MRV Calcs'!$E$15:$E$16) -> 3.1077397 | AF88: ='MRV Calcs'!$E$27 -> 71.2 | AG88: =(($Q88*1.1)*$AF88*'MRV Calcs'!$E$7)+($AF88*'MRV Calcs'!$E$8) -> 0.21247839 | AH88: =(($Q88*1.1)/20)*SUM('MRV Calcs'!$E$19:$E$20) -> 0.02890624 | AI88: =SUM(AH88,AG88,AE88,AD88,AB88,Z88,X88,V88) -> 11.907828 | AJ88: =U88-AI88 -> -11.907828 | AK88: =AJ88+AK87 -> #VALUE! | AL88: =AJ88/Q88 -> -0.58002086 | AN88: =COUNTIF(Blends!H$4:H$1007,B89)+COUNTIF(Blends!J$4:J$1007,B89)+COUNTIF(#REF!,B89) -> 1
A89: 88 | B89: Jan 2025 Truck 5 | C89: 1902 | D89: RS3-250111-1 | E89: TRUE | F89: paid | G89: NA | H89: AECN | I89: truck | K89: KAG | L89: Gus | N89: 45672 | O89: 45677 | Q89: 20.54 | S89: =iferror(if(AN89=1,VLOOKUP(B90, Blends!H$4:AK$1004,32,0), ""), "") | U89: =Q89*T89*(44.01/12.011) -> 0 | V89: =$Q89*('MRV Calcs'!$E$3+'MRV Calcs'!$E$4) -> 3.0387274 | W89: =IF(H89="AECN",2030,"ERROR") -> 2030 | X89: =IF($I89="truck",($Q89*$W89*'MRV Calcs'!$E$7)+($W89*'MRV Calcs'!$E$8),0) -> 5.5240695 | Y89: =IF($I89="train",'MRV Calcs'!$E$24,0) -> 0 | Z89: =IF($I89="train",($Q89*$Y89*'MRV Calcs'!$E$7)+($Y89*'MRV Calcs'!$E$8),0) -> 0 | AA89: =IF($I89="train",'MRV Calcs'!$E$25,0) -> 0 | AB89: =IF($I89="train",($Q89*$AA89*'MRV Calcs'!$E$11)+($AA89*'MRV Calcs'!$E$12),0) -> 0 | AC89: =IF($I89="train",'MRV Calcs'!$E$26,0) -> 0 | AD89: =IF($I89="train",($Q89*$AC89*'MRV Calcs'!$E$7)+($AC89*'MRV Calcs'!$E$8),0) -> 0 | AE89: =($Q89/30)*SUM('MRV Calcs'!$E$15:$E$16) -> 3.1092535 | AF89: ='MRV Calcs'!$E$27 -> 71.2 | AG89: =(($Q89*1.1)*$AF89*'MRV Calcs'!$E$7)+($AF89*'MRV Calcs'!$E$8) -> 0.21257922 | AH89: =(($Q89*1.1)/20)*SUM('MRV Calcs'!$E$19:$E$20) -> 0.02892032 | AI89: =SUM(AH89,AG89,AE89,AD89,AB89,Z89,X89,V89) -> 11.91355 | AJ89: =U89-AI89 -> -11.91355 | AK89: =AJ89+AK88 -> #VALUE! | AL89: =AJ89/Q89 -> -0.58001703 | AN89: =COUNTIF(Blends!H$4:H$1007,B90)+COUNTIF(Blends!J$4:J$1007,B90)+COUNTIF(#REF!,B90) -> 1
A90: 89 | B90: Jan 2025 Truck 6 | C90: 1907 | D90: RS1-250116-1 | E90: TRUE | F90: paid | G90: NA | H90: AECN | I90: truck | K90: Contrans | L90: Jeff | N90: 45674 | O90: 45676 | Q90: 19.95 | S90: =iferror(if(AN90=1,VLOOKUP(B91, Blends!H$4:AK$1004,32,0), ""), "") | U90: =Q90*T90*(44.01/12.011) -> 0 | V90: =$Q90*('MRV Calcs'!$E$3+'MRV Calcs'!$E$4) -> 2.9514417 | W90: =IF(H90="AECN",2030,"ERROR") -> 2030 | X90: =IF($I90="truck",($Q90*$W90*'MRV Calcs'!$E$7)+($W90*'MRV Calcs'!$E$8),0) -> 5.369869 | Y90: =IF($I90="train",'MRV Calcs'!$E$24,0) -> 0 | Z90: =IF($I90="train",($Q90*$Y90*'MRV Calcs'!$E$7)+($Y90*'MRV Calcs'!$E$8),0) -> 0 | AA90: =IF($I90="train",'MRV Calcs'!$E$25,0) -> 0 | AB90: =IF($I90="train",($Q90*$AA90*'MRV Calcs'!$E$11)+($AA90*'MRV Calcs'!$E$12),0) -> 0 | AC90: =IF($I90="train",'MRV Calcs'!$E$26,0) -> 0 | AD90: =IF($I90="train",($Q90*$AC90*'MRV Calcs'!$E$7)+($AC90*'MRV Calcs'!$E$8),0) -> 0 | AE90: =($Q90/30)*SUM('MRV Calcs'!$E$15:$E$16) -> 3.0199419 | AF90: ='MRV Calcs'!$E$27 -> 71.2 | AG90: =(($Q90*1.1)*$AF90*'MRV Calcs'!$E$7)+($AF90*'MRV Calcs'!$E$8) -> 0.20662997 | AH90: =(($Q90*1.1)/20)*SUM('MRV Calcs'!$E$19:$E$20) -> 0.0280896 | AI90: =SUM(AH90,AG90,AE90,AD90,AB90,Z90,X90,V90) -> 11.575972 | AJ90: =U90-AI90 -> -11.575972 | AK90: =AJ90+AK89 -> #VALUE! | AL90: =AJ90/Q90 -> -0.58024923 | AN90: =COUNTIF(Blends!H$4:H$1007,B91)+COUNTIF(Blends!J$4:J$1007,B91)+COUNTIF(#REF!,B91) -> 2
A91: 90 | B91: Jan 2025 Truck 7 | C91: 1910 | D91: RS1-250116-1 | E91: TRUE | F91: paid | G91: NA | H91: AECN | I91: truck | K91: KAG | L91: Darryl | N91: 45674 | O91: 45679 | Q91: 20.13 | S91: =iferror(if(AN91=1,VLOOKUP(B92, Blends!H$4:AK$1004,32,0), ""), "") | U91: =Q91*T91*(44.01/12.011) -> 0 | V91: =$Q91*('MRV Calcs'!$E$3+'MRV Calcs'!$E$4) -> 2.9780712 | W91: =IF(H91="AECN",2030,"ERROR") -> 2030 | X91: =IF($I91="truck",($Q91*$W91*'MRV Calcs'!$E$7)+($W91*'MRV Calcs'!$E$8),0) -> 5.4169132 | Y91: =IF($I91="train",'MRV Calcs'!$E$24,0) -> 0 | Z91: =IF($I91="train",($Q91*$Y91*'MRV Calcs'!$E$7)+($Y91*'MRV Calcs'!$E$8),0) -> 0 | AA91: =IF($I91="train",'MRV Calcs'!$E$25,0) -> 0 | AB91: =IF($I91="train",($Q91*$AA91*'MRV Calcs'!$E$11)+($AA91*'MRV Calcs'!$E$12),0) -> 0 | AC91: =IF($I91="train",'MRV Calcs'!$E$26,0) -> 0 | AD91: =IF($I91="train",($Q91*$AC91*'MRV Calcs'!$E$7)+($AC91*'MRV Calcs'!$E$8),0) -> 0 | AE91: =($Q91/30)*SUM('MRV Calcs'!$E$15:$E$16) -> 3.0471895 | AF91: ='MRV Calcs'!$E$27 -> 71.2 | AG91: =(($Q91*1.1)*$AF91*'MRV Calcs'!$E$7)+($AF91*'MRV Calcs'!$E$8) -> 0.208445 | AH91: =(($Q91*1.1)/20)*SUM('MRV Calcs'!$E$19:$E$20) -> 0.02834304 | AI91: =SUM(AH91,AG91,AE91,AD91,AB91,Z91,X91,V91) -> 11.678962 | AJ91: =U91-AI91 -> -11.678962 | AK91: =AJ91+AK90 -> #VALUE! | AL91: =AJ91/Q91 -> -0.58017695 | AN91: =COUNTIF(Blends!H$4:H$1007,B92)+COUNTIF(Blends!J$4:J$1007,B92)+COUNTIF(#REF!,B92) -> 1
A92: 91 | B92: Jan 2025 Truck 8 | C92: 1913 | D92: RS1-250116-1 | E92: TRUE | F92: paid | G92: NA | H92: AECN | I92: truck | K92: Contrans | L92: Byron | N92: 45676 | O92: 45679 | Q92: 19.86 | S92: =iferror(if(AN92=1,VLOOKUP(B93, Blends!H$4:AK$1004,32,0), ""), "") | U92: =Q92*T92*(44.01/12.011) -> 0 | V92: =$Q92*('MRV Calcs'!$E$3+'MRV Calcs'!$E$4) -> 2.9381269 | W92: =IF(H92="AECN",2030,"ERROR") -> 2030 | X92: =IF($I92="truck",($Q92*$W92*'MRV Calcs'!$E$7)+($W92*'MRV Calcs'!$E$8),0) -> 5.3463469 | Y92: =IF($I92="train",'MRV Calcs'!$E$24,0) -> 0 | Z92: =IF($I92="train",($Q92*$Y92*'MRV Calcs'!$E$7)+($Y92*'MRV Calcs'!$E$8),0) -> 0 | AA92: =IF($I92="train",'MRV Calcs'!$E$25,0) -> 0 | AB92: =IF($I92="train",($Q92*$AA92*'MRV Calcs'!$E$11)+($AA92*'MRV Calcs'!$E$12),0) -> 0 | AC92: =IF($I92="train",'MRV Calcs'!$E$26,0) -> 0 | AD92: =IF($I92="train",($Q92*$AC92*'MRV Calcs'!$E$7)+($AC92*'MRV Calcs'!$E$8),0) -> 0 | AE92: =($Q92/30)*SUM('MRV Calcs'!$E$15:$E$16) -> 3.0063181 | AF92: ='MRV Calcs'!$E$27 -> 71.2 | AG92: =(($Q92*1.1)*$AF92*'MRV Calcs'!$E$7)+($AF92*'MRV Calcs'!$E$8) -> 0.20572246 | AH92: =(($Q92*1.1)/20)*SUM('MRV Calcs'!$E$19:$E$20) -> 0.02796288 | AI92: =SUM(AH92,AG92,AE92,AD92,AB92,Z92,X92,V92) -> 11.524477 | AJ92: =U92-AI92 -> -11.524477 | AK92: =AJ92+AK91 -> #VALUE! | AL92: =AJ92/Q92 -> -0.58028586 | AN92: =COUNTIF(Blends!H$4:H$1007,B93)+COUNTIF(Blends!J$4:J$1007,B93)+COUNTIF(#REF!,B93) -> 1
A93: 92 | B93: Jan 2025 Truck 9 | C93: 1915 | D93: RS1-250116-1 | E93: TRUE | F93: paid | G93: NA | H93: AECN | I93: truck | K93: Contrans | L93: Bryan | N93: 45676 | O93: 45680 | Q93: 20.07 | S93: =iferror(if(AN93=1,VLOOKUP(B94, Blends!H$4:AK$1004,32,0), ""), "") | U93: =Q93*T93*(44.01/12.011) -> 0 | V93: =$Q93*('MRV Calcs'!$E$3+'MRV Calcs'!$E$4) -> 2.9691947 | W93: =IF(H93="AECN",2030,"ERROR") -> 2030 | X93: =IF($I93="truck",($Q93*$W93*'MRV Calcs'!$E$7)+($W93*'MRV Calcs'!$E$8),0) -> 5.4012318 | Y93: =IF($I93="train",'MRV Calcs'!$E$24,0) -> 0 | Z93: =IF($I93="train",($Q93*$Y93*'MRV Calcs'!$E$7)+($Y93*'MRV Calcs'!$E$8),0) -> 0 | AA93: =IF($I93="train",'MRV Calcs'!$E$25,0) -> 0 | AB93: =IF($I93="train",($Q93*$AA93*'MRV Calcs'!$E$11)+($AA93*'MRV Calcs'!$E$12),0) -> 0 | AC93: =IF($I93="train",'MRV Calcs'!$E$26,0) -> 0 | AD93: =IF($I93="train",($Q93*$AC93*'MRV Calcs'!$E$7)+($AC93*'MRV Calcs'!$E$8),0) -> 0 | AE93: =($Q93/30)*SUM('MRV Calcs'!$E$15:$E$16) -> 3.038107 | AF93: ='MRV Calcs'!$E$27 -> 71.2 | AG93: =(($Q93*1.1)*$AF93*'MRV Calcs'!$E$7)+($AF93*'MRV Calcs'!$E$8) -> 0.20783999 | AH93: =(($Q93*1.1)/20)*SUM('MRV Calcs'!$E$19:$E$20) -> 0.02825856 | AI93: =SUM(AH93,AG93,AE93,AD93,AB93,Z93,X93,V93) -> 11.644632 | AJ93: =U93-AI93 -> -11.644632 | AK93: =AJ93+AK92 -> #VALUE! | AL93: =AJ93/Q93 -> -0.5802009 | AN93: =COUNTIF(Blends!H$4:H$1007,B94)+COUNTIF(Blends!J$4:J$1007,B94)+COUNTIF(#REF!,B94) -> 1
A94: 93 | B94: Jan 2025 Truck 10 | C94: 1917 | D94: RS2-250119-1 | E94: TRUE | F94: paid | G94: NA | H94: AECN | I94: truck | K94: Contrans | L94: Dave P | N94: 45677 | O94: 45681 | Q94: 20.09 | S94: =iferror(if(AN94=1,VLOOKUP(B95, Blends!H$4:AK$1004,32,0), ""), "") | U94: =Q94*T94*(44.01/12.011) -> 0 | V94: =$Q94*('MRV Calcs'!$E$3+'MRV Calcs'!$E$4) -> 2.9721535 | W94: =IF(H94="AECN",2030,"ERROR") -> 2030 | X94: =IF($I94="truck",($Q94*$W94*'MRV Calcs'!$E$7)+($W94*'MRV Calcs'!$E$8),0) -> 5.4064589 | Y94: =IF($I94="train",'MRV Calcs'!$E$24,0) -> 0 | Z94: =IF($I94="train",($Q94*$Y94*'MRV Calcs'!$E$7)+($Y94*'MRV Calcs'!$E$8),0) -> 0 | AA94: =IF($I94="train",'MRV Calcs'!$E$25,0) -> 0 | AB94: =IF($I94="train",($Q94*$AA94*'MRV Calcs'!$E$11)+($AA94*'MRV Calcs'!$E$12),0) -> 0 | AC94: =IF($I94="train",'MRV Calcs'!$E$26,0) -> 0 | AD94: =IF($I94="train",($Q94*$AC94*'MRV Calcs'!$E$7)+($AC94*'MRV Calcs'!$E$8),0) -> 0 | AE94: =($Q94/30)*SUM('MRV Calcs'!$E$15:$E$16) -> 3.0411345 | AF94: ='MRV Calcs'!$E$27 -> 71.2 | AG94: =(($Q94*1.1)*$AF94*'MRV Calcs'!$E$7)+($AF94*'MRV Calcs'!$E$8) -> 0.20804166 | AH94: =(($Q94*1.1)/20)*SUM('MRV Calcs'!$E$19:$E$20) -> 0.02828672 | AI94: =SUM(AH94,AG94,AE94,AD94,AB94,Z94,X94,V94) -> 11.656075 | AJ94: =U94-AI94 -> -11.656075 | AK94: =AJ94+AK93 -> #VALUE! | AL94: =AJ94/Q94 -> -0.5801929 | AN94: =COUNTIF(Blends!H$4:H$1007,B95)+COUNTIF(Blends!J$4:J$1007,B95)+COUNTIF(#REF!,B95) -> 1
A95: 94 | B95: Jan 2025 Truck 11 | C95: 1928 | D95: RS3-250123-1 | E95: TRUE | F95: paid | G95: NA | H95: AECN | I95: truck | K95: Contrans | L95: Chris | N95: 45682 | O95: 45685 | Q95: 19.84 | S95: =iferror(if(AN95=1,VLOOKUP(B96, Blends!H$4:AK$1004,32,0), ""), "") | U95: =Q95*T95*(44.01/12.011) -> 0 | V95: =$Q95*('MRV Calcs'!$E$3+'MRV Calcs'!$E$4) -> 2.935168 | W95: =IF(H95="AECN",2030,"ERROR") -> 2030 | X95: =IF($I95="truck",($Q95*$W95*'MRV Calcs'!$E$7)+($W95*'MRV Calcs'!$E$8),0) -> 5.3411197 | Y95: =IF($I95="train",'MRV Calcs'!$E$24,0) -> 0 | Z95: =IF($I95="train",($Q95*$Y95*'MRV Calcs'!$E$7)+($Y95*'MRV Calcs'!$E$8),0) -> 0 | AA95: =IF($I95="train",'MRV Calcs'!$E$25,0) -> 0 | AB95: =IF($I95="train",($Q95*$AA95*'MRV Calcs'!$E$11)+($AA95*'MRV Calcs'!$E$12),0) -> 0 | AC95: =IF($I95="train",'MRV Calcs'!$E$26,0) -> 0 | AD95: =IF($I95="train",($Q95*$AC95*'MRV Calcs'!$E$7)+($AC95*'MRV Calcs'!$E$8),0) -> 0 | AE95: =($Q95/30)*SUM('MRV Calcs'!$E$15:$E$16) -> 3.0032906 | AF95: ='MRV Calcs'!$E$27 -> 71.2 | AG95: =(($Q95*1.1)*$AF95*'MRV Calcs'!$E$7)+($AF95*'MRV Calcs'!$E$8) -> 0.20552079 | AH95: =(($Q95*1.1)/20)*SUM('MRV Calcs'!$E$19:$E$20) -> 0.02793472 | AI95: =SUM(AH95,AG95,AE95,AD95,AB95,Z95,X95,V95) -> 11.513034 | AJ95: =U95-AI95 -> -11.513034 | AK95: =AJ95+AK94 -> #VALUE! | AL95: =AJ95/Q95 -> -0.58029404 | AN95: =COUNTIF(Blends!H$4:H$1007,B96)+COUNTIF(Blends!J$4:J$1007,B96)+COUNTIF(#REF!,B96) -> 2
A96: 95 | B96: Jan 2025 Truck 12 | C96: 1929 | D96: RS3-250123-1 | E96: TRUE | F96: paid | G96: NA | H96: AECN | I96: truck | K96: Contrans | L96: Chris | N96: 45682 | O96: 45686 | Q96: 19.83 | S96: =iferror(if(AN96=1,VLOOKUP(B97, Blends!H$4:AK$1004,32,0), ""), "") | U96: =Q96*T96*(44.01/12.011) -> 0 | V96: =$Q96*('MRV Calcs'!$E$3+'MRV Calcs'!$E$4) -> 2.9336886 | W96: =IF(H96="AECN",2030,"ERROR") -> 2030 | X96: =IF($I96="truck",($Q96*$W96*'MRV Calcs'!$E$7)+($W96*'MRV Calcs'!$E$8),0) -> 5.3385062 | Y96: =IF($I96="train",'MRV Calcs'!$E$24,0) -> 0 | Z96: =IF($I96="train",($Q96*$Y96*'MRV Calcs'!$E$7)+($Y96*'MRV Calcs'!$E$8),0) -> 0 | AA96: =IF($I96="train",'MRV Calcs'!$E$25,0) -> 0 | AB96: =IF($I96="train",($Q96*$AA96*'MRV Calcs'!$E$11)+($AA96*'MRV Calcs'!$E$12),0) -> 0 | AC96: =IF($I96="train",'MRV Calcs'!$E$26,0) -> 0 | AD96: =IF($I96="train",($Q96*$AC96*'MRV Calcs'!$E$7)+($AC96*'MRV Calcs'!$E$8),0) -> 0 | AE96: =($Q96/30)*SUM('MRV Calcs'!$E$15:$E$16) -> 3.0017768 | AF96: ='MRV Calcs'!$E$27 -> 71.2 | AG96: =(($Q96*1.1)*$AF96*'MRV Calcs'!$E$7)+($AF96*'MRV Calcs'!$E$8) -> 0.20541995 | AH96: =(($Q96*1.1)/20)*SUM('MRV Calcs'!$E$19:$E$20) -> 0.02792064 | AI96: =SUM(AH96,AG96,AE96,AD96,AB96,Z96,X96,V96) -> 11.507312 | AJ96: =U96-AI96 -> -11.507312 | AK96: =AJ96+AK95 -> #VALUE! | AL96: =AJ96/Q96 -> -0.58029814 | AN96: =COUNTIF(Blends!H$4:H$1007,B97)+COUNTIF(Blends!J$4:J$1007,B97)+COUNTIF(#REF!,B97) -> 1
A97: 96 | B97: Jan 2025 Truck 13 | C97: 1930 | D97: RS3-250123-1 | E97: TRUE | F97: paid | G97: NA | H97: AECN | I97: truck | K97: KAG | L97: Darryl | N97: 45682 | O97: 45686 | Q97: 20.33 | S97: =iferror(if(AN97=1,VLOOKUP(B98, Blends!H$4:AK$1004,32,0), ""), "") | U97: =Q97*T97*(44.01/12.011) -> 0 | V97: =$Q97*('MRV Calcs'!$E$3+'MRV Calcs'!$E$4) -> 3.0076596 | W97: =IF(H97="AECN",2030,"ERROR") -> 2030 | X97: =IF($I97="truck",($Q97*$W97*'MRV Calcs'!$E$7)+($W97*'MRV Calcs'!$E$8),0) -> 5.4691846 | Y97: =IF($I97="train",'MRV Calcs'!$E$24,0) -> 0 | Z97: =IF($I97="train",($Q97*$Y97*'MRV Calcs'!$E$7)+($Y97*'MRV Calcs'!$E$8),0) -> 0 | AA97: =IF($I97="train",'MRV Calcs'!$E$25,0) -> 0 | AB97: =IF($I97="train",($Q97*$AA97*'MRV Calcs'!$E$11)+($AA97*'MRV Calcs'!$E$12),0) -> 0 | AC97: =IF($I97="train",'MRV Calcs'!$E$26,0) -> 0 | AD97: =IF($I97="train",($Q97*$AC97*'MRV Calcs'!$E$7)+($AC97*'MRV Calcs'!$E$8),0) -> 0 | AE97: =($Q97/30)*SUM('MRV Calcs'!$E$15:$E$16) -> 3.0774646 | AF97: ='MRV Calcs'!$E$27 -> 71.2 | AG97: =(($Q97*1.1)*$AF97*'MRV Calcs'!$E$7)+($AF97*'MRV Calcs'!$E$8) -> 0.21046169 | AH97: =(($Q97*1.1)/20)*SUM('MRV Calcs'!$E$19:$E$20) -> 0.02862464 | AI97: =SUM(AH97,AG97,AE97,AD97,AB97,Z97,X97,V97) -> 11.793395 | AJ97: =U97-AI97 -> -11.793395 | AK97: =AJ97+AK96 -> #VALUE! | AL97: =AJ97/Q97 -> -0.58009813 | AN97: =COUNTIF(Blends!H$4:H$1007,B98)+COUNTIF(Blends!J$4:J$1007,B98)+COUNTIF(#REF!,B98) -> 1
A98: 97 | B98: Jan 2025 Truck 14 | C98: 1934 | D98: RS3-250123-1 | E98: TRUE | F98: paid | G98: NA | H98: AECN | I98: truck | K98: Contrans | L98: Gordon | N98: 45683 | O98: 45687 | Q98: 19.97 | S98: =iferror(if(AN98=1,VLOOKUP(#REF!, Blends!H$4:AK$1004,32,0), ""), "") | U98: =Q98*T98*(44.01/12.011) -> 0 | V98: =$Q98*('MRV Calcs'!$E$3+'MRV Calcs'!$E$4) -> 2.9544005 | W98: =IF(H98="AECN",2030,"ERROR") -> 2030 | X98: =IF($I98="truck",($Q98*$W98*'MRV Calcs'!$E$7)+($W98*'MRV Calcs'!$E$8),0) -> 5.3750961 | Y98: =IF($I98="train",'MRV Calcs'!$E$24,0) -> 0 | Z98: =IF($I98="train",($Q98*$Y98*'MRV Calcs'!$E$7)+($Y98*'MRV Calcs'!$E$8),0) -> 0 | AA98: =IF($I98="train",'MRV Calcs'!$E$25,0) -> 0 | AB98: =IF($I98="train",($Q98*$AA98*'MRV Calcs'!$E$11)+($AA98*'MRV Calcs'!$E$12),0) -> 0 | AC98: =IF($I98="train",'MRV Calcs'!$E$26,0) -> 0 | AD98: =IF($I98="train",($Q98*$AC98*'MRV Calcs'!$E$7)+($AC98*'MRV Calcs'!$E$8),0) -> 0 | AE98: =($Q98/30)*SUM('MRV Calcs'!$E$15:$E$16) -> 3.0229694 | AF98: ='MRV Calcs'!$E$27 -> 71.2 | AG98: =(($Q98*1.1)*$AF98*'MRV Calcs'!$E$7)+($AF98*'MRV Calcs'!$E$8) -> 0.20683164 | AH98: =(($Q98*1.1)/20)*SUM('MRV Calcs'!$E$19:$E$20) -> 0.02811776 | AI98: =SUM(AH98,AG98,AE98,AD98,AB98,Z98,X98,V98) -> 11.587415 | AJ98: =U98-AI98 -> -11.587415 | AK98: =AJ98+AK97 -> #VALUE! | AL98: =AJ98/Q98 -> -0.58024113 | AN98: =COUNTIF(Blends!H$4:H$1007,#REF!)+COUNTIF(Blends!J$4:J$1007,#REF!)+COUNTIF(#REF!,#REF!) -> 1
A99: 98 | B99: Jan 2025 Truck 15 | C99: 1937 | D99: RS3-250123-1 | E99: TRUE | F99: paid | G99: NA | H99: AECN | I99: truck | K99: Contrans | L99: Luc | N99: 45685 | O99: 45688 | Q99: 19.36 | S99: =iferror(if(AN99=1,VLOOKUP(B99, Blends!H$4:AK$1004,32,0), ""), "") | U99: =Q99*T99*(44.01/12.011) -> 0 | V99: =$Q99*('MRV Calcs'!$E$3+'MRV Calcs'!$E$4) -> 2.8641559 | W99: =IF(H99="AECN",2030,"ERROR") -> 2030 | X99: =IF($I99="truck",($Q99*$W99*'MRV Calcs'!$E$7)+($W99*'MRV Calcs'!$E$8),0) -> 5.2156684 | Y99: =IF($I99="train",'MRV Calcs'!$E$24,0) -> 0 | Z99: =IF($I99="train",($Q99*$Y99*'MRV Calcs'!$E$7)+($Y99*'MRV Calcs'!$E$8),0) -> 0 | AA99: =IF($I99="train",'MRV Calcs'!$E$25,0) -> 0 | AB99: =IF($I99="train",($Q99*$AA99*'MRV Calcs'!$E$11)+($AA99*'MRV Calcs'!$E$12),0) -> 0 | AC99: =IF($I99="train",'MRV Calcs'!$E$26,0) -> 0 | AD99: =IF($I99="train",($Q99*$AC99*'MRV Calcs'!$E$7)+($AC99*'MRV Calcs'!$E$8),0) -> 0 | AE99: =($Q99/30)*SUM('MRV Calcs'!$E$15:$E$16) -> 2.9306303 | AF99: ='MRV Calcs'!$E$27 -> 71.2 | AG99: =(($Q99*1.1)*$AF99*'MRV Calcs'!$E$7)+($AF99*'MRV Calcs'!$E$8) -> 0.20068072 | AH99: =(($Q99*1.1)/20)*SUM('MRV Calcs'!$E$19:$E$20) -> 0.02725888 | AI99: =SUM(AH99,AG99,AE99,AD99,AB99,Z99,X99,V99) -> 11.238394 | AJ99: =U99-AI99 -> -11.238394 | AK99: =AJ99+#REF! -> #REF! | AL99: =AJ99/Q99 -> -0.58049557 | AN99: =COUNTIF(Blends!H$4:H$1007,B99)+COUNTIF(Blends!J$4:J$1007,B99)+COUNTIF(#REF!,B99) -> 1
A100: 99 | B100: Jan 2025 Truck 16 | C100: 1948T | D100: RS1-250127-1 | E100: TRUE | F100: paid | G100: NA | H100: AECN | I100: truck | K100: KAG | L100: Darryl | N100: 45689 | O100: 45694 | Q100: 18.86 | S100: =iferror(if(AN100=1,VLOOKUP(B100, Blends!H$4:AK$1004,32,0), ""), "") | U100: =Q100*T100*(44.01/12.011) -> 0 | V100: =$Q100*('MRV Calcs'!$E$3+'MRV Calcs'!$E$4) -> 2.7901849 | W100: =IF(H100="AECN",2030,"ERROR") -> 2030 | X100: =IF($I100="truck",($Q100*$W100*'MRV Calcs'!$E$7)+($W100*'MRV Calcs'!$E$8),0) -> 5.08499 | Y100: =IF($I100="train",'MRV Calcs'!$E$24,0) -> 0 | Z100: =IF($I100="train",($Q100*$Y100*'MRV Calcs'!$E$7)+($Y100*'MRV Calcs'!$E$8),0) -> 0 | AA100: =IF($I100="train",'MRV Calcs'!$E$25,0) -> 0 | AB100: =IF($I100="train",($Q100*$AA100*'MRV Calcs'!$E$11)+($AA100*'MRV Calcs'!$E$12),0) -> 0 | AC100: =IF($I100="train",'MRV Calcs'!$E$26,0) -> 0 | AD100: =IF($I100="train",($Q100*$AC100*'MRV Calcs'!$E$7)+($AC100*'MRV Calcs'!$E$8),0) -> 0 | AE100: =($Q100/30)*SUM('MRV Calcs'!$E$15:$E$16) -> 2.8549426 | AF100: ='MRV Calcs'!$E$27 -> 71.2 | AG100: =(($Q100*1.1)*$AF100*'MRV Calcs'!$E$7)+($AF100*'MRV Calcs'!$E$8) -> 0.19563898 | AH100: =(($Q100*1.1)/20)*SUM('MRV Calcs'!$E$19:$E$20) -> 0.02655488 | AI100: =SUM(AH100,AG100,AE100,AD100,AB100,Z100,X100,V100) -> 10.952311 | AJ100: =U100-AI100 -> -10.952311 | AK100: =AJ100+AK99 -> #REF! | AL100: =AJ100/Q100 -> -0.5807164 | AN100: =COUNTIF(Blends!H$4:H$1007,B100)+COUNTIF(Blends!J$4:J$1007,B100)+COUNTIF(#REF!,B100) -> 1
...

Sheet COAs
A1: Date of Analysis | B1: Reference Number | C1: Water % | D1: Viscosity (cSt) | E1: pH | F1: Density @ 60°F, kg/dm3 | G1: Drive URL | I1: Average %WC
A2: 45497 | B2: RS2-240724-1 | C2: 24.3 | D2: 27 | E2: 3 | G2: https://drive.google.com/file/d/1K4mJuB3617D1yU3aezTvr8gTw2w4wlPh/view | I2: =AVERAGE(C2:C243) -> 23.815768
A3: 45498 | B3: RS1-240725-1 | C3: 24.3 | D3: 28.1 | E3: 3 | G3: https://drive.google.com/file/d/1aFNIUFBwfotViRK-ysaa93LpsURa4Q6l/view | I3: =STDEV(C2:C244) -> 1.2035774
A4: 45502 | B4: RS1-240729-2 | C4: 24.1 | D4: 29.6 | E4: 3 | G4: https://drive.google.com/file/d/13N48Lm8GBaBZv4Hq56zveS2NkB9GOIV8/view
A5: 45497 | B5: RS2-240724-1 | C5: 24.3 | D5: 27 | E5: 3 | G5: https://drive.google.com/file/d/1IriTsU4q-YKweMOi7u-iRjjmjL7GfRiI/view
A6: 45519 | B6: RS1-240815-1 | C6: 24.4 | D6: 33.8 | E6: 3 | G6: https://drive.google.com/file/d/1LlDf3QP1s3nw4utaPgPpZguJP637oq76/view
A7: 45519 | B7: RS1-240815-1 | C7: 24.4 | D7: 33.8 | E7: 3 | G7: https://drive.google.com/file/d/1gMUT9xcssKLBYcpfuw_LPL3QoNGCuRuS/view
A8: 45527 | B8: RS2-240822-1 | C8: 23.6 | D8: 32.5 | E8: 3 | G8: https://drive.google.com/file/d/1Imr6ONWF-fMLPk4OSxBDb_1Rz7cWPKZ0/view
A9: 45523 | B9: RS3-240819-1 | C9: 24.3 | D9: 28.7 | E9: 3 | G9: https://drive.google.com/file/d/142XTlCZ9V5TbQW6qSu_WMdJU1atrM_Pm/view
A10: 45532 | B10: RS1-240828-1 | C10: 23.5 | D10: 38.8 | E10: 2.9 | G10: https://drive.google.com/file/d/14xq0hdznqYxJ00JY48fIb9-oA2Iv69EP/view
A11: 45527 | B11: RS2-240822-1 | C11: 23.6 | D11: 32.5 | E11: 3 | G11: https://drive.google.com/file/d/151VV9-49KY5wuWjIpuX4pj-40ZUHS0NK/view
A12: 45537 | B12: RS3-240902-1 | C12: 23.4 | D12: 36.3 | E12: 3.1 | G12: https://drive.google.com/file/d/10CAzUnjJSbWsQrfjbwB5nfq65qZWIF7f/view
A13: 45532 | B13: RS1-240828-1 | C13: 23.5 | D13: 38.8 | E13: 2.9 | G13: https://drive.google.com/file/d/10rOTOrdW59rY4z4kE_tB7QTAGOeWSFQl/view
A14: 45537 | B14: RS3-240902-1 | C14: 23.4 | D14: 36.3 | E14: 3.1 | G14: https://drive.google.com/file/d/13fg7CY0tgZzGCABy8odErLQGcxTe3Dh1/view
A15: 45541 | B15: RS2-240906-1 | C15: 23.2 | D15: 30.6 | E15: 3.1 | G15: https://drive.google.com/file/d/1557UPDyQ4OxLW7D8T0HBDVIoRSIOcPRV/view
... A21: 45551 | B21: RS2-240916-1 | C21: 22.3 | D21: 30.1 | E21: 3.1 | G21: https://drive.google.com/file/d/1b6lmYT-XCrooDwiqu0vz4bxgheBqSIlM/view
A22: 45556 | B22: RS2-240921-1 | C22: 22.9 | D22: 30.7 | E22: 3.1 | G22: https://drive.google.com/file/d/1kT_4Ka4qbww481PKwJo7p38EK9No8wgM/view | J22: 8000 | K22: 7000 | L22: =J22/K22 -> 1.1428571
A23: 45559 | B23: RS3-240924-1 | C23: 23 | D23: 29.3 | E23: 3.1 | G23: https://drive.google.com/file/d/1d-wWHKOnfp8-OSQmPqOuBHHMZfcsAhaU/view | J23: 8000 | K23: =L23*J23 -> 5485.7143 | L23: =L22*0.6 -> 0.68571429
A24: 45563 | B24: RS3-240928-1 | C24: 24.2 | D24: 31.7 | E24: 3.1 | G24: https://drive.google.com/file/d/1o8BeLmOjk0mbw0kEbLeMWKOGq4QIsXGZ/view
A25: 45566 | B25: RS2-241001-1 | C25: 25.4 | D25: 30.8 | E25: 3.1 | G25: https://drive.google.com/file/d/1gAdJxXpK_JAfxBax3Fg_9xbF_OWg8RBe/view | K25: =K23*0.23 -> 1261.7143
A26: 45567 | B26: RS3-241002-1 | C26: 24.9 | D26: 37.2 | E26: 3.1 | G26: https://drive.google.com/file/d/1TzHIFCEHwEXiNc-R196BGhP5JQrYISdk/view
A27: 45573 | B27: RS1-241008-1 | C27: 25.1 | D27: 28.4 | E27: 3.1 | G27: https://drive.google.com/file/d/1IiEvfHjKg7VAwmgxfGwQEahfYZpyKORH/view
A28: 45566 | B28: RS2-241001-1 | C28: 25.4 | D28: 30.8 | E28: 3.1 | G28: https://drive.google.com/file/d/1HqeLvpq3nvk5V3fMI5rjp88wsMLSn3a4/view
A29: 45563 | B29: RS3-240928-1 | C29: 24.2 | D29: 31.7 | E29: 3.1 | G29: https://drive.google.com/file/d/16_auAIo5a73MrD7xgKlQzENvcMe55rhm/view
A30: 45579 | B30: RS1-241013-1 | C30: 25.4 | D30: 33 | E30: 3 | G30: https://drive.google.com/file/d/1AUSPFkFCMZmktY30jHqr8A2-XGd-xNq9/view
A31: 45576 | B31: RS3-241011-1 | C31: 23.6 | D31: 29.7 | E31: 3.1 | G31: https://drive.google.com/file/d/1b4b-XGRQLH8yBJVN6Y0tUiUXBmgJh8eS/view
A32: 45583 | B32: RS2-241018-1 | C32: 22.7 | D32: 30.5 | E32: 3 | G32: https://drive.google.com/file/d/1aexe7KRlE-5x8IusRX4pQ4_AQKnncyjc/view
A33: 45576 | B33: RS3-241011-1 | C33: 23.6 | D33: 29.7 | E33: 3.1 | G33: https://drive.google.com/file/d/1HqglTQ9_6lBP5yRRZI3flIX3tASEl4kN/view
A34: 45587 | B34: RS3-241022-1 | C34: 23.4 | D34: 33 | E34: 3 | G34: https://drive.google.com/file/d/1l2zp6ab3tGvJ-_OuX8R25GEYGWML2Uhp/view
A35: 45583 | B35: RS2-241018-1 | C35: 22.7 | D35: 30.5 | E35: 3 | G35: https://drive.google.com/file/d/1VggJJ-LaIgINU-aTOCXqfYW1dft9ECLG/view
A36: 45591 | B36: RS1-241026-1 | C36: 24 | D36: 35.4 | E36: 3.1 | G36: https://drive.google.com/file/d/1ON2S6OAmgVcOyV8VuhbUh3FP-AQNZNrt/view
A37: 45587 | B37: RS3-241022-1 | C37: 23.4 | D37: 33 | E37: 3 | G37: https://drive.google.com/file/d/1NkCCKmmXphQf12IcMFryKy8by0ZGwloL/view
... A41: 45600 | B41: RS3-241104-1 | C41: 23.4 | D41: 36.9 | E41: 3 | G41: https://drive.google.com/file/d/1zkLgD_5McPRyWdfudHONZbOTdVdupPyw/view
A42: 45603 | B42: RS1-241107-1 | C42: 23.8 | D42: 34.8 | E42: 3.1 | F42: 1.2198 | G42: https://drive.google.com/file/d/1jiPyi3Z3W1W8bKO0hdjDL6G8mUsJKxCP/view
A43: 45600 | B43: RS3-241104-1 | C43: 23.4 | D43: 36.9 | E43: 3 | G43: https://drive.google.com/file/d/1jRnCUn4adSSpsYhSfVR3IFW8IFy2v1Tr/view
A44: 45614 | B44: RS1-241118-1 | C44: 23.5 | D44: 33.4 | E44: 3 | G44: https://drive.google.com/file/d/1FvdvlKCEh7DSuQuAgAJgSHuq9VAI04sP/view
A45: 45603 | B45: RS1-241107-1 | C45: 23.8 | D45: 34.8 | E45: 3.1 | F45: 1.2198 | G45: https://drive.google.com/file/d/1McFSeUg5Y7rDLqPK389hucT4JhrD5P4Y/view
A46: 45614 | B46: RS1-241118-1 | C46: 23.5 | D46: 33.4 | E46: 3 | G46: https://drive.google.com/file/d/1JwzEEm4RG6CmkBzkNADn8b9BP7UahID7/view
A47: 45614 | B47: RS1-241118-1 | C47: 23.5 | D47: 33.4 | E47: 3 | G47: https://drive.google.com/file/d/1NYnENZmnA9pzPaz1sU4XHrgAxiqOeQY2/view
A48: 45617 | B48: RS3-241121-1 | C48: 23.7 | D48: 34.2 | E48: 3 | F48: 1.2205 | G48: https://drive.google.com/file/d/1l-clIgTl7O1sK3SzvWurtNDP633zmm6Q/view
A49: 45610 | B49: RS3-241114-1 | C49: 24.2 | D49: 31.9 | E49: 3 | F49: 1.2191 | G49: https://drive.google.com/file/d/15mw0YBYbZIhP7mL9yWgPEciTYKsKyfyO/view
A50: 45616 | B50: RS2-241119-1 | C50: 24.8 | D50: 36.5 | E50: 3 | F50: 1.2197 | G50: https://drive.google.com/file/d/1CmmXBTmZtWe3S84T3OCj6v5pAtFsXKKZ/view
A51: 45606 | B51: RS2-241110-1 | C51: 24.5 | D51: 30.5 | E51: 3 | F51: 1.2181 | G51: https://drive.google.com/file/d/1L3XPhSl_0PorvhmvcHKUQAWeqOtKWVkk/view
A52: 45616 | B52: RS2-241119-1 | C52: 24.8 | D52: 36.5 | E52: 3 | F52: 1.2197 | G52: https://drive.google.com/file/d/1vEW99VggeAxvVt8KdHjoW181DJAWDgZz/view
A53: 45614 | B53: RS1-241118-1 | C53: 23.5 | D53: 33.4 | E53: 3 | F53: 1.2221 | G53: https://drive.google.com/file/d/1ji-iJWbI0WCJQ0TyKISZ9Yj8LfroF5sp/view
A54: 45614 | B54: RS1-241118-1 | C54: 23.5 | D54: 33.4 | E54: 3 | F54: 1.2221 | G54: https://drive.google.com/file/d/1ltu0yd0JYq5Kk4rmKDD6y0gCZu5pVEJV/view
A55: 45614 | B55: RS1-241118-1 | C55: 23.5 | D55: 33.4 | E55: 3 | F55: 1.2221 | G55: https://drive.google.com/file/d/1UtiXZ-aQ8Sz5crQZANvZuQptCyOJ0SKf/view
A56: 45614 | B56: RS1-241118-1 | C56: 23.5 | D56: 33.4 | E56: 3 | F56: 1.2221 | G56: https://drive.google.com/file/d/1sjt03ot1l9EbEJzp5x_Vx1tzADsXM1Lt/view
A57: 45616 | B57: RS2-241119-1 | C57: 24.8 | D57: 36.5 | E57: 3 | F57: 1.2197 | G57: https://drive.google.com/file/d/14C07v6-fpt4e7nmJZQA5ZrSPLBUoPtR3/view
A58: 45617 | B58: RS3-241121-1 | C58: 23.7 | D58: 34.2 | E58: 3 | F58: 1.2205 | G58: https://drive.google.com/file/d/13dp4_pX1y-qoMGZJNRvUWqKNnLMNRnHA/view
A59: 45629 | B59: RS1-241203-1 | C59: 22.6 | D59: 56.1 | E59: 2.9 | F59: 1.2275 | G59: https://drive.google.com/file/d/1xGnbZgkk6eT8X4I4IoIK8o_yNIVEzdSU/view
... A130: 45728 | B130: RS3-250312-1 | C130: 23.4 | D130: 25.5 | E130: 2.9 | F130: 1.2148 | G130: https://drive.google.com/file/d/1uQe3VZxGTTO3lRoJhx61GwcEGIt3BjLS/view
A131: 45737 | B131: RS3-250320-1 | C131: 24 | D131: 26.7 | E131: 2.9 | G131: https://drive.google.com/file/d/1ft-St0-PEDk3-kIVJyfavW2wvLzFwgPD/view
A132: 45732 | B132: RS3-250316-1 | C132: 23.3 | D132: 26.3 | E132: 2.9 | G132: https://drive.google.com/file/d/1PUjMG7tMF8vR8sTwmC-ebn5KtslFsdU9/view
A133: 45739 | B133: RS1-250323-1 | C133: 22.1 | D133: 30.2 | E133: 2.9 | G133: https://drive.google.com/file/d/1qajxwp3lBa43Qzby76VhHBs6DkI5-7uV/view
A134: 45734 | B134: RS1-250318-1 | C134: 24.5 | D134: 24.3 | E134: 2.9 | G134: https://drive.google.com/file/d/13x_r5byLaBzFewotlH3xMKtxpMp-PqkB/view
A135: 45737 | B135: RS3-250320-1 | C135: 24 | D135: 26.7 | E135: 2.9 | G135: https://drive.google.com/file/d/1_V4iitkCRPA0gaGWAb_0FMZdwRwMfBYY/view
A136: 45739 | B136: RS1-250323-1 | C136: 22.1 | D136: 30.2 | E136: 2.9 | G136: https://drive.google.com/file/d/1KW-IlyQjl-zZo63FW6tLRWhdvK_sS__Z/view
A137: 45743 | B137: RS3-250327-1 | C137: 25.4 | D137: 30.2 | E137: 2.8 | G137: https://drive.google.com/file/d/1DQhPhxsdFTVyeQ7aYbZjN-rvmo2MNGbX/view
A138: 45751 | B138: RS3-250404-1 | C138: 24.9 | D138: 25.1 | E138: 2.8 | G138: https://drive.google.com/file/d/1qpjVdNtMaQWSrb82pAXu3X9oc_aEZQqn/view
A139: 45753 | B139: RS1-250406-1 | C139: 23.4 | D139: 26 | E139: 2.8 | G139: https://drive.google.com/file/d/1PSLNacmtmG69QbijyVXh8a7mCdzg0rP4/view
A140: 45755 | B140: RS3-250408-1 | C140: 24.1 | D140: 23.5 | E140: 2.7 | G140: https://drive.google.com/file/d/1O0Mh8MQTIBkpvZJMQQX9R-rWkKInpYg8/view
A141: 45751 | B141: RS3-250404-1 | C141: 24.9 | D141: 25.1 | E141: 2.8 | G141: https://drive.google.com/file/d/1ectRKZ-xxSBv5pi8YBZrMZilnSWSbArF/view
A142: 45756 | B142: RS1-250409-1 | C142: 21.6 | D142: 24.1 | E142: 3.1 | G142: https://drive.google.com/file/d/10dFIT-4qwePcefOljqnZMHrSCkyYwEPO/view
... A165: 45788 | B165: RS3-250511-1 | C165: 25.3 | D165: 29.7 | E165: 2.9 | G165: https://drive.google.com/file/d/1Y8rFoguq1NdVRBJ8gXsEBl6yuJgtd_d5/view
B166: RS1-250512-1 | C166: 24.7 | D166: 30.7 | E166: 2.9 | G166: https://drive.google.com/file/d/1FlNfv2a-fRdUmR9Rw-FUcejluyJY_ntR/view
A167: 45789 | B167: RS1-250512-1 | C167: 24.7 | D167: 30.7 | E167: 2.9 | G167: https://drive.google.com/file/d/1sd9XJED0U0nNzq1frPzvT-P-8lZm_bvT/view
A168: 45781 | B168: RS3-250504-1 | C168: 24.3 | D168: 26.7 | E168: 2.8 | G168: https://drive.google.com/file/d/1xJeh8sjzFscns2ylVyb3UPayeml8pFCg/view
A169: 45779 | B169: RS1-250502-1 | C169: 23.4 | D169: 26.2 | E169: 3 | G169: https://drive.google.com/file/d/1kj1996YdBElhoPC8e4rmVAt6q0se7CHx/view
A170: 45782 | B170: RS1-250505-1 | C170: 23.6 | D170: 28 | E170: 3 | G170: https://drive.google.com/file/d/1bKchXlLmQkCW5Ln1QzU0cU2NUwOQXwSY/view
A171: 45783 | B171: RS3-250506-1 | C171: 23.5 | D171: 26.2 | E171: 3 | G171: https://drive.google.com/file/d/1MCz3kd1vc1LQS5fOCu4rMzSWIA1JeWJJ/view
A172: 45791 | B172: RS3-250513-1 | C172: 24.3 | D172: 30 | E172: 2.9 | G172: https://drive.google.com/file/d/1Bqe1jBD4NX36pyOyf2xU3Lew4Xf3jyK-/view
A173: 45791 | B173: RS3-250421-1 | C173: 22.4 | D173: 27.5 | E173: 2.9 | G173: https://drive.google.com/file/d/1gCkgDjuXQMP02byADdYr-xN4IQGwBqGR/view?usp=drive_link
A174: 45791 | B174: RS3-250426-1 | C174: 23.9 | D174: 34.4 | E174: 2.9 | G174: https://drive.google.com/file/d/1u0vtskJe-OTTUy_tj5xtlpiDIGy22sGL/view?usp=drive_link
A175: 45791 | B175: RS1-250429-1 | C175: 22.5 | D175: 29.1 | E175: 3 | G175: https://drive.google.com/file/d/1R3O63rNrX_Cyk_qUvHLk_y1bNn12VM9K/view?usp=drive_link
A176: 45793 | B176: RS1-250516-1 | C176: 23.8 | D176: 30.7 | E176: 2.8 | G176: https://drive.google.com/file/d/1bhI6WDXzCIH63wdYa91YSSlDehmxYTRI/view
A177: 45791 | B177: RS3-250513-1 | C177: 24.3 | D177: 30 | E177: 2.9 | G177: https://drive.google.com/file/d/1Hm7gxzaYSvxreZ67iokpqp4tq21n_hTJ/view
A178: 45789 | B178: RS1-250512-1 | C178: 24.7 | D178: 30.7 | E178: 2.9 | G178: https://drive.google.com/file/d/1hdiKvUjHRqHRg0dBgY024y51LMEyAWJm/view
... A183: 45812 | B183: RS1-250604-1 | C183: 23.6 | D183: 33.8 | E183: 2.9 | G183: https://drive.google.com/file/d/1kWblfMsmJHs9xMVUTMpDokCn7epXbYtF/view
B184: RS1-250526-1 | D184: 31.6 | E184: 2.8 | G184: https://drive.google.com/file/d/19JOgx0ABBEvZspVsfKKYmoEHHXWYKY9I/view
A185: 45816 | B185: RS1-250608-1 | C185: 23.3 | D185: 33.9 | E185: 2.9 | G185: https://drive.google.com/file/d/1n64Oswp2NnIsxY3kbjAJSrGyyFBn4vn-/view
A186: 45817 | B186: RS3-250511-1 | C186: 25.3 | D186: 29.7 | E186: 2.9 | G186: https://drive.google.com/file/d/1DRRUkwS1CgqVjUNksDYCtH8q6MqI-wlK/view?usp=drive_link
A187: 45817 | B187: RS3-250519-1 | C187: 23.3 | D187: 30.7 | E187: 2.8 | G187: https://drive.google.com/file/d/1mW08is17mbSbnbSoGVv6xsXJKr8icOtk/view?usp=drive_link
A188: 45817 | B188: RS1-250521-1 | C188: 23.7 | D188: 32 | E188: 2.8 | G188: https://drive.google.com/file/d/1XYOM8HiQUbS9kilGm0ChyN-zL5Jh1n1o/view?usp=drive_link
A189: 45818 | B189: RS3-250610-1 | C189: 22.2 | D189: 36.3 | E189: 2.9 | G189: https://drive.google.com/file/d/1l-0H5gZa7EuljbIhbGMHFjQgur3-uz9B/view
A190: 45812 | B190: RS1-250604-1 | C190: 23.6 | D190: 33.8 | E190: 2.9 | G190: https://drive.google.com/file/d/1PArCv-ChT5CfVwUfrn0ckUPKRe24avkG/view
A191: 45816 | B191: RS1-250608-1 | C191: 23.3 | D191: 33.9 | E191: 2.9 | G191: https://drive.google.com/file/d/1rTv9vC1DGijPIMYwlHxtjXkr-45ST_ul/view
A192: 45818 | B192: RS3-250610-1 | C192: 22.2 | D192: 36.3 | E192: 2.9 | G192: https://drive.google.com/file/d/1uBYMtSpsgywrCtyoZsfm4nbuS1Aj57kX/view
A193: 45823 | B193: RS1-250615-1 | C193: 22.1 | D193: 36.5 | E193: 2.9 | G193: https://drive.google.com/file/d/1GYSFNvKdjzqMT4KWORJNjlKzetIbsXvT/view
A194: 45824 | B194: RS3-250616-1 | C194: 24.4 | D194: 38.7 | E194: 2.9 | G194: https://drive.google.com/file/d/1lSn7zC1NpFD-ekgqRezX6-0nBOnhY3JE/view
A195: 45825 | B195: RS3-250531-1 | C195: 23.2 | D195: 32 | E195: 2.9 | G195: https://drive.google.com/file/d/1YhpedaMWb_wCZ95CMEtfTzQRHPta26oc/view?usp=drive_link
A196: 45826 | B196: RS1-250618-1 | C196: 23.1 | D196: 39.4 | E196: 2.9 | G196: https://drive.google.com/file/d/1KNGyZcL71nfSiSRlucoJc-XT5ErqnNXo/view
... A305: 46077 | B305: RS3-260219-1 | C305: 26.8 | D305: 20 | E305: 3 | G305: https://drive.google.com/file/d/1CndXSlkDFITRZrCMbawccCngmWYq4G-N/view?usp=drive_link
A306: 46079 | B306: RS3-260205-1 | C306: N/a | D306: N/a | E306: N/a | G306: https://drive.google.com/file/d/1llMoJlQ_OShGGKjmNDt7eKNx6ZXNsEt_/view?usp=drive_link
A307: 46079 | B307: RS1-260225-1 | C307: 24.5 | D307: 24.5 | E307: 3 | G307: https://drive.google.com/file/d/1Bttux9YkkqyvnFbIdlQdI8rWCKALE6Pn/view?usp=drive_link
A308: 46080 | B308: RS1-260302-1 | C308: 24.2 | D308: 30.4 | E308: 2.9 | G308: https://drive.google.com/file/d/1iJpUnsTsu4oHnIk33wUvAlZUsXTYzfiT/view?usp=drive_link
A309: 46081 | B309: RS3-260223-1 | C309: 25 | D309: 21.8 | E309: 3 | G309: https://drive.google.com/file/d/1YhtzQMMNY-QchbdPNRl0mnILf4vgpSWM/view?usp=drive_link
A310: 46082 | B310: RS3-260303-1 | C310: 24.7 | D310: 29 | E310: 2.9 | G310: https://drive.google.com/file/d/1hOeW8nKmm89zW2_188tD6oEDm08xlS56/view?usp=drive_link
A311: 46082 | B311: RS3-260228-1 | C311: 26.7 | D311: 33.6 | E311: 2.8 | G311: https://drive.google.com/file/d/1xiolMkft05i0eXmDNPttT-mFCIYVBxqH/view?usp=drive_link
A312: 46085 | B312: RS1-260221-1 | C312: 27.1 | D312: 22.7 | E312: 3 | G312: https://drive.google.com/file/d/1KcRGfEJa5-lhcU9QxVfJRNVuHEqKJWi7/view?usp=drive_link
...

Sheet DEPRECATED 2023 PO  Injection T
A1: # | B1: PO # | C1: Driver Tracking | D1: Supplier | E1: Mode | F1: PO Placed Date | G1: Pickup Date | H1: Delivery Date | I1: Injection Date | J1: Amount (Tons) | K1: Unit Price | L1: Total Cost | M1: Injection Location | N1: Actual Loaded (tons) | O1: Invoiced ($) | P1: Deposit Remaining? | Q1: Export Doc Link | R1: Carbon Content (%) | S1: Water Content (%) | T1: Status | U1: Gross (t CO₂e) | V1: Bio-oil Yield (%) | W1: Transport Distance (mi) | X1: Biomass Transport (t CO₂e ) | Y1: Pyrolysis (t CO₂e ) | Z1: Transport Distance (mi) | AA1: Injectant Transport (t CO₂e) | AB1: Injection (t CO₂e) | AC1: Emitted (t CO₂e) | AD1: Net (t CO₂e) | AE1: Verified (t CO₂e) | AF1: Diff | AG1: 2023 t CO₂e | AH1: Injection Data summary | AI1: Product Cost | AJ1: Freight Cost | AK1: Injection Cost | AL1: Lab Cost | AM1: Total Cost | AN1: $/m.t.CO2e | AO1: Sale Price | AP1: Gross Profit | AQ1: Gross Margin | AR1: Notes | AS1: ratio of bio oil loaded and tons verified
A2: 1 | B2: 001T1R0 | C2: Guy Guillemette | D2: AECN | E2: truck | F2: 44922 | G2: 44931 | I2: 44936 | J2: 20.5 | K2: 327.52 | L2: =K2*J2 -> 6714.16 | M2: Injection @ Hildreth A6 | N2: 17.55 | O2: =K2*N2 -> 5747.976 | P2: =100000-O2 -> 94252.024 | Q2: 001T1R0 | R2: 0.316 | T2: verified | U2: =N2*R2*(44.01/12.011) -> 20.320594 | V2: =IF(D2="AECN",0.68,"ERROR") -> 0.68 | W2: =IF(D2="AECN",0.2,"ERROR") -> 0.2 | X2: =(0.1738*((N2/V2)*W2))/1000 -> 0.00089711471 | Y2: =IF(D2="AECN",(140.5*N2)/1000,ERROR) -> 2.465775 | Z2: =IF(D2="AECN",2030,"ERROR") -> 2030 | AA2: =(0.1046*N2*Z2)/1000 -> 3.7265319 | AB2: =(0.7205*N2)/1000 -> 0.012644775 | AC2: =SUM(AA2:AB2,Y2,X2) -> 6.2058488 | AD2: =U2-AC2 -> 14.114745 | AE2: =(1619+5478+3531+4765)/1000 -> 15.393 | AF2: =(AE2-AD2)/AD2 -> 0.09056164 | AG2: =IF(T2="verified",AE2,AD2) -> 15.393 | AR2: blended at AJs, phase separated, we injected light ends at Advantek and then pumped out heavy ends into totes | AS2: =AE2/N2 -> 0.87709402
A3: 2 | B3: 002T1R0 | C3: Luc Garant | D3: AECN | E3: truck | F3: 44929 | G3: 44935 | I3: 44951 | J3: 20.5 | K3: 327.52 | L3: =K3*J3 -> 6714.16 | M3: Injection @ Hildreth A6 | N3: 18.57 | O3: =K3*N3 -> 6082.0464 | P3: =P2-O3 -> 88169.978 | Q3: 002T1R0 | R3: 0.316 | T3: verified | U3: =N3*R3*(44.01/12.011) -> 21.50162 | V3: =IF(D3="AECN",0.68,"ERROR") -> 0.68 | W3: =IF(D3="AECN",0.2,"ERROR") -> 0.2 | X3: =(0.1738*((N3/V3)*W3))/1000 -> 0.00094925471 | Y3: =IF(D3="AECN",(140.5*N3)/1000,ERROR) -> 2.609085 | Z3: =IF(D3="AECN",2030,"ERROR") -> 2030 | AA3: =(0.1046*N3*Z3)/1000 -> 3.9431167 | AB3: =(0.7205*N3)/1000 -> 0.013379685 | AC3: =SUM(AA3:AB3,Y3,X3) -> 6.5665306 | AD3: =U3-AC3 -> 14.93509 | AE3: =13724/1000 -> 13.724 | AF3: =(AE3-AD3)/AD3 -> -0.081090218 | AG3: =IF(T3="verified",IFERROR(AG2+AE3,AG2), IFERROR(AG2+AD3,AG2)) -> 29.117 | AR3: unloaded into totes -1000 gallon tank and one 275 gallon blended still onsite, sent two to HQ, injected the rest at hildreth | AS3: =AE3/N3 -> 0.73904146
A4: 3 | B4: 003T1R0 | C4: Guy Guillemette | D4: AECN | E4: truck | F4: 44936 | G4: 44946 | I4: 44952 | J4: 20.5 | K4: 327.52 | L4: =K4*J4 -> 6714.16 | M4: Injection @ Hildreth A6 | N4: 19.77 | O4: =K4*N4 -> 6475.0704 | P4: =P3-O4 -> 81694.907 | Q4: 003T1R0 | R4: 0.316 | T4: verified | U4: =N4*R4*(44.01/12.011) -> 22.891063 | V4: =IF(D4="AECN",0.68,"ERROR") -> 0.68 | W4: =IF(D4="AECN",0.2,"ERROR") -> 0.2 | X4: =(0.1738*((N4/V4)*W4))/1000 -> 0.0010105959 | Y4: =IF(D4="AECN",(140.5*N4)/1000,ERROR) -> 2.777685 | Z4: =IF(D4="AECN",2030,"ERROR") -> 2030 | AA4: =(0.1046*N4*Z4)/1000 -> 4.1979223 | AB4: =(0.7205*N4)/1000 -> 0.014244285 | AC4: =SUM(AA4:AB4,Y4,X4) -> 6.9908621 | AD4: =U4-AC4 -> 15.9002 | AE4: =11626/1000 -> 11.626 | AF4: =(AE4-AD4)/AD4 -> -0.26881425 | AG4: =IF(T4="verified",IFERROR(AG3+AE4,AG3), IFERROR(AG3+AD4,AG3)) -> 40.743 | AH4: link | AR4: blended at AJs, unloaded some at Advantek and some at Hildreth | AS4: =AE4/N4 -> 0.58806272
A5: 4 | B5: 004T1R0 | C5: Kevin Wood | D5: AECN | E5: truck | F5: 44936 | G5: 44966 | I5: 44972 | J5: 20.5 | K5: 327.52 | L5: =K5*J5 -> 6714.16 | M5: Injection @ Hildreth A6 | N5: 20.31 | O5: =K5*N5 -> 6651.9312 | P5: =P4-O5 -> 75042.976 | Q5: 004T1R0 | R5: 0.429 | S5: 0.233 | T5: verified | U5: =N5*R5*(44.01/12.011) -> 31.925626 | V5: =IF(D5="AECN",0.68,"ERROR") -> 0.68 | W5: =IF(D5="AECN",0.2,"ERROR") -> 0.2 | X5: =(0.1738*((N5/V5)*W5))/1000 -> 0.0010381994 | Y5: =IF(D5="AECN",(140.5*N5)/1000,ERROR) -> 2.853555 | Z5: =IF(D5="AECN",2030,"ERROR") -> 2030 | AA5: =(0.1046*N5*Z5)/1000 -> 4.3125848 | AB5: =(0.7205*N5)/1000 -> 0.014633355 | AC5: =SUM(AA5:AB5,Y5,X5) -> 7.1818113 | AD5: =U5-AC5 -> 24.743814 | AE5: =25997/1000 -> 25.997 | AF5: =(AE5-AD5)/AD5 -> 0.050646422 | AG5: =IF(T5="verified",IFERROR(AG4+AE5,AG4), IFERROR(AG4+AD5,AG4)) -> 66.74 | AH5: link | AR5: injected at Hildreth | AS5: =AE5/N5 -> 1.2800098
A6: 5 | B6: 006T1R0 | C6: Guy Guillemette | D6: AECN | E6: truck | F6: 44965 | G6: 45002 | I6: 45006 | J6: 20.5 | K6: 327.52 | L6: =K6*J6 -> 6714.16 | M6: Injection @ Hildreth A6 | N6: 20.13 | O6: =K6*N6 -> 6592.9776 | P6: =P5-O6 -> 68449.998 | Q6: 006T1R0 | R6: 0.425 | S6: 0.264 | T6: verified | U6: =N6*R6*(44.01/12.011) -> 31.347644 | V6: =IF(D6="AECN",0.68,"ERROR") -> 0.68 | W6: =IF(D6="AECN",0.2,"ERROR") -> 0.2 | X6: =(0.1738*((N6/V6)*W6))/1000 -> 0.0010289982 | Y6: =IF(D6="AECN",(140.5*N6)/1000,ERROR) -> 2.828265 | Z6: =IF(D6="AECN",2030,"ERROR") -> 2030 | AA6: =(0.1046*N6*Z6)/1000 -> 4.2743639 | AB6: =(0.7205*N6)/1000 -> 0.014503665 | AC6: =SUM(AA6:AB6,Y6,X6) -> 7.1181616 | AD6: =U6-AC6 -> 24.229482 | AE6: =25554/1000 -> 25.554 | AF6: =(AE6-AD6)/AD6 -> 0.054665533 | AG6: =IF(T6="verified",IFERROR(AG5+AE6,AG5), IFERROR(AG5+AD6,AG5)) -> 92.294 | AH6: link | AR6: Injected @ Hildreth 3/21 | AS6: =AE6/N6 -> 1.2694486
A7: 6 | B7: 005T1R0 | C7: Jeffrey Armu | D7: AECN | E7: truck | F7: 44965 | G7: 44981 | I7: 45007 | J7: 20.5 | K7: 327.52 | L7: =K7*J7 -> 6714.16 | M7: Injection @ Hildreth A6 | N7: 20.26 | O7: =K7*N7 -> 6635.5552 | P7: =P6-O7 -> 61814.443 | Q7: 005T1R0 | R7: 0.415 | S7: 0.254 | T7: verified | U7: =N7*R7*(44.01/12.011) -> 30.807733 | V7: =IF(D7="AECN",0.68,"ERROR") -> 0.68 | W7: =IF(D7="AECN",0.2,"ERROR") -> 0.2 | X7: =(0.1738*((N7/V7)*W7))/1000 -> 0.0010356435 | Y7: =IF(D7="AECN",(140.5*N7)/1000,ERROR) -> 2.84653 | Z7: =IF(D7="AECN",2030,"ERROR") -> 2030 | AA7: =(0.1046*N7*Z7)/1000 -> 4.3019679 | AB7: =(0.7205*N7)/1000 -> 0.01459733 | AC7: =SUM(AA7:AB7,Y7,X7) -> 7.1641309 | AD7: =U7-AC7 -> 23.643602 | AE7: =24925/1000 -> 24.925 | AF7: =(AE7-AD7)/AD7 -> 0.054196396 | AG7: =IF(T7="verified",IFERROR(AG6+AE7,AG6), IFERROR(AG6+AD7,AG6)) -> 117.219 | AH7: link | AR7: Unloaded into totes at AJs awaiting TCLP results. injected in Hildreth 3/22 | AS7: =AE7/N7 -> 1.2302567
A8: 7 | B8: 007T1R0 | C8: Patrick Aubertin | D8: AECN | E8: truck | F8: 44998 | G8: 45016 | I8: 45019 | K8: 327.52 | L8: =K8*J8 -> 0 | M8: Injection @ Hildreth A6 | N8: 19.61 | O8: =K8*N8 -> 6422.6672 | P8: =P7-O8 -> 55391.776 | Q8: 007T1R0 | R8: 0.431 | T8: verified | U8: =N8*R8*(44.01/12.011) -> 30.968992 | V8: =IF(D8="AECN",0.68,"ERROR") -> 0.68 | W8: =IF(D8="AECN",0.2,"ERROR") -> 0.2 | X8: =(0.1738*((N8/V8)*W8))/1000 -> 0.0010024171 | Y8: =IF(D8="AECN",(140.5*N8)/1000,ERROR) -> 2.755205 | Z8: =IF(D8="AECN",2030,"ERROR") -> 2030 | AA8: =(0.1046*N8*Z8)/1000 -> 4.1639482 | AB8: =(0.7205*N8)/1000 -> 0.014129005 | AC8: =SUM(AA8:AB8,Y8,X8) -> 6.9342846 | AD8: =U8-AC8 -> 24.034707 | AE8: =25346/1000 -> 25.346 | AF8: =(AE8-AD8)/AD8 -> 0.054558307 | AG8: =IF(T8="verified",IFERROR(AG7+AE8,AG7), IFERROR(AG7+AD8,AG7)) -> 142.565 | AH8: link | AR8: Injected @ Hildreth 4/3 - power outage day | AS8: =AE8/N8 -> 1.2925038
A9: 8 | B9: 008T1R0 | C9: Guy Guillemette | D9: AECN | E9: truck | F9: 44998 | G9: 45024 | I9: 45027 | K9: 327.52 | L9: =K9*J9 -> 0 | M9: Injection @ Hildreth A6 | N9: 19.25 | O9: =K9*N9 -> 6304.76 | P9: =P8-O9 -> 49087.016 | Q9: 008T1R0 | R9: 0.42875 | T9: verified | U9: =N9*R9*(44.01/12.011) -> 30.24176 | V9: =IF(D9="AECN",0.68,"ERROR") -> 0.68 | W9: =IF(D9="AECN",0.2,"ERROR") -> 0.2 | X9: =(0.1738*((N9/V9)*W9))/1000 -> 0.00098401471 | Y9: =IF(D9="AECN",(140.5*N9)/1000,ERROR) -> 2.704625 | Z9: =IF(D9="AECN",2030,"ERROR") -> 2030 | AA9: =(0.1046*N9*Z9)/1000 -> 4.0875065 | AB9: =(0.7205*N9)/1000 -> 0.013869625 | AC9: =SUM(AA9:AB9,Y9,X9) -> 6.8069851 | AD9: =U9-AC9 -> 23.434775 | AE9: =24742/1000 -> 24.742 | AF9: =(AE9-AD9)/AD9 -> 0.055781406 | AG9: =IF(T9="verified",IFERROR(AG8+AE9,AG8), IFERROR(AG8+AD9,AG8)) -> 167.307 | AH9: link | AR9: Injected @ Hildreth, < 2 hrs injection time | AS9: =AE9/N9 -> 1.2852987
A10: 9 | B10: 009T1R0 | C10: Andrew Stanbook | D10: AECN | E10: truck | F10: 45019 | G10: 45029 | I10: =IF(E10="truck", G10+4, G10+16) -> 45033 | K10: 327.52 | L10: =K10*J10 -> 0 | M10: Injection @ Hildreth A6 | N10: 18.23 | O10: =K10*N10 -> 5970.6896 | P10: =P9-O10 -> 43116.326 | Q10: 009T1R0 | R10: 0.4252 | T10: verified | U10: =N10*R10*(44.01/12.011) -> 28.402209 | V10: =IF(D10="AECN",0.68,"ERROR") -> 0.68 | W10: =IF(D10="AECN",0.2,"ERROR") -> 0.2 | X10: =(0.1738*((N10/V10)*W10))/1000 -> 0.00093187471 | Y10: =IF(D10="AECN",(140.5*N10)/1000,ERROR) -> 2.561315 | Z10: =IF(D10="AECN",2030,"ERROR") -> 2030 | AA10: =(0.1046*N10*Z10)/1000 -> 3.8709217 | AB10: =(0.7205*N10)/1000 -> 0.013134715 | AC10: =SUM(AA10:AB10,Y10,X10) -> 6.4463033 | AD10: =U10-AC10 -> 21.955906 | AE10: =23160/1000 -> 23.16 | AF10: =(AE10-AD10)/AD10 -> 0.054841456 | AG10: =IF(T10="verified",IFERROR(AG9+AE10,AG9), IFERROR(AG9+AD10,AG9)) -> 190.467 | AH10: link | AI10: 5970.69 | AJ10: =210.16+15716.12 -> 15926.28 | AK10: =14*55 -> 770 | AL10: 1000 | AM10: =SUM(AI10:AL10) -> 23666.97 | AN10: =AM10/AE10 -> 1021.8899 | AO10: 600 | AP10: =(AO10*AE10)-AM10 -> -9770.97 | AQ10: =((AO10*AE10)-AM10)/(AE10*AO10) -> -0.70314983 | AR10: Valve not fully open on tanker side, impeding flow to PCP; see linked surface pressure plot for signature | AS10: =AE10/N10 -> 1.2704334
A11: 10 | B11: 010T1R0 | C11: Guy Guillemette | D11: AECN | E11: truck | F11: 45019 | G11: 45033 | I11: 45036 | K11: 327.52 | L11: =K11*J11 -> 0 | M11: Injection @ Hildreth A6 | N11: 19.86 | O11: =K11*N11 -> 6504.5472 | P11: =P10-O11 -> 36611.779 | Q11: 010T1R0 | R11: 0.43075 | T11: verified | U11: =N11*R11*(44.01/12.011) -> 31.34561 | V11: =IF(D11="AECN",0.68,"ERROR") -> 0.68 | W11: =IF(D11="AECN",0.2,"ERROR") -> 0.2 | X11: =(0.1738*((N11/V11)*W11))/1000 -> 0.0010151965 | Y11: =IF(D11="AECN",(140.5*N11)/1000,ERROR) -> 2.79033 | Z11: =IF(D11="AECN",2030,"ERROR") -> 2030 | AA11: =(0.1046*N11*Z11)/1000 -> 4.2170327 | AB11: =(0.7205*N11)/1000 -> 0.01430913 | AC11: =SUM(AA11:AB11,Y11,X11) -> 7.022687 | AD11: =U11-AC11 -> 24.322923 | AE11: =25670/1000 -> 25.67 | AF11: =(AE11-AD11)/AD11 -> 0.055383004 | AG11: =IF(T11="verified",IFERROR(AG10+AE11,AG10), IFERROR(AG10+AD11,AG10)) -> 216.137 | AH11: link | AI11: 6504.15 | AJ11: =215.16+15716.12 -> 15931.28 | AK11: =10*55 -> 550 | AL11: 1000 | AM11: =SUM(AI11:AL11) -> 23985.43 | AN11: =AM11/AE11 -> 934.37593 | AO11: 600 | AP11: =(AO11*AE11)-AM11 -> -8583.43 | AQ11: =((AO11*AE11)-AM11)/(AE11*AO11) -> -0.55729321 | AR11: Uneventful (!); 2.3 hrs to inject | AS11: =AE11/N11 -> 1.2925478
A12: 11 | B12: 011T1R0 | C12: Darryl Kennedy | D12: AECN | E12: truck | F12: 45019 | G12: 45037 | I12: 45043 | K12: 327.52 | L12: =K12*J12 -> 0 | M12: Injection @ Hildreth A6 | N12: 19.64 | O12: =K12*N12 -> 6432.4928 | P12: =P11-O12 -> 30179.286 | Q12: 011T1R0 | R12: =((42.19+42.72)/2)/100 -> 0.42455 | T12: verified | U12: =N12*R12*(44.01/12.011) -> 30.552203 | V12: =IF(D12="AECN",0.68,"ERROR") -> 0.68 | W12: =IF(D12="AECN",0.2,"ERROR") -> 0.2 | X12: =(0.1738*((N12/V12)*W12))/1000 -> 0.0010039506 | Y12: =IF(D12="AECN",(140.5*N12)/1000,ERROR) -> 2.75942 | Z12: =IF(D12="AECN",2030,"ERROR") -> 2030 | AA12: =(0.1046*N12*Z12)/1000 -> 4.1703183 | AB12: =(0.7205*N12)/1000 -> 0.01415062 | AC12: =SUM(AA12:AB12,Y12,X12) -> 6.9448929 | AD12: =U12-AC12 -> 23.60731 | AE12: =24925/1000 -> 24.925 | AF12: =(AE12-AD12)/AD12 -> 0.05581703 | AG12: =IF(T12="verified",IFERROR(AG11+AE12,AG11), IFERROR(AG11+AD12,AG11)) -> 241.062 | AH12: link | AI12: 6432.1 | AJ12: =215.16+15716.12 -> 15931.28 | AK12: =10*55 -> 550 | AL12: 1000 | AM12: =SUM(AI12:AL12) -> 23913.38 | AN12: =AM12/AE12 -> 959.41344 | AO12: 600 | AP12: =(AO12*AE12)-AM12 -> -8958.38 | AQ12: =((AO12*AE12)-AM12)/(AE12*AO12) -> -0.5990224 | AR12: ~ 2.12 hrs injection time | AS12: =AE12/N12 -> 1.2690937
A13: 12 | B13: 012T1R0 | C13: Guy Guillemette | D13: AECN | E13: truck | F13: 45019 | G13: 45044 | I13: 45047 | K13: 327.52 | L13: =K13*J13 -> 0 | M13: Injection @ Hildreth A6 | N13: 19.7 | O13: =K13*N13 -> 6452.144 | Q13: 012T1R0 | R13: =((43.23+43.1)/2)/100 -> 0.43165 | T13: verified | U13: =N13*R13*(44.01/12.011) -> 31.158043 | V13: =IF(D13="AECN",0.68,"ERROR") -> 0.68 | W13: =IF(D13="AECN",0.2,"ERROR") -> 0.2 | X13: =(0.1738*((N13/V13)*W13))/1000 -> 0.0010070176 | Y13: =IF(D13="AECN",(140.5*N13)/1000,ERROR) -> 2.76785 | Z13: =IF(D13="AECN",2030,"ERROR") -> 2030 | AA13: =(0.1046*N13*Z13)/1000 -> 4.1830586 | AB13: =(0.7205*N13)/1000 -> 0.01419385 | AC13: =SUM(AA13:AB13,Y13,X13) -> 6.9661095 | AD13: =U13-AC13 -> 24.191934 | AE13: =25515/1000 -> 25.515 | AF13: =(AE13-AD13)/AD13 -> 0.054690396 | AG13: =IF(T13="verified",IFERROR(AG12+AE13,AG12), IFERROR(AG12+AD13,AG12)) -> 266.577 | AH13: link | AI13: 6441.9 | AJ13: =215.16+15716.12 -> 15931.28 | AK13: =55*11 -> 605 | AL13: 1000 | AM13: =SUM(AI13:AL13) -> 23978.18 | AN13: =AM13/AE13 -> 939.76798 | AO13: 600 | AP13: =(AO13*AE13)-AM13 -> -8669.18 | AQ13: =((AO13*AE13)-AM13)/(AE13*AO13) -> -0.56627997 | AR13: filled tubing, ~08:00 PDT | AS13: =AE13/N13 -> 1.2951777
A14: 13 | B14: 013T1R0 | C14: Darryl Kennedy | D14: AECN | E14: truck | F14: 45040 | G14: 45047 | I14: 45050 | K14: 327.52 | L14: =K14*J14 -> 0 | M14: Injection @ Hildreth A6 | N14: 19.08 | O14: =K14*N14 -> 6249.0816 | Q14: 013T1R0 | R14: =((44.86+43.57)/2)/100 -> 0.44215 | T14: verified | U14: =N14*R14*(44.01/12.011) -> 30.911509 | V14: =IF(D14="AECN",0.68,"ERROR") -> 0.68 | W14: =IF(D14="AECN",0.2,"ERROR") -> 0.2 | X14: =(0.1738*((N14/V14)*W14))/1000 -> 0.00097532471 | Y14: =IF(D14="AECN",(140.5*N14)/1000,ERROR) -> 2.68074 | Z14: =IF(D14="AECN",2030,"ERROR") -> 2030 | AA14: =(0.1046*N14*Z14)/1000 -> 4.051409 | AB14: =(0.7205*N14)/1000 -> 0.01374714 | AC14: =SUM(AA14:AB14,Y14,X14) -> 6.7468715 | AD14: =U14-AC14 -> 24.164637 | AE14: =25446/1000 -> 25.446 | AF14: =(AE14-AD14)/AD14 -> 0.053026365 | AG14: =IF(T14="verified",IFERROR(AG13+AE14,AG13), IFERROR(AG13+AD14,AG13)) -> 292.023 | AH14: link | AI14: 6249.08 | AJ14: =215.16+15716.12 -> 15931.28 | AK14: =9.5*55 -> 522.5 | AL14: 1000 | AM14: =SUM(AI14:AL14) -> 23702.86 | AN14: =AM14/AE14 -> 931.4965 | AO14: 600 | AP14: =(AO14*AE14)-AM14 -> -8435.26 | AQ14: =((AO14*AE14)-AM14)/(AE14*AO14) -> -0.55249417 | AS14: =AE14/N14 -> 1.3336478
A15: 14 | B15: 014T1R0 | C15: Guy Guillemette | D15: AECN | E15: truck | F15: 45040 | G15: 45053 | I15: 45058 | K15: 327.52 | L15: =K15*J15 -> 0 | M15: Injection @ Hildreth A6 | N15: 20.12 | O15: =K15*N15 -> 6589.7024 | Q15: 014T1R0 | R15: =(0.4438+0.4665)/2 -> 0.45515 | T15: verified | U15: =N15*R15*(44.01/12.011) -> 33.554805 | V15: =IF(D15="AECN",0.68,"ERROR") -> 0.68 | W15: =IF(D15="AECN",0.2,"ERROR") -> 0.2 | X15: =(0.1738*((N15/V15)*W15))/1000 -> 0.0010284871 | Y15: =IF(D15="AECN",(140.5*N15)/1000,ERROR) -> 2.82686 | Z15: =IF(D15="AECN",2030,"ERROR") -> 2030 | AA15: =(0.1046*N15*Z15)/1000 -> 4.2722406 | AB15: =(0.7205*N15)/1000 -> 0.01449646 | AC15: =SUM(AA15:AB15,Y15,X15) -> 7.1146255 | AD15: =U15-AC15 -> 26.44018 | AE15: =27791/1000 -> 27.791 | AF15: =(AE15-AD15)/AD15 -> 0.05108967 | AG15: =IF(T15="verified",IFERROR(AG14+AE15,AG14), IFERROR(AG14+AD15,AG14)) -> 319.814 | AH15: link | AI15: 6589.7 | AJ15: =175.5+15716.12 -> 15891.62 | AK15: =7.25*55 -> 398.75 | AL15: 1000 | AM15: =SUM(AI15:AL15) -> 23880.07 | AN15: =AM15/AE15 -> 859.27351 | AO15: 600 | AP15: =(AO15*AE15)-AM15 -> -7205.47 | AQ15: =((AO15*AE15)-AM15)/(AE15*AO15) -> -0.43212251 | AS15: =AE15/N15 -> 1.3812624
A16: 15 | B16: 015T1R0 | C16: Darryl Kennedy | D16: AECN | E16: truck | F16: 45040 | G16: 45055 | I16: 45059 | K16: 327.52 | L16: =K16*J16 -> 0 | M16: Injection @ Hildreth A6 | N16: 20.72 | O16: =K16*N16 -> 6786.2144 | Q16: 015T2R0 | R16: =((45.84+44.32)/2)/100 -> 0.4508 | T16: verified | U16: =N16*R16*(44.01/12.011) -> 34.225189 | V16: =IF(D16="AECN",0.68,"ERROR") -> 0.68 | W16: =IF(D16="AECN",0.2,"ERROR") -> 0.2 | X16: =(0.1738*((N16/V16)*W16))/1000 -> 0.0010591576 | Y16: =IF(D16="AECN",(140.5*N16)/1000,ERROR) -> 2.91116 | Z16: =IF(D16="AECN",2030,"ERROR") -> 2030 | AA16: =(0.1046*N16*Z16)/1000 -> 4.3996434 | AB16: =(0.7205*N16)/1000 -> 0.01492876 | AC16: =SUM(AA16:AB16,Y16,X16) -> 7.3267913 | AD16: =U16-AC16 -> 26.898398 | AE16: =28286/1000 -> 28.286 | AF16: =(AE16-AD16)/AD16 -> 0.051586785 | AG16: =IF(T16="verified",IFERROR(AG15+AE16,AG15), IFERROR(AG15+AD16,AG15)) -> 348.1 | AH16: link | AI16: 6786.21 | AJ16: =222.16+15716.12 -> 15938.28 | AK16: =7*55 -> 385 | AL16: 1000 | AM16: =SUM(AI16:AL16) -> 24109.49 | AN16: =AM16/AE16 -> 852.3471 | AO16: 600 | AP16: =(AO16*AE16)-AM16 -> -7137.89 | AQ16: =((AO16*AE16)-AM16)/(AE16*AO16) -> -0.4205785 | AS16: =AE16/N16 -> 1.3651544
A17: 16 | B17: 017T1R0 | C17: Jeffrey Omofola Aremu | D17: AECN | E17: truck | F17: 45040 | G17: 45062 | I17: 45065 | M17: Injection @ Hildreth A6 | N17: 19.98 | Q17: 017T1R1 | R17: =((43.43+43.29)/2)/100 -> 0.4336 | T17: verified | U17: =N17*R16*(44.01/12.011) -> 33.002861 | V17: =IF(D17="AECN",0.68,"ERROR") -> 0.68 | W17: =IF(D17="AECN",0.2,"ERROR") -> 0.2 | X17: =(0.1738*((N17/V17)*W17))/1000 -> 0.0010213306 | Y17: =IF(D17="AECN",(140.5*N17)/1000,ERROR) -> 2.80719 | Z17: =IF(D17="AECN",2030,"ERROR") -> 2030 | AA17: =(0.1046*N17*Z17)/1000 -> 4.2425132 | AB17: =(0.7205*N17)/1000 -> 0.01439559 | AC17: =SUM(AA17:AB17,Y17,X17) -> 7.0651202 | AD17: =U17-AC17 -> 25.937741 | AE17: =27408/1000 -> 27.408 | AF17: =(AE17-AD17)/AD17 -> 0.056684156 | AG17: =IF(T17="verified",IFERROR(AG16+AE17,AG16), IFERROR(AG16+AD17,AG16)) -> 375.508 | AH17: link | AI17: 6543.85 | AJ17: =175.5+15716.12 -> 15891.62 | AK17: =9*55 -> 495 | AL17: 1000 | AM17: =SUM(AI17:AL17) -> 23930.47 | AN17: =AM17/AE17 -> 873.11989 | AO17: 600 | AP17: =(AO17*AE17)-AM17 -> -7485.67 | AQ17: =((AO17*AE17)-AM17)/(AE17*AO17) -> -0.45519982 | AS17: =AE17/N17 -> 1.3717718
A18: 17 | B18: 016T1R0 | C18: Derrick Dufresne | D18: AECN | E18: truck | F18: 45040 | G18: 45062 | I18: 45068 | K18: 327.52 | L18: =K18*J18 -> 0 | M18: Injection @ Hildreth A6 | N18: 20.74 | O18: =K18*N18 -> 6792.7648 | Q18: 016R3R1 | R18: =((44.56+45.95)/2)/100 -> 0.45255 | T18: verified | U18: =N18*R19*(44.01/12.011) -> 33.369092 | V18: =IF(D18="AECN",0.68,"ERROR") -> 0.68 | W18: =IF(D18="AECN",0.2,"ERROR") -> 0.2 | X18: =(0.1738*((N18/V18)*W18))/1000 -> 0.00106018 | Y18: =IF(D18="AECN",(140.5*N18)/1000,ERROR) -> 2.91397 | Z18: =IF(D18="AECN",2030,"ERROR") -> 2030 | AA18: =(0.1046*N18*Z18)/1000 -> 4.4038901 | AB18: =(0.7205*N18)/1000 -> 0.01494317 | AC18: =SUM(AA18:AB18,Y18,X18) -> 7.3338635 | AD18: =U18-AC18 -> 26.035229 | AE18: =27007/1000 -> 27.007 | AF18: =(AE18-AD18)/AD18 -> 0.037325248 | AG18: =IF(T18="verified",IFERROR(AG17+AE18,AG17), IFERROR(AG17+AD18,AG17)) -> 402.515 | AH18: link | AI18: 6792.76 | AJ18: =175.5+15716.12 -> 15891.62 | AK18: =9*55 -> 495 | AL18: 1000 | AM18: =SUM(AI18:AL18) -> 24179.38 | AN18: =AM18/AE18 -> 895.30048 | AO18: 600 | AP18: =(AO18*AE18)-AM18 -> -7975.18 | AQ18: =((AO18*AE18)-AM18)/(AE18*AO18) -> -0.49216746 | AS18: =AE18/N18 -> 1.3021697
A19: 18 | B19: 018T1R0 | C19: Darryl Kennedy | D19: AECN | E19: truck | F19: 45040 | G19: 45064 | I19: 45069 | K19: 327.52 | L19: =K19*J19 -> 0 | M19: Injection @ Hildreth A6 | N19: 20.01 | O19: =K19*N19 -> 6553.6752 | Q19: 018T2R1 | R19: =((43.62+44.2)/2)/100 -> 0.4391 | T19: verified | U19: =N19*R19*(44.01/12.011) -> 32.194577 | V19: =IF(D19="AECN",0.68,"ERROR") -> 0.68 | W19: =IF(D19="AECN",0.2,"ERROR") -> 0.2 | X19: =(0.1738*((N19/V19)*W19))/1000 -> 0.0010228641 | Y19: =IF(D19="AECN",(140.5*N19)/1000,ERROR) -> 2.811405 | Z19: =IF(D19="AECN",2030,"ERROR") -> 2030 | AA19: =(0.1046*N19*Z19)/1000 -> 4.2488834 | AB19: =(0.7205*N19)/1000 -> 0.014417205 | AC19: =SUM(AA19:AB19,Y19,X19) -> 7.0757284 | AD19: =U19-AC19 -> 25.118849 | AE19: =26459/1000 -> 26.459 | AF19: =(AE19-AD19)/AD19 -> 0.053352411 | AG19: =IF(T19="verified",IFERROR(AG18+AE19,AG18), IFERROR(AG18+AD19,AG18)) -> 428.974 | AH19: link | AI19: 6553.68 | AJ19: =220.16+15716.12 -> 15936.28 | AK19: =11*55 -> 605 | AL19: 1000 | AM19: =SUM(AI19:AL19) -> 24094.96 | AN19: =AM19/AE19 -> 910.65271 | AO19: 600 | AP19: =(AO19*AE19)-AM19 -> -8219.56 | AQ19: =((AO19*AE19)-AM19)/(AE19*AO19) -> -0.51775451 | AS19: =AE19/N19 -> 1.3222889
A20: 19 | B20: 019T1R0 | C20: Jonathan Fortier | D20: AECN | E20: truck | F20: 45040 | G20: 45071 | I20: 45076 | K20: 327.52 | L20: =K20*J20 -> 0 | M20: Injection @ Hildreth A6 | N20: 20.26 | O20: 45069 | Q20: 019T3R1 | R20: =(0.4475+0.446)/2 -> 0.44675 | T20: verified | U20: =N20*R20*(44.01/12.011) -> 33.16471 | V20: =IF(D20="AECN",0.68,"ERROR") -> 0.68 | W20: =IF(D20="AECN",0.2,"ERROR") -> 0.2 | X20: =(0.1738*((N20/V20)*W20))/1000 -> 0.0010356435 | Y20: =IF(D20="AECN",(140.5*N20)/1000,ERROR) -> 2.84653 | Z20: =IF(D20="AECN",2030,"ERROR") -> 2030 | AA20: =(0.1046*N20*Z20)/1000 -> 4.3019679 | AB20: =(0.7205*N20)/1000 -> 0.01459733 | AC20: =SUM(AA20:AB20,Y20,X20) -> 7.1641309 | AD20: =U20-AC20 -> 26.000579 | AE20: =27361/1000 -> 27.361 | AF20: =(AE20-AD20)/AD20 -> 0.052322714 | AG20: =IF(T20="verified",IFERROR(AG19+AE20,AG19), IFERROR(AG19+AD20,AG19)) -> 456.335 | AH20: link | AI20: 6635.56 | AJ20: =57.5+15176.12 -> 15233.62 | AK20: =55*5 -> 275 | AL20: 1000 | AM20: =SUM(AI20:AL20) -> 23144.18 | AN20: =AM20/AE20 -> 845.8821 | AO20: 600 | AP20: =(AO20*AE20)-AM20 -> -6727.58 | AQ20: =((AO20*AD20)-AM20)/(AD20*AO20) -> -0.48356824 | AS20: =AE20/#REF! -> #REF!
A21: 20 | B21: 020T1R0 | C21: Guy Guillemette | D21: AECN | E21: truck | F21: 45069 | G21: 45073 | I21: 45076 | K21: 327.52 | L21: =K21*J21 -> 0 | M21: Injection @ Hildreth A6 | N21: 20.13 | O21: =K21*N21 -> 6592.9776 | Q21: 020T3R1 | R21: =(0.4469+0.4377)/2 -> 0.4423 | T21: verified | U21: =N21*R21*(44.01/12.011) -> 32.623678 | V21: =IF(D21="AECN",0.68,"ERROR") -> 0.68 | W21: =IF(D21="AECN",0.2,"ERROR") -> 0.2 | X21: =(0.1738*((N21/V21)*W21))/1000 -> 0.0010289982 | Y21: =IF(D21="AECN",(140.5*N21)/1000,ERROR) -> 2.828265 | Z21: =IF(D21="AECN",2030,"ERROR") -> 2030 | AA21: =(0.1046*N21*Z21)/1000 -> 4.2743639 | AB21: =(0.7205*N21)/1000 -> 0.014503665 | AC21: =SUM(AA21:AB21,Y21,X21) -> 7.1181616 | AD21: =U21-AC21 -> 25.505516 | AE21: =26856/1000 -> 26.856 | AF21: =(AE21-AD21)/AD21 -> 0.052948706 | AG21: =IF(T21="verified",IFERROR(AG20+AE21,AG20), IFERROR(AG20+AD21,AG20)) -> 483.191 | AH21: [same as above] | AI21: 6592.98 | AJ21: =87.16+15716.12 -> 15803.28 | AK21: =5*55 -> 275 | AL21: 1000 | AM21: =SUM(AI21:AL21) -> 23671.26 | AN21: =AM21/AE21 -> 881.41421 | AO21: 600 | AP21: =(AO21*AD21)-AM21 -> -8367.9504 | AQ21: =((AO21*AD21)-AM21)/(AD21*AO21) -> -0.54680658 | AS21: =AE21/N20 -> 1.3255676
A22: 21 | B22: 021T1R0 | C22: Darryl Kennedy | D22: AECN | E22: truck | F22: 45040 | G22: 45072 | I22: 45077 | M22: Injection @ Hildreth A6 | N22: 20.7 | Q22: 021T3R1 | R22: =(0.4469+0.4377)/2 -> 0.4423 | T22: verified | U22: =N21*R22*(44.01/12.011) -> 32.623678 | V22: =IF(D22="AECN",0.68,"ERROR") -> 0.68 | W22: =IF(D22="AECN",0.2,"ERROR") -> 0.2 | X22: =(0.1738*((N21/V22)*W22))/1000 -> 0.0010289982 | Y22: =IF(D22="AECN",(140.5*N21)/1000,ERROR) -> 2.828265 | Z22: =IF(D22="AECN",2030,"ERROR") -> 2030 | AA22: =(0.1046*N21*Z22)/1000 -> 4.2743639 | AB22: =(0.7205*N21)/1000 -> 0.014503665 | AC22: =SUM(AA22:AB22,Y22,X22) -> 7.1181616 | AD22: =U22-AC22 -> 25.505516 | AE22: =27614/1000 -> 27.614 | AF22: =(AE22-AD22)/AD22 -> 0.082667767 | AG22: =IF(T22="verified",IFERROR(AG21+AE22,AG21), IFERROR(AG21+AD22,AG21)) -> 510.805 | AH22: link | AI22: 6779.66 | AJ22: =222.16+15716.12 -> 15938.28 | AK22: =8*55 -> 440 | AL22: 1000 | AM22: =SUM(AI22:AL22) -> 24157.94 | AN22: =AM22/AE22 -> 874.84392 | AO22: 600 | AP22: =(AO22*AD22)-AM22 -> -8854.6304 | AQ22: =((AO22*AD22)-AM22)/(AD22*AO22) -> -0.57860886 | AS22: =AE22/N22 -> 1.3340097
A23: 22 | B23: 022T1R0 | C23: Guy Guillemette | D23: AECN | E23: truck | F23: 45069 | G23: 45081 | I23: 45085 | M23: Injection @ Hildreth A6 | N23: 20.45 | Q23: 022T3R1 | R23: =(0.4442+0.4413)/2 -> 0.44275 | T23: verified | U23: =N25*R23*(44.01/12.011) -> 32.689315 | V23: =IF(D23="AECN",0.68,"ERROR") -> 0.68 | W23: =IF(D23="AECN",0.2,"ERROR") -> 0.2 | X23: =(0.1738*((N25/V23)*W23))/1000 -> 0.0010300206 | Y23: =IF(D23="AECN",(140.5*N25)/1000,ERROR) -> 2.831075 | Z23: =IF(D23="AECN",2030,"ERROR") -> 2030 | AA23: =(0.1046*N25*Z23)/1000 -> 4.2786107 | AB23: =(0.7205*N25)/1000 -> 0.014518075 | AC23: =SUM(AA23:AB23,Y23,X23) -> 7.1252338 | AD23: =U23-AC23 -> 25.564081 | AE23: =27319/1000 -> 27.319 | AF23: =(AE23-AD23)/AD23 -> 0.068647828 | AG23: =IF(T23="verified",IFERROR(AG22+#REF!,AG22), IFERROR(AG22+AD23,AG22)) -> 510.805 | AH23: link | AI23: =N23*References!$B$6 -> 6697.784 | AJ23: =215.16+15716.12 -> 15931.28 | AK23: =References!$B$8*55 -> 385 | AL23: 1000 | AM23: =SUM(AI23:AL23) -> 24014.064 | AN23: =AM23/AE23 -> 879.02427 | AO23: 600 | AP23: =(AO23*AD23)-AM23 -> -8675.6152 | AQ23: =((AO23*AD23)-AM23)/(AD23*AO23) -> -0.56561229 | AS23: =#REF!/N25 -> #REF!
A24: 23 | B24: 023T1R0 | C24: Darryl Kennedy | D24: AECN | E24: truck | F24: 45069 | G24: 45082 | I24: 45085 | M24: Injection @ Hildreth A6 | N24: 20.81 | Q24: 023T3R1 | R24: =(0.4442+0.4413)/2 -> 0.44275 | T24: verified | U24: =N23*R24*(44.01/12.011) -> 33.176005 | V24: =IF(D24="AECN",0.68,"ERROR") -> 0.68 | W24: =IF(D24="AECN",0.2,"ERROR") -> 0.2 | X24: =(0.1738*((N23/V24)*W24))/1000 -> 0.0010453559 | Y24: =IF(D24="AECN",(140.5*N23)/1000,ERROR) -> 2.873225 | Z24: =IF(D24="AECN",2030,"ERROR") -> 2030 | AA24: =(0.1046*N23*Z24)/1000 -> 4.3423121 | AB24: =(0.7205*N23)/1000 -> 0.014734225 | AC24: =SUM(AA24:AB24,Y24,X24) -> 7.2313167 | AD24: =U24-AC24 -> 25.944688 | AE24: =27800/1000 -> 27.8 | AF24: =(AE24-AD24)/AD24 -> 0.071510283 | AG24: =IF(T24="verified",IFERROR(AG23+AE23,AG23), IFERROR(AG23+AD24,AG23)) -> 538.124 | AH24: [same as above] | AI24: =N23*References!$B$6 -> 6697.784 | AJ24: =220.16+15716.12 -> 15936.28 | AK24: =References!$B$8*55 -> 385 | AL24: 1000 | AM24: =SUM(AI24:AL24) -> 24019.064 | AN24: =AM24/AE24 -> 863.99511 | AO24: 600 | AP24: =(AO24*AD24)-AM24 -> -8452.2512 | AQ24: =((AO24*AD24)-AM24)/(AD24*AO24) -> -0.54296607 | AS24: =AE23/N23 -> 1.3358924
A25: 24 | B25: 024T1R0 | C25: Jonathan Fortier | D25: AECN | E25: truck | F25: 45069 | G25: 45083 | I25: 45090 | M25: Injection @ Hildreth A6 | N25: 20.15 | Q25: 024T3R1 | R25: =(0.4442+0.4413)/2 -> 0.44275 | T25: verified | U25: =N25*R25*(44.01/12.011) -> 32.689315 | V25: =IF(D25="AECN",0.68,"ERROR") -> 0.68 | W25: =IF(D25="AECN",0.2,"ERROR") -> 0.2 | X25: =(0.1738*((N25/V25)*W25))/1000 -> 0.0010300206 | Y25: =IF(D25="AECN",(140.5*N25)/1000,ERROR) -> 2.831075 | Z25: =IF(D25="AECN",2030,"ERROR") -> 2030 | AA25: =(0.1046*N25*Z25)/1000 -> 4.2786107 | AB25: =(0.7205*N25)/1000 -> 0.014518075 | AC25: =SUM(AA25:AB25,Y25,X25) -> 7.1252338 | AD25: =U25-AC25 -> 25.564081 | AE25: =26917/1000 -> 26.917 | AF25: =(AE25-AD25)/AD25 -> 0.052922639 | AG25: =IF(T25="verified",IFERROR(AG24+AE25,AG24), IFERROR(AG24+AD25,AG24)) -> 565.041 | AH25: link | AI25: =N25*References!$B$6 -> 6599.528 | AJ25: =200+15716.12 -> 15916.12 | AK25: =References!$B$8*55 -> 385 | AL25: 1000 | AM25: =SUM(AI25:AL25) -> 23900.648 | AN25: =AM25/AE25 -> 887.93877 | AO25: 600 | AP25: =(AO25*AD25)-AM25 -> -8562.1992 | AQ25: =((AO25*AD25)-AM25)/(AD25*AO25) -> -0.55821806 | AS25: =AE25/#REF! -> #REF!
A26: 25 | B26: 025T1R0 | C26: Patrick Tremblay | D26: AECN | E26: truck | F26: 45069 | G26: 45085 | I26: 45091 | M26: Injection @ Hildreth A6 | N26: 19.79 | Q26: 025T1R0 | R26: =(0.4442+0.4413)/2 -> 0.44275 | T26: verified | U26: =N26*R26*(44.01/12.011) -> 32.105288 | V26: =IF(D26="AECN",0.68,"ERROR") -> 0.68 | W26: =IF(D26="AECN",0.2,"ERROR") -> 0.2 | X26: =(0.1738*((N26/V26)*W26))/1000 -> 0.0010116182 | Y26: =IF(D26="AECN",(140.5*N26)/1000,ERROR) -> 2.780495 | Z26: =IF(D26="AECN",2030,"ERROR") -> 2030 | AA26: =(0.1046*N26*Z26)/1000 -> 4.202169 | AB26: =(0.7205*N26)/1000 -> 0.014258695 | AC26: =SUM(AA26:AB26,Y26,X26) -> 6.9979343 | AD26: =U26-AC26 -> 25.107353 | AE26: =26436/1000 -> 26.436 | AF26: =(AE26-AD26)/AD26 -> 0.052918627 | AG26: =IF(T26="verified",IFERROR(AG25+AE26,AG25), IFERROR(AG25+AD26,AG25)) -> 591.477 | AH26: link | AI26: =N26*References!$B$6 -> 6481.6208 | AJ26: =200+15716.12 -> 15916.12 | AK26: =References!$B$8*55 -> 385 | AL26: 1000 | AM26: =SUM(AI26:AL26) -> 23782.741 | AN26: =AM26/AE26 -> 899.63462 | AO26: 600 | AP26: =(AO26*AD26)-AM26 -> -8718.3288 | AQ26: =((AO26*AD26)-AM26)/(AD26*AO26) -> -0.57873675 | AS26: =AE26/N26 -> 1.3358262
A27: 26 | B27: 026T1R0 | C27: Guy Guillemette | D27: AECN | E27: truck | F27: 45069 | G27: 45089 | I27: 45093 | M27: Injection @ Hildreth A6 | N27: 19.82 | Q27: 026T1R0 | R27: 0.434 | T27: verified | U27: =N27*R27*(44.01/12.011) -> 31.518503 | V27: =IF(D27="AECN",0.68,"ERROR") -> 0.68 | W27: =IF(D27="AECN",0.2,"ERROR") -> 0.2 | X27: =(0.1738*((N27/V27)*W27))/1000 -> 0.0010131518 | Y27: =IF(D27="AECN",(140.5*N27)/1000,ERROR) -> 2.78471 | Z27: =IF(D27="AECN",2030,"ERROR") -> 2030 | AA27: =(0.1046*N27*Z27)/1000 -> 4.2085392 | AB27: =(0.7205*N27)/1000 -> 0.01428031 | AC27: =SUM(AA27:AB27,Y27,X27) -> 7.0085426 | AD27: =U27-AC27 -> 24.50996 | AE27: =25837/1000 -> 25.837 | AF27: =(AE27-AD27)/AD27 -> 0.054142874 | AG27: =IF(T27="verified",IFERROR(AG26+AE27,AG26), IFERROR(AG26+AD27,AG26)) -> 617.314 | AI27: =N27*References!$B$6 -> 6491.4464 | AJ27: =200+15716.12 -> 15916.12 | AK27: =References!$B$8*55 -> 385 | AL27: 1000 | AM27: =SUM(AI27:AL27) -> 23792.566 | AN27: =AM27/AE27 -> 920.87187 | AO27: 600 | AP27: =(AO27*AD27)-AM27 -> -9086.5902 | AQ27: =((AO27*AD27)-AM27)/(AD27*AO27) -> -0.61788419 | AR27: The driver, Guy, way short on his log book so he did not take time to fuel his truck before the loading. He asked the control room to load a maximum of 79000 lbs, giving a target of 16 974 L to have enough room for his fuel later on. With the density adjustment the final volume was 16369 L. Tho normal aim volume should have been to load 17165 with its empty weight. | AS27: =AE27/N27 -> 1.3035822
A28: 27 | B28: 027T1R0 | C28: Stephane Boucher | D28: AECN | E28: truck | F28: 45069 | G28: 45090 | I28: 45094 | M28: Injection @ Hildreth A6 | N28: 20.81 | Q28: 027T1R0 | R28: 0.433 | T28: verified | U28: =N28*R28*(44.01/12.011) -> 33.016587 | V28: =IF(D28="AECN",0.68,"ERROR") -> 0.68 | W28: =IF(D28="AECN",0.2,"ERROR") -> 0.2 | X28: =(0.1738*((N28/V28)*W28))/1000 -> 0.0010637582 | Y28: =IF(D28="AECN",(140.5*N28)/1000,ERROR) -> 2.923805 | Z28: =IF(D28="AECN",2030,"ERROR") -> 2030 | AA28: =(0.1046*N28*Z28)/1000 -> 4.4187538 | AB28: =(0.7205*N28)/1000 -> 0.014993605 | AC28: =SUM(AA28:AB28,Y28,X28) -> 7.3586161 | AD28: =U28-AC28 -> 25.657971 | AE28: =27051/1000 -> 27.051 | AF28: =(AE28-AD28)/AD28 -> 0.054292254 | AG28: =IF(T28="verified",IFERROR(AG27+AE28,AG27), IFERROR(AG27+AD28,AG27)) -> 644.365 | AI28: =N28*References!$B$6 -> 6815.6912 | AJ28: =200+15716.12 -> 15916.12 | AK28: =References!$B$8*55 -> 385 | AL28: 1000 | AM28: =SUM(AI28:AL28) -> 24116.811 | AN28: =AM28/AE28 -> 891.53123 | AO28: 600 | AP28: =(AO28*AD28)-AM28 -> -8722.0286 | AQ28: =((AO28*AD28)-AM28)/(AD28*AO28) -> -0.56655744 | AS28: =AE28/N28 -> 1.2999039
A29: 28 | B29: 028T1R0 | C29: Guy Guillemette | D29: AECN | E29: truck | G29: 45092 | I29: 45096 | M29: Injection @ Hildreth A6 | N29: 19.77 | Q29: 028T1R0 | R29: 0.429 | T29: verified | U29: =N29*R29*(44.01/12.011) -> 31.076791 | V29: =IF(D29="AECN",0.68,"ERROR") -> 0.68 | W29: =IF(D29="AECN",0.2,"ERROR") -> 0.2 | X29: =(0.1738*((N29/V29)*W29))/1000 -> 0.0010105959 | Y29: =IF(D29="AECN",(140.5*N29)/1000,ERROR) -> 2.777685 | Z29: =IF(D29="AECN",2030,"ERROR") -> 2030 | AA29: =(0.1046*N29*Z29)/1000 -> 4.1979223 | AB29: =(0.7205*N29)/1000 -> 0.014244285 | AC29: =SUM(AA29:AB29,Y29,X29) -> 6.9908621 | AD29: =U29-AC29 -> 24.085929 | AE29: =25410/1000 -> 25.41 | AF29: =(AE29-AD29)/AD29 -> 0.05497282 | AG29: =IF(T29="verified",IFERROR(AG28+AE29,AG28), IFERROR(AG28+AD29,AG28)) -> 669.775 | AI29: =N29*References!$B$6 -> 6475.0704 | AJ29: =200+15716.12 -> 15916.12 | AK29: =References!$B$8*55 -> 385 | AL29: 1000 | AM29: =SUM(AI29:AL29) -> 23776.19 | AN29: =AM29/AE29 -> 935.7021 | AO29: 600 | AP29: =(AO29*AD29)-AM29 -> -9324.6333 | AQ29: =((AO29*AD29)-AM29)/(AD29*AO29) -> -0.64523381 | AS29: =AE29/N29 -> 1.2852807
A30: 29 | B30: 029T1R0 | C30: Guy Guillemette | D30: AECN | E30: truck | G30: 45244 | I30: 11/17/2023 (totes) | M30: Injection @ Hildreth A6 | N30: 20.08 | Q30: 029T1R0 | R30: 0.4443 | T30: recorded | U30: =N30*R30*(44.01/12.011) -> 32.689797 | V30: =IF(D30="AECN",0.68,"ERROR") -> 0.68 | W30: =IF(D30="AECN",0.2,"ERROR") -> 0.2 | X30: =(0.1738*((N30/V30)*W30))/1000 -> 0.0010264424 | Y30: =IF(D30="AECN",(140.5*N30)/1000,ERROR) -> 2.82124 | Z30: =IF(D30="AECN",2030,"ERROR") -> 2030 | AA30: =(0.1046*N30*Z30)/1000 -> 4.263747 | AB30: =(0.7205*N30)/1000 -> 0.01446764 | AC30: =SUM(AA30:AB30,Y30,X30) -> 7.1004811 | AD30: =U30-AC30 -> 25.589316 | AG30: =IF(T30="verified",IFERROR(AG29+AE30,AG29), IFERROR(AG29+AD30,AG29)) -> 695.36432 | AI30: =N30*References!$B$6 -> 6576.6016 | AJ30: =200+15716.12 -> 15916.12 | AK30: =References!$B$8*55 -> 385 | AL30: 1000 | AM30: =SUM(AI30:AL30) -> 23877.722 | AO30: 600 | AP30: =(AO30*AD30)-AM30 -> -8524.1321 | AQ30: =((AO30*AD30)-AM30)/(AD30*AO30) -> -0.55518822 | AS30: =AE30/N30 -> 0
A31: 30 | B31: 030T1R0 | C31: Guy Guillemette | D31: AECN | E31: truck | G31: 45258 | I31: 12/1/2023 (totes) | M31: Injection @ Hildreth A6 | N31: 19.91 | Q31: 030T1R0 | R31: 0.4518 | T31: recorded | U31: =N31*R31*(44.01/12.011) -> 32.960189 | V31: =IF(D31="AECN",0.68,"ERROR") -> 0.68 | W31: =IF(D31="AECN",0.2,"ERROR") -> 0.2 | X31: =(0.1738*((N31/V31)*W31))/1000 -> 0.0010177524 | Y31: =IF(D31="AECN",(140.5*N31)/1000,ERROR) -> 2.797355 | Z31: =IF(D31="AECN",2030,"ERROR") -> 2030 | AA31: =(0.1046*N31*Z31)/1000 -> 4.2276496 | AB31: =(0.7205*N31)/1000 -> 0.014345155 | AC31: =SUM(AA31:AB31,Y31,X31) -> 7.0403675 | AD31: =U31-AC31 -> 25.919821 | AG31: =IF(T31="verified",IFERROR(AG30+AE31,AG30), IFERROR(AG30+AD31,AG30)) -> 721.28414 | AI31: =N31*References!$B$6 -> 6520.9232 | AJ31: =200+15716.12 -> 15916.12 | AK31: =References!$B$8*55 -> 385 | AL31: 1000 | AM31: =SUM(AI31:AL31) -> 23822.043 | AO31: 600 | AP31: =(AO31*AD31)-AM31 -> -8270.1505 | AQ31: =((AO31*AD31)-AM31)/(AD31*AO31) -> -0.53177775 | AS31: =AE31/N31 -> 0
A32: 31 | B32: 031T1R0 | C32: Guy Guillemette | D32: AECN | E32: truck | G32: 45272 | I32: 12/16/2023 (totes) | M32: Injection @ Hildreth A6 | N32: 19.8 | Q32: 031T1R0 | R32: =References!$B$12 -> 0.435 | T32: recorded | U32: =N32*R32*(44.01/12.011) -> 31.559248 | V32: =IF(D32="AECN",0.68,"ERROR") -> 0.68 | W32: =IF(D32="AECN",0.2,"ERROR") -> 0.2 | X32: =(0.1738*((N32/V32)*W32))/1000 -> 0.0010121294 | Y32: =IF(D32="AECN",(140.5*N32)/1000,ERROR) -> 2.7819 | Z32: =IF(D32="AECN",2030,"ERROR") -> 2030 | AA32: =(0.1046*N32*Z32)/1000 -> 4.2042924 | AB32: =(0.7205*N32)/1000 -> 0.0142659 | AC32: =SUM(AA32:AB32,Y32,X32) -> 7.0014704 | AD32: =U32-AC32 -> 24.557778 | AG32: =IF(T32="verified",IFERROR(AG31+AE32,AG31), IFERROR(AG31+AD32,AG31)) -> 745.84191 | AI32: =N32*References!$B$6 -> 6484.896 | AJ32: =200+15716.12 -> 15916.12 | AK32: =References!$B$8*55 -> 385 | AL32: 1000 | AM32: =SUM(AI32:AL32) -> 23786.016 | AO32: 600 | AP32: =(AO32*AD32)-AM32 -> -9051.3493 | AQ32: =((AO32*AD32)-AM32)/(AD32*AO32) -> -0.61428939 | AS32: =AE32/N32 -> 0
