Workbook

Sheet 2024
B1: Unit | C1: Baseline Quantity | D1: Uncertainty Factor | E1: Final Quantity | F1: Source
A2: Normalized
A3: Production Emissions for AECN Oil | B3: MTCO2e/MT Oil | C3: 0.12678253 | D3: 0.0020880613 | E3: 0.12704726 | F3: AECN LCA
A4: Embodied Emissions for AECN Oil | B4: MTCO2e/MT Oil | C4: 0.021159411 | D4: N/A | E4: 0.021159411 | F4: AECN Information, NAICS Supply Chain Emissions Factors
A5: Truck Transport Fuel Use (Well to Wheel) -- Tanker Truck | B5: MT CO2e/t-mi | C5: 0.0001287472 | D5: N/A | E5: 0.0001287472 | F5: GLEC V3.0
A6: Truck Transport Fuel Use (Well to Wheel) -- Flatbed Truck | B6: MT CO2e/t-mi | C6: 0.0001367939 | D6: N/A | E6: 0.0001367939 | F6: GLEC V3.0 | G6: =E6*1000 -> 0.1367939
A7: Truck Transport Fuel Use (Well to Wheel) -- Specialized Truck | B7: MT CO2e/t-mi | C7: 0.00020760486 | D7: N/A | E7: 0.00020760486 | F7: GLEC V3.0
A8: Self-Loading Truck Lumber Handling (No Transport) | B8: MT CO2e/MT logs | C8: 0.0015187908 | D8: N/A | E8: 0.0015187908 | F8: Log Handling Emissions
A9: Air Transport Fuel Use (Well to Wheel) -- Unknown Type | B9: MT CO2e/T-mi | C9: 0.0013148308 | D9: N/A | E9: 0.0013148308 | F9: GLEC V3.0
A10: Rail Transport Fuel Use (Well to Wheel) | B10: MTCO2e/T-mi | C10: 2.6071308e-05 | D10: N/A | E10: 2.6071308e-05 | F10: GLEC V3.0
A11: Vehicle Embodied Emissions --Tanker Truck | B11: MT CO2e/mi | C11: 7.6749011e-05 | D11: N/A | E11: 7.6749011e-05 | F11: USEPA/GREET 2023
A12: Vehicle Embodied Emissions --Non-Tanker Truck | B12: MT CO2e/mi | C12: 6.2814439e-05 | D12: N/A | E12: 6.2814439e-05 | F12: USEPA/GREET 2023
A13: Vehicle Embodied Emissions --Railcar | B13: MT CO2e/mi | C13: 5.5333333e-05 | D13: N/A | E13: 5.5333333e-05
A14: Electricity Use -- Kansas | B14: MTCO2e/kWh | C14: 0.00045727647 | D14: N/A | E14: 0.00045727647 | F14: USEPA, GLEC
A15: Electricity Use -- Colorado | B15: MTCO2e/kWh | C15: 0.00053412001 | D15: N/A | E15: 0.00053412001 | F15: USEPA, GLEC
A16: Diesel Fuel Combustion (Total WTW) | B16: MTCO2e/kg fuel | C16: 0.00389 | D16: N/A | E16: 0.00389 | F16: GLEC V3.0
A17: LPG Consumption (Total WTW) | B17: MTCO2e/kg fuel | C17: 0.00366 | D17: N/A | E17: 0.00366 | F17: GLEC V3.0
A18: Gasoline Consumption (Total WTW) | B18: MTCO2e/kg fuel | C18: 0.00374 | D18: N/A | E18: 0.00374
A19: Drinking Water -- US | B19: MTCO2e/gal water | C19: 1.7412898e-06 | D19: N/A | E19: 1.7412898e-06 | F19: https://www.sciencedirect.com/science/article/abs/pii/S0959652621030110
A20: Embodied Emissions -- Steel (Virgin Steel FInal Average Stamped Steel Product: Combined) | B20: MTCO2e/T Steel | C20: 2.750989 | D20: N/A | E20: 2.750989 | F20: GREET 2023
A21: Embodied Emissions -- Stainless Steel (Final Steel Product:Commbined) | B21: MTCO2e/T Steel | C21: 0.784292 | D21: N/A | E21: 0.784292 | F21: GREET 2023
A22: Embodied Emissions -- Rubber (Final Average Rubber Product: Combined) | B22: MTCO2e/T Rubber | C22: 3.504988 | D22: N/A | E22: 3.504988 | F22: GREET 2023
A23: Embodied Emissions --HDPE (Fossil HDPE Resin) | B23: MTCO2e/T HDPE | C23: 1.171796 | D23: N/A | E23: 1.171796 | F23: GREET 2023
A24: Embodied Emissions -- Concrete (Ready-mix concrete US nat'l average ton delivered) | B24: MTCO2e/T Concrete | C24: 0.087248 | D24: N/A | E24: 0.087248 | F24: GREET 2023
A25: Embodied Emissions -- Liquid Caustic Soda (50% NaOH) | B25: MTCO2e/T LCS | C25: 0.930829 | D25: 0.0012002604 | E25: =C25*(1+D25) -> 0.93194624 | F25: GREET 2023
A26: Embodied Emissions -- NAICS Supply Chain Emissions Factors: Other Industrial Machinery Manufacturing | B26: MTCO2e/2021 USD, purchaser price | C26: 0.00021 | D26: N/A | E26: 0.00021 | F26: NAICS Supply Chain Emissions Factors
A27: Embodied Emissions -- NAICS Supply Chain Emissions Factors: Industrial Building Construction | B27: MTCO2e/2021 USD, purchaser price | C27: 0.00031 | D27: N/A | E27: 0.00031 | F27: NAICS Supply Chain Emissions Factors
A28: Embodied Emissions -- NAICS Supply Chain Emissions Factors: Contractors and Installation (Var.) | B28: MTCO2e/2021 USD, purchaser price | C28: 0.000245 | D28: N/A | E28: 0.000245 | F28: NAICS Supply Chain Emissions Factors
A29: Embodied Emissions -- NAICS Supply Chain Emissions Factors: Motor and Generator Manufacturing | B29: MTCO2e/2021 USD, purchaser price | C29: 0.000229 | D29: N/A | E29: 0.000229 | F29: NAICS Supply Chain Emissions Factors
A30: Embodied Emissions -- NAICS Supply Chain Emissions Factors: Construction Machinery Manufacturing | B30: MTCO2e/2021 USD, purchaser price | C30: 0.000246 | D30: N/A | E30: 0.000246 | F30: NAICS Supply Chain Emissions Factors
A31: Embodied Emissions -- NAICS Supply Chain Emissions Factors: Railroad Rolling Stock Manufacturing | B31: MTCO2e/2021 USD, purchaser price | C31: 0.000415 | D31: N/A | E31: 0.000415 | F31: NAICS Supply Chain Emissions Factors
A32: Embodied Emissions -- NAICS Supply Chain Emissions Factors: Industrial and Commercial Fan and Blower and Air Purification Equipment Manufacturing | B32: MTCO2e/2021 USD, purchaser price | C32: 0.000242 | D32: N/A | E32: 0.000242 | F32: NAICS Supply Chain Emissions Factors
A33: Embodied Emissions -- NAICS Supply Chain Emissions Factors: Air-Conditioning and Warm Air Heating Equipment and Commercial and Industrial Refrigeration Equipment Manufacturing | B33: MTCO2e/2021 USD, purchaser price | C33: 0.000236 | D33: N/A | E33: 0.000236 | F33: NAICS Supply Chain Emissions Factors
A34: Bio-Oil Disposal, Incineration | B34: MTCO2e/kg Material | C34: =0.0377/1000 -> 3.77e-05 | D34: Bespoke analysis using Climate change openLCA LCIA Methods 2.4.3/EF 3.1 Method (adapted)
A35: Bio-Oil Disposal, Landfilling [IBC Totes] | B35: MTCO2e/kg Material | C35: =0.0121/1000 -> 1.21e-05 | D35: Bespoke analysis using Climate change openLCA LCIA Methods 2.4.3/EF 3.1 Method (adapted)
A36: Bio-Oil Disposal, Landfilling [Open Dump] | B36: MTCO2e/kg Material | C36: =0.603/1000 -> 0.000603 | D36: Bespoke analysis using Climate change openLCA LCIA Methods 2.4.3/EF 3.1 Method (adapted)
A37: Bio-Oil Contaminated Gravel, Landfilling [Open Dump] | B37: MTCO2e/kg Material | C37: =0.07776/1000 -> 7.776e-05 | D37: Bespoke analysis using Climate change openLCA LCIA Methods 2.4.3/EF 3.1 Method (adapted)
E42: =E14*1000 -> 0.45727647
E43: =35712*E42 -> 16330.257

Sheet 2026
A1: Updated? | C1: Unit | D1: Baseline Quantity | E1: Uncertainty Factor | F1: Final Quantity | G1: Source | H1: kgCO2e/kg (converted) | N1: Constant
N2: km/t --> T/mi | O2: =1.60934 -> 1.60934
A3: Updated | B3: Production Emissions for AECN Oil--H1 2026 | C3: MTCO2e/MT Oil | D3: 0.1038 | E3: 0.0020880613 | F3: =D3*(1+E3) -> 0.10401674 | G3: AECN LCA
A4: Updated | B4: Production Emissions for AECN Oil--H2 2026 | C4: MTCO2e/MT Oil | D4: 0.13711713 | E4: 0 | F4: =D4*(1+E4) -> 0.13711713 | G4: FH 2026 LCA w Stack Emissions
A5: Updated | B5: Embodied Emissions for AECN Oil | C5: MTCO2e/MT Oil | D5: 0.02116 | E5: 0 | F5: =D5*(1+E5) -> 0.02116 | G5: AECN Information, NAICS Supply Chain Emissions Factors
A6: Updated | B6: Truck Transport Fuel Use (Well to Wheel) -- Tanker Truck | C6: MT CO2e/t-mi | D6: 0.0001143 | E6: 0 | F6: =D6*(1+E6) -> 0.0001143 | G6: GLEC V3.2 2025 | H6: ISOMETRIC
A7: Updated | B7: Truck Transport Fuel Use (Well to Wheel) -- Flatbed Truck | C7: MT CO2e/t-mi | D7: 0.0001384 | E7: 0 | F7: =D7*(1+E7) -> 0.0001384 | G7: GLEC V3.2 2025 | H7: ISOMETRIC
A8: Updated | B8: Self-Loading Truck Lumber Handling (No Transport) | C8: MT CO2e/MT logs | D8: 0.0015187908 | E8: 0 | F8: =D8*(1+E8) -> 0.0015187908 | G8: Log Handling Emissions
A9: Updated | B9: Air Transport Fuel Use (Well to Wheel) -- Unknown Type, Long Haul | C9: MT CO2e/T-mi | D9: =(788/1000000)*1.609 -> 0.001267892 | E9: 0 | F9: =D9*(1+E9) -> 0.001267892 | G9: GLEC V3.2 2025
A10: Updated | B10: Rail Transport Fuel Use (Well to Wheel) | C10: MTCO2e/T-mi | D10: =(0.0161*O2)/1000 -> 2.5910374e-05 | E10: 0 | F10: =D10*(1+E10) -> 2.5910374e-05 | G10: GLEC V3.2 2025 | H10: ISOMETRIC
A11: Updated | B11: Vehicle Embodied Emissions --Tanker Truck | C11: MT CO2e/mi | D11: ='Truck and Trailer EE 2026'!B17 -> 0.00023756059 | E11: 0 | F11: =D11*(1+E11) -> 0.00023756059 | G11: GLEC V3.2 2025
A12: Updated | B12: Vehicle Embodied Emissions --Non-Tanker Truck | C12: MT CO2e/mi | D12: ='Truck and Trailer EE 2026'!B23 -> 0.00019279083 | E12: 0 | F12: =D12*(1+E12) -> 0.00019279083 | G12: GLEC V3.2 2025
A13: Updated | B13: Vehicle Embodied Emissions --Railcar | C13: MTCO2e/mi | D13: ='2026 Railcar Embodied Emissions'!B5 -> 3.1130665e-05 | E13: 0 | F13: =D13*(1+E13) -> 3.1130665e-05 | G13: GLEC V3.2 2025
A14: Updated | B14: Grid Electricity Use -- Kansas | C14: MTCO2e/kWh | D14: ='2026 SPNO Electricity EFs'!D23/1000 -> 0.00046555169 | E14: 0 | F14: =D14*(1+E14) -> 0.00046555169 | G14: Green-E,USEPA, GREET 2025
A15: Updated | B15: Grid Electricity Use -- Colorado | C15: MTCO2e/kWh | D15: ='2026 RMPA Electricity EFs'!D26/1000 -> 0.00048902383 | E15: 0 | F15: =D15*(1+E15) -> 0.00048902383 | G15: Green-E,USEPA, GREET 2025
A16: Updated | B16: Grid Electricity Use -- Louisiana | C16: MTCO2e/kWh | D16: ='2026 SPSO Electricity EFs'!D5 -> 0.00046301403 | E16: 0 | F16: =D16*(1+E16) -> 0.00046301403
A17: Updated | B17: Wind RECs Use -- Kansas | C17: MTCO2e/kWh | D17: ='2026 SPNO Electricity EFs'!B30/1000 -> 1.0027197e-05 | E17: 0 | F17: =D17*(1+E17) -> 1.0027197e-05 | G17: Green-E,USEPA, GREET 2025
A18: Updated | B18: Solar RECs Use -- Colorado | C18: MTCO2e/kWh | D18: ='2026 RMPA Electricity EFs'!B33/1000 -> 3.6641546e-05 | E18: 0 | F18: =D18*(1+E18) -> 3.6641546e-05 | G18: Green-E,USEPA, GREET 2025
A19: Updated | B19: Solar RECs Use -- Louisiana | C19: MTCO2e/kWh | D19: ='2026 SPSO Electricity EFs'!B33/1000 -> 3.6641546e-05 | E19: 0 | F19: =D19*(1+E19) -> 3.6641546e-05 | G19: Green-E,USEPA, GREET 2025
A20: Updated | B20: Diesel Fuel Combustion (Total WTW) | C20: kgCO2e/kg fuel | D20: 3.87 | E20: 0 | F20: =D20*(1+E20) -> 3.87 | G20: GLEC V3.2 2025 | H20: ISOMETRIC
A21: Updated | B21: LPG Consumption (Total WTW) | C21: kgCO2e/kg fuel | D21: 3.63 | E21: 0 | F21: =D21*(1+E21) -> 3.63 | G21: GLEC V3.2 2025 | H21: ISOMETRIC
A22: Updated | B22: Gasoline Consumption (Total WTW) | C22: kgCO2e/kg fuel | D22: 3.74 | E22: 0 | F22: =D22*(1+E22) -> 3.74 | G22: GLEC V3.2 2025 | H22: ISOMETRIC
A23: Updated | B23: Drinking Water -- US | C23: MTCO2e/gal water | D23: ='2026 Water'!A4 -> 1.7412898e-06 | E23: 0 | F23: =D23*(1+E23) -> 1.7412898e-06 | G23: https://www.sciencedirect.com/science/article/abs/pii/S0959652621030110
A24: Updated | B24: Sample Transport Emissions | C24: MT CO2e/Injection Batch | D24: N/A Immaterial | F24: N/A Immaterial
A25: Updated | B25: Embodied Emissions -- Copper Cathode | C25: kgCO2e/kg Copper | D25: 3.965 | E25: 0 | F25: =D25*(1+E25) -> 3.965 | G25: International Copper Association (Page 9)
A26: Updated | B26: Embodied Emissions -- Steel (Virgin Steel FInal Average Stamped Steel Product: Combined) | C26: MTCO2e/T Steel | D26: =2817607/1000000 -> 2.817607 | E26: 0 | F26: =D26*(1+E26) -> 2.817607 | G26: GREET 2025 | H26: 3.106312
A27: Updated | B27: Embodied Emissions -- Stainless Steel (Final Steel Product:Combined) | C27: MTCO2e/T Steel | D27: =720746/1000000 -> 0.720746 | E27: 0 | F27: =D27*(1+E27) -> 0.720746 | G27: GREET 2025 | H27: 0.794486
A28: Updated | B28: Embodied Emissions -- Rubber (Final Average Rubber Product: Combined) | C28: MTCO2e/T Rubber | D28: =3372324/1000000 -> 3.372324 | E28: 0 | F28: =D28*(1+E28) -> 3.372324 | G28: GREET 2025 | H28: 3.71735
A29: Updated | B29: Embodied Emissions --HDPE | C29: MTCO2e/T HDPE | D29: =1702514/1000000 -> 1.702514 | E29: 0 | F29: =D29*(1+E29) -> 1.702514 | G29: GREET 2025 | H29: 1.8767
A30: Updated | B30: Embodied Emissions --LDPE | C30: MTCO2e/T LDPE | D30: =1980563/1000000 -> 1.980563 | E30: 0 | F30: =D30*(1+E30) -> 1.980563 | G30: GREET 2025 | H30: 2.183196
A31: Updated | B31: Embodied Emissions -- Concrete (Ready-mix concrete US nat'l average ton delivered) | C31: MTCO2e/T Concrete | D31: =86234/1000000 -> 0.086234 | E31: 0 | F31: =D31*(1+E31) -> 0.086234 | G31: GREET 2025 | H31: 0.095057
A32: Updated | B32: Embodied Emissions -- Liquid Caustic Soda (50% NaOH) | C32: MTCO2e/T LCS | D32: ='2026 LCS Embodied Emissions'!B7 -> 0.9524086 | E32: 0.0012002604 | F32: =D32*(1+E32) -> 0.95355174 | G32: GREET 2025 | H32: 1.051111
A33: Updated | B33: Embodied Emissions -- NAICS Supply Chain Emissions Factors: Other Industrial Machinery Manufacturing | C33: kg CO2e/2024 USD, purchaser price | D33: ='2026 Currency Conversions for C'!H9 -> 0.1577 | E33: 0 | F33: =D33*(1+E33) -> 0.1577 | G33: NAICS Supply Chain Emissions Factors 1.4.0
A34: Updated | B34: Embodied Emissions -- NAICS Supply Chain Emissions Factors: Industrial Building Construction | C34: kg CO2e/2024 USD, purchaser price | D34: ='2026 Currency Conversions for C'!H3 -> 0.1995 | E34: 0 | F34: =D34*(1+E34) -> 0.1995 | G34: NAICS Supply Chain Emissions Factors 1.4.0
A35: Updated | B35: Embodied Emissions -- NAICS Supply Chain Emissions Factors: All Other Specialty Trade Contractors | C35: kg CO2e/2024 USD, purchaser price | D35: ='2026 Currency Conversions for C'!H4 -> 0.19095 | E35: 0 | F35: =D35*(1+E35) -> 0.19095 | G35: NAICS Supply Chain Emissions Factors 1.4.0
A36: Updated | B36: Embodied Emissions -- NAICS Supply Chain Emissions Factors: Motor and Generator Manufacturing | C36: kg CO2e/2024 USD, purchaser price | D36: ='2026 Currency Conversions for C'!H10 -> 0.1235 | E36: 0 | F36: =D36*(1+E36) -> 0.1235 | G36: NAICS Supply Chain Emissions Factors 1.4.0
A37: Updated | B37: Embodied Emissions -- NAICS Supply Chain Emissions Factors: Construction Machinery Manufacturing | C37: kg CO2e/2024 USD, purchaser price | D37: ='2026 Currency Conversions for C'!H5 -> 0.17765 | E37: 0 | F37: =D37*(1+E37) -> 0.17765 | G37: NAICS Supply Chain Emissions Factors 1.4.0
A38: Updated | B38: Embodied Emissions -- NAICS Supply Chain Emissions Factors: Railroad Rolling Stock Manufacturing | C38: kg CO2e/2024 USD, purchaser price | D38: ='2026 Currency Conversions for C'!H2 -> 0.37715 | E38: 0 | F38: =D38*(1+E38) -> 0.37715 | G38: NAICS Supply Chain Emissions Factors 1.4.0
A39: Updated | B39: Embodied Emissions -- NAICS Supply Chain Emissions Factors: Industrial and Commercial Fan and Blower and Air Purification Equipment Manufacturing | C39: kg CO2e/2024 USD, purchaser price | D39: ='2026 Currency Conversions for C'!H6 -> 0.1767 | E39: 0 | F39: =D39*(1+E39) -> 0.1767 | G39: NAICS Supply Chain Emissions Factors 1.4.0
A40: Updated | B40: Embodied Emissions -- NAICS Supply Chain Emissions Factors: Air-Conditioning and Warm Air Heating Equipment and Commercial and Industrial Refrigeration Equipment Manufacturing | C40: kg CO2e/2024 USD, purchaser price | D40: ='2026 Currency Conversions for C'!H7 -> 0.1748 | E40: 0 | F40: =D40*(1+E40) -> 0.1748 | G40: NAICS Supply Chain Emissions Factors 1.4.0
A41: Updated | B41: Bio-Oil Disposal, Incineration | C41: MTCO2e/kg Material | D41: =0.0377/1000 -> 3.77e-05 | E41: 0 | F41: =D41*(1+E41) -> 3.77e-05 | G41: Bespoke analysis using Climate change openLCA LCIA Methods 2.4.3/EF 3.1 Method (adapted)
A42: Updated | B42: Bio-Oil Disposal, Landfilling [IBC Totes] | C42: MTCO2e/kg Material | D42: =0.0121/1000 -> 1.21e-05 | E42: 0 | F42: =D42*(1+E42) -> 1.21e-05 | G42: Bespoke analysis using Climate change openLCA LCIA Methods 2.4.3/EF 3.1 Method (adapted)
A43: Updated | B43: Bio-Oil Disposal, Landfilling [Open Dump] | C43: MTCO2e/kg Material | D43: =0.603/1000 -> 0.000603 | E43: 0 | F43: =D43*(1+E43) -> 0.000603 | G43: Bespoke analysis using Climate change openLCA LCIA Methods 2.4.3/EF 3.1 Method (adapted)
A44: Updated | B44: Bio-Oil Contaminated Gravel, Landfilling [Open Dump] | C44: MTCO2e/kg Material | D44: =0.259/1000 -> 0.000259 | E44: 0 | F44: =D44*(1+E44) -> 0.000259 | G44: Bespoke analysis using Climate change openLCA LCIA Methods 2.4.3/EF 3.1 Method (adapted)
A45: Updated | B45: Embodied Emissions -- NAICS Supply Chain Emissions Factors: Prefabricating Wood Building Manufacturing | C45: kgCO2e/2022 USD, purchaser price | D45: ='2026 Currency Conversions for C'!H8 -> 0.16815 | E45: 0 | F45: =D45*(1+E45) -> 0.16815 | G45: NAICS Supply Chain Emissions Factors 1.4.0
A46: Updated | B46: Aluminium, General, North America Cradle to Gate | C46: kgCO2e/kg fuel | D46: 5.65 | E46: 0 | F46: =D46*(1+E46) -> 5.65 | G46: ICE Database 4.0 - ISOMETRIC | H46: 5.65
A47: Updated | B47: Methanol | C47: kgCO2e/gal | D47: ='2026 Methanol'!C2 -> 1.3988008 | E47: 0 | F47: =D47*(1+E47) -> 1.3988008 | G47: GREET 2025
A48: Updated | B48: Limestone | C48: kgCO2e/T Limestone | D48: =8179/1000 -> 8.179 | E48: 0 | F48: =D48*(1+E48) -> 8.179 | G48: GREET 2025 | H48: 0.009016
A49: Updated | B49: Aggregate from virgin land won resources, bulk, loose | C49: kg CO2e/kg Material | D49: 0.00436 | E49: 0 | F49: =D49*(1+E49) -> 0.00436 | G49: ICE DB Advanced 4.1 Oct 2025 | H49: 0.00436
A50: Updated | B50: Asphalt -- Road Asphalt Average | C50: kgCO2e/kg Material | D50: 0.048 | E50: 0 | F50: =D50*(1+E50) -> 0.048 | G50: ICE DB Advanced 4.1 Oct 2025 | H50: 0.048
A51: Updated | B51: Treated Softwood Lumber | C51: kgCO2e/kg | D51: 0.263 | E51: 0 | F51: =D51*(1+E51) -> 0.263 | G51: ICE DB Advanced 4.1 Oct 2026 | H51: 0.263
A52: Updated | B52: Embodied Emissions -- NAICS Supply Chain Emissions Factors: All Other Miscellaneous Textile Product Mills (314999) | C52: kg CO2e/2024 USD, purchaser price | D52: 0.22 | E52: 0 | F52: 0.22 | G52: NAICS Supply Chain Emissions Factors 1.4.0
A53: Updated | B53: Embodied Emissions -- NAICS Supply Chain Emissions Factors: Paper Bag and Coated and Treated Paper Manufacturing (322220) | C53: kg CO2e/2024 USD, purchaser price | D53: 0.325 | E53: 0 | F53: 0.325 | G53: NAICS Supply Chain Emissions Factors 1.4.0
A54: Updated | B54: Embodied Emissions -- NAICS Supply Chain Emissions Factors: Petroleum Lubricating Oil and Grease Manufacturing (324191) | C54: kg CO2e/2024 USD, purchaser price | D54: 0.544 | E54: 0 | F54: 0.544 | G54: NAICS Supply Chain Emissions Factors 1.4.0
A55: Updated | B55: Embodied Emissions -- NAICS Supply Chain Emissions Factors: Polish and Other Sanitation Good Manufacturing (325612) | C55: kg CO2e/2024 USD, purchaser price | D55: 0.298 | E55: 0 | F55: 0.298 | G55: NAICS Supply Chain Emissions Factors 1.4.0
A56: Updated | B56: Embodied Emissions -- NAICS Supply Chain Emissions Factors: Plastics Pipe and Pipe Fitting Manufacturing (326122) | C56: kg CO2e/2024 USD, purchaser price | D56: 0.348 | E56: 0 | F56: 0.348 | G56: NAICS Supply Chain Emissions Factors 1.4.0
A57: Updated | B57: Embodied Emissions -- NAICS Supply Chain Emissions Factors: Urethane and Other Foam Product (except Polystyrene) Manufacturing (326150) | C57: kg CO2e/2024 USD, purchaser price | D57: 0.346 | E57: 0 | F57: 0.346 | G57: NAICS Supply Chain Emissions Factors 1.4.0
A58: Updated | B58: Embodied Emissions -- NAICS Supply Chain Emissions Factors: Plastics Bottle Manufacturing (326160) | C58: kg CO2e/2024 USD, purchaser price | D58: 0.526 | E58: 0 | F58: 0.526 | G58: NAICS Supply Chain Emissions Factors 1.4.0
A59: Updated | B59: Embodied Emissions -- NAICS Supply Chain Emissions Factors: Rubber and Plastics Hoses and Belting Manufacturing (326220) | C59: kg CO2e/2024 USD, purchaser price | D59: 0.281 | E59: 0 | F59: 0.281 | G59: NAICS Supply Chain Emissions Factors 1.4.0
A60: Updated | B60: Embodied Emissions -- NAICS Supply Chain Emissions Factors: Saw Blade and Handtool Manufacturing (332216) | C60: kg CO2e/2024 USD, purchaser price | D60: 0.192 | E60: 0 | F60: 0.192 | G60: NAICS Supply Chain Emissions Factors 1.4.0
A61: Updated | B61: Embodied Emissions -- NAICS Supply Chain Emissions Factors: Bolt, Nut, Screw, Rivet, and Washer Manufacturing (332722) | C61: kg CO2e/2024 USD, purchaser price | D61: 0.207 | E61: 0 | F61: 0.207 | G61: NAICS Supply Chain Emissions Factors 1.4.0
A62: Updated | B62: Embodied Emissions -- NAICS Supply Chain Emissions Factors: Industrial Valve Manufacturing (332911) | C62: kg CO2e/2024 USD, purchaser price | D62: 0.14 | E62: 0 | F62: 0.14 | G62: NAICS Supply Chain Emissions Factors 1.4.0
A63: Updated | B63: Embodied Emissions -- NAICS Supply Chain Emissions Factors: Fabricated Pipe and Pipe Fitting Manufacturing (332996) | C63: kg CO2e/2024 USD, purchaser price | D63: 0.213 | E63: 0 | F63: 0.213 | G63: NAICS Supply Chain Emissions Factors 1.4.0
... A69: Updated | B69: Embodied Emissions -- NAICS Supply Chain Emissions Factors: All Other Miscellaneous Manufacturing (339999) | C69: kg CO2e/2024 USD, purchaser price | D69: 0.159 | E69: 0 | F69: 0.159 | G69: NAICS Supply Chain Emissions Factors 1.4.0

Sheet 2025
A1: Updated? | C1: Unit | D1: Baseline Quantity | E1: Uncertainty Factor | F1: Final Quantity | G1: Source
A3: Updated | B3: Production Emissions for AECN Oil--H1 2025 | C3: MTCO2e/MT Oil | D3: ='H1 2025 AECN Process Emissions'!I11 -> 0.12678 | E3: 0.0020880613 | F3: =D3*(1+E3) -> 0.12704472 | G3: AECN LCA
A4: Updated | B4: Embodied Emissions for AECN Oil | C4: MTCO2e/MT Oil | D4: 0.021159411 | E4: N/A | F4: 0.021159411 | G4: AECN Information, NAICS Supply Chain Emissions Factors
A5: Updated | B5: Truck Transport Fuel Use (Well to Wheel) -- Tanker Truck | C5: MT CO2e/t-mi | D5: =(70/1000000)*1.609 -> 0.00011263 | E5: 0 | F5: =SUM(D5:E5) -> 0.00011263 | G5: GLEC V3.0 2024
A6: Updated | B6: Truck Transport Fuel Use (Well to Wheel) -- Flatbed Truck | C6: MT CO2e/t-mi | D6: =(84/1000000)*1.609 -> 0.000135156 | E6: 0 | F6: =SUM(D6:E6) -> 0.000135156 | G6: GLEC V3.0 2024
A7: Updated | B7: Self-Loading Truck Lumber Handling (No Transport) | C7: MT CO2e/MT logs | D7: 0.0015187908 | E7: N/A | F7: 0.0015187908 | G7: Log Handling Emissions
A8: Updated | B8: Air Transport Fuel Use (Well to Wheel) -- Unknown Type, Long Haul | C8: MT CO2e/T-mi | D8: =(788/1000000)*1.609 -> 0.001267892 | E8: 0 | F8: =SUM(D8:E8) -> 0.001267892 | G8: GLEC V3.0 2024
A9: Updated | B9: Rail Transport Fuel Use (Well to Wheel) | C9: MTCO2e/T-mi | D9: =(16.1/1000000)*1.609 -> 2.59049e-05 | E9: 0 | F9: =SUM(D9:E9) -> 2.59049e-05 | G9: GLEC V3.0 2024 | P9: MT CO2e/mi | Q9: Kg CO2e/mi | R9: AECN Journey mi | T9: % Reduction vs. Tanker
A10: Updated | B10: Vehicle Embodied Emissions --Tanker Truck | C10: MT CO2e/mi | D10: ='Truck and Trailer EE 2025'!B15 -> 7.8799528e-05 | E10: 0 | F10: =SUM(D10:E10) -> 7.8799528e-05 | G10: USEPA/GREET 2024 | O10: Vehicle Embodied Emissions --Tanker Truck | P10: 7.8799528e-05 | Q10: =P10*1000 -> 0.078799528 | R10: 2033 | S10: =R10*Q10 -> 160.19944 | T10: --
A11: Updated | B11: Vehicle Embodied Emissions --Non-Tanker Truck | C11: MT CO2e/mi | D11: ='Truck and Trailer EE 2025'!B20 -> 6.4492663e-05 | E11: 0 | F11: =SUM(D11:E11) -> 6.4492663e-05 | G11: USEPA/GREET 2024 | O11: Vehicle Embodied Emissions --Non-Tanker Truck | P11: 6.4492663e-05 | Q11: =P11*1000 -> 0.064492663 | R11: 2033 | S11: =R11*Q11 -> 131.11358 | T11: =($Q$10-Q11)/$Q$10 -> 0.18156028
A12: Updated | B12: Vehicle Embodied Emissions --Railcar | C12: MT CO2e/mi | D12: ='2025 Railcar Embodied Emissions'!B9 -> 3.5224e-05 | F12: =SUM(D12:E12) -> 3.5224e-05 | G12: USDOT/USEPA/Cambridge Systematics | O12: Vehicle Embodied Emissions --Railcar | P12: 3.5224e-05 | Q12: =P12*1000 -> 0.035224 | R12: 2033 | S12: =R12*Q12 -> 71.610392 | T12: =($Q$10-Q12)/$Q$10 -> 0.55299224
A13: Updated | B13: Grid Electricity Use -- Kansas | C13: MTCO2e/kWh | D13: ='2025 KS Electricity EFs'!D22 -> 0.00046550696 | E13: 0 | F13: =SUM(D13:E13) -> 0.00046550696 | G13: Green-E,USEPA, GREET 2024
A14: Updated | B14: Grid Electricity Use -- Colorado | C14: MTCO2e/kWh | D14: ='2025 CO Electricity EFs'!D25 -> 0.00052474462 | E14: 0 | F14: =SUM(D14:E14) -> 0.00052474462 | G14: Green-E,USEPA, GREET 2024
A15: Updated | B15: Grid Electricity Use -- Louisiana | C15: MTCO2e/kWh | D15: ='2025 LA Electricity EFs'!D25 -> 0.0003656312 | F15: =SUM(D15:E15) -> 0.0003656312
A16: Updated | B16: Wind RECs Use -- Kansas | C16: MTCO2e/kWh | D16: ='2025 KS Electricity EFs'!B30/1000 -> 1.0044151e-05 | E16: 0 | F16: =SUM(D16:E16) -> 1.0044151e-05 | G16: Green-E,USEPA, GREET 2024
A17: Updated | B17: Solar RECs Use -- Colorado | C17: MTCO2e/kWh | D17: ='2025 CO Electricity EFs'!B33/1000 -> 3.67494e-05 | E17: 0 | F17: =SUM(D17:E17) -> 3.67494e-05 | G17: Green-E,USEPA, GREET 2024
A18: Updated | B18: Diesel Fuel Combustion (Total WTW) | C18: MTCO2e/kg fuel | D18: =3.87/1000 -> 0.00387 | E18: 0 | F18: =SUM(D18:E18) -> 0.00387 | G18: GLEC V3.0 2024
A19: Updated | B19: LPG Consumption (Total WTW) | C19: MTCO2e/kg fuel | D19: =3.63/1000 -> 0.00363 | E19: 0 | F19: =SUM(D19:E19) -> 0.00363 | G19: GLEC V3.0 2024
A20: Updated | B20: Gasoline Consumption (Total WTW) | C20: MTCO2e/kg fuel | D20: =3.74/1000 -> 0.00374 | E20: 0 | F20: =D20 -> 0.00374 | G20: GLEC V3.0 2024
A21: Updated | B21: Drinking Water -- US | C21: MTCO2e/gal water | D21: 1.7412898e-06 | E21: 0 | F21: =SUM(D21:E21) -> 1.7412898e-06 | G21: https://www.sciencedirect.com/science/article/abs/pii/S0959652621030110
A22: Updated | B22: Sample Transport Emissions | C22: MT CO2e/Injection Batch | D22: ='2025 MRV Sample Shipping'!B16 -> 0.00036776416 | E22: 0 | F22: =SUM(D22:E22) -> 0.00036776416
A23: Updated | B23: Embodied Emissions -- Steel (Virgin Steel FInal Average Stamped Steel Product: Combined) | C23: MTCO2e/T Steel | D23: =2708691/1000000 -> 2.708691 | E23: 0 | F23: =SUM(D23:E23) -> 2.708691 | G23: GREET 2024
A24: Updated | B24: Embodied Emissions -- Stainless Steel (Final Steel Product:Commbined) | C24: MTCO2e/T Steel | D24: =740914/1000000 -> 0.740914 | E24: 0 | F24: =SUM(D24:E24) -> 0.740914 | G24: GREET 2024
A25: Updated | B25: Embodied Emissions -- Rubber (Final Average Rubber Product: Combined) | C25: MTCO2e/T Rubber | D25: =3459258/1000000 -> 3.459258 | E25: 0 | F25: =SUM(D25:E25) -> 3.459258 | G25: GREET 2024
A26: Updated | B26: Embodied Emissions --HDPE | C26: MTCO2e/T HDPE | D26: =1776962/1000000 -> 1.776962 | E26: 0 | F26: =SUM(D26:E26) -> 1.776962 | G26: GREET 2024
A27: Updated | B27: Embodied Emissions --LDPE | C27: MTCO2e/T LDPE | D27: =2065206/1000000 -> 2.065206 | E27: 0 | F27: =SUM(D27:E27) -> 2.065206 | G27: GREET 2024
A28: Updated | B28: Embodied Emissions -- Concrete (Ready-mix concrete US nat'l average ton delivered) | C28: MTCO2e/T Concrete | D28: =86893/1000000 -> 0.086893 | E28: 0 | F28: =SUM(D28:E28) -> 0.086893 | G28: GREET 2024
A29: Updated | B29: Embodied Emissions -- Liquid Caustic Soda (50% NaOH) | C29: MTCO2e/T LCS | D29: ='2025 LCS Embodied Emissions'!B1/1000000 -> 0.89272 | E29: 0.0012002604 | F29: =D29*(1+E29) -> 0.8937915 | G29: GREET 2024
A30: Updated | B30: Embodied Emissions -- NAICS Supply Chain Emissions Factors: Other Industrial Machinery Manufacturing | C30: kg CO2e/2022 USD, purchaser price | D30: 0.185 | E30: 0 | F30: =SUM(D30:E30) -> 0.185 | G30: NAICS Supply Chain Emissions Factors
A31: Updated | B31: Embodied Emissions -- NAICS Supply Chain Emissions Factors: Industrial Building Construction | C31: kg CO2e/2022 USD, purchaser price | D31: 0.239 | E31: 0 | F31: =SUM(D31:E31) -> 0.239 | G31: NAICS Supply Chain Emissions Factors
A32: Updated | B32: Embodied Emissions -- NAICS Supply Chain Emissions Factors: All Other Specialty Trade Contractors | C32: kgCO2e/2022 USD, purchaser price | D32: 0.221 | E32: 0 | F32: =SUM(D32:E32) -> 0.221 | G32: NAICS Supply Chain Emissions Factors
A33: Updated | B33: Embodied Emissions -- NAICS Supply Chain Emissions Factors: Motor and Generator Manufacturing | C33: kgCO2e/2022 USD, purchaser price | D33: 0.152 | E33: 0 | F33: =SUM(D33:E33) -> 0.152 | G33: NAICS Supply Chain Emissions Factors
A34: Updated | B34: Embodied Emissions -- NAICS Supply Chain Emissions Factors: Construction Machinery Manufacturing | C34: kgCO2e/2022 USD, purchaser price | D34: 0.228 | E34: 0 | F34: =SUM(D34:E34) -> 0.228 | G34: NAICS Supply Chain Emissions Factors
A35: Updated | B35: Embodied Emissions -- NAICS Supply Chain Emissions Factors: Railroad Rolling Stock Manufacturing | C35: kgCO2e/2022 USD, purchaser price | D35: 0.444 | E35: 0 | F35: =SUM(D35:E35) -> 0.444 | G35: NAICS Supply Chain Emissions Factors
A36: Updated | B36: Embodied Emissions -- NAICS Supply Chain Emissions Factors: Industrial and Commercial Fan and Blower and Air Purification Equipment Manufacturing | C36: kgCO2e/2022 USD, purchaser price | D36: 0.21 | E36: 0 | F36: =SUM(D36:E36) -> 0.21 | G36: NAICS Supply Chain Emissions Factors
A37: Updated | B37: Embodied Emissions -- NAICS Supply Chain Emissions Factors: Air-Conditioning and Warm Air Heating Equipment and Commercial and Industrial Refrigeration Equipment Manufacturing | C37: kgCO2e/2022 USD, purchaser price | D37: 0.184 | E37: 0 | F37: =SUM(D37:E37) -> 0.184 | G37: NAICS Supply Chain Emissions Factors
A38: Updated | B38: Bio-Oil Disposal, Incineration | C38: MTCO2e/kg Material | D38: =0.0377/1000 -> 3.77e-05 | E38: Bespoke analysis using Climate change openLCA LCIA Methods 2.4.3/EF 3.1 Method (adapted)
A39: Updated | B39: Bio-Oil Disposal, Landfilling [IBC Totes] | C39: MTCO2e/kg Material | D39: =0.0121/1000 -> 1.21e-05 | E39: Bespoke analysis using Climate change openLCA LCIA Methods 2.4.3/EF 3.1 Method (adapted)
A40: Updated | B40: Bio-Oil Disposal, Landfilling [Open Dump] | C40: MTCO2e/kg Material | D40: =0.603/1000 -> 0.000603 | E40: Bespoke analysis using Climate change openLCA LCIA Methods 2.4.3/EF 3.1 Method (adapted)
A41: Updated | B41: Bio-Oil Contaminated Gravel, Landfilling [Open Dump] | C41: MTCO2e/kg Material | D41: =0.259/1000 -> 0.000259 | E41: Bespoke analysis using Climate change openLCA LCIA Methods 2.4.3/EF 3.1 Method (adapted)
A42: Updated | B42: Embodied Emissions -- NAICS Supply Chain Emissions Factors: Prefabricating Wood Building Manufacturing | C42: kgCO2e/2022 USD, purchaser price | D42: 0.164 | E42: 0 | F42: =SUM(D42:E42) -> 0.164 | G42: NAICS Supply Chain Emissions Factors

Sheet Truck and Trailer EE 2025
A1: GREET 2024 Values | B1: g CO2e | E1: Km per Mile | F1: 1.60934
A2: MHDV Summary of Energy Consumption and Emissions Related to Part Manufacturing and Vehicle Assembly (VMA): per-vehicle lifetime | B2: 7294804
A3: MHDV Assembly, Disposal and Recyclining (incl. paint production) | B3: 1711534
A4: MHDV Trailer Summary of Energy Consumption and Emissions Related to Part Manufacturing and Trailer Assembly (VMA): per-trailer lifetime | B4: 14988739
A5: MHDV Trailer Assembly, Disposal and Recyclining (incl. paint production) | B5: 1321367
A7: Total Lifetime Embodied Emissions Truck and Trailer | B7: =SUM(B2:B6) -> 25316444
A8: EPA Vehicle Useful Life Heavy Duty Diesel Engine | B8: 453000
A10: Total Embodied Emissions (g CO2e)/Mile | B10: =B7/B8 -> 55.88619
A11: Total Embodied Emissions (kg CO2e)/Mile | B11: =B10/1000 -> 0.05588619
A12: Total Embodied Emissions (MT CO2e)/Mile | B12: =B11/1000 -> 5.588619e-05
A14: 2022 Deadhead Average % of Overall Mileage --Tanker Truck | B14: 0.41
A15: Tanker Truck Total Embodied Emissions (MTCO2e)/Mile w/ Deadhead | B15: =B12*(1+B14) -> 7.8799528e-05
A16: Converted to MTCO2e/km | B16: =B15/F1 -> 4.8963878e-05
A17: Converted to kgCO2e/km | B17: =B16*1000 -> 0.048963878
A19: 2022 Deadhead Average % of Overall Mileage -- Non-Tanker Truck | B19: 0.154
A20: Non- Tanker Truck Total Embodied Emissions (MTCO2e)/Mile w/ Deadhead | B20: =B12*(1+B19) -> 6.4492663e-05
A21: Converted to MTCO2e/km | B21: =B20/F1 -> 4.0073983e-05
A22: Converted to kgCO2e/km | B22: =B21*1000 -> 0.040073983

Sheet Truck and Trailer EE 2026
A1: GREET 2025 Values | B1: g CO2e | E1: Km per Mile | F1: 1.60934
A2: MHDV Summary of Energy Consumption and Emissions Related to Part Manufacturing and Vehicle Assembly (VMA): per-vehicle lifetime | B2: 69523675
A3: MHDV Assembly, Disposal and Recycling (incl. paint production) | B3: 1670181
A4: MHDV Trailer Summary of Energy Consumption and Emissions Related to Part Manufacturing and Trailer Assembly (VMA): per-trailer lifetime | B4: 34903879
A5: MHDV Trailer Assembly, Disposal and Recycling (incl. paint production) | B5: 1283616
A7: Total Lifetime Embodied Emissions Truck and Trailer | B7: =SUM(B2:B6) -> 107381351
A8: EPA Vehicle Useful Life Heavy Duty Diesel Engine | B8: 650000 | C8: Source: EPA
A10: Total Embodied Emissions (g CO2e)/Mile | B10: =B7/B8 -> 165.20208
A11: Total Embodied Emissions (kg CO2e)/Mile | B11: =B10/1000 -> 0.16520208
A12: Total Embodied Emissions (MT CO2e)/Mile | B12: =B11/1000 -> 0.00016520208
A14: 2022 Deadhead Average % of Overall Mileage --Tanker Truck | B14: 0.438 | C14: Source: ATRI
A15: Tanker Truck Total Embodied Emissions (MTCO2e)/Mile w/ Deadhead | B15: =B12*(1+B14) -> 0.00023756059
A16: Converted to MTCO2e/km | B16: =B15/F1 -> 0.00014761367
A17: Converted to MTCO2e/mi | B17: =B16*F1 -> 0.00023756059
A18: Converted to kgCO2e/km | B18: =B16*1000 -> 0.14761367
A20: 2022 Deadhead Average % of Overall Mileage -- Non-Tanker Truck | B20: 0.167 | C20: Source: ATRI
A21: Non- Tanker Truck Total Embodied Emissions (MTCO2e)/Mile w/ Deadhead | B21: =B12*(1+B20) -> 0.00019279083
A22: Converted to MTCO2e/km | B22: =B21/F1 -> 0.00011979496
A23: Converted to MTCO2e/mi | B23: =B22*F1 -> 0.00019279083
A24: Converted to kgCO2e/km | B24: =B22*1000 -> 0.11979496

Sheet 2025 KS Electricity EFs
A1: Residual Mix Emissions | I1: Constants
F2: Emissions Factor Source: Green-e 2024 Residual Grid Mix | I2: kWh per MWh | J2: 1000
C3: Total lb CO2e/MWh for eGrid Subregion | D3: 1016.89 | I3: kWh per mmBTU | J3: 293.07107
C4: Convert to lb CO2e/kWh for eGrid Subregion | D4: =D3/1000 -> 1.01689 | I4: Lbs per MT | J4: 2204.62
C5: Convert to MT CO2e/kWh for eGrid Subregion | D5: =D4/2204.62 -> 0.00046125409 | I5: Grams per MT | J5: 1000000
A7: Grid Infrastructure
A8: Generation Method | B8: % of Infrastructure | C8: G CO2e/mmBTU Electricity Available at Plant Gate | D8: G CO2e/ Average mmBTU for eGrid Subregion | F8: Infrastructure Mix Source: EPA eGrid
A9: Coal | B9: 0.316 | C9: 227 | D9: =C9*B9 -> 71.732 | F9: Infrastructure Emissions Source: GREET 2024
A10: Wind | B10: 0.397 | C10: 2825 | D10: =C10*B10 -> 1121.525
A11: Nuclear | B11: 0.14 | C11: 79 | D11: =C11*B11 -> 11.06
A12: Gas | B12: 0.14 | C12: 120 | D12: =C12*B12 -> 16.8
A13: Oil | B13: 0.002 | C13: 120 | D13: =C13*B13 -> 0.24
A14: Hydro | B14: 0.002 | C14: 2056 | D14: =C14*B14 -> 4.112
A15: Biomass | B15: 0.001 | C15: 231 | D15: =C15*B15 -> 0.231
A16: Solar | B16: 0.002 | C16: 10346 | D16: =C16*B16 -> 20.692
C18: Blended Average g CO2e/mmBTU for eGrid Subregion | D18: =SUM(D9:D16) -> 1246.392
C19: Convert to gCO2e/kWh for eGrid Subregion | D19: =D18/293.07107 -> 4.252866
C20: Convert to MTCO2e/kWh for eGrid Subregion | D20: =D19/1000000 -> 4.252866e-06
C22: Total Emissions for eGrid Subregion (MTCO2e/kWh) | D22: =SUM(D5,D20) -> 0.00046550696
C23: Convert to KgCO2e/kWh | D23: =D22*1000 -> 0.46550696
A25: EF elect, r | B25: =D23 -> 0.46550696 | C25: kg CO2e/kwh | D25: =B28*B30 -> 1.0044151 | E25: RECs Calc | H25: Constants
A26: mp | B26: =1-I28 -> 0.958 | D26: =B27*B25 -> 46.550696 | E26: No RECs | H26: MJ per MMBTU | I26: 1055.0559 | J26: https://www.inchcalculator.com/convert/million-btu-to-megajoule/
A27: kwhl | B27: 100 | H27: MJ per kWh | I27: 3.6 | J27: https://www.inchcalculator.com/convert/kilowatt-hour-to-megajoule/
A28: Gp | B28: 100 | D28: % Reduction | E28: =(D26-D25)/D26 -> 0.9784232 | H28: Grid Region Derating Factor | I28: 0.042 | J28: https://www.epa.gov/system/files/documents/2025-01/egrid2023_summary_tables_rev1.pdf
A29: fp -- No Derating | B29: =B37 -> 0.0096393001 | C29: kg CO2e/kwh
A30: fp -- Derating | B30: =B29*(1+(1-B26)) -> 0.010044151 | C30: kg CO2e/kwh
A33: fp -- Wind
A34: mmBTU/kWh | B34: =I27/I26 -> 0.0034121416
A35: g CO2e/mmBTU | B35: =C10 -> 2825
A36: gCO2e/kWh | B36: =B35*B34 -> 9.6393001
A37: kgCO2e/kWh | B37: =B36/1000 -> 0.0096393001

Sheet 2025 CO Electricity EFs
A1: Combustion for Energy Production (Green-E 2024 Residual Mix) | F1: Source | H1: Constants
F2: Green-E 2024 | H2: kWh per MWh | I2: 1000
C3: Total lb CO2e/MWh for eGrid Subregion | D3: 1144.77 | H3: kWh per mmBTU | I3: 293.07107
C4: Convert to lb CO2e/kWh for eGrid Subregion | D4: =D3/I2 -> 1.14477 | H4: Lbs per MT | I4: 2204.62
C5: Convert to MT CO2e/kWh for eGrid Subregion | D5: =D4/I4 -> 0.00051925955 | H5: Grams per MT | I5: 1000000
D6: =D5*1000 -> 0.51925955
A10: Grid Infrastructure (EPA eGrid 2023, GREET 2023) | F10: Source
A11: Generation Method | B11: % of Infrastructure | C11: G CO2e/mmBTU Electricity Available at Plant Gate | D11: G CO2e/ Average mmBTU for eGrid Subregion | F11: Infrastructure Mix Source: EPA eGrid
A12: Coal | B12: 0.317 | C12: 227 | D12: =C12*B12 -> 71.959 | F12: Infrastructure Emissions Source: GREET 2024
A13: Wind | B13: 0.258 | C13: 2825 | D13: =C13*B13 -> 728.85
A14: Nuclear | B14: 0 | C14: 79 | D14: =C14*B14 -> 0
A15: Gas | B15: 0.263 | C15: 120 | D15: =C15*B15 -> 31.56
A16: Oil | B16: 0.001 | C16: 120 | D16: =C16*B16 -> 0.12
A17: Hydro | B17: 0.105 | C17: 2056 | D17: =C17*B17 -> 215.88
A18: Biomass | B18: 0.002 | C18: 231 | D18: =C18*B18 -> 0.462
A19: Solar | B19: 0.054 | C19: 10346 | D19: =C19*B19 -> 558.684
C21: Blended Average g CO2e/mmBTU for eGrid Subregion | D21: =SUM(D12:D19) -> 1607.515
C22: Convert to gCO2e/kWh for eGrid Subregion | D22: =D21/I3 -> 5.4850689
C23: Convert to MTCO2e/kWh for eGrid Subregion | D23: =D22/I5 -> 5.4850689e-06
C25: Total Emissions for eGrid Subregion (MTCO2e/kWh) | D25: =SUM(D5,D23) -> 0.00052474462
C26: Convert to KgCO2e/kWh | D26: =D25*1000 -> 0.52474462
A28: EF elect, r | B28: =D26 -> 0.52474462 | C28: kg CO2e/kwh | D28: =B31*B33 -> 3.67494 | E28: RECs Calc | H28: Constants
A29: mp | B29: =1-I31 -> 0.959 | D29: =B30*B28 -> 52.474462 | E29: No RECs | H29: MJ per MMBTU | I29: 1055.0559 | J29: https://www.inchcalculator.com/convert/million-btu-to-megajoule/
A30: kwhl | B30: 100 | H30: MJ per kWh | I30: 3.6 | J30: https://www.inchcalculator.com/convert/kilowatt-hour-to-megajoule/
A31: Gp | B31: 100 | D31: % Reduction | E31: =(D29-D28)/D29 -> 0.92996708 | H31: Grid Region Derating Factor | I31: 0.041 | J31: https://www.epa.gov/egrid/summary-data
A32: fp -- No Derating | B32: =B40 -> 0.035302017 | C32: kg CO2e/kwh
A33: fp -- Derating | B33: =B32*(1+(1-B29)) -> 0.0367494 | C33: kg CO2e/kwh
A36: fp -- Solar
A37: mmBTU/kWh | B37: =I30/I29 -> 0.0034121416
A38: g CO2e/mmBTU | B38: =C19 -> 10346
A39: gCO2e/kWh | B39: =B38*B37 -> 35.302017
A40: kgCO2e/kWh | B40: =B39/1000 -> 0.035302017

Sheet 2026 SPSO Electricity EFs
A1: Combustion for Energy Production (Green-E 2024 Residual Mix) | F1: Source | H1: Constants
F2: Green-E 2024 | H2: kWh per MWh | I2: 1000
C3: Total lb CO2e/MWh for eGrid Subregion | D3: 1020.77 | H3: kWh per mmBTU | I3: 293.07107
C4: Convert to lb CO2e/kWh for eGrid Subregion | D4: =D3/I2 -> 1.02077 | H4: Lbs per MT | I4: 2204.62
C5: Convert to MT CO2e/kWh for eGrid Subregion | D5: =D4/I4 -> 0.00046301403 | H5: Grams per MT | I5: 1000000
D6: =D5*1000 -> 0.46301403
A10: Grid Infrastructure (EPA eGrid 2023, GREET 2023) | F10: Source
A11: Generation Method | B11: % of Infrastructure | C11: G CO2e/mmBTU Electricity Available at Plant Gate | D11: G CO2e/ Average mmBTU for eGrid Subregion | F11: Infrastructure Mix Source: EPA eGrid
A12: Coal | B12: 0.162 | C12: ='ElecInfra Summary'!$J$12 -> 230.18917 | D12: =C12*B12 -> 37.290645 | F12: Infrastructure Emissions Source: GREET 2025
A13: Wind | B13: 0.325 | C13: ='ElecInfra Summary'!$J$18 -> 2820.2316 | D13: =C13*B13 -> 916.57526
A14: Nuclear | B14: 0 | C14: ='ElecInfra Summary'!$J$16 -> 75.669918 | D14: =C14*B14 -> 0
A15: Gas | B15: 0.461 | C15: ='ElecInfra Summary'!$J$13 -> 230.18917 | D15: =C15*B15 -> 106.11721
A16: Oil | B16: 0.005 | C16: ='ElecInfra Summary'!$J$14 -> 230.18917 | D16: =C16*B16 -> 1.1509458
A17: Hydro | B17: 0.025 | C17: ='ElecInfra Summary'!$J$17 -> 2001.0594 | D17: =C17*B17 -> 50.026484
A18: Biomass | B18: 0.012 | C18: ='ElecInfra Summary'!$J$15 -> 234.55938 | D18: =C18*B18 -> 2.8147125
A19: Solar | B19: 0.01 | C19: ='ElecInfra Summary'!$J$19 -> 10305.736 | D19: =C19*B19 -> 103.05736
B21: =SUM(B12:B19) -> 1 | C21: Blended Average g CO2e/mmBTU for eGrid Subregion | D21: =SUM(D12:D19) -> 1217.0326
C22: Convert to gCO2e/kWh for eGrid Subregion | D22: =D21/I3 -> 4.1526876
C23: Convert to MTCO2e/kWh for eGrid Subregion | D23: =D22/I5 -> 4.1526876e-06
C25: Total Emissions for eGrid Subregion (MTCO2e/kWh) | D25: =SUM(D5,D23) -> 0.00046716672
C26: Convert to KgCO2e/kWh | D26: =D25*1000 -> 0.46716672
A28: EF elect, r | B28: =D26 -> 0.46716672 | C28: kg CO2e/kwh | D28: =B31*B33 -> 3.6641546 | E28: RECs Calc | H28: Constants
A29: mp | B29: =1-I31 -> 0.958 | D29: =B30*B28 -> 46.716672 | E29: No RECs | H29: MJ per MMBTU | I29: 1055.0559 | J29: https://www.inchcalculator.com/convert/million-btu-to-megajoule/
A30: kwhl | B30: 100 | H30: MJ per kWh | I30: 3.6 | J30: https://www.inchcalculator.com/convert/kilowatt-hour-to-megajoule/
A31: Gp | B31: 100 | D31: % Reduction | E31: =(D29-D28)/D29 -> 0.92156645 | H31: Grid Region Derating Factor | I31: 0.042 | J31: https://www.epa.gov/egrid/detailed-data
A32: fp -- No Derating | B32: =B40 -> 0.035164631 | C32: kg CO2e/kwh
A33: fp -- Derating | B33: =B32*(1+(1-B29)) -> 0.036641546 | C33: kg CO2e/kwh
A36: fp -- Solar
A37: mmBTU/kWh | B37: =I30/I29 -> 0.0034121416
A38: g CO2e/mmBTU | B38: =C19 -> 10305.736
A39: gCO2e/kWh | B39: =B38*B37 -> 35.164631
A40: kgCO2e/kWh | B40: =B39/1000 -> 0.035164631

Sheet 2026 RMPA Electricity EFs
A1: Combustion for Energy Production (Green-E 2024 Residual Mix) | F1: Source | H1: Constants
F2: Emissions Factor Source: Green-e 2025 Residual Grid Mix | H2: kWh per MWh | I2: 1000
C3: Total lb CO2e/MWh for eGrid Subregion | D3: 1065.86 | H3: kWh per mmBTU | I3: 293.07107
C4: Convert to lb CO2e/kWh for eGrid Subregion | D4: =D3/I2 -> 1.06586 | H4: Lbs per MT | I4: 2204.62
C5: Convert to MT CO2e/kWh for eGrid Subregion | D5: =D4/I4 -> 0.00048346654 | H5: Grams per MT | I5: 1000000
D6: =D5*1000 -> 0.48346654
A10: Grid Infrastructure (EPA eGrid 2023, GREET 2023) | F10: Source
A11: Generation Method | B11: % of Infrastructure | C11: G CO2e/mmBTU Electricity Available at Plant Gate | D11: G CO2e/ Average mmBTU for eGrid Subregion | F11: Infrastructure Mix Source: EPA eGrid
A12: Coal | B12: 0.317 | C12: ='ElecInfra Summary'!$J$12 -> 230.18917 | D12: =C12*B12 -> 72.969966 | F12: Infrastructure Emissions Source: GREET 2025
A13: Wind | B13: 0.258 | C13: ='ElecInfra Summary'!$J$18 -> 2820.2316 | D13: =C13*B13 -> 727.61974
A14: Nuclear | B14: 0 | C14: ='ElecInfra Summary'!$J$16 -> 75.669918 | D14: =C14*B14 -> 0
A15: Gas | B15: 0.264 | C15: ='ElecInfra Summary'!$J$13 -> 230.18917 | D15: =C15*B15 -> 60.76994
A16: Oil | B16: 0.001 | C16: ='ElecInfra Summary'!$J$14 -> 230.18917 | D16: =C16*B16 -> 0.23018917
A17: Hydro | B17: 0.105 | C17: ='ElecInfra Summary'!$J$17 -> 2001.0594 | D17: =C17*B17 -> 210.11123
A18: Biomass | B18: 0.002 | C18: ='ElecInfra Summary'!$J$15 -> 234.55938 | D18: =C18*B18 -> 0.46911876
A19: Solar | B19: 0.054 | C19: ='ElecInfra Summary'!$J$19 -> 10305.736 | D19: =C19*B19 -> 556.50975
C21: Blended Average g CO2e/mmBTU for eGrid Subregion | D21: =SUM(D12:D19) -> 1628.6799
C22: Convert to gCO2e/kWh for eGrid Subregion | D22: =D21/I3 -> 5.5572866
C23: Convert to MTCO2e/kWh for eGrid Subregion | D23: =D22/I5 -> 5.5572866e-06
C25: Total Emissions for eGrid Subregion (MTCO2e/kWh) | D25: =SUM(D5,D23) -> 0.00048902383
C26: Convert to KgCO2e/kWh | D26: =D25*1000 -> 0.48902383
A28: EF elect, r | B28: =D26 -> 0.48902383 | C28: kg CO2e/kwh | D28: =B31*B33 -> 3.6641546 | E28: RECs Calc | H28: Constants
A29: mp | B29: =1-I31 -> 0.958 | D29: =B30*B28 -> 48.902383 | E29: No RECs | H29: MJ per MMBTU | I29: 1055.0559 | J29: https://www.inchcalculator.com/convert/million-btu-to-megajoule/
A30: kwhl | B30: 100 | H30: MJ per kWh | I30: 3.6 | J30: https://www.inchcalculator.com/convert/kilowatt-hour-to-megajoule/
A31: Gp | B31: 100 | D31: % Reduction | E31: =(D29-D28)/D29 -> 0.92507206 | H31: Grid Region Derating Factor | I31: 0.042 | J31: https://www.epa.gov/egrid/detailed-data
A32: fp -- No Derating | B32: =B40 -> 0.035164631 | C32: kg CO2e/kwh
A33: fp -- Derating | B33: =B32*(1+(1-B29)) -> 0.036641546 | C33: kg CO2e/kwh
A36: fp -- Solar
A37: mmBTU/kWh | B37: =I30/I29 -> 0.0034121416
A38: g CO2e/mmBTU | B38: =C19 -> 10305.736
A39: gCO2e/kWh | B39: =B38*B37 -> 35.164631
A40: kgCO2e/kWh | B40: =B39/1000 -> 0.035164631

Sheet 2025 LA Electricity EFs
A1: Combustion for Energy Production (Green-E 2024 Residual Mix) | F1: Source | H1: Constants
F2: Green-E 2024 | H2: kWh per MWh | I2: 1000
C3: Total lb CO2e/MWh for eGrid Subregion | D3: 804.43161 | H3: kWh per mmBTU | I3: 293.07107
C4: Convert to lb CO2e/kWh for eGrid Subregion | D4: =D3/I2 -> 0.80443161 | H4: Lbs per MT | I4: 2204.62
C5: Convert to MT CO2e/kWh for eGrid Subregion | D5: =D4/I4 -> 0.00036488448 | H5: Grams per MT | I5: 1000000
D6: =D5*1000 -> 0.36488448
A10: Grid Infrastructure (EPA eGrid 2023, GREET 2023) | F10: Source
A11: Generation Method | B11: % of Infrastructure | C11: G CO2e/mmBTU Electricity Available at Plant Gate | D11: G CO2e/ Average mmBTU for eGrid Subregion | F11: Infrastructure Mix Source: EPA eGrid
A12: Coal | B12: =8.2%+1.2%+0.1% -> 0.095 | C12: 227 | D12: =C12*B12 -> 21.565 | F12: Infrastructure Emissions Source: GREET 2024
A13: Wind | B13: 0 | C13: 2825 | D13: =C13*B13 -> 0
A14: Nuclear | B14: 0.221 | C14: 79 | D14: =C14*B14 -> 17.459
A15: Gas | B15: 0.652 | C15: 120 | D15: =C15*B15 -> 78.24
A16: Oil | B16: 0.001 | C16: 120 | D16: =C16*B16 -> 0.12
A17: Hydro | B17: 0.013 | C17: 2056 | D17: =C17*B17 -> 26.728
A18: Biomass | B18: 0.01 | C18: 231 | D18: =C18*B18 -> 2.31
A19: Solar | B19: 0.007 | C19: 10346 | D19: =C19*B19 -> 72.422
C21: Blended Average g CO2e/mmBTU for eGrid Subregion | D21: =SUM(D12:D19) -> 218.844
C22: Convert to gCO2e/kWh for eGrid Subregion | D22: =D21/I3 -> 0.74672672
C23: Convert to MTCO2e/kWh for eGrid Subregion | D23: =D22/I5 -> 7.4672672e-07
C25: Total Emissions for eGrid Subregion (MTCO2e/kWh) | D25: =SUM(D5,D23) -> 0.0003656312
C26: Convert to KgCO2e/kWh | D26: =D25*1000 -> 0.3656312
A28: EF elect, r | B28: =D26 -> 0.3656312 | C28: kg CO2e/kwh | D28: =B31*B33 -> 3.6784702 | E28: RECs Calc | H28: Constants
A29: mp | B29: =1-I31 -> 0.958 | D29: =B30*B28 -> 36.56312 | E29: No RECs | H29: MJ per MMBTU | I29: 1055.0559 | J29: https://www.inchcalculator.com/convert/million-btu-to-megajoule/
A30: kwhl | B30: 100 | H30: MJ per kWh | I30: 3.6 | J30: https://www.inchcalculator.com/convert/kilowatt-hour-to-megajoule/
A31: Gp | B31: 100 | D31: % Reduction | E31: =(D29-D28)/D29 -> 0.89939397 | H31: Grid Region Derating Factor | I31: 0.042 | J31: https://www.epa.gov/system/files/documents/2025-01/egrid2023_summary_tables_rev1.pdf
A32: fp -- No Derating | B32: =B40 -> 0.035302017 | C32: kg CO2e/kwh
A33: fp -- Derating | B33: =B32*(1+(1-B29)) -> 0.036784702 | C33: kg CO2e/kwh
A36: fp -- Solar
A37: mmBTU/kWh | B37: =I30/I29 -> 0.0034121416
A38: g CO2e/mmBTU | B38: =C19 -> 10346
A39: gCO2e/kWh | B39: =B38*B37 -> 35.302017
A40: kgCO2e/kWh | B40: =B39/1000 -> 0.035302017

Sheet 2026 SPNO Electricity EFs
A1: Residual Mix Emissions | I1: Constants
F2: Emissions Factor Source: Green-e 2025 Residual Grid Mix | I2: kWh per MWh | J2: 1000
C3: Total lb CO2e/MWh for eGrid Subregion | D3: 1016.82 | I3: kWh per mmBTU | J3: 293.07107
C4: Convert to lb CO2e/kWh for eGrid Subregion | D4: =D3/1000 -> 1.01682 | I4: Lbs per MT | J4: 2204.62
C5: Convert to MT CO2e/kWh for eGrid Subregion | D5: =D4/2204.62 -> 0.00046122234 | I5: Grams per MT | J5: 1000000
A7: Grid Infrastructure
A8: Generation Method | B8: % of Infrastructure | C8: G CO2e/mmBTU Electricity Available at Plant Gate | D8: G CO2e/ Average mmBTU for eGrid Subregion | F8: Infrastructure Mix Source: EPA eGrid
A9: Coal | B9: 0.316 | C9: ='ElecInfra Summary'!$J$12 -> 230.18917 | D9: =C9*B9 -> 72.739777 | F9: Infrastructure Emissions Source: GREET 2025
A10: Wind | B10: 0.397 | C10: ='ElecInfra Summary'!$J$18 -> 2820.2316 | D10: =C10*B10 -> 1119.6319
A11: Nuclear | B11: 0.14 | C11: ='ElecInfra Summary'!$J$16 -> 75.669918 | D11: =C11*B11 -> 10.593788
A12: Gas | B12: 0.14 | C12: ='ElecInfra Summary'!$J$13 -> 230.18917 | D12: =C12*B12 -> 32.226483
A13: Oil | B13: 0.002 | C13: ='ElecInfra Summary'!$J$14 -> 230.18917 | D13: =C13*B13 -> 0.46037833
A14: Hydro | B14: 0.001 | C14: ='ElecInfra Summary'!$J$17 -> 2001.0594 | D14: =C14*B14 -> 2.0010594
A15: Biomass | B15: 0.001 | C15: ='ElecInfra Summary'!$J$15 -> 234.55938 | D15: =C15*B15 -> 0.23455938
A16: Solar | B16: 0.003 | C16: ='ElecInfra Summary'!$J$19 -> 10305.736 | D16: =C16*B16 -> 30.917208
C18: Blended Average g CO2e/mmBTU for eGrid Subregion | D18: =SUM(D9:D16) -> 1268.8052
C19: Convert to gCO2e/kWh for eGrid Subregion | D19: =D18/293.07107 -> 4.329343
C20: Convert to MTCO2e/kWh for eGrid Subregion | D20: =D19/1000000 -> 4.329343e-06
C22: Total Emissions for eGrid Subregion (MTCO2e/kWh) | D22: =SUM(D5,D20) -> 0.00046555169
C23: Convert to KgCO2e/kWh | D23: =D22*1000 -> 0.46555169
A25: EF elect, r | B25: =D23 -> 0.46555169 | C25: kg CO2e/kwh | D25: =B28*B30 -> 1.0027197 | E25: RECs Calc | H25: Constants
A26: mp | B26: =1-I28 -> 0.958 | D26: =B27*B25 -> 46.555169 | E26: No RECs | H26: MJ per MMBTU | I26: 1055.0559 | J26: https://www.inchcalculator.com/convert/million-btu-to-megajoule/
A27: kwhl | B27: 100 | H27: MJ per kWh | I27: 3.6 | J27: https://www.inchcalculator.com/convert/kilowatt-hour-to-megajoule/
A28: Gp | B28: 100 | D28: % Reduction | E28: =(D26-D25)/D26 -> 0.97846169 | H28: Grid Region Derating Factor | I28: 0.042 | J28: https://www.epa.gov/egrid/detailed-data
A29: fp -- No Derating | B29: =B37 -> 0.0096230295 | C29: kg CO2e/kwh
A30: fp -- Derating | B30: =B29*(1+(1-B26)) -> 0.010027197 | C30: kg CO2e/kwh
A33: fp -- Wind
A34: mmBTU/kWh | B34: =I27/I26 -> 0.0034121416
A35: g CO2e/mmBTU | B35: =C10 -> 2820.2316
A36: gCO2e/kWh | B36: =B35*B34 -> 9.6230295
A37: kgCO2e/kWh | B37: =B36/1000 -> 0.0096230295

Sheet ElecInfra Summary
A1: Power Plant Infrastructure Embodied GHG Emission Factors — g CO₂e per mmBtu at Plant Gate
A2: Charm Industrial | Source: GREET1 2025 (R_D_GREET1_2025.xlsm), Electric sheet, Section 7 (rows 174–176)
A4: SECTION 1 — AR6 GLOBAL WARMING POTENTIALS (100-yr)
A5: Gas | B5: GWP (AR6, 100-yr) | C5: Units | D5: GREET1 2025 Source | E5: Note
A6: CO₂ | B6: 1 | C6: g CO₂e / g CO₂ | D6: Fuel_Specs B150 | E6: By definition
A7: CH₄ | B7: 29.8 | C7: g CO₂e / g CH₄ | D7: Fuel_Specs B151 | E7: IPCC AR6, 100-yr GWP including climate-carbon feedbacks
A8: N₂O | B8: 273 | C8: g CO₂e / g N₂O | D8: Fuel_Specs B152 | E8: IPCC AR6, 100-yr GWP including climate-carbon feedbacks
A10: SECTION 2 — INFRASTRUCTURE EMBODIED GHG BY PLANT TYPE (g CO₂e / mmBtu at Plant Gate)
A11: Plant Type | B11: CO₂ (g/mmBtu) | C11: Source cell | D11: CH₄ (g/mmBtu) | E11: Source cell | F11: N₂O (g/mmBtu) | G11: Source cell | H11: CH₄ as CO₂e (g/mmBtu) | I11: N₂O as CO₂e (g/mmBtu) | J11: Total GHG (g CO₂e/mmBtu) | K11: Notes
A12: Coal | B12: 219.34394 | C12: P176 | D12: 0.3411448 | E12: P174 | F12: 0.0024875901 | G12: P175 | H12: =D12*$B$7 -> 10.166115 | I12: =F12*$B$8 -> 0.6791121 | J12: =B12+H12+I12 -> 230.18917 | K12: GREET1 Electric sheet, Section 7
A13: Natural Gas | B13: 219.34394 | C13: H176 | D13: 0.3411448 | E13: H174 | F13: 0.0024875901 | G13: H175 | H13: =D13*$B$7 -> 10.166115 | I13: =F13*$B$8 -> 0.6791121 | J13: =B13+H13+I13 -> 230.18917 | K13: GREET1 Electric sheet, Section 7
A14: Oil | B14: 219.34394 | C14: B176 | D14: 0.3411448 | E14: B174 | F14: 0.0024875901 | G14: B175 | H14: =D14*$B$7 -> 10.166115 | I14: =F14*$B$8 -> 0.6791121 | J14: =B14+H14+I14 -> 230.18917 | K14: GREET1 Electric sheet, Section 7
A15: Biomass | B15: 223.43104 | C15: T176 | D15: 0.35134437 | E15: T174 | F15: 0.0024112748 | G15: T175 | H15: =D15*$B$7 -> 10.470062 | I15: =F15*$B$8 -> 0.65827801 | J15: =B15+H15+I15 -> 234.55938 | K15: GREET1 Electric sheet, Section 7
A16: Nuclear | B16: 70.950672 | C16: X176 | D16: 0.14587753 | E16: X174 | F16: 0.0013629854 | G16: X175 | H16: =D16*$B$7 -> 4.3471503 | I16: =F16*$B$8 -> 0.37209502 | J16: =B16+H16+I16 -> 75.669918 | K16: GREET1 Electric sheet, Section 7
A17: Hydro | B17: 1819.4547 | C17: AB176 | D17: 5.7751896 | E17: AB174 | F17: 0.03481325 | G17: AB175 | H17: =D17*$B$7 -> 172.10065 | I17: =F17*$B$8 -> 9.5040172 | J17: =B17+H17+I17 -> 2001.0594 | K17: GREET1 Electric sheet, Section 7
A18: Wind | B18: 2678.8028 | C18: AD176 | D18: 4.247982 | E18: AD174 | F18: 0.05435485 | G18: AD175 | H18: =D18*$B$7 -> 126.58986 | I18: =F18*$B$8 -> 14.838874 | J18: =B18+H18+I18 -> 2820.2316 | K18: GREET1 Electric sheet, Section 7
A19: Solar PV | B19: 9705.3465 | C19: AF176 | D19: 17.205444 | E19: AF174 | F19: 0.32112586 | G19: AF175 | H19: =D19*$B$7 -> 512.72222 | I19: =F19*$B$8 -> 87.667358 | J19: =B19+H19+I19 -> 10305.736 | K19: GREET1 Electric sheet, Section 7
A21: SECTION 3 — METHODOLOGY NOTES
A22: Scope | B22: Infrastructure/embodied emissions only — plant construction, manufacturing, and equipment. Excludes all operating/combustion emissions.
A23: Source section | B23: GREET1 2025, Electric sheet, Section 7: "Energy Use, Water Consumption, and Emissions for Power Plant Infrastructure from GREET2 — per mmBtu of Electricity Available at Power Plant Gate." Infrastructure factors originate from GREET2 calculations.
A24: GWP basis | B24: IPCC Sixth Assessment Report (AR6), 100-year GWP including climate-carbon feedbacks. Values from GREET1 2025 Fuel_Specs sheet: CH₄=29.8 (B151), N₂O=273 (B152).
A25: Unit basis | B25: g CO₂e per mmBtu of electricity at the power plant gate (pre-transmission and distribution losses). T&D losses are not reflected in these figures.
A26: Pattern note | B26: Boiler-type plants (Coal, NG, Oil, Biomass boilers) share identical infrastructure CO₂/CH₄/N₂O values — plant construction emissions in GREET2 depend on configuration type (boiler vs. turbine), not fuel identity.
A27: Vintage caveat | B27: The ElecInfra sheet that previously housed these values in standalone GREET2 releases has been removed in GREET2 2025. Section 7 values in GREET1 2025 carry forward infrastructure factors from an earlier GREET2 vintage. This is a known limitation.
A28: Duplicate Values | B28: Where GREET gives multiple options based on specific infrastructure features we don't/can't know, the highest value was selected to ensure a conservative estimate

Sheet 2025 MRV Sample Shipping
A1: Tests for Each Injection Batch | F1: SGS Geo Info
A2: Testing Type | F2: Address | G2: 151 James Drive West St Rose, LA 70087
A3: Carbon | F3: Distance from El Dorado Site (mi) | G3: 879 | H3: https://drive.google.com/drive/folders/10qP33ema8rcTUsXUzN2qC1qNTEPeZs10
B4: Number of Samples | C4: 1
B5: Sample Size (oz) | C5: 6.64 | F5: Conversions
B6: Destination Lab | C6: SGS | F6: Oz per MT | G6: 35274
A7: Total Acid Number + Density | F7: Km per Mile | G7: 1.60934
B8: Number of Samples | C8: 5
B9: Sample Size (oz) | C9: 1
B10: Destination Lab | C10: SGS
A12: Total Sample Weight to SGS (oz) | B12: =(C4*C5)+(C8*C9) -> 11.64
A13: Total Sample Weight to SGS (MT) | B13: =B12/G6 -> 0.00032998809
A14: CO2e from Transport to SGS (MT) | B14: =B13*G3*'2025'!F8 -> 0.00036776416
A16: Total Sample Emissions per Injection Batch (MTCO2e) | B16: =B14 -> 0.00036776416
A17: Convert to Kg CO2e | B17: =B16*1000 -> 0.36776416

Sheet Copy of 2025 MRV Sample Shippin
A1: Tests for Each Injection Batch | F1: SGS Geo Info
A2: Testing Type | F2: Address | G2: 151 James Drive West St Rose, LA 70087
A3: Carbon | F3: Distance from El Dorado Site (mi) | G3: 879 | H3: https://drive.google.com/drive/folders/10qP33ema8rcTUsXUzN2qC1qNTEPeZs10
B4: Number of Samples | C4: 1
B5: Sample Size (oz) | C5: 6.64 | F5: Conversions
B6: Destination Lab | C6: SGS | F6: Oz per MT | G6: 35274
A7: Total Acid Number + Density | F7: Km per Mile | G7: 1.60934
B8: Number of Samples | C8: 5
B9: Sample Size (oz) | C9: 1
B10: Destination Lab | C10: SGS
A12: Total Sample Weight to SGS (oz) | B12: =(C4*C5)+(C8*C9) -> 11.64
A13: Total Sample Weight to SGS (MT) | B13: =B12/G6 -> 0.00032998809
A14: CO2e from Transport to SGS (MT) | B14: =B13*G3*'2025'!F8 -> 0.00036776416
A16: Total Sample Emissions per Injection Batch (MTCO2e) | B16: =B14 -> 0.00036776416
A17: Convert to Kg CO2e | B17: =B16*1000 -> 0.36776416

Sheet 2025 Railcar Embodied Emissions
C1: Source
A2: DOT 111 Average Purchase Cost (DOT, 2016) | B2: 140000 | C2: US DOT
A3: Convert to 2022 USD | B3: =B2*1.19 -> 166600 | C3: BLS CPI Inflation Calculator
A4: Railroad Rolling Stock Manufacturing (kgCO2e/2022 USD) | B4: 0.444 | C4: NAICS Supply Chain Emission Factors v1.3
A5: Embodied Emissions from Manufacture (MTCO2e) | B5: =(B4*B3)/1000 -> 73.9704
A6: Expected Useful Life in Years (Cambridge Systematics) | B6: 35 | C6: Cambridge Systematics
A7: Typical Annual Mileage (Cambridge Systematics) | B7: 60000 | C7: Cambridge Systematics
A8: Expected Lifetime Mileage | B8: =B7*B6 -> 2100000
A9: Embodied Emissions per Mile Traveled (MTCO2e) | B9: =B5/B8 -> 3.5224e-05

Sheet Copy of 2025 Railcar Embodied E
C1: Source
A2: DOT 111 Average Purchase Cost (DOT, 2016) | B2: 140000 | C2: US DOT
A3: Convert to 2022 USD | B3: =B2*1.19 -> 166600 | C3: BLS CPI Inflation Calculator
A4: Railroad Rolling Stock Manufacturing (kgCO2e/2022 USD) | B4: 0.444 | C4: NAICS Supply Chain Emission Factors v1.3
A5: Embodied Emissions from Manufacture (MTCO2e) | B5: =(B4*B3)/1000 -> 73.9704
A6: Expected Useful Life in Years (Cambridge Systematics) | B6: 35 | C6: Cambridge Systematics
A7: Typical Annual Mileage (Cambridge Systematics) | B7: 60000 | C7: Cambridge Systematics
A8: Expected Lifetime Mileage | B8: =B7*B6 -> 2100000
A9: Embodied Emissions per Mile Traveled (MTCO2e) | B9: =B5/B8 -> 3.5224e-05

Sheet 2026 Railcar Embodied Emissions
A1: Embodied Emissions from Manufacture (MTCO2e) | B1: =B103 -> 65.374397
A2: Expected Useful Life in Years (Cambridge Systematics) | B2: 35 | C2: Cambridge Systematics
A3: Typical Annual Mileage (Cambridge Systematics) | B3: 60000 | C3: Cambridge Systematics
A4: Expected Lifetime Mileage | B4: =B3*B2 -> 2100000
A5: Embodied Emissions per Mile Traveled (MTCO2e) | B5: =B1/B4 -> 3.1130665e-05
A7: DOT-111 Tank Car — Cradle-to-Grave Embodied Emissions
A8: Materials-Based Quantification
A9: Charm Industrial — MRV Team | April 2026
A10: Blue = source-backed | Red = estimate | Purple = GREET2 ref | Black = formula/derived
A12: 1. DOT-111 PHYSICAL SPECIFICATIONS
A13: Parameter | B13: Value | C13: Unit | D13: Source / Reference | E13: Classification | G13: URL
A14: Tare weight (light weight) | B14: 39168 | C14: kg (86,350 lbs) | D14: GBRX spec sheet (Jan 2021): 29,000-gal DOT 111A100W1, C&I. Quote: "Light weight: 86,350 lbs." Conversion: 86350/2.20462 = 39168 kg. | E14: SOURCED | G14: https://www.gbrx.com/wp-content/uploads/2021/06/29000-Gallon-DOT-111-Tank-Car.pdf
A15: Configuration | B15: Coiled & insulated (C&I) | D15: GBRX spec sheet. Quote: "coiled and insulated tank car...DOT 111A100W1 specification." | E15: SOURCED | G15: https://www.gbrx.com/wp-content/uploads/2021/06/29000-Gallon-DOT-111-Tank-Car.pdf
A16: Shell material | B16: ASTM A516 Gr 70 carbon steel | D16: 49 CFR 179.200-7: permits carbon steel. A516 Gr 70 is industry standard, not regulatory mandate. | E16: PARTIAL | G16: https://www.ecfr.gov/current/title-49/part-179/subpart-D
A17: Tank outer diameter — feet component (GBRX: 9'-10 3/4") | B17: 9 | C17: feet | D17: GBRX spec: "Tank, outside diameter: 9'-10 3/4"." Feet component = 9. | E17: SOURCED | G17: https://www.gbrx.com/wp-content/uploads/2021/06/29000-Gallon-DOT-111-Tank-Car.pdf
A18: Tank outer diameter — inches component (GBRX: 10 3/4") | B18: 10.75 | C18: inches | D18: GBRX spec: inches component = 10 3/4 = 10.75 in. | E18: SOURCED
A19: Tank outer diameter — total inches | B19: =B17*12+B18 -> 118.75 | C19: inches | D19: DERIVED. =B11*12 + B12. | E19: DERIVED
A20: Tank outer diameter — meters | B20: =B19*0.0254 -> 3.01625 | C20: m | D20: DERIVED. =B13 x 0.0254 m/in. | E20: DERIVED
A21: Tank outside length — feet component (GBRX: 53'-4 7/8") | B21: 53 | C21: feet | D21: GBRX spec: "Tank, outside length: 53'-4 7/8"." Feet component = 53. | E21: SOURCED | G21: https://www.gbrx.com/wp-content/uploads/2021/06/29000-Gallon-DOT-111-Tank-Car.pdf
A22: Tank outside length — inches component (GBRX: 4 7/8") | B22: 4.875 | C22: inches | D22: GBRX spec: inches component = 4 7/8 = 4.875 in. | E22: SOURCED
A23: Tank outside length — total inches | B23: =B21*12+B22 -> 640.875 | C23: inches | D23: DERIVED. =B15*12 + B16. | E23: DERIVED
A24: Tank outside length — meters | B24: =B23*0.0254 -> 16.278225 | C24: m | D24: DERIVED. =B17 x 0.0254 m/in. | E24: DERIVED
A25: Min shell thickness — numerator (49 CFR: 7/16 in) | B25: 7 | C25: (numerator) | D25: 49 CFR 179.201-1: "not less than 7/16 inch." Numerator = 7. | E25: SOURCED | G25: https://www.ecfr.gov/current/title-49/part-179/subpart-D
A26: Min shell thickness — denominator | B26: 16 | C26: (denominator) | D26: 49 CFR 179.201-1: denominator = 16. | E26: SOURCED
A27: Min shell thickness — meters | B27: =(B25/B26)*0.0254 -> 0.0111125 | C27: m | D27: DERIVED. =(B19/B20) x 0.0254 m/in. | E27: DERIVED
A28: Jacket thickness — raw (49 CFR: 11 gauge = 0.1196 in) | B28: 0.1196 | C28: inches | D28: 49 CFR 179.200-4: "not less than 11 gauge (0.1196 inch) nominal." 0.1196 in is the regulatory value. | E28: SOURCED | G28: https://www.govregs.com/regulations/expand/title49_chapterI-i1_part179_subpartD_section179.200-4
A29: Jacket thickness — meters | B29: =B28*0.0254 -> 0.00303784 | C29: m | D29: DERIVED. =B22 x 0.0254 m/in. | E29: DERIVED
A30: Steel density (A516 Gr 70) | B30: 7850 | C30: kg/m³ | D30: AZoM / SSAB: ASTM A516 Gr 70 density 7,850 kg/m³. Standard nominal for carbon steel plate. | E30: SOURCED | G30: https://www.azom.com/article.aspx?ArticleID=4787
A31: Useful service life | B31: 50 | C31: years | D31: AAR Interchange Rule 88 / OT-24: 50-year condemning limit. | E31: SOURCED | G31: https://public.railinc.com/sites/default/files/documents/OT-24.pdf
A33: 2. NON-STEEL MATERIAL INPUTS & GEOMETRY
A34: Input Parameter | B34: Value | C34: Unit | D34: Source / Reference | E34: Classification | G34: URL
A35: Insulation thickness | B35: 0.1016 | C35: m (4 in) | D35: PROXY. 49 CFR 179.200-4 sets max thermal conductance of 0.225 Btu/(hr·ft²·°F) but not thickness. Mineral wool k ≈ 0.24 Btu·in/(hr·ft²·°F) (Engineering Toolbox) gives a theoretical minimum of ~1.07 in. UTLX tank car build specifications list 4 inches of fiberglass/mineral wool as industry standard for insulated cars, consistent with FRA-approved thermal protection systems. 4 in = 101.6 mm = 0.1016 m. | E35: PROXY | G35: https://www.utlx.com/build-a-tank-car/4-jacket.html
A36: Insulation density, mineral wool (est.) | B36: 113 | C36: kg/m³ | D36: ESTIMATE. Knauf EPD (DP7-DP8) states rock mineral wool density range 25–200 kg/m³. 113 = midpoint. No railcar-specific density standard identified. | E36: ESTIMATE | G36: https://www.knaufinsulation.com/sites/ki_com/files/uploads/Rock%20Mineral%20Wool%20DP7-DP8.pdf
A37: Insulation overlap/support factor (est.) | B37: 1.45 | D37: ESTIMATE. No public source. Accounts for batt overlaps, metal support bands, vapor barrier, and installation wastage. 1.45 is an unsourced engineering estimate. | E37: ESTIMATE
A38: Jacket outer diameter (derived) | B38: =B20+2*B35 -> 3.21945 | C38: m | D38: DERIVED. =Tank OD (B14) + 2 x insulation thickness (B29). | E38: DERIVED
A39: Underframe/truck primer area allowance (est.) | B39: 23 | C39: m² | D39: ESTIMATE. No public source for tank car underframe surface area. 23 m² is an unsourced engineering estimate based on geometric approximation: 2 longitudinal sills (~18 m x 0.4 m = ~14 m²), transverse members (~4 m²), truck frame surfaces (~4 m²), draft gear area (~1 m²). Immaterial: at 0.5 kg/m² coating rate, this is ~12 kg of coatings, or 0.03% of tare. | E39: ESTIMATE
A40: Paintable surface area (derived geometry) | B40: =PI()*B38*B24+2*PI()*(B38/2)^2+B39 -> 203.92231 | C40: m² | D40: DERIVED. Jacket exterior cylinder (PI x jacket OD x tank length) + 2 flat-approx heads (2 x PI x (jacket OD/2)²) + underframe allowance (B33). | E40: DERIVED
A41: Top fittings mass — brass/bronze (est.) | B41: 350 | C41: kg | D41: ESTIMATE. No public source. Aggregate estimate for manway cover+ring, PRD, safety valve, gauging device, sample/thermo wells, misc nozzle hardware. 350 kg is an unsourced engineering estimate. Immaterial: <1% of tare; even a 50% error changes CTGrave by <0.1 MT. | E41: ESTIMATE
A42: Coating coverage rate (est.) | B42: 0.5 | C42: kg/m² | D42: PROXY. Standard industrial coating calculation: DFT x density x 10 = kg/m². For a 2-coat system (primer ~40 µm + topcoat ~50 µm = 90 µm DFT) at epoxy density ~1.2 g/cm³: 90 x 1.2 x 10 = 1.08 kg/m² theoretical. 0.50 kg/m² assumes thinner application typical of rail (less corrosion protection than marine). Conservative: understates coating mass, but coatings are immaterial (<0.3% of tare). | E42: PROXY
A43: Rubber/elastomers (draft gear cushions, gaskets) (est.) | B43: 50 | C43: kg | D43: ESTIMATE. No public source. Draft gear elastomer cushion elements + gaskets/seals. 50 kg is an unsourced engineering estimate. Immaterial: 0.1% of tare. Even if doubled, CTGrave impact < 0.01 MT. | E43: ESTIMATE
A44: Fabrication energy intensity (est.) | B44: 2 | C44: GJ/t | D44: ESTIMATE. No tank car-specific data. LBNL-62806 REV.2 reports best practice hot rolling at 1.28 GJ/t; UNIDO 2014 benchmarking reports 1.0–1.5 GJ/t for rolling/forming/heat treatment. 2.0 GJ/t adds margin for welding, stress relief, and assembly. Conservative upper bound. | E44: ESTIMATE | G44: https://eta-publications.lbl.gov/sites/default/files/industrial_best_practice_en.pdf
A46: 3. MATERIAL MASS BREAKDOWN
A47: Approach: Tare weight is the sourced anchor (GBRX). Non-steel materials are identified and their masses estimated or derived from geometry. Steel mass = tare minus all non-steel. Of the non-steel materials, only thermal insulation is material (~5% of tare). Brass (<1%), coatings (<0.3%), and rubber (0.1%) are marginal.
A48: Material Category | B48: Mass (kg) | C48: % of Tare | D48: Formula / Basis | E48: Classification | F48: EF Applied
A49: Thermal insulation (mineral wool) | B49: =PI()/4*((B20+2*B35)^2-B20^2)*B24*B36*B37 -> 2654.314 | C49: =B49/B14 -> 0.067767411 | D49: Annular cylinder volume x density x overlap factor. Cylinder only; head insulation (~181 kg) absorbed by steel residual at steel EF — conservative (steel EF > mineral wool EF). | E49: DERIVED from estimates | F49: Mineral wool
A50: Brass fittings (top fittings assembly) | B50: =B41 -> 350 | C50: =B50/B14 -> 0.008935866 | D50: From Sec 2. Marginal: <1% of tare. Even a 50% error changes CTGrave by <0.1 MT. | E50: ESTIMATE | F50: Brass (Cu/Zn)
A51: Coatings + lining (epoxy/polyurethane) | B51: =B40*B42 -> 101.96116 | C51: =B51/B14 -> 0.0026031749 | D51: Surface area (B34) x coverage rate (B36). | E51: DERIVED from estimates | F51: Coatings
A52: Rubber/elastomers (draft gear, gaskets) | B52: =B43 -> 50 | C52: =B52/B14 -> 0.0012765523 | D52: From Sec 2. Immaterial: 0.1% of tare. Even if doubled, CTGrave impact < 0.01 MT. | E52: ESTIMATE | F52: Rubber
A53: SUBTOTAL: Non-steel materials | B53: =SUM(B49:B52) -> 3156.2751 | C53: =B53/B14 -> 0.080583004 | D53: Sum of insulation + brass + coatings + rubber.
A54: STEEL (all grades — residual) | B54: =B14-B53 -> 36011.725 | C54: =B54/B14 -> 0.919417 | D54: Tare minus non-steel. Covers: shell/heads, jacket, frame, trucks, couplers, draft gear, brakes, heating coils, all structural steel. One blended US steel EF. | E54: DERIVED (residual) | F54: US blended steel
A55: TOTAL BOM | B55: =B54+B53 -> 39168 | C55: =B55/B14 -> 1
A56: Residual (tare − BOM) | B56: =B14-B55 -> 0 | D56: Must be 0. Steel absorbs the difference by construction.
A58: 4. EMISSION FACTORS
A59: 4A. GREET2 2025 Reference Values (Argonne National Lab)
A60: Material / Parameter | B60: Raw GREET Value | C60: Raw Unit | D60: Converted EF (kgCO₂e/kg) | E60: GREET2 Cell Ref | G60: URL
A61: Virgin Steel (BF-BOF) | B61: 1408.8 | C61: g/lb | D61: =B61*2.20462/1000 -> 3.1058687 | E61: Mat_Sum, row 65, col B | G61: https://greet.anl.gov/
A62: Recycled Steel (EAF) | B62: 292.68 | C62: g/lb | D62: =B62*2.20462/1000 -> 0.64524818 | E62: Mat_Sum, row 65, col C | G62: https://greet.anl.gov/
A63: Copper | B63: 1742.3 | C63: g/lb | D63: =B63*2.20462/1000 -> 3.8411094 | E63: Mat_Sum, row 65, col BE | G63: https://greet.anl.gov/
A64: Zinc | B64: 1062.57 | C64: g/lb | D64: =B64*2.20462/1000 -> 2.3425631 | E64: Mat_Sum, row 65, col BF | G64: https://greet.anl.gov/
A65: Rubber (synthetic) | B65: 1686.16 | C65: g/lb | D65: =B65*2.20462/1000 -> 3.7173421 | E65: Mat_Sum, row 65, col BU | G65: https://greet.anl.gov/
A66: Steel EoL recycling rate | B66: 0.96 | C66: (fraction) | D66: =B66 -> 0.96 | E66: Mat_Sum, cell B19 | G66: https://greet.anl.gov/
A68: 4B. Derivation Assumptions
A69: Assumption | B69: Value | C69: Unit | D69: Source | G69: URL
A70: US steel: BF-BOF share | B70: 0.33 | C70: (fraction) | D70: Hasanbeigi & Springer 2019. US 2018: 33% BF-BOF, 67% EAF. Data is 8 years old; EAF share has likely increased, making this conservative. | G70: https://www.bluegreenalliance.org/wp-content/uploads/2021/04/HowCleanistheU.S.SteelIndustry.pdf
A71: US steel: EAF share | B71: =1-B70 -> 0.67 | C71: (fraction) | D71: 1 − BF-BOF share (B64).
A72: Brass: Cu share (C26000) | B72: 0.7 | C72: (fraction) | D72: UNS C26000 per ASTM B927: Cu 68.5–71.5%, bal Zn. Nominal 70/30. | G72: https://alloys.copper.org/alloy/C26000
A73: Brass: Zn share | B73: =1-B72 -> 0.3 | C73: (fraction) | D73: 1 − Cu share (B66).
A74: US grid EF (eGRID 2023) | B74: 0.367 | C74: kgCO₂e/kWh | D74: EPA eGRID 2023 (Jan 2025). US avg: 0.81 lbs CO₂/kWh. 0.81 / 2.20462 = 0.367 kg. | G74: https://www.epa.gov/egrid
A75: US grid EF (per GJ) | B75: =B74*277.78/1000 -> 0.10194526 | C75: tCO₂e/GJ | D75: DERIVED. B68 x 277.78 kWh/GJ / 1000.
A77: 4C. Applied Emission Factors
A78: Material Category | B78: EF (kgCO₂e/kg) | C78: Formula | D78: Source Classification | E78: Notes
A79: US blended steel (BF-BOF/EAF weighted) | B79: =B70*D61+B71*D62 -> 1.4572529 | C79: BOF_share*BF-BOF_EF + EAF_share*EAF_EF | D79: DERIVED — GREET2 + Hasanbeigi mix
A80: Mineral wool insulation | B80: 1.25 | C80: ICE v4.1: 1.25 | D80: DIRECT — ICE v4.1
A81: Brass/bronze (Cu-Zn, C26000) | B81: =B72*D63+B73*D64 -> 3.3915455 | C81: Cu_share*Cu_EF + Zn_share*Zn_EF | D81: DERIVED — GREET2 Cu+Zn weighted
A82: Coatings (waterborne paint) | B82: 2.152 | C82: ICE v4.1: 2.152 | D82: DIRECT — ICE v2.0
A83: Rubber (synthetic) | B83: =D65 -> 3.7173421 | C83: GREET2 synthetic rubber | D83: DIRECT — GREET2
A84: Manufacturing energy (per kg of tare) | B84: =B44*B75 -> 0.20389052 | C84: Fab_GJ_per_t x Grid_tCO2e_per_GJ | D84: ESTIMATE — fab energy is unsourced estimate
A86: 5. CRADLE-TO-GATE EMISSIONS
A87: Material Category | B87: Mass (kg) | C87: EF (kgCO₂e/kg) | D87: Emissions (kgCO₂e) | E87: Emissions (MT CO₂e) | F87: % of Total
A88: Steel (all grades) | B88: =B54 -> 36011.725 | C88: =B79 -> 1.4572529 | D88: =B88*C88 -> 52478.192 | E88: =D88/1000 -> 52.478192 | F88: =D88/D94 -> 0.8027331
A89: Thermal insulation | B89: =B49 -> 2654.314 | C89: =B80 -> 1.25 | D89: =B89*C89 -> 3317.8924 | E89: =D89/1000 -> 3.3178924 | F89: =D89/D94 -> 0.050752169
A90: Brass fittings | B90: =B50 -> 350 | C90: =B81 -> 3.3915455 | D90: =B90*C90 -> 1187.0409 | E90: =D90/1000 -> 1.1870409 | F90: =D90/D94 -> 0.018157581
A91: Coatings + lining | B91: =B51 -> 101.96116 | C91: =B82 -> 2.152 | D91: =B91*C91 -> 219.42041 | E91: =D91/1000 -> 0.21942041 | F91: =D91/D94 -> 0.0033563661
A92: Rubber/elastomers | B92: =B52 -> 50 | C92: =B83 -> 3.7173421 | D92: =B92*C92 -> 185.8671 | E92: =D92/1000 -> 0.1858671 | F92: =D92/D94 -> 0.0028431177
A93: Manufacturing / fabrication energy | B93: =B14 -> 39168 | C93: =B84 -> 0.20389052 | D93: =B93*C93 -> 7985.9839 | E93: =D93/1000 -> 7.9859839 | F93: =D93/D94 -> 0.12215767
A94: SUBTOTAL: Cradle-to-Gate | D94: =SUM(D88:D93) -> 65374.397 | E94: =D94/1000 -> 65.374397
A96: 6. END-OF-LIFE METHOD & CRADLE-TO-GRAVE TOTAL
A97: Parameter | B97: Value | C97: Unit | D97: Notes
A98: EoL allocation method | B98: Cut-off (recycled content) | D98: No end-of-life recycling credit. Steel LCA typically shows a net-negative EoL due to high recycling rates (~96%), but computing an avoided-burden credit requires data we do not have (net scrap balance, grade-specific virgin/recycled split, scrap market displacement factors). Rather than fabricate those inputs, we conservatively set the EoL credit to zero. This is the cut-off (recycled content) method: the benefit of recycled content is already partially captured in the blended production EF (67% EAF route).
A99: EoL recycling credit | B99: 0 | C99: MT CO₂e | D99: Zero under cut-off method.
A100: Lifecycle modules C1-C4 | B100: Declared, zero impact | D100: Cut-off method: EoL modules declared per Isometric GHG Accounting v1.0 but contribute zero net emissions. Single EoL at 50-year condemning limit (AAR Rule 88).
A102: CRADLE-TO-GRAVE TOTAL | B102: =E94 -> 65.374397 | C102: MT CO₂e | D102: Equal to CTGate under cut-off method (no EoL credit or debit).
A103: CRADLE-TO-GATE TOTAL | B103: =E94 -> 65.374397 | C103: MT CO₂e

Sheet H1 2025 AECN Process Emissions
A1: Stack Emissions Calculation
A2: AECN LCA Data | D2: GHGenius Ensyn RTP Model | G2: Calculations Based on Model
A3: Biomass Input (MT) | B3: 14132 | D3: GHG | E3: g/GJ Feedstock | G3: g/MT Bio Oil | H3: g CO2e/MT Bio Oil
A4: Bio Oil Output (L) | B4: 7510281 | D4: CH4 | E4: 0.34 | G4: 1.4072839 | H4: 37.996666
A5: HHV (MJ/L) | B5: 17.88 | D5: N2O | E5: 1.01 | G5: 4.1804611 | H5: 1141.2659
A7: Conversions | G7: Emissions Totals
A8: Total HHV (MJ) | B8: 134283818 | G8: Total Stack Emissions g CO2e/ MT Bio Oil | I8: 1179.2626
A9: MJ/MT Feedstock | B9: 9502.0012 | G9: Total Stack Emissions MT CO2e/ MT Bio Oil | I9: 0.0011792626
A10: GJ/MT Feedstock | B10: 9.5020012 | G10: Total Other Process Emissions MT COT2e/MT Bio Oil (From Vendor LCA) | I10: 0.1256
A11: Kg Feedstock/GJ | B11: 105.24099 | G11: Total Process Emissions MT CO2e/MT Bio Oil | I11: 0.12678
A13: Biomass Input (kg) | B13: 14132162
A14: Kg biomass/L BO | B14: 0.53143183
A15: L BO/MT BO | B15: 819.67213
A16: Kg biomass/MT BO | B16: 435.59986
A17: GJ Biomass/MT BO | B17: 4.1390704
A19: IPCC AR6 GWPs - 100 Yr
A20: Methane - non-fossil | B20: 27
A21: Nitrous Oxide | B21: 273

Sheet H1 2026 AECN Process Emissions
A1: Stack Emissions Calculation | B1: Inputs from LCA
A2: AECN LCA Data | D2: GHGenius Ensyn RTP Model | G2: Calculations Based on Model
A3: Biomass Input (MT) | B3: 19110.591 | D3: GHG | E3: g/GJ Feedstock | G3: g/MT Bio Oil | H3: g CO2e/MT Bio Oil
A4: Bio Oil Output (L) | B4: 10334884 | D4: CH4 | E4: 0.34 | G4: =round(E4*$B$18,2) -> 4.85 | H4: =G4*B21 -> 130.95
A5: HHV (MJ/L) | B5: 17.406969 | D5: N2O | E5: 1.01 | G5: =Round(E5*$B$18,2) -> 14.41 | H5: =G5*B22 -> 3933.93
A6: BO Density (kg/L) | B6: 1.22
A8: Conversions | G8: Emissions Totals
A9: Total HHV (MJ) | B9: =B5*B4 -> 1.7989901e+08 | G9: Total Stack Emissions g CO2e/ MT Bio Oil | I9: =SUM(H4:H5) -> 4064.88
A10: MJ/MT Feedstock | B10: =B9/B3 -> 9413.5768 | G10: Total Stack Emissions MT CO2e/ MT Bio Oil | I10: =I9/1000000 -> 0.00406488
A11: GJ/MT Feedstock | B11: =B10/1000 -> 9.4135768 | G11: Total Other Process Emissions MT COT2e/MT Bio Oil (From Vendor LCA) | I11: 0.13305203
G12: Total Process Emissions MT CO2e/MT Bio Oil | I12: =SUM(I10:I11) -> 0.13711691
A14: Biomass Input (kg) | B14: =B3*1000 -> 19110591
A15: Kg biomass/L BO | B15: =B14/B4 -> 1.8491345
A16: L BO/MT BO | B16: =1000/B6 -> 819.67213
A17: Kg biomass/MT BO | B17: =B15*B16 -> 1515.684
A18: GJ Biomass/MT BO | B18: =(B17/1000)*B11 -> 14.268008
A20: IPCC AR6 GWPs - 100 Yr
A21: Methane - non-fossil | B21: 27
A22: Nitrous Oxide | B22: 273

Sheet H2 2026 AECN Process Emissions
A1: Stack Emissions Calculation | B1: Inputs from LCA — 'FH 2026 LCA w Stack Emissions' (H1 2026 operating data), applies to H2 2026 reporting periods from the Aug 1–31 2026 RP onward
A2: AECN LCA Data | D2: GHGenius Ensyn RTP Model | G2: Calculations Based on Model
A3: Biomass Input (MT) | B3: 19110.591 | D3: GHG | E3: g/GJ Feedstock | G3: g/MT Bio Oil | H3: g CO2e/MT Bio Oil
A4: Bio Oil Output (L) | B4: 10334884 | D4: CH4 | E4: 0.34 | G4: =E4*$B$18 -> 4.8511226 | H4: =G4*$B$21 -> 130.98031
A5: HHV (MJ/L) | B5: 17.406969 | D5: N2O | E5: 1.01 | G5: =E5*$B$18 -> 14.410688 | H5: =G5*$B$22 -> 3934.1177
A6: BO Density (kg/L) | B6: 1.22
A8: Conversions | G8: Emissions Totals
A9: Total HHV (MJ) | B9: =B5*B4 -> 1.7989901e+08 | G9: Total Stack Emissions g CO2e/ MT Bio Oil | I9: =SUM(H4:H5) -> 4065.098
A10: MJ/MT Feedstock | B10: =B9/B3 -> 9413.5768 | G10: Total Stack Emissions MT CO2e/ MT Bio Oil | I10: =I9/1000000 -> 0.004065098
A11: GJ/MT Feedstock | B11: =B10/1000 -> 9.4135768 | G11: Total Other Process Emissions MT CO2e/MT Bio Oil (From Vendor LCA) | I11: 0.13305203
A12: Kg Feedstock/GJ | B12: =1000/B11 -> 106.22955 | G12: Total Process Emissions MT CO2e/MT Bio Oil | I12: =SUM(I10:I11) -> 0.13711713
A14: Biomass Input (kg) | B14: =B3*1000 -> 19110591
A15: Kg biomass/L BO | B15: =B14/B4 -> 1.8491345
A16: L BO/MT BO | B16: =1000/B6 -> 819.67213
A17: Kg biomass/MT BO | B17: =B15*B16 -> 1515.684
A18: GJ Biomass/MT BO | B18: =(B17/1000)*B11 -> 14.268008
A20: IPCC AR6 GWPs - 100 Yr
A21: Methane - non-fossil | B21: 27
A22: Nitrous Oxide | B22: 273
A24: NOTE | B24: I12 is the AECN pyrolysis PROCESS carbon intensity pushed to Isometric Certify (tCO2e/MT == kgCO2e/kg). Embodied CI is unchanged at 0.02116 tCO2e/MT. G4/G5 are intentionally NOT rounded here — the H1 2026 tab's round(,2) understates I12 by 2.2e-7.

Sheet 2025 LCS Embodied Emissions
A1: GREET 2024 EF (g CO2e/T Material) | B1: 892720 | H1: Conversions
A2: Uncertainty Factor | B2: 0.0012002604 | H2: Kg per Tons | I2: 907.185
A3: GREET 2024 EF (g CO2e/T Material) w Uncert. | B3: =B1*(1+B2) -> 893791.5 | H3: LCS Density (lb/gal) | I3: 12.76 | J3: https://labelsds.com/images/user_uploads/Univar%20CausSoda%20.50%20SDS%204-22-21.pdf
A4: "" (g CO2e/kg Material) | B4: =B3/I2 -> 985.23619 | H4: LCS Density (kg/gal) | I4: =I3*0.453592 -> 5.7878339
A5: "" (g CO2e/gal Material) | B5: =B4*I4 -> 5702.3835 | H5: Liters/gal | I5: 3.785
A6: "" (kg CO2e/gal Material) | B6: =B5/I6 -> 5.7023835 | H6: Grams/kg | I6: 1000
A7: "" (kg CO2e/kg Material) | B7: =B4/1000 -> 0.98523619

Sheet 2026 LCS Embodied Emissions
A1: GREET 2025 EF (g CO2e/T Material) | B1: 862975 | H1: Conversions
A2: Uncertainty Factor | B2: 0.0012002604 | H2: Kg per Tons | I2: 907.185
A3: GREET 2024 EF (g CO2e/T Material) w Uncert. | B3: =B1*(1+B2) -> 864010.79 | H3: LCS Density (lb/gal) | I3: 12.76 | J3: https://labelsds.com/images/user_uploads/Univar%20CausSoda%20.50%20SDS%204-22-21.pdf
A4: "" (g CO2e/kg Material) | B4: =B3/I2 -> 952.4086 | H4: LCS Density (kg/gal) | I4: =I3*0.453592 -> 5.7878339
A5: "" (g CO2e/gal Material) | B5: =B4*I4 -> 5512.3828 | H5: Liters/gal | I5: 3.785
A6: "" (kg CO2e/gal Material) | B6: =B5/I6 -> 5.5123828 | H6: Grams/kg | I6: 1000
A7: "" (kg CO2e/kg Material) | B7: =B4/1000 -> 0.9524086

Sheet Vaulted- EE 825 Update
A1: Original Values
A2: Equipment Embodied Emissions | C2: Information Source
A3: Cavern Emplacement Capacity (MT) | B3: 2000000 | C3: Vaulted GHG Statement
A4: T Equipment Steel/MT Material Emplaced | B4: 3.51566e-05 | C4: Vaulted GHG Statement
A5: T Concrete/MT Material Emplaced | B5: 7.7e-05 | C5: Vaulted GHG Statement
A7: Embodied Emissions: Steel (MT CO2e/MT Emplaced) | B7: 9.671542e-05 | C7: GREET 2023
A8: Embodied Emissions: Concrete (MT CO2e/MT Emplaced) | B8: 6.718096e-06 | C8: GREET 2023
A9: Total Embodied Emissions/MT Material Emplaced | B9: 0.00010343352
A11: New Values 8/25 | B11: MT CO2e
A12: Processing Cement Pit | B12: 264
A13: Processing and Brine Tanks Replacement | B13: 206
A14: SW-13 | B14: 84
A15: AR-05 | B15: 60
A17: Total MT CO2e | B17: =SUM(B12:B15) -> 614
A18: Total Embodied Emissions/MT Material Emplaced for 2025 Work | B18: =B17/B3 -> 0.000307
A20: Total Embodied Emissions/MT Material Emplaced | B20: =SUM(B9,B18) -> 0.00041043352
B21: =B20*1000 -> 0.41043352

Sheet 2025 Rock Salt Emissions
A1: GREET 2024 EF (g CO2e/T Material) | B1: 235180 | F1: Conversions
A2: "" (kg CO2e/T Material) | B2: =B1/1000 -> 235.18 | F2: Kg per Tons | G2: 907.185
A3: ""(kg CO2e/kg Material) | B3: =B2/G2 -> 0.2592415

Sheet Vaulted EE 825 Update
A1: Original Values
A2: Equipment Embodied Emissions | C2: Information Source
A3: Cavern Emplacement Capacity (MT) | B3: 2000000 | C3: Vaulted GHG Statement
A4: T Equipment Steel/MT Material Emplaced | B4: 3.51566e-05 | C4: Vaulted GHG Statement
A5: T Concrete/MT Material Emplaced | B5: 7.7e-05 | C5: Vaulted GHG Statement
A7: Embodied Emissions: Steel (MT CO2e/MT Emplaced) | B7: 9.671542e-05 | C7: GREET 2023
A8: Embodied Emissions: Concrete (MT CO2e/MT Emplaced) | B8: 6.718096e-06 | C8: GREET 2023
A9: Total Embodied Emissions/MT Material Emplaced | B9: 0.00010343352
A11: New Values 8/25 | B11: MT CO2e
A12: Processing Cement Pit | B12: 264
A13: Processing and Brine Tanks Replacement | B13: 206
A14: SW-13 | B14: 84
A15: AR-05 | B15: 60
A17: Total MT CO2e | B17: =SUM(B12:B15) -> 614
A18: Total Embodied Emissions/MT Material Emplaced for 2025 Work | B18: =B17/B3 -> 0.000307
A20: Total Embodied Emissions/MT Material Emplaced | B20: =SUM(B9,B18) -> 0.00041043352
B21: =B20*1000 -> 0.41043352

Sheet 2026 Methanol
A1: mmBtu/gal | B1: kg CO2e/mmBtu | C1: kg CO2e/gal
A2: 0.0652 | B2: =(8073+13381)/1000 -> 21.454 | C2: =B2*A2 -> 1.3988008

Sheet 2026 Water
A1: Drinking Water Value from Study | D1: Constants
A2: 0.46 | B2: kgCO2e/m3 | D2: US Gal/m3 | E2: 264.172
A3: =A2/E2 -> 0.0017412898 | B3: kgCO2e/gal | D3: kg/MT | E3: 1000
A4: =A3/E3 -> 1.7412898e-06 | B4: MTCO2e/gal

Sheet 2026 Sample Transport Materiali
D1: Source
A2: Max Indiv. Sample Size | B2: 1 | C2: liter
A3: Conservative Density Estimate | B3: 1.3 | C3: kg/l
A4: Sample Mass | B4: =B3*B2 -> 1.3 | C4: kg
A6: Distance from Injection Site to Lab | B6: 183 | C6: mi | D6: https://maps.app.goo.gl/Df3S7FzHb1Q4em3r7
A8: Air Transport Emissions/Sample | B8: =B6*(B4/1000)*'2026'!F9 -> 0.00030163151 | C8: MTCO2e
A10: Q1 Average tCDR/Batch | B10: 24.92
A11: Samples per Batch | B11: 1
A13: Sampe Emissions as % of Batch CDR | B13: =B8/B10 -> 1.2103993e-05

Sheet 2026 Currency Conversions for C
A1: NAICS Code | B1: NAICS Title | C1: GHG | D1: Unit | E1: EF without Margins (kg CO2e/2024 USD) | F1: Margins | G1: EF with Margins (kg CO2e/2024 USD) | H1: EF with Margins (kg CO2e/2026] USD) | I1: USEEIO Code | L1: Cum. Dollar Value Change 2024-2026 | M1: 0.05 | N1: Source: BLS Inflation Calculator
A2: 336510 | B2: Railroad Rolling Stock Manufacturing | C2: All GHGs | D2: kg CO2e/2024 USD, purchaser price | E2: 0.366 | F2: 0.031 | G2: 0.397 | H2: =G2*(1-$M$1) -> 0.37715 | I2: 336500
A3: 236210 | B3: Industrial Building Construction | C3: All GHGs | D3: kg CO2e/2024 USD, purchaser price | E3: 0.21 | F3: 0 | G3: 0.21 | H3: =G3*(1-$M$1) -> 0.1995 | I3: 230301, 233230
A4: 238990 | B4: All Other Specialty Trade Contractors | C4: All GHGs | D4: kg CO2e/2024 USD, purchaser price | E4: 0.201 | F4: 0 | G4: 0.201 | H4: =G4*(1-$M$1) -> 0.19095 | I4: 230301, 230302, 233210, 233230, 233240, 233262, 2332A0, 2332D0, 233411, 233412, 2334A0
A5: 333120 | B5: Construction Machinery Manufacturing | C5: All GHGs | D5: kg CO2e/2024 USD, purchaser price | E5: 0.163 | F5: 0.023 | G5: 0.187 | H5: =G5*(1-$M$1) -> 0.17765 | I5: 333120
A6: 333413 | B6: Industrial and Commercial Fan and Blower and Air Purification Equipment Manufacturing | C6: All GHGs | D6: kg CO2e/2024 USD, purchaser price | E6: 0.163 | F6: 0.023 | G6: 0.186 | H6: =G6*(1-$M$1) -> 0.1767 | I6: 333413
A7: 333415 | B7: Air-Conditioning and Warm Air Heating Equipment and Commercial and Industrial Refrigeration Equipment Manufacturing | C7: All GHGs | D7: kg CO2e/2024 USD, purchaser price | E7: 0.159 | F7: 0.024 | G7: 0.184 | H7: =G7*(1-$M$1) -> 0.1748 | I7: 333415
A8: 321992 | B8: Prefabricated Wood Building Manufacturing | C8: All GHGs | D8: kg CO2e/2024 USD, purchaser price | E8: 0.144 | F8: 0.032 | G8: 0.177 | H8: =G8*(1-$M$1) -> 0.16815 | I8: 3219A0
A9: 333249 | B9: Other Industrial Machinery Manufacturing | C9: All GHGs | D9: kg CO2e/2024 USD, purchaser price | E9: 0.149 | F9: 0.017 | G9: 0.166 | H9: =G9*(1-$M$1) -> 0.1577 | I9: 33329A
A10: 335312 | B10: Motor and Generator Manufacturing | C10: All GHGs | D10: kg CO2e/2024 USD, purchaser price | E10: 0.113 | F10: 0.016 | G10: 0.13 | H10: =G10*(1-$M$1) -> 0.1235 | I10: 335312
